Workbook

Sheet Films
A1: ID | B1: Titre français | C1: Titre original | D1: Année | E1: Type | F1: Durée (min) | G1: Pays | H1: Réalisation | I1: Scénario | J1: Image | K1: Montage | L1: Décors | M1: Musique | N1: Production | O1: Distribution artistique | P1: Équipe technique | Q1: Synopsis | R1: Extraits | S1: Analyse | T1: Bibliographie | U1: Affiche | V1: Légende affiche | W1: Source affiche | X1: Liens chronologie | Y1: Mots-clés | Z1: Sources | AA1: Statut | AB1: ID normalisé V22 | AC1: IDs entourage — distribution artistique | AD1: IDs entourage — équipe technique
A2: rwf-1966-this-night | B2: This night | C2: This night | D2: 1966 | E2: Court-métrage | G2: RFA | H2: Rainer Werner Fassbinder
A3: rwf-1966-le-clochard | B3: Le Clochard | C3: Der Stadtstreicher | D3: 1966 | E3: Court-métrage | F3: 10 | G3: RFA | H3: Rainer Werner Fassbinder | I3: Rainer Werner Fassbinder | J3: Michael Fengler ; Josef Jung | N3: Roser Film | O3: Christoph Roser : le clochard Susanne Schimkus : la serveuse Michael Fengler : un homme Thomas Fengler : un homme Irm Hermann : Frau Pigue | P3: Format : noir et blanc, mono Genre : court métrage dramatique Sortie : 1966 | Q3: Un clochard trouve un pistolet dans la rue. | Z3: Wikipédia : https://fr.wikipedia.org/wiki/Le_Clochard | AB3: film-1966-le-clochard
A4: rwf-1967-petit-chaos | B4: Petit chaos | C4: Das kleine Chaos | D4: 1967 | E4: Court-métrage | F4: 9 | G4: RFA | H4: Rainer Werner Fassbinder | I4: Rainer Werner Fassbinder | J4: Michael Fengler | N4: Roser Film | O4: Christoph Roser : Theo Marite Greiselis : Marite Rainer Werner Fassbinder : Franz Lilo Pempeit : Mme Eder | P4: Format : noir et blanc, 1,37:1, mono Genre : court métrage de comédie Sortie : 1967 | Q4: Theo, Marite et Franz tentent de gagner de l’argent en vendant des revues en porte-à-porte. Après leurs échecs répétés, ils décident de commettre de petits vols. | Z4: Wikipédia : https://fr.wikipedia.org/wiki/Le_Petit_Chaos | AB4: film-1967-petit-chaos
A5: rwf-1969-amour-plus-froid | B5: L’Amour est plus froid que la mort | C5: Liebe ist kälter als der Tod | D5: 1969 | E5: Long métrage | F5: 88 | G5: RFA | H5: Rainer Werner Fassbinder | I5: Rainer Werner Fassbinder | K5: Franz Walsch (pseudonyme de Rainer Werner Fassbinder) | L5: Ulli Lommel ; Rainer Werner Fassbinder | M5: Peer Raben ; Holga Münzer | N5: Antiteater-X-Film | O5: Rainer Werner Fassbinder : Franz Ulli Lommel : Bruno Hanna Schygulla : Joanna Hans Hirschmüller : Peter Katrin Schaake : la jeune femme dans le train Peter Berling : le cordonnier Irm Hermann : la vendeuse de lunettes Hannes Gromball : le client de Joanna Gisela Otto : une prostituée Ingrid Caven : une prostituée Ursula Strätz : une prostituée Les Olvides : Georges Peer Raben : Jürgen Peter Moland : un homme du syndicat Anastassios Karalas : le Turc Kurt Raab : le surveillant du supermarché Rudolf Waldemar Brem : le motard policier Yaak Karsunke : le commissaire Monoka Stadler : la jeune fille | P5: Son : Gottfried Hüngsberg Format : noir et blanc, 35 mm Tournage : 24 jours en avril 1969, Munich et environs Sortie RFA : 26 juin 1969 (Berlinale), puis 16 janvier 1970 | Q5: Franz, souteneur de petite envergure, refuse de s’allier à un syndicat du crime. Celui-ci lui envoie Bruno, qui forme avec Franz et sa compagne Joanna un trio de jeunes criminels. Bruno commet des crimes que la police impute à Franz, puis les deux hommes décident d’attaquer une banque. | U5: Films_images/L_Amour_est_plus_froid_que_la_mort.jpg | X5: 1969 | Z5: Wikipédia : https://fr.wikipedia.org/wiki/L%27amour_est_plus_froid_que_la_mort | AA5: À compléter | AB5: film-1969-l-amour-est-plus-froid-que-la-mort | AC5: =IF(O5="","",_xlfn.TEXTJOIN("; ",TRUE,IF(ISNUMBER(SEARCH('Référentiel entourage'!$B$2,O5)),'Référentiel entourage'!$A$2,""),IF(ISNUMBER(SEARCH('Référentiel entourage'!$B$3,O5)),'Référentiel entourage'!$A$3,""),IF(ISNUMBER(SEARCH('Référentiel entourage'!$B$4,O5)),'Référentiel entourage'!$A$4,""),IF(ISNUMBER(SEARCH('Référentiel entourage'!$B$5,O5)),'Référentiel entourage'!$A$5,""),IF(ISNUMBER(SEARCH('Référentiel entourage'!$B$6,O5)),'Référentiel entourage'!$A$6,""),IF(ISNUMBER(SEARCH('Référentiel entourage'!$B$7,O5)),'Référentiel entourage'!$A$7,""),IF(ISNUMBER(SEARCH('Référentiel entourage'!$B$8,O5)),'Référentiel entourage'!$A$8,""),IF(ISNUMBER(SEARCH('Référentiel entourage'!$B$9,O5)),'Référentiel entourage'!$A$9,""),IF(ISNUMBER(SEARCH('Référentiel entourage'!$B$10,O5)),'Référentiel entourage'!$A$10,""),IF(ISNUMBER(SEARCH('Référentiel entourage'!$B$11,O5)),'Référentiel entourage'!$A$11,""),IF(ISNUMBER(SEARCH('Référentiel entourage'!$B$12,O5)),'Référentiel entourage'!$A$12,""),IF(ISNUMBER(SEARCH('Référentiel entourage'!$B$13,O5)),'Référentiel entourage'!$A$13,""),IF(ISNUMBER(SEARCH('Référentiel entourage'!$B$14,O5)),'Référentiel entourage'!$A$14,""),IF(ISNUMBER(SEARCH('Référentiel entourage'!$B$15,O5)),'Référentiel entourage'!$A$15,""),IF(ISNUMBER(SEARCH('Référentiel entourage'!$B$16,O5)),'Référentiel entourage'!$A$16,""),IF(ISNUMBER(SEARCH('Référentiel entourage'!$B$17,O5)),'Référentiel entourage'!$A$17,""),IF(ISNUMBER(SEARCH('Référentiel entourage'!$B$18,O5)),'Référentiel entourage'!$A$18,""),IF(ISNUMBER(SEARCH('Référentiel entourage'!$B$19,O5)),'Référentiel entourage'!$A$19,""),IF(ISNUMBER(SEARCH('Référentiel entourage'!$B$20,O5)),'Référentiel entourage'!$A$20,""),IF(ISNUMBER(SEARCH('Référentiel entourage'!$B$21,O5)),'Référentiel entourage'!$A$21,""),IF(ISNUMBER(SEARCH('Référentiel entourage'!$B$22,O5)),'Référentiel entourage'!$A$22,""),IF(ISNUMBER(SEARCH('Référentiel entourage'!$B$23,O5)),'Référentiel entourage'!$A$23,""),IF(ISNUMBER(SEARCH('Référentiel entourage'!$B$24,O5)),'Référentiel entourage'!$A$24,""))) -> pers-ingrid-caven; pers-irm-hermann; pers-ulli-lommel; pers-kurt-raab; pers-peer-raben; pers-hanna-schygulla; pers-ursula-stratz | AD5: =_xlfn.LET(_xlpm.texte,_xlfn.TEXTJOIN(" | ",TRUE,H5:N5,P5),IF(_xlpm.texte="","",_xlfn.TEXTJOIN("; ",TRUE,IF(ISNUMBER(SEARCH('Référentiel entourage'!$B$2,_xlpm.texte)),'Référentiel entourage'!$A$2,""),IF(ISNUMBER(SEARCH('Référentiel entourage'!$B$3,_xlpm.texte)),'Référentiel entourage'!$A$3,""),IF(ISNUMBER(SEARCH('Référentiel entourage'!$B$4,_xlpm.texte)),'Référentiel entourage'!$A$4,""),IF(ISNUMBER(SEARCH('Référentiel entourage'!$B$5,_xlpm.texte)),'Référentiel entourage'!$A$5,""),IF(ISNUMBER(SEARCH('Référentiel entourage'!$B$6,_xlpm.texte)),'Référentiel entourage'!$A$6,""),IF(ISNUMBER(SEARCH('Référentiel entourage'!$B$7,_xlpm.texte)),'Référentiel entourage'!$A$7,""),IF(ISNUMBER(SEARCH('Référentiel entourage'!$B$8,_xlpm.texte)),'Référentiel entourage'!$A$8,""),IF(ISNUMBER(SEARCH('Référentiel entourage'!$B$9,_xlpm.texte)),'Référentiel entourage'!$A$9,""),IF(ISNUMBER(SEARCH('Référentiel entourage'!$B$10,_xlpm.texte)),'Référentiel entourage'!$A$10,""),IF(ISNUMBER(SEARCH('Référentiel entourage'!$B$11,_xlpm.texte)),'Référentiel entourage'!$A$11,""),IF(ISNUMBER(SEARCH('Référentiel entourage'!$B$12,_xlpm.texte)),'Référentiel entourage'!$A$12,""),IF(ISNUMBER(SEARCH('Référentiel entourage'!$B$13,_xlpm.texte)),'Référentiel entourage'!$A$13,""),IF(ISNUMBER(SEARCH('Référentiel entourage'!$B$14,_xlpm.texte)),'Référentiel entourage'!$A$14,""),IF(ISNUMBER(SEARCH('Référentiel entourage'!$B$15,_xlpm.texte)),'Référentiel entourage'!$A$15,""),IF(ISNUMBER(SEARCH('Référentiel entourage'!$B$16,_xlpm.texte)),'Référentiel entourage'!$A$16,""),IF(ISNUMBER(SEARCH('Référentiel entourage'!$B$17,_xlpm.texte)),'Référentiel entourage'!$A$17,""),IF(ISNUMBER(SEARCH('Référentiel entourage'!$B$18,_xlpm.texte)),'Référentiel entourage'!$A$18,""),IF(ISNUMBER(SEARCH('Référentiel entourage'!$B$19,_xlpm.texte)),'Référentiel entourage'!$A$19,""),IF(ISNUMBER(SEARCH('Référentiel entourage'!$B$20,_xlpm.texte)),'Référentiel entourage'!$A$20,""),IF(ISNUMBER(SEARCH('Référentiel entourage'!$B$21,_xlpm.texte)),'Référentiel entourage'!$A$21,""),IF(ISNUMBER(SEARCH('Référentiel entourage'!$B$22,_xlpm.texte)),'Référentiel entourage'!$A$22,""),IF(ISNUMBER(SEARCH('Référentiel entourage'!$B$23,_xlpm.texte)),'Référentiel entourage'!$A$23,""),IF(ISNUMBER(SEARCH('Référentiel entourage'!$B$24,_xlpm.texte)),'Référentiel entourage'!$A$24,"")))) -> pers-ulli-lommel; pers-peer-raben
A6: rwf-1969-katzelmacher | B6: Le Bouc | C6: Katzelmacher | D6: 1969 | E6: Long métrage | F6: 88 | G6: RFA | H6: Rainer Werner Fassbinder | I6: Rainer Werner Fassbinder | J6: Dietrich Lohmann | K6: Rainer Werner Fassbinder | M6: Peer Raben | N6: Peer Raben ; Antiteater-X-Film | O6: Hanna Schygulla : Marie Lilith Ungerer : Helga Rudolf Waldemar Brem : Paul Elga Sorbas : Rosy Doris Mattes : Gunda Irm Hermann : Elisabeth Peter Moland : Peter Rainer Werner Fassbinder : Jorgos Hans Hirschmüller : Erich Harry Baer : Franz Hannes Gromball : Klaus Katrin Schaake : la femme sur la route | P6: Format : noir et blanc, 1,37:1, mono Genre : drame, romance Sortie : 1969 | Q6: Jorgos, travailleur immigré grec, rejoint un groupe de jeunes gens à Munich. Son arrivée suscite hostilité et jalousie ; insulté, il confie à Marie son désir de rentrer chez lui. | S6: Le film dénonce la violence exercée par une société étriquée contre les étrnagers, violence que le personnage principal, d'origine grecque, reconduit avec des individus encore plus dominés que lui. Film à l'esthétique avant-gardiste, brechtienne par son caractère anti-illustionniste. Il est constitué d'une suite de brefs tableaux, d'images figées, de plans fontaux. Les mouvements de caméra sont rares : des travellings latéraux, sans profondeur d'images, conservent une forme de théâtralité à l'image. Comme d'autres films de RWF de la période, Le bouc vise un public qui n'est ni restreint et cinéphile, ni populaire. | U6: Films_images/Le_Bouc.jpg | X6: 1969 | Z6: Wikipédia : https://fr.wikipedia.org/wiki/Le_Bouc | AA6: À compléter | AB6: film-1969-le-bouc | AC6: =IF(O6="","",_xlfn.TEXTJOIN("; ",TRUE,IF(ISNUMBER(SEARCH('Référentiel entourage'!$B$2,O6)),'Référentiel entourage'!$A$2,""),IF(ISNUMBER(SEARCH('Référentiel entourage'!$B$3,O6)),'Référentiel entourage'!$A$3,""),IF(ISNUMBER(SEARCH('Référentiel entourage'!$B$4,O6)),'Référentiel entourage'!$A$4,""),IF(ISNUMBER(SEARCH('Référentiel entourage'!$B$5,O6)),'Référentiel entourage'!$A$5,""),IF(ISNUMBER(SEARCH('Référentiel entourage'!$B$6,O6)),'Référentiel entourage'!$A$6,""),IF(ISNUMBER(SEARCH('Référentiel entourage'!$B$7,O6)),'Référentiel entourage'!$A$7,""),IF(ISNUMBER(SEARCH('Référentiel entourage'!$B$8,O6)),'Référentiel entourage'!$A$8,""),IF(ISNUMBER(SEARCH('Référentiel entourage'!$B$9,O6)),'Référentiel entourage'!$A$9,""),IF(ISNUMBER(SEARCH('Référentiel entourage'!$B$10,O6)),'Référentiel entourage'!$A$10,""),IF(ISNUMBER(SEARCH('Référentiel entourage'!$B$11,O6)),'Référentiel entourage'!$A$11,""),IF(ISNUMBER(SEARCH('Référentiel entourage'!$B$12,O6)),'Référentiel entourage'!$A$12,""),IF(ISNUMBER(SEARCH('Référentiel entourage'!$B$13,O6)),'Référentiel entourage'!$A$13,""),IF(ISNUMBER(SEARCH('Référentiel entourage'!$B$14,O6)),'Référentiel entourage'!$A$14,""),IF(ISNUMBER(SEARCH('Référentiel entourage'!$B$15,O6)),'Référentiel entourage'!$A$15,""),IF(ISNUMBER(SEARCH('Référentiel entourage'!$B$16,O6)),'Référentiel entourage'!$A$16,""),IF(ISNUMBER(SEARCH('Référentiel entourage'!$B$17,O6)),'Référentiel entourage'!$A$17,""),IF(ISNUMBER(SEARCH('Référentiel entourage'!$B$18,O6)),'Référentiel entourage'!$A$18,""),IF(ISNUMBER(SEARCH('Référentiel entourage'!$B$19,O6)),'Référentiel entourage'!$A$19,""),IF(ISNUMBER(SEARCH('Référentiel entourage'!$B$20,O6)),'Référentiel entourage'!$A$20,""),IF(ISNUMBER(SEARCH('Référentiel entourage'!$B$21,O6)),'Référentiel entourage'!$A$21,""),IF(ISNUMBER(SEARCH('Référentiel entourage'!$B$22,O6)),'Référentiel entourage'!$A$22,""),IF(ISNUMBER(SEARCH('Référentiel entourage'!$B$23,O6)),'Référentiel entourage'!$A$23,""),IF(ISNUMBER(SEARCH('Référentiel entourage'!$B$24,O6)),'Référentiel entourage'!$A$24,""))) -> pers-irm-hermann; pers-hanna-schygulla; pers-lilith-ungerer | AD6: =_xlfn.LET(_xlpm.texte,_xlfn.TEXTJOIN(" | ",TRUE,H6:N6,P6),IF(_xlpm.texte="","",_xlfn.TEXTJOIN("; ",TRUE,IF(ISNUMBER(SEARCH('Référentiel entourage'!$B$2,_xlpm.texte)),'Référentiel entourage'!$A$2,""),IF(ISNUMBER(SEARCH('Référentiel entourage'!$B$3,_xlpm.texte)),'Référentiel entourage'!$A$3,""),IF(ISNUMBER(SEARCH('Référentiel entourage'!$B$4,_xlpm.texte)),'Référentiel entourage'!$A$4,""),IF(ISNUMBER(SEARCH('Référentiel entourage'!$B$5,_xlpm.texte)),'Référentiel entourage'!$A$5,""),IF(ISNUMBER(SEARCH('Référentiel entourage'!$B$6,_xlpm.texte)),'Référentiel entourage'!$A$6,""),IF(ISNUMBER(SEARCH('Référentiel entourage'!$B$7,_xlpm.texte)),'Référentiel entourage'!$A$7,""),IF(ISNUMBER(SEARCH('Référentiel entourage'!$B$8,_xlpm.texte)),'Référentiel entourage'!$A$8,""),IF(ISNUMBER(SEARCH('Référentiel entourage'!$B$9,_xlpm.texte)),'Référentiel entourage'!$A$9,""),IF(ISNUMBER(SEARCH('Référentiel entourage'!$B$10,_xlpm.texte)),'Référentiel entourage'!$A$10,""),IF(ISNUMBER(SEARCH('Référentiel entourage'!$B$11,_xlpm.texte)),'Référentiel entourage'!$A$11,""),IF(ISNUMBER(SEARCH('Référentiel entourage'!$B$12,_xlpm.texte)),'Référentiel entourage'!$A$12,""),IF(ISNUMBER(SEARCH('Référentiel entourage'!$B$13,_xlpm.texte)),'Référentiel entourage'!$A$13,""),IF(ISNUMBER(SEARCH('Référentiel entourage'!$B$14,_xlpm.texte)),'Référentiel entourage'!$A$14,""),IF(ISNUMBER(SEARCH('Référentiel entourage'!$B$15,_xlpm.texte)),'Référentiel entourage'!$A$15,""),IF(ISNUMBER(SEARCH('Référentiel entourage'!$B$16,_xlpm.texte)),'Référentiel entourage'!$A$16,""),IF(ISNUMBER(SEARCH('Référentiel entourage'!$B$17,_xlpm.texte)),'Référentiel entourage'!$A$17,""),IF(ISNUMBER(SEARCH('Référentiel entourage'!$B$18,_xlpm.texte)),'Référentiel entourage'!$A$18,""),IF(ISNUMBER(SEARCH('Référentiel entourage'!$B$19,_xlpm.texte)),'Référentiel entourage'!$A$19,""),IF(ISNUMBER(SEARCH('Référentiel entourage'!$B$20,_xlpm.texte)),'Référentiel entourage'!$A$20,""),IF(ISNUMBER(SEARCH('Référentiel entourage'!$B$21,_xlpm.texte)),'Référentiel entourage'!$A$21,""),IF(ISNUMBER(SEARCH('Référentiel entourage'!$B$22,_xlpm.texte)),'Référentiel entourage'!$A$22,""),IF(ISNUMBER(SEARCH('Référentiel entourage'!$B$23,_xlpm.texte)),'Référentiel entourage'!$A$23,""),IF(ISNUMBER(SEARCH('Référentiel entourage'!$B$24,_xlpm.texte)),'Référentiel entourage'!$A$24,"")))) -> pers-peer-raben
A7: rwf-1970-les-dieux-de-la-peste | B7: Les Dieux de la peste | C7: Götter der Pest | D7: 1970 | E7: Long métrage | F7: 91 | G7: RFA | H7: Rainer Werner Fassbinder | I7: Rainer Werner Fassbinder | J7: Dietrich Lohmann | K7: Rainer Werner Fassbinder | L7: Kurt Raab | M7: Peer Raben | N7: Rainer Werner Fassbinder ; Michael Fengler | O7: Hanna Schygulla : Johanna Reiher Margarethe von Trotta : Margarethe Harry Baer : Franz Walsch Günther Kaufmann : Günther Carla Aulalu : Carla Ingrid Caven : Magdalena Fuller Lilith Ungerer : la jeune fille du premier café Katrin Schaake : la propriétaire du deuxième café Hannes Gromball : le directeur du supermarché Jan George : un policier Micha Cochina : Joe Lilo Pempeit : la mère Marian Seidowski : Marian Yaak Karsunke : le commissaire Rainer Werner Fassbinder : l’homme qui achète des revues pornographiques | P7: Format : noir et blanc, 35 mm, 1,37:1, mono Genre : drame Sortie : 1970 | Q7: À sa sortie de prison, le petit escroc Franz Walsch retrouve Joanna. Il recherche le « gorille », vieux gangster qui a assassiné son frère, mais décide néanmoins de refaire équipe avec lui pour un dernier braquage. | U7: Films_images/Les_Dieux_de_la_peste.jpg | X7: 1970 | Z7: Wikipédia : https://fr.wikipedia.org/wiki/Les_Dieux_de_la_peste | AA7: À compléter | AB7: film-1970-les-dieux-de-la-peste | AC7: =IF(O7="","",_xlfn.TEXTJOIN("; ",TRUE,IF(ISNUMBER(SEARCH('Référentiel entourage'!$B$2,O7)),'Référentiel entourage'!$A$2,""),IF(ISNUMBER(SEARCH('Référentiel entourage'!$B$3,O7)),'Référentiel entourage'!$A$3,""),IF(ISNUMBER(SEARCH('Référentiel entourage'!$B$4,O7)),'Référentiel entourage'!$A$4,""),IF(ISNUMBER(SEARCH('Référentiel entourage'!$B$5,O7)),'Référentiel entourage'!$A$5,""),IF(ISNUMBER(SEARCH('Référentiel entourage'!$B$6,O7)),'Référentiel entourage'!$A$6,""),IF(ISNUMBER(SEARCH('Référentiel entourage'!$B$7,O7)),'Référentiel entourage'!$A$7,""),IF(ISNUMBER(SEARCH('Référentiel entourage'!$B$8,O7)),'Référentiel entourage'!$A$8,""),IF(ISNUMBER(SEARCH('Référentiel entourage'!$B$9,O7)),'Référentiel entourage'!$A$9,""),IF(ISNUMBER(SEARCH('Référentiel entourage'!$B$10,O7)),'Référentiel entourage'!$A$10,""),IF(ISNUMBER(SEARCH('Référentiel entourage'!$B$11,O7)),'Référentiel entourage'!$A$11,""),IF(ISNUMBER(SEARCH('Référentiel entourage'!$B$12,O7)),'Référentiel entourage'!$A$12,""),IF(ISNUMBER(SEARCH('Référentiel entourage'!$B$13,O7)),'Référentiel entourage'!$A$13,""),IF(ISNUMBER(SEARCH('Référentiel entourage'!$B$14,O7)),'Référentiel entourage'!$A$14,""),IF(ISNUMBER(SEARCH('Référentiel entourage'!$B$15,O7)),'Référentiel entourage'!$A$15,""),IF(ISNUMBER(SEARCH('Référentiel entourage'!$B$16,O7)),'Référentiel entourage'!$A$16,""),IF(ISNUMBER(SEARCH('Référentiel entourage'!$B$17,O7)),'Référentiel entourage'!$A$17,""),IF(ISNUMBER(SEARCH('Référentiel entourage'!$B$18,O7)),'Référentiel entourage'!$A$18,""),IF(ISNUMBER(SEARCH('Référentiel entourage'!$B$19,O7)),'Référentiel entourage'!$A$19,""),IF(ISNUMBER(SEARCH('Référentiel entourage'!$B$20,O7)),'Référentiel entourage'!$A$20,""),IF(ISNUMBER(SEARCH('Référentiel entourage'!$B$21,O7)),'Référentiel entourage'!$A$21,""),IF(ISNUMBER(SEARCH('Référentiel entourage'!$B$22,O7)),'Référentiel entourage'!$A$22,""),IF(ISNUMBER(SEARCH('Référentiel entourage'!$B$23,O7)),'Référentiel entourage'!$A$23,""),IF(ISNUMBER(SEARCH('Référentiel entourage'!$B$24,O7)),'Référentiel entourage'!$A$24,""))) -> pers-ingrid-caven; pers-lilo-pempeit; pers-gunther-kaufmann; pers-hanna-schygulla; pers-lilith-ungerer | AD7: =_xlfn.LET(_xlpm.texte,_xlfn.TEXTJOIN(" | ",TRUE,H7:N7,P7),IF(_xlpm.texte="","",_xlfn.TEXTJOIN("; ",TRUE,IF(ISNUMBER(SEARCH('Référentiel entourage'!$B$2,_xlpm.texte)),'Référentiel entourage'!$A$2,""),IF(ISNUMBER(SEARCH('Référentiel entourage'!$B$3,_xlpm.texte)),'Référentiel entourage'!$A$3,""),IF(ISNUMBER(SEARCH('Référentiel entourage'!$B$4,_xlpm.texte)),'Référentiel entourage'!$A$4,""),IF(ISNUMBER(SEARCH('Référentiel entourage'!$B$5,_xlpm.texte)),'Référentiel entourage'!$A$5,""),IF(ISNUMBER(SEARCH('Référentiel entourage'!$B$6,_xlpm.texte)),'Référentiel entourage'!$A$6,""),IF(ISNUMBER(SEARCH('Référentiel entourage'!$B$7,_xlpm.texte)),'Référentiel entourage'!$A$7,""),IF(ISNUMBER(SEARCH('Référentiel entourage'!$B$8,_xlpm.texte)),'Référentiel entourage'!$A$8,""),IF(ISNUMBER(SEARCH('Référentiel entourage'!$B$9,_xlpm.texte)),'Référentiel entourage'!$A$9,""),IF(ISNUMBER(SEARCH('Référentiel entourage'!$B$10,_xlpm.texte)),'Référentiel entourage'!$A$10,""),IF(ISNUMBER(SEARCH('Référentiel entourage'!$B$11,_xlpm.texte)),'Référentiel entourage'!$A$11,""),IF(ISNUMBER(SEARCH('Référentiel entourage'!$B$12,_xlpm.texte)),'Référentiel entourage'!$A$12,""),IF(ISNUMBER(SEARCH('Référentiel entourage'!$B$13,_xlpm.texte)),'Référentiel entourage'!$A$13,""),IF(ISNUMBER(SEARCH('Référentiel entourage'!$B$14,_xlpm.texte)),'Référentiel entourage'!$A$14,""),IF(ISNUMBER(SEARCH('Référentiel entourage'!$B$15,_xlpm.texte)),'Référentiel entourage'!$A$15,""),IF(ISNUMBER(SEARCH('Référentiel entourage'!$B$16,_xlpm.texte)),'Référentiel entourage'!$A$16,""),IF(ISNUMBER(SEARCH('Référentiel entourage'!$B$17,_xlpm.texte)),'Référentiel entourage'!$A$17,""),IF(ISNUMBER(SEARCH('Référentiel entourage'!$B$18,_xlpm.texte)),'Référentiel entourage'!$A$18,""),IF(ISNUMBER(SEARCH('Référentiel entourage'!$B$19,_xlpm.texte)),'Référentiel entourage'!$A$19,""),IF(ISNUMBER(SEARCH('Référentiel entourage'!$B$20,_xlpm.texte)),'Référentiel entourage'!$A$20,""),IF(ISNUMBER(SEARCH('Référentiel entourage'!$B$21,_xlpm.texte)),'Référentiel entourage'!$A$21,""),IF(ISNUMBER(SEARCH('Référentiel entourage'!$B$22,_xlpm.texte)),'Référentiel entourage'!$A$22,""),IF(ISNUMBER(SEARCH('Référentiel entourage'!$B$23,_xlpm.texte)),'Référentiel entourage'!$A$23,""),IF(ISNUMBER(SEARCH('Référentiel entourage'!$B$24,_xlpm.texte)),'Référentiel entourage'!$A$24,"")))) -> pers-michael-fengler; pers-kurt-raab; pers-peer-raben
A8: rwf-1970-pourquoi-m-r-est-il-atteint-de-folie-meurtriere | B8: Pourquoi M. R. est-il atteint de folie meurtrière ? | C8: Warum läuft Herr R. Amok? | D8: 1970 | E8: Long métrage | F8: 88 | G8: RFA | H8: Rainer Werner Fassbinder et Michael Fengler | I8: Rainer Werner Fassbinder ; Michael Fengler | J8: Dietrich Lohmann | K8: Rainer Werner Fassbinder ; Michael Fengler | L8: Kurt Raab | M8: Peer Raben | N8: Michael Fengler ; Peer Raben | O8: Kurt Raab : Monsieur R. Lilith Ungerer : Madame R. Lilo Pempeit : une collègue de bureau Franz Maron : le chef Harry Baer : un collègue de bureau Peter Moland : un collègue de bureau Hanna Schygulla : l’amie dans le bar Ingrid Caven : une voisine Peer Raben : un ami Doris Mattes : une voisine Irm Hermann : une voisine Amadeus Fengler : Amadeus, le fils Carla Aulalu : une vendeuse du magasin de disques Eva Pampusch : une vendeuse du magasin de disques Peter Hamm : un commissaire Jochen Pinkert : un commissaire | P8: Format : couleur, 35 mm, 1,37:1, mono Genre : drame Sortie : 1970 | Q8: Le film montre la vie quotidienne de Monsieur R., dessinateur industriel quadragénaire, mari et père de famille. | X8: 1970 | Z8: Wikipédia : https://fr.wikipedia.org/wiki/Pourquoi_monsieur_R._est-il_atteint_de_folie_meurtri%C3%A8re_%3F | AA8: À compléter | AB8: film-1970-pourquoi-m-r-est-il-atteint-de-folie-meurtriere | AC8: =IF(O8="","",_xlfn.TEXTJOIN("; ",TRUE,IF(ISNUMBER(SEARCH('Référentiel entourage'!$B$2,O8)),'Référentiel entourage'!$A$2,""),IF(ISNUMBER(SEARCH('Référentiel entourage'!$B$3,O8)),'Référentiel entourage'!$A$3,""),IF(ISNUMBER(SEARCH('Référentiel entourage'!$B$4,O8)),'Référentiel entourage'!$A$4,""),IF(ISNUMBER(SEARCH('Référentiel entourage'!$B$5,O8)),'Référentiel entourage'!$A$5,""),IF(ISNUMBER(SEARCH('Référentiel entourage'!$B$6,O8)),'Référentiel entourage'!$A$6,""),IF(ISNUMBER(SEARCH('Référentiel entourage'!$B$7,O8)),'Référentiel entourage'!$A$7,""),IF(ISNUMBER(SEARCH('Référentiel entourage'!$B$8,O8)),'Référentiel entourage'!$A$8,""),IF(ISNUMBER(SEARCH('Référentiel entourage'!$B$9,O8)),'Référentiel entourage'!$A$9,""),IF(ISNUMBER(SEARCH('Référentiel entourage'!$B$10,O8)),'Référentiel entourage'!$A$10,""),IF(ISNUMBER(SEARCH('Référentiel entourage'!$B$11,O8)),'Référentiel entourage'!$A$11,""),IF(ISNUMBER(SEARCH('Référentiel entourage'!$B$12,O8)),'Référentiel entourage'!$A$12,""),IF(ISNUMBER(SEARCH('Référentiel entourage'!$B$13,O8)),'Référentiel entourage'!$A$13,""),IF(ISNUMBER(SEARCH('Référentiel entourage'!$B$14,O8)),'Référentiel entourage'!$A$14,""),IF(ISNUMBER(SEARCH('Référentiel entourage'!$B$15,O8)),'Référentiel entourage'!$A$15,""),IF(ISNUMBER(SEARCH('Référentiel entourage'!$B$16,O8)),'Référentiel entourage'!$A$16,""),IF(ISNUMBER(SEARCH('Référentiel entourage'!$B$17,O8)),'Référentiel entourage'!$A$17,""),IF(ISNUMBER(SEARCH('Référentiel entourage'!$B$18,O8)),'Référentiel entourage'!$A$18,""),IF(ISNUMBER(SEARCH('Référentiel entourage'!$B$19,O8)),'Référentiel entourage'!$A$19,""),IF(ISNUMBER(SEARCH('Référentiel entourage'!$B$20,O8)),'Référentiel entourage'!$A$20,""),IF(ISNUMBER(SEARCH('Référentiel entourage'!$B$21,O8)),'Référentiel entourage'!$A$21,""),IF(ISNUMBER(SEARCH('Référentiel entourage'!$B$22,O8)),'Référentiel entourage'!$A$22,""),IF(ISNUMBER(SEARCH('Référentiel entourage'!$B$23,O8)),'Référentiel entourage'!$A$23,""),IF(ISNUMBER(SEARCH('Référentiel entourage'!$B$24,O8)),'Référentiel entourage'!$A$24,""))) -> pers-ingrid-caven; pers-lilo-pempeit; pers-irm-hermann; pers-kurt-raab; pers-peer-raben; pers-hanna-schygulla; pers-lilith-ungerer | AD8: =_xlfn.LET(_xlpm.texte,_xlfn.TEXTJOIN(" | ",TRUE,H8:N8,P8),IF(_xlpm.texte="","",_xlfn.TEXTJOIN("; ",TRUE,IF(ISNUMBER(SEARCH('Référentiel entourage'!$B$2,_xlpm.texte)),'Référentiel entourage'!$A$2,""),IF(ISNUMBER(SEARCH('Référentiel entourage'!$B$3,_xlpm.texte)),'Référentiel entourage'!$A$3,""),IF(ISNUMBER(SEARCH('Référentiel entourage'!$B$4,_xlpm.texte)),'Référentiel entourage'!$A$4,""),IF(ISNUMBER(SEARCH('Référentiel entourage'!$B$5,_xlpm.texte)),'Référentiel entourage'!$A$5,""),IF(ISNUMBER(SEARCH('Référentiel entourage'!$B$6,_xlpm.texte)),'Référentiel entourage'!$A$6,""),IF(ISNUMBER(SEARCH('Référentiel entourage'!$B$7,_xlpm.texte)),'Référentiel entourage'!$A$7,""),IF(ISNUMBER(SEARCH('Référentiel entourage'!$B$8,_xlpm.texte)),'Référentiel entourage'!$A$8,""),IF(ISNUMBER(SEARCH('Référentiel entourage'!$B$9,_xlpm.texte)),'Référentiel entourage'!$A$9,""),IF(ISNUMBER(SEARCH('Référentiel entourage'!$B$10,_xlpm.texte)),'Référentiel entourage'!$A$10,""),IF(ISNUMBER(SEARCH('Référentiel entourage'!$B$11,_xlpm.texte)),'Référentiel entourage'!$A$11,""),IF(ISNUMBER(SEARCH('Référentiel entourage'!$B$12,_xlpm.texte)),'Référentiel entourage'!$A$12,""),IF(ISNUMBER(SEARCH('Référentiel entourage'!$B$13,_xlpm.texte)),'Référentiel entourage'!$A$13,""),IF(ISNUMBER(SEARCH('Référentiel entourage'!$B$14,_xlpm.texte)),'Référentiel entourage'!$A$14,""),IF(ISNUMBER(SEARCH('Référentiel entourage'!$B$15,_xlpm.texte)),'Référentiel entourage'!$A$15,""),IF(ISNUMBER(SEARCH('Référentiel entourage'!$B$16,_xlpm.texte)),'Référentiel entourage'!$A$16,""),IF(ISNUMBER(SEARCH('Référentiel entourage'!$B$17,_xlpm.texte)),'Référentiel entourage'!$A$17,""),IF(ISNUMBER(SEARCH('Référentiel entourage'!$B$18,_xlpm.texte)),'Référentiel entourage'!$A$18,""),IF(ISNUMBER(SEARCH('Référentiel entourage'!$B$19,_xlpm.texte)),'Référentiel entourage'!$A$19,""),IF(ISNUMBER(SEARCH('Référentiel entourage'!$B$20,_xlpm.texte)),'Référentiel entourage'!$A$20,""),IF(ISNUMBER(SEARCH('Référentiel entourage'!$B$21,_xlpm.texte)),'Référentiel entourage'!$A$21,""),IF(ISNUMBER(SEARCH('Référentiel entourage'!$B$22,_xlpm.texte)),'Référentiel entourage'!$A$22,""),IF(ISNUMBER(SEARCH('Référentiel entourage'!$B$23,_xlpm.texte)),'Référentiel entourage'!$A$23,""),IF(ISNUMBER(SEARCH('Référentiel entourage'!$B$24,_xlpm.texte)),'Référentiel entourage'!$A$24,"")))) -> pers-michael-fengler; pers-kurt-raab; pers-peer-raben
A9: rwf-1970-le-soldat-americain | B9: Le Soldat américain | C9: Der amerikanische Soldat | D9: 1970 | E9: Long métrage | F9: 80 | G9: RFA | H9: Rainer Werner Fassbinder | I9: Rainer Werner Fassbinder | J9: Dietrich Lohmann | K9: Thea Eymèsz | L9: Kurt Raab ; Rainer Werner Fassbinder | M9: Peer Raben | N9: Antiteater-X-Film | O9: Karl Scheydt : Richard Murphy, dit Ricky Elga Sorbas : Rosa Jan George : Jan Margarethe von Trotta : la femme de chambre Hark Bohm : Doc Ingrid Caven : la chanteuse Eva Ingeborg Scholz : la mère de Ricky Kurt Raab : le frère de Ricky Marius Aicher : un policier Gustl Datz : le chef de la police Marquard Bohm : le détective privé Rainer Werner Fassbinder : Franz Katrin Schaake : Magdalena Fuller Ulli Lommel : un Tzigane Irm Hermann : une prostituée | P9: Langue : allemand Format : noir et blanc, 35 mm, 1,33:1, mono Tournage : 15 jours en août 1970, Munich Sortie RFA : 9 octobre 1970 (festival), puis 27 novembre 1970 | Q9: À Munich, trois policiers recrutent Ricky, tueur à gages natif de la ville revenu du Vietnam, afin d’éliminer plusieurs personnes. | U9: Films_images/Le_Soldat_americain.jpg | X9: 1970 | Z9: Wikipédia : https://fr.wikipedia.org/wiki/Le_Soldat_am%C3%A9ricain | AA9: À compléter | AB9: film-1970-le-soldat-americain | AC9: =IF(O9="","",_xlfn.TEXTJOIN("; ",TRUE,IF(ISNUMBER(SEARCH('Référentiel entourage'!$B$2,O9)),'Référentiel entourage'!$A$2,""),IF(ISNUMBER(SEARCH('Référentiel entourage'!$B$3,O9)),'Référentiel entourage'!$A$3,""),IF(ISNUMBER(SEARCH('Référentiel entourage'!$B$4,O9)),'Référentiel entourage'!$A$4,""),IF(ISNUMBER(SEARCH('Référentiel entourage'!$B$5,O9)),'Référentiel entourage'!$A$5,""),IF(ISNUMBER(SEARCH('Référentiel entourage'!$B$6,O9)),'Référentiel entourage'!$A$6,""),IF(ISNUMBER(SEARCH('Référentiel entourage'!$B$7,O9)),'Référentiel entourage'!$A$7,""),IF(ISNUMBER(SEARCH('Référentiel entourage'!$B$8,O9)),'Référentiel entourage'!$A$8,""),IF(ISNUMBER(SEARCH('Référentiel entourage'!$B$9,O9)),'Référentiel entourage'!$A$9,""),IF(ISNUMBER(SEARCH('Référentiel entourage'!$B$10,O9)),'Référentiel entourage'!$A$10,""),IF(ISNUMBER(SEARCH('Référentiel entourage'!$B$11,O9)),'Référentiel entourage'!$A$11,""),IF(ISNUMBER(SEARCH('Référentiel entourage'!$B$12,O9)),'Référentiel entourage'!$A$12,""),IF(ISNUMBER(SEARCH('Référentiel entourage'!$B$13,O9)),'Référentiel entourage'!$A$13,""),IF(ISNUMBER(SEARCH('Référentiel entourage'!$B$14,O9)),'Référentiel entourage'!$A$14,""),IF(ISNUMBER(SEARCH('Référentiel entourage'!$B$15,O9)),'Référentiel entourage'!$A$15,""),IF(ISNUMBER(SEARCH('Référentiel entourage'!$B$16,O9)),'Référentiel entourage'!$A$16,""),IF(ISNUMBER(SEARCH('Référentiel entourage'!$B$17,O9)),'Référentiel entourage'!$A$17,""),IF(ISNUMBER(SEARCH('Référentiel entourage'!$B$18,O9)),'Référentiel entourage'!$A$18,""),IF(ISNUMBER(SEARCH('Référentiel entourage'!$B$19,O9)),'Référentiel entourage'!$A$19,""),IF(ISNUMBER(SEARCH('Référentiel entourage'!$B$20,O9)),'Référentiel entourage'!$A$20,""),IF(ISNUMBER(SEARCH('Référentiel entourage'!$B$21,O9)),'Référentiel entourage'!$A$21,""),IF(ISNUMBER(SEARCH('Référentiel entourage'!$B$22,O9)),'Référentiel entourage'!$A$22,""),IF(ISNUMBER(SEARCH('Référentiel entourage'!$B$23,O9)),'Référentiel entourage'!$A$23,""),IF(ISNUMBER(SEARCH('Référentiel entourage'!$B$24,O9)),'Référentiel entourage'!$A$24,""))) -> pers-hark-bohm; pers-ingrid-caven; pers-irm-hermann; pers-ulli-lommel; pers-kurt-raab | AD9: =_xlfn.LET(_xlpm.texte,_xlfn.TEXTJOIN(" | ",TRUE,H9:N9,P9),IF(_xlpm.texte="","",_xlfn.TEXTJOIN("; ",TRUE,IF(ISNUMBER(SEARCH('Référentiel entourage'!$B$2,_xlpm.texte)),'Référentiel entourage'!$A$2,""),IF(ISNUMBER(SEARCH('Référentiel entourage'!$B$3,_xlpm.texte)),'Référentiel entourage'!$A$3,""),IF(ISNUMBER(SEARCH('Référentiel entourage'!$B$4,_xlpm.texte)),'Référentiel entourage'!$A$4,""),IF(ISNUMBER(SEARCH('Référentiel entourage'!$B$5,_xlpm.texte)),'Référentiel entourage'!$A$5,""),IF(ISNUMBER(SEARCH('Référentiel entourage'!$B$6,_xlpm.texte)),'Référentiel entourage'!$A$6,""),IF(ISNUMBER(SEARCH('Référentiel entourage'!$B$7,_xlpm.texte)),'Référentiel entourage'!$A$7,""),IF(ISNUMBER(SEARCH('Référentiel entourage'!$B$8,_xlpm.texte)),'Référentiel entourage'!$A$8,""),IF(ISNUMBER(SEARCH('Référentiel entourage'!$B$9,_xlpm.texte)),'Référentiel entourage'!$A$9,""),IF(ISNUMBER(SEARCH('Référentiel entourage'!$B$10,_xlpm.texte)),'Référentiel entourage'!$A$10,""),IF(ISNUMBER(SEARCH('Référentiel entourage'!$B$11,_xlpm.texte)),'Référentiel entourage'!$A$11,""),IF(ISNUMBER(SEARCH('Référentiel entourage'!$B$12,_xlpm.texte)),'Référentiel entourage'!$A$12,""),IF(ISNUMBER(SEARCH('Référentiel entourage'!$B$13,_xlpm.texte)),'Référentiel entourage'!$A$13,""),IF(ISNUMBER(SEARCH('Référentiel entourage'!$B$14,_xlpm.texte)),'Référentiel entourage'!$A$14,""),IF(ISNUMBER(SEARCH('Référentiel entourage'!$B$15,_xlpm.texte)),'Référentiel entourage'!$A$15,""),IF(ISNUMBER(SEARCH('Référentiel entourage'!$B$16,_xlpm.texte)),'Référentiel entourage'!$A$16,""),IF(ISNUMBER(SEARCH('Référentiel entourage'!$B$17,_xlpm.texte)),'Référentiel entourage'!$A$17,""),IF(ISNUMBER(SEARCH('Référentiel entourage'!$B$18,_xlpm.texte)),'Référentiel entourage'!$A$18,""),IF(ISNUMBER(SEARCH('Référentiel entourage'!$B$19,_xlpm.texte)),'Référentiel entourage'!$A$19,""),IF(ISNUMBER(SEARCH('Référentiel entourage'!$B$20,_xlpm.texte)),'Référentiel entourage'!$A$20,""),IF(ISNUMBER(SEARCH('Référentiel entourage'!$B$21,_xlpm.texte)),'Référentiel entourage'!$A$21,""),IF(ISNUMBER(SEARCH('Référentiel entourage'!$B$22,_xlpm.texte)),'Référentiel entourage'!$A$22,""),IF(ISNUMBER(SEARCH('Référentiel entourage'!$B$23,_xlpm.texte)),'Référentiel entourage'!$A$23,""),IF(ISNUMBER(SEARCH('Référentiel entourage'!$B$24,_xlpm.texte)),'Référentiel entourage'!$A$24,"")))) -> pers-kurt-raab; pers-peer-raben
A10: rwf-1970-le-voyage-a-niklashausen | B10: Le Voyage à Niklashausen | C10: Die Niklashauser Fart | D10: 1970 | E10: Téléfilm | F10: 90 | G10: RFA | H10: Rainer Werner Fassbinder | I10: Rainer Werner Fassbinder ; Michael Fengler | J10: Dietrich Lohmann | K10: Thea Eymèsz ; Rainer Werner Fassbinder | L10: Kurt Raab | M10: Peer Raben | N10: Janus Film und Fernsehen | O10: Michael König : Hans Boehm Hanna Schygulla : Johanna Margit Carstensen : Margarethe Franz Maron : le mari de Margarethe Michael Gordon : Antonio Günther Kaufmann : le chef des fermiers Siggi Graue : le premier paysan Michael Fengler : le deuxième paysan Elga Sorbas : la jeune fille évanouie Carla Aulalu : la jeune fille épileptique Kurt Raab : l’évêque Peter Berling : le bourreau Ingrid Caven : la fille qui crie Peer Raben : Monseigneur Rainer Werner Fassbinder : le moine noir Walter Sedlmayr : le prêtre Günther Rupp : le conseiller Karl Scheydt : un bourgeois de Niklashausen Magdalena Montezuma : Penthésilée | P10: Format : couleur, mono Genre : drame Diffusion : 1970 | X10: 1970 | Z10: Wikipédia : https://fr.wikipedia.org/wiki/Le_Voyage_%C3%A0_Niklashausen | AA10: À compléter | AB10: film-1970-le-voyage-a-niklashausen | AC10: =IF(O10="","",_xlfn.TEXTJOIN("; ",TRUE,IF(ISNUMBER(SEARCH('Référentiel entourage'!$B$2,O10)),'Référentiel entourage'!$A$2,""),IF(ISNUMBER(SEARCH('Référentiel entourage'!$B$3,O10)),'Référentiel entourage'!$A$3,""),IF(ISNUMBER(SEARCH('Référentiel entourage'!$B$4,O10)),'Référentiel entourage'!$A$4,""),IF(ISNUMBER(SEARCH('Référentiel entourage'!$B$5,O10)),'Référentiel entourage'!$A$5,""),IF(ISNUMBER(SEARCH('Référentiel entourage'!$B$6,O10)),'Référentiel entourage'!$A$6,""),IF(ISNUMBER(SEARCH('Référentiel entourage'!$B$7,O10)),'Référentiel entourage'!$A$7,""),IF(ISNUMBER(SEARCH('Référentiel entourage'!$B$8,O10)),'Référentiel entourage'!$A$8,""),IF(ISNUMBER(SEARCH('Référentiel entourage'!$B$9,O10)),'Référentiel entourage'!$A$9,""),IF(ISNUMBER(SEARCH('Référentiel entourage'!$B$10,O10)),'Référentiel entourage'!$A$10,""),IF(ISNUMBER(SEARCH('Référentiel entourage'!$B$11,O10)),'Référentiel entourage'!$A$11,""),IF(ISNUMBER(SEARCH('Référentiel entourage'!$B$12,O10)),'Référentiel entourage'!$A$12,""),IF(ISNUMBER(SEARCH('Référentiel entourage'!$B$13,O10)),'Référentiel entourage'!$A$13,""),IF(ISNUMBER(SEARCH('Référentiel entourage'!$B$14,O10)),'Référentiel entourage'!$A$14,""),IF(ISNUMBER(SEARCH('Référentiel entourage'!$B$15,O10)),'Référentiel entourage'!$A$15,""),IF(ISNUMBER(SEARCH('Référentiel entourage'!$B$16,O10)),'Référentiel entourage'!$A$16,""),IF(ISNUMBER(SEARCH('Référentiel entourage'!$B$17,O10)),'Référentiel entourage'!$A$17,""),IF(ISNUMBER(SEARCH('Référentiel entourage'!$B$18,O10)),'Référentiel entourage'!$A$18,""),IF(ISNUMBER(SEARCH('Référentiel entourage'!$B$19,O10)),'Référentiel entourage'!$A$19,""),IF(ISNUMBER(SEARCH('Référentiel entourage'!$B$20,O10)),'Référentiel entourage'!$A$20,""),IF(ISNUMBER(SEARCH('Référentiel entourage'!$B$21,O10)),'Référentiel entourage'!$A$21,""),IF(ISNUMBER(SEARCH('Référentiel entourage'!$B$22,O10)),'Référentiel entourage'!$A$22,""),IF(ISNUMBER(SEARCH('Référentiel entourage'!$B$23,O10)),'Référentiel entourage'!$A$23,""),IF(ISNUMBER(SEARCH('Référentiel entourage'!$B$24,O10)),'Référentiel entourage'!$A$24,""))) -> pers-margit-carstensen; pers-ingrid-caven; pers-michael-fengler; pers-gunther-kaufmann; pers-kurt-raab; pers-peer-raben; pers-hanna-schygulla | AD10: =_xlfn.LET(_xlpm.texte,_xlfn.TEXTJOIN(" | ",TRUE,H10:N10,P10),IF(_xlpm.texte="","",_xlfn.TEXTJOIN("; ",TRUE,IF(ISNUMBER(SEARCH('Référentiel entourage'!$B$2,_xlpm.texte)),'Référentiel entourage'!$A$2,""),IF(ISNUMBER(SEARCH('Référentiel entourage'!$B$3,_xlpm.texte)),'Référentiel entourage'!$A$3,""),IF(ISNUMBER(SEARCH('Référentiel entourage'!$B$4,_xlpm.texte)),'Référentiel entourage'!$A$4,""),IF(ISNUMBER(SEARCH('Référentiel entourage'!$B$5,_xlpm.texte)),'Référentiel entourage'!$A$5,""),IF(ISNUMBER(SEARCH('Référentiel entourage'!$B$6,_xlpm.texte)),'Référentiel entourage'!$A$6,""),IF(ISNUMBER(SEARCH('Référentiel entourage'!$B$7,_xlpm.texte)),'Référentiel entourage'!$A$7,""),IF(ISNUMBER(SEARCH('Référentiel entourage'!$B$8,_xlpm.texte)),'Référentiel entourage'!$A$8,""),IF(ISNUMBER(SEARCH('Référentiel entourage'!$B$9,_xlpm.texte)),'Référentiel entourage'!$A$9,""),IF(ISNUMBER(SEARCH('Référentiel entourage'!$B$10,_xlpm.texte)),'Référentiel entourage'!$A$10,""),IF(ISNUMBER(SEARCH('Référentiel entourage'!$B$11,_xlpm.texte)),'Référentiel entourage'!$A$11,""),IF(ISNUMBER(SEARCH('Référentiel entourage'!$B$12,_xlpm.texte)),'Référentiel entourage'!$A$12,""),IF(ISNUMBER(SEARCH('Référentiel entourage'!$B$13,_xlpm.texte)),'Référentiel entourage'!$A$13,""),IF(ISNUMBER(SEARCH('Référentiel entourage'!$B$14,_xlpm.texte)),'Référentiel entourage'!$A$14,""),IF(ISNUMBER(SEARCH('Référentiel entourage'!$B$15,_xlpm.texte)),'Référentiel entourage'!$A$15,""),IF(ISNUMBER(SEARCH('Référentiel entourage'!$B$16,_xlpm.texte)),'Référentiel entourage'!$A$16,""),IF(ISNUMBER(SEARCH('Référentiel entourage'!$B$17,_xlpm.texte)),'Référentiel entourage'!$A$17,""),IF(ISNUMBER(SEARCH('Référentiel entourage'!$B$18,_xlpm.texte)),'Référentiel entourage'!$A$18,""),IF(ISNUMBER(SEARCH('Référentiel entourage'!$B$19,_xlpm.texte)),'Référentiel entourage'!$A$19,""),IF(ISNUMBER(SEARCH('Référentiel entourage'!$B$20,_xlpm.texte)),'Référentiel entourage'!$A$20,""),IF(ISNUMBER(SEARCH('Référentiel entourage'!$B$21,_xlpm.texte)),'Référentiel entourage'!$A$21,""),IF(ISNUMBER(SEARCH('Référentiel entourage'!$B$22,_xlpm.texte)),'Référentiel entourage'!$A$22,""),IF(ISNUMBER(SEARCH('Référentiel entourage'!$B$23,_xlpm.texte)),'Référentiel entourage'!$A$23,""),IF(ISNUMBER(SEARCH('Référentiel entourage'!$B$24,_xlpm.texte)),'Référentiel entourage'!$A$24,"")))) -> pers-michael-fengler; pers-kurt-raab; pers-peer-raben
A11: rwf-1970-le-cafe | B11: Le Café | C11: Das Kaffehause | D11: 1970 | E11: Téléfilm | G11: RFA | H11: Rainer Werner Fassbinder
A12: rwf-1970-rio-das-mortes | B12: Rio das mortes | D12: 1970 | E12: Film | F12: 84 | G12: RFA | H12: Rainer Werner Fassbinder | I12: Rainer Werner Fassbinder | J12: Dietrich Lohmann | K12: Thea Eymèsz ; Rainer Werner Fassbinder | L12: Kurt Raab | M12: Peer Raben | N12: Klaus Hellwig ; Peer Raben | O12: Hanna Schygulla : Hanna Michael König : Michel Günther Kaufmann : Günther Katrin Schaake : Katrin Harry Baer : le collègue de Michel Ulli Lommel : le vendeur de voitures Ingrid Caven : une collègue de Hanna Magdalena Montezuma : une collègue de Hanna Kurt Raab : le pompiste Joachim von Mengershausen : Joachim Lilo Pempeit : la mère de Günther Walter Sedlmayr : le secrétaire Rainer Werner Fassbinder : le partenaire de danse de Hanna | P12: Costumes : Kurt Raab Format : couleur, mono Genre : comédie Diffusion : 15 février 1971 | Q12: Michel et Günther, lassés de leur vie monotone, projettent de partir au Pérou et tentent de réunir l’argent nécessaire au voyage. | X12: 1970 | Z12: Wikipédia : https://fr.wikipedia.org/wiki/Rio_das_Mortes | AB12: film-1970-rio-das-mortes
A13: rwf-1971-whity | B13: Whity | D13: 1971 | E13: Long métrage | F13: 95 | G13: RFA | H13: Rainer Werner Fassbinder | I13: Rainer Werner Fassbinder | J13: Michael Ballhaus | K13: Thea Eymèsz ; Rainer Werner Fassbinder | L13: Kurt Raab | M13: Peer Raben | N13: Peter Berling ; Ulli Lommel ; Peer Raben ; Antiteater-X-Film ; Atlantis Film | O13: Günther Kaufmann : Whity Ron Randell : Benjamin Nicholson Hanna Schygulla : Hanna Katrin Schaake : Katherine Nicholson Harry Baer : Davy Nicholson Ulli Lommel : Frank Nicholson Thomas Blanco : le faux médecin mexicain Stefano Capriati : le juge Helga Ballhaus : la femme du juge Elaine Baker : la mère de Whity Mark Salvage : le shérif Kurt Raab : le pianiste Rainer Werner Fassbinder : le client du saloon | P13: Format : couleur, 2,35:1, mono Genre : drame, western Sortie : 1971 | Q13: Dans le sud des États-Unis à la fin du XIXe siècle, Whity, fils illégitime métis du riche Ben Nicholson, vit en esclave dans sa propre famille. Humilié par son père, ses demi-frères et l’épouse de celui-ci, il aspire pourtant à une autre condition et fréquente une danseuse de cabaret. | X13: 1971 | Z13: Wikipédia : https://fr.wikipedia.org/wiki/Whity | AA13: À compléter | AB13: film-1971-whity | AC13: =IF(O13="","",_xlfn.TEXTJOIN("; ",TRUE,IF(ISNUMBER(SEARCH('Référentiel entourage'!$B$2,O13)),'Référentiel entourage'!$A$2,""),IF(ISNUMBER(SEARCH('Référentiel entourage'!$B$3,O13)),'Référentiel entourage'!$A$3,""),IF(ISNUMBER(SEARCH('Référentiel entourage'!$B$4,O13)),'Référentiel entourage'!$A$4,""),IF(ISNUMBER(SEARCH('Référentiel entourage'!$B$5,O13)),'Référentiel entourage'!$A$5,""),IF(ISNUMBER(SEARCH('Référentiel entourage'!$B$6,O13)),'Référentiel entourage'!$A$6,""),IF(ISNUMBER(SEARCH('Référentiel entourage'!$B$7,O13)),'Référentiel entourage'!$A$7,""),IF(ISNUMBER(SEARCH('Référentiel entourage'!$B$8,O13)),'Référentiel entourage'!$A$8,""),IF(ISNUMBER(SEARCH('Référentiel entourage'!$B$9,O13)),'Référentiel entourage'!$A$9,""),IF(ISNUMBER(SEARCH('Référentiel entourage'!$B$10,O13)),'Référentiel entourage'!$A$10,""),IF(ISNUMBER(SEARCH('Référentiel entourage'!$B$11,O13)),'Référentiel entourage'!$A$11,""),IF(ISNUMBER(SEARCH('Référentiel entourage'!$B$12,O13)),'Référentiel entourage'!$A$12,""),IF(ISNUMBER(SEARCH('Référentiel entourage'!$B$13,O13)),'Référentiel entourage'!$A$13,""),IF(ISNUMBER(SEARCH('Référentiel entourage'!$B$14,O13)),'Référentiel entourage'!$A$14,""),IF(ISNUMBER(SEARCH('Référentiel entourage'!$B$15,O13)),'Référentiel entourage'!$A$15,""),IF(ISNUMBER(SEARCH('Référentiel entourage'!$B$16,O13)),'Référentiel entourage'!$A$16,""),IF(ISNUMBER(SEARCH('Référentiel entourage'!$B$17,O13)),'Référentiel entourage'!$A$17,""),IF(ISNUMBER(SEARCH('Référentiel entourage'!$B$18,O13)),'Référentiel entourage'!$A$18,""),IF(ISNUMBER(SEARCH('Référentiel entourage'!$B$19,O13)),'Référentiel entourage'!$A$19,""),IF(ISNUMBER(SEARCH('Référentiel entourage'!$B$20,O13)),'Référentiel entourage'!$A$20,""),IF(ISNUMBER(SEARCH('Référentiel entourage'!$B$21,O13)),'Référentiel entourage'!$A$21,""),IF(ISNUMBER(SEARCH('Référentiel entourage'!$B$22,O13)),'Référentiel entourage'!$A$22,""),IF(ISNUMBER(SEARCH('Référentiel entourage'!$B$23,O13)),'Référentiel entourage'!$A$23,""),IF(ISNUMBER(SEARCH('Référentiel entourage'!$B$24,O13)),'Référentiel entourage'!$A$24,""))) -> pers-gunther-kaufmann; pers-ulli-lommel; pers-kurt-raab; pers-hanna-schygulla | AD13: =_xlfn.LET(_xlpm.texte,_xlfn.TEXTJOIN(" | ",TRUE,H13:N13,P13),IF(_xlpm.texte="","",_xlfn.TEXTJOIN("; ",TRUE,IF(ISNUMBER(SEARCH('Référentiel entourage'!$B$2,_xlpm.texte)),'Référentiel entourage'!$A$2,""),IF(ISNUMBER(SEARCH('Référentiel entourage'!$B$3,_xlpm.texte)),'Référentiel entourage'!$A$3,""),IF(ISNUMBER(SEARCH('Référentiel entourage'!$B$4,_xlpm.texte)),'Référentiel entourage'!$A$4,""),IF(ISNUMBER(SEARCH('Référentiel entourage'!$B$5,_xlpm.texte)),'Référentiel entourage'!$A$5,""),IF(ISNUMBER(SEARCH('Référentiel entourage'!$B$6,_xlpm.texte)),'Référentiel entourage'!$A$6,""),IF(ISNUMBER(SEARCH('Référentiel entourage'!$B$7,_xlpm.texte)),'Référentiel entourage'!$A$7,""),IF(ISNUMBER(SEARCH('Référentiel entourage'!$B$8,_xlpm.texte)),'Référentiel entourage'!$A$8,""),IF(ISNUMBER(SEARCH('Référentiel entourage'!$B$9,_xlpm.texte)),'Référentiel entourage'!$A$9,""),IF(ISNUMBER(SEARCH('Référentiel entourage'!$B$10,_xlpm.texte)),'Référentiel entourage'!$A$10,""),IF(ISNUMBER(SEARCH('Référentiel entourage'!$B$11,_xlpm.texte)),'Référentiel entourage'!$A$11,""),IF(ISNUMBER(SEARCH('Référentiel entourage'!$B$12,_xlpm.texte)),'Référentiel entourage'!$A$12,""),IF(ISNUMBER(SEARCH('Référentiel entourage'!$B$13,_xlpm.texte)),'Référentiel entourage'!$A$13,""),IF(ISNUMBER(SEARCH('Référentiel entourage'!$B$14,_xlpm.texte)),'Référentiel entourage'!$A$14,""),IF(ISNUMBER(SEARCH('Référentiel entourage'!$B$15,_xlpm.texte)),'Référentiel entourage'!$A$15,""),IF(ISNUMBER(SEARCH('Référentiel entourage'!$B$16,_xlpm.texte)),'Référentiel entourage'!$A$16,""),IF(ISNUMBER(SEARCH('Référentiel entourage'!$B$17,_xlpm.texte)),'Référentiel entourage'!$A$17,""),IF(ISNUMBER(SEARCH('Référentiel entourage'!$B$18,_xlpm.texte)),'Référentiel entourage'!$A$18,""),IF(ISNUMBER(SEARCH('Référentiel entourage'!$B$19,_xlpm.texte)),'Référentiel entourage'!$A$19,""),IF(ISNUMBER(SEARCH('Référentiel entourage'!$B$20,_xlpm.texte)),'Référentiel entourage'!$A$20,""),IF(ISNUMBER(SEARCH('Référentiel entourage'!$B$21,_xlpm.texte)),'Référentiel entourage'!$A$21,""),IF(ISNUMBER(SEARCH('Référentiel entourage'!$B$22,_xlpm.texte)),'Référentiel entourage'!$A$22,""),IF(ISNUMBER(SEARCH('Référentiel entourage'!$B$23,_xlpm.texte)),'Référentiel entourage'!$A$23,""),IF(ISNUMBER(SEARCH('Référentiel entourage'!$B$24,_xlpm.texte)),'Référentiel entourage'!$A$24,"")))) -> pers-michael-ballhaus; pers-ulli-lommel; pers-kurt-raab; pers-peer-raben
A14: rwf-1971-prenez-garde-a-la-sainte-putain | B14: Prenez garde à la sainte putain | C14: Warnung vor einer heiligen Nutte | D14: 1971 | E14: Long métrage | F14: 103 | G14: RFA | H14: Rainer Werner Fassbinder | I14: Rainer Werner Fassbinder | J14: Michael Ballhaus | K14: Thea Eymèsz ; Rainer Werner Fassbinder (sous le nom de Franz Walsch) | L14: Kurt Raab | M14: Peer Raben | N14: Peter Berling ; Antiteater-X-Film ; Nova International Films | O14: Lou Castel : Jeff, le metteur en scène Eddie Constantine : lui-même Marquard Bohm : Ricky Hanna Schygulla : Hanna Rainer Werner Fassbinder : Sascha Margarethe von Trotta : la secrétaire de production Katrin Schaake : la script Hannes Fuchs : David Marcella Michelangeli : Margret Karl Scheydt : Manfred Ulli Lommel : Korbinian Kurt Raab : Fred Herb Andress : Coach Benjamin Lev : Candy Monika Teuber : Billi Gianni di Luigi : le caméraman Rudolf Waldemar Brem : le chef éclairagiste Thomas Schieder : Jesus Ingrid Caven : une figurante Harry Baer : le mari de la figurante Magdalena Montezuma : Irm Werner Schroeter : Deiters | P14: Langues : allemand, anglais, français, espagnol Format : couleur Genre : comédie dramatique Sortie : 1971 | Q14: Une équipe de cinéma réunie pour un tournage affronte des difficultés multiples : retard du réalisateur, matériel manquant, jalousies et conflits. | S14: Le cinéma comme espace de pouvoir et de destruction Dans Prenez garde à la sainte putain, Fassbinder met en scène une équipe de tournage immobilisée dans un hôtel espagnol par des difficultés financières. L'attente, les rivalités et les relations affectives révèlent progressivement les tensions qui traversent le collectif cinématographique. L'hôtel devient un espace de surveillance, de désir et de violence, où les rapports professionnels et les relations privées s'entremêlent. Le pouvoir du metteur en scène, incarné par Jeff, repose sur l'autorité, l'humiliation et la menace, mais cette violence révèle aussi son impuissance face aux contraintes économiques et à ses propres dépendances. La mise en scène associe le chaos de la production à une forme fragmentée : saynètes discontinues, corps dispersés, dialogues et conflits qui désagrègent le groupe. La séquence finale du film tourné par l'équipe, Patria o Muerte , introduit cependant une rupture : le désordre laisse place à une composition maîtrisée, à des mouvements de caméra élégants et à une temporalité propre au cinéma. Le film interroge ainsi la contradiction entre la dimension collective de la création cinématographique et les rapports de domination qui l'organisent. Il met en tension la représentation de la violence et sa reproduction dans les conditions mêmes du tournage. La beauté de l'image finale ne résout pas cette contradiction : elle fait apparaître la puissance formelle du cinéma au sein d'un système de relations destructrices. | U14: Films_images/Prenez_garde_a_la_sainte_putain.jpg | X14: 1971 | Z14: Wikipédia : https://fr.wikipedia.org/wiki/Prenez_garde_%C3%A0_la_sainte_putain | AA14: À compléter | AB14: film-1971-prenez-garde-a-la-sainte-putain | AC14: =IF(O14="","",_xlfn.TEXTJOIN("; ",TRUE,IF(ISNUMBER(SEARCH('Référentiel entourage'!$B$2,O14)),'Référentiel entourage'!$A$2,""),IF(ISNUMBER(SEARCH('Référentiel entourage'!$B$3,O14)),'Référentiel entourage'!$A$3,""),IF(ISNUMBER(SEARCH('Référentiel entourage'!$B$4,O14)),'Référentiel entourage'!$A$4,""),IF(ISNUMBER(SEARCH('Référentiel entourage'!$B$5,O14)),'Référentiel entourage'!$A$5,""),IF(ISNUMBER(SEARCH('Référentiel entourage'!$B$6,O14)),'Référentiel entourage'!$A$6,""),IF(ISNUMBER(SEARCH('Référentiel entourage'!$B$7,O14)),'Référentiel entourage'!$A$7,""),IF(ISNUMBER(SEARCH('Référentiel entourage'!$B$8,O14)),'Référentiel entourage'!$A$8,""),IF(ISNUMBER(SEARCH('Référentiel entourage'!$B$9,O14)),'Référentiel entourage'!$A$9,""),IF(ISNUMBER(SEARCH('Référentiel entourage'!$B$10,O14)),'Référentiel entourage'!$A$10,""),IF(ISNUMBER(SEARCH('Référentiel entourage'!$B$11,O14)),'Référentiel entourage'!$A$11,""),IF(ISNUMBER(SEARCH('Référentiel entourage'!$B$12,O14)),'Référentiel entourage'!$A$12,""),IF(ISNUMBER(SEARCH('Référentiel entourage'!$B$13,O14)),'Référentiel entourage'!$A$13,""),IF(ISNUMBER(SEARCH('Référentiel entourage'!$B$14,O14)),'Référentiel entourage'!$A$14,""),IF(ISNUMBER(SEARCH('Référentiel entourage'!$B$15,O14)),'Référentiel entourage'!$A$15,""),IF(ISNUMBER(SEARCH('Référentiel entourage'!$B$16,O14)),'Référentiel entourage'!$A$16,""),IF(ISNUMBER(SEARCH('Référentiel entourage'!$B$17,O14)),'Référentiel entourage'!$A$17,""),IF(ISNUMBER(SEARCH('Référentiel entourage'!$B$18,O14)),'Référentiel entourage'!$A$18,""),IF(ISNUMBER(SEARCH('Référentiel entourage'!$B$19,O14)),'Référentiel entourage'!$A$19,""),IF(ISNUMBER(SEARCH('Référentiel entourage'!$B$20,O14)),'Référentiel entourage'!$A$20,""),IF(ISNUMBER(SEARCH('Référentiel entourage'!$B$21,O14)),'Référentiel entourage'!$A$21,""),IF(ISNUMBER(SEARCH('Référentiel entourage'!$B$22,O14)),'Référentiel entourage'!$A$22,""),IF(ISNUMBER(SEARCH('Référentiel entourage'!$B$23,O14)),'Référentiel entourage'!$A$23,""),IF(ISNUMBER(SEARCH('Référentiel entourage'!$B$24,O14)),'Référentiel entourage'!$A$24,""))) -> pers-ingrid-caven; pers-ulli-lommel; pers-kurt-raab; pers-hanna-schygulla | AD14: =_xlfn.LET(_xlpm.texte,_xlfn.TEXTJOIN(" | ",TRUE,H14:N14,P14),IF(_xlpm.texte="","",_xlfn.TEXTJOIN("; ",TRUE,IF(ISNUMBER(SEARCH('Référentiel entourage'!$B$2,_xlpm.texte)),'Référentiel entourage'!$A$2,""),IF(ISNUMBER(SEARCH('Référentiel entourage'!$B$3,_xlpm.texte)),'Référentiel entourage'!$A$3,""),IF(ISNUMBER(SEARCH('Référentiel entourage'!$B$4,_xlpm.texte)),'Référentiel entourage'!$A$4,""),IF(ISNUMBER(SEARCH('Référentiel entourage'!$B$5,_xlpm.texte)),'Référentiel entourage'!$A$5,""),IF(ISNUMBER(SEARCH('Référentiel entourage'!$B$6,_xlpm.texte)),'Référentiel entourage'!$A$6,""),IF(ISNUMBER(SEARCH('Référentiel entourage'!$B$7,_xlpm.texte)),'Référentiel entourage'!$A$7,""),IF(ISNUMBER(SEARCH('Référentiel entourage'!$B$8,_xlpm.texte)),'Référentiel entourage'!$A$8,""),IF(ISNUMBER(SEARCH('Référentiel entourage'!$B$9,_xlpm.texte)),'Référentiel entourage'!$A$9,""),IF(ISNUMBER(SEARCH('Référentiel entourage'!$B$10,_xlpm.texte)),'Référentiel entourage'!$A$10,""),IF(ISNUMBER(SEARCH('Référentiel entourage'!$B$11,_xlpm.texte)),'Référentiel entourage'!$A$11,""),IF(ISNUMBER(SEARCH('Référentiel entourage'!$B$12,_xlpm.texte)),'Référentiel entourage'!$A$12,""),IF(ISNUMBER(SEARCH('Référentiel entourage'!$B$13,_xlpm.texte)),'Référentiel entourage'!$A$13,""),IF(ISNUMBER(SEARCH('Référentiel entourage'!$B$14,_xlpm.texte)),'Référentiel entourage'!$A$14,""),IF(ISNUMBER(SEARCH('Référentiel entourage'!$B$15,_xlpm.texte)),'Référentiel entourage'!$A$15,""),IF(ISNUMBER(SEARCH('Référentiel entourage'!$B$16,_xlpm.texte)),'Référentiel entourage'!$A$16,""),IF(ISNUMBER(SEARCH('Référentiel entourage'!$B$17,_xlpm.texte)),'Référentiel entourage'!$A$17,""),IF(ISNUMBER(SEARCH('Référentiel entourage'!$B$18,_xlpm.texte)),'Référentiel entourage'!$A$18,""),IF(ISNUMBER(SEARCH('Référentiel entourage'!$B$19,_xlpm.texte)),'Référentiel entourage'!$A$19,""),IF(ISNUMBER(SEARCH('Référentiel entourage'!$B$20,_xlpm.texte)),'Référentiel entourage'!$A$20,""),IF(ISNUMBER(SEARCH('Référentiel entourage'!$B$21,_xlpm.texte)),'Référentiel entourage'!$A$21,""),IF(ISNUMBER(SEARCH('Référentiel entourage'!$B$22,_xlpm.texte)),'Référentiel entourage'!$A$22,""),IF(ISNUMBER(SEARCH('Référentiel entourage'!$B$23,_xlpm.texte)),'Référentiel entourage'!$A$23,""),IF(ISNUMBER(SEARCH('Référentiel entourage'!$B$24,_xlpm.texte)),'Référentiel entourage'!$A$24,"")))) -> pers-michael-ballhaus; pers-kurt-raab; pers-peer-raben
A15: rwf-1971-pionniers-a-ingolstadt | B15: Pionniers à Ingolstadt | C15: Pioniere in Ingolstadt | D15: 1971 | E15: Téléfilm | F15: 84 | G15: RFA | H15: Rainer Werner Fassbinder | I15: Rainer Werner Fassbinder, d’après la pièce de Marieluise Fleisser | J15: Dietrich Lohmann | K15: Thea Eymèsz | L15: Kurt Raab | M15: Peer Raben | N15: Janus Film und Fernsehen ; Antiteater pour la ZDF | O15: Hanna Schygulla : Berta Harry Baer : Karl Irm Hermann : Alma Rudolf Waldemar Brem : Fabian Walter Sedlmayr : le sergent-major Klaus Löwitsch : le sergent Günther Kaufmann : Max Carla Aulalu : Frida Elga Sorbas : Marie Burghard Schlicht : Klaus Günther Krää : Gottfried | P15: Assistant de réalisation : Günther Krää Tournage : 25 jours en novembre 1970, Landsberg-Lech et Munich Diffusion RFA : 8 mai 1973 ; présentation à Cannes : 19 mai 1971 | Q15: Une compagnie de soldats du génie arrive à Ingolstadt pour réparer un pont de bois. Les jeunes femmes de la ville, qui s’ennuient, sont attirées par les soldats et s’engagent avec eux dans des jeux de désir et de sexe. | X15: 1971 | Z15: Wikipédia : https://fr.wikipedia.org/wiki/Pionniers_%C3%A0_Ingolstadt | AA15: À compléter | AB15: film-1971-pionniers-a-ingolstadt | AC15: =IF(O15="","",_xlfn.TEXTJOIN("; ",TRUE,IF(ISNUMBER(SEARCH('Référentiel entourage'!$B$2,O15)),'Référentiel entourage'!$A$2,""),IF(ISNUMBER(SEARCH('Référentiel entourage'!$B$3,O15)),'Référentiel entourage'!$A$3,""),IF(ISNUMBER(SEARCH('Référentiel entourage'!$B$4,O15)),'Référentiel entourage'!$A$4,""),IF(ISNUMBER(SEARCH('Référentiel entourage'!$B$5,O15)),'Référentiel entourage'!$A$5,""),IF(ISNUMBER(SEARCH('Référentiel entourage'!$B$6,O15)),'Référentiel entourage'!$A$6,""),IF(ISNUMBER(SEARCH('Référentiel entourage'!$B$7,O15)),'Référentiel entourage'!$A$7,""),IF(ISNUMBER(SEARCH('Référentiel entourage'!$B$8,O15)),'Référentiel entourage'!$A$8,""),IF(ISNUMBER(SEARCH('Référentiel entourage'!$B$9,O15)),'Référentiel entourage'!$A$9,""),IF(ISNUMBER(SEARCH('Référentiel entourage'!$B$10,O15)),'Référentiel entourage'!$A$10,""),IF(ISNUMBER(SEARCH('Référentiel entourage'!$B$11,O15)),'Référentiel entourage'!$A$11,""),IF(ISNUMBER(SEARCH('Référentiel entourage'!$B$12,O15)),'Référentiel entourage'!$A$12,""),IF(ISNUMBER(SEARCH('Référentiel entourage'!$B$13,O15)),'Référentiel entourage'!$A$13,""),IF(ISNUMBER(SEARCH('Référentiel entourage'!$B$14,O15)),'Référentiel entourage'!$A$14,""),IF(ISNUMBER(SEARCH('Référentiel entourage'!$B$15,O15)),'Référentiel entourage'!$A$15,""),IF(ISNUMBER(SEARCH('Référentiel entourage'!$B$16,O15)),'Référentiel entourage'!$A$16,""),IF(ISNUMBER(SEARCH('Référentiel entourage'!$B$17,O15)),'Référentiel entourage'!$A$17,""),IF(ISNUMBER(SEARCH('Référentiel entourage'!$B$18,O15)),'Référentiel entourage'!$A$18,""),IF(ISNUMBER(SEARCH('Référentiel entourage'!$B$19,O15)),'Référentiel entourage'!$A$19,""),IF(ISNUMBER(SEARCH('Référentiel entourage'!$B$20,O15)),'Référentiel entourage'!$A$20,""),IF(ISNUMBER(SEARCH('Référentiel entourage'!$B$21,O15)),'Référentiel entourage'!$A$21,""),IF(ISNUMBER(SEARCH('Référentiel entourage'!$B$22,O15)),'Référentiel entourage'!$A$22,""),IF(ISNUMBER(SEARCH('Référentiel entourage'!$B$23,O15)),'Référentiel entourage'!$A$23,""),IF(ISNUMBER(SEARCH('Référentiel entourage'!$B$24,O15)),'Référentiel entourage'!$A$24,""))) -> pers-irm-hermann; pers-gunther-kaufmann; pers-hanna-schygulla | AD15: =_xlfn.LET(_xlpm.texte,_xlfn.TEXTJOIN(" | ",TRUE,H15:N15,P15),IF(_xlpm.texte="","",_xlfn.TEXTJOIN("; ",TRUE,IF(ISNUMBER(SEARCH('Référentiel entourage'!$B$2,_xlpm.texte)),'Référentiel entourage'!$A$2,""),IF(ISNUMBER(SEARCH('Référentiel entourage'!$B$3,_xlpm.texte)),'Référentiel entourage'!$A$3,""),IF(ISNUMBER(SEARCH('Référentiel entourage'!$B$4,_xlpm.texte)),'Référentiel entourage'!$A$4,""),IF(ISNUMBER(SEARCH('Référentiel entourage'!$B$5,_xlpm.texte)),'Référentiel entourage'!$A$5,""),IF(ISNUMBER(SEARCH('Référentiel entourage'!$B$6,_xlpm.texte)),'Référentiel entourage'!$A$6,""),IF(ISNUMBER(SEARCH('Référentiel entourage'!$B$7,_xlpm.texte)),'Référentiel entourage'!$A$7,""),IF(ISNUMBER(SEARCH('Référentiel entourage'!$B$8,_xlpm.texte)),'Référentiel entourage'!$A$8,""),IF(ISNUMBER(SEARCH('Référentiel entourage'!$B$9,_xlpm.texte)),'Référentiel entourage'!$A$9,""),IF(ISNUMBER(SEARCH('Référentiel entourage'!$B$10,_xlpm.texte)),'Référentiel entourage'!$A$10,""),IF(ISNUMBER(SEARCH('Référentiel entourage'!$B$11,_xlpm.texte)),'Référentiel entourage'!$A$11,""),IF(ISNUMBER(SEARCH('Référentiel entourage'!$B$12,_xlpm.texte)),'Référentiel entourage'!$A$12,""),IF(ISNUMBER(SEARCH('Référentiel entourage'!$B$13,_xlpm.texte)),'Référentiel entourage'!$A$13,""),IF(ISNUMBER(SEARCH('Référentiel entourage'!$B$14,_xlpm.texte)),'Référentiel entourage'!$A$14,""),IF(ISNUMBER(SEARCH('Référentiel entourage'!$B$15,_xlpm.texte)),'Référentiel entourage'!$A$15,""),IF(ISNUMBER(SEARCH('Référentiel entourage'!$B$16,_xlpm.texte)),'Référentiel entourage'!$A$16,""),IF(ISNUMBER(SEARCH('Référentiel entourage'!$B$17,_xlpm.texte)),'Référentiel entourage'!$A$17,""),IF(ISNUMBER(SEARCH('Référentiel entourage'!$B$18,_xlpm.texte)),'Référentiel entourage'!$A$18,""),IF(ISNUMBER(SEARCH('Référentiel entourage'!$B$19,_xlpm.texte)),'Référentiel entourage'!$A$19,""),IF(ISNUMBER(SEARCH('Référentiel entourage'!$B$20,_xlpm.texte)),'Référentiel entourage'!$A$20,""),IF(ISNUMBER(SEARCH('Référentiel entourage'!$B$21,_xlpm.texte)),'Référentiel entourage'!$A$21,""),IF(ISNUMBER(SEARCH('Référentiel entourage'!$B$22,_xlpm.texte)),'Référentiel entourage'!$A$22,""),IF(ISNUMBER(SEARCH('Référentiel entourage'!$B$23,_xlpm.texte)),'Référentiel entourage'!$A$23,""),IF(ISNUMBER(SEARCH('Référentiel entourage'!$B$24,_xlpm.texte)),'Référentiel entourage'!$A$24,"")))) -> pers-kurt-raab; pers-peer-raben
A16: rwf-1971-marchand-quatre-saisons | B16: Le Marchand des quatre saisons | C16: Händler der vier Jahreszeiten | D16: 1972 | E16: Long métrage | F16: 88 | G16: RFA | H16: Rainer Werner Fassbinder | I16: Rainer Werner Fassbinder | J16: Dietrich Lohmann | K16: Thea Eymèsz | L16: Kurt Raab | N16: Tango Film | O16: Hans Hirschmüller : Hans Epp Irm Hermann : Irmgard Epp Hanna Schygulla : Anna Epp Heide Simon : Heide Kurt Raab : Kurt Andrea Schober : Renate Epp Gusti Kreissl : la mère de Hans Ingrid Caven : le grand amour de Hans Peter Chatel : le docteur Harlach Klaus Löwitsch : Harry Radek Karl Scheydt : Anzell Elga Sorbas : Mariele Kosemund Lilo Pempeit : une cliente Walter Sedlmayr : le vendeur Daniel Schmid : premier candidat Harry Baer : deuxième candidat Michael Fengler : le playboy Hark Bohm : le chef de la police | P16: Format : couleur, 1,37:1, mono Genre : drame Sortie : 1972 | Q16: Méprisé par sa famille, Hans a connu la Légion étrangère puis la police. Il vend désormais des fruits avec sa femme, qu’il brutalise. Après un infarctus et la reprise de leur activité avec du personnel, les affaires prospèrent mais Hans sombre dans une profonde dépression. | U16: Films_images/Le_Marchand_des_quatre_saisons.jpg | X16: 1972 | Z16: Wikipédia : https://fr.wikipedia.org/wiki/Le_Marchand_des_quatre_saisons | AA16: À compléter | AB16: film-1972-le-marchand-des-quatre-saisons | AC16: =IF(O16="","",_xlfn.TEXTJOIN("; ",TRUE,IF(ISNUMBER(SEARCH('Référentiel entourage'!$B$2,O16)),'Référentiel entourage'!$A$2,""),IF(ISNUMBER(SEARCH('Référentiel entourage'!$B$3,O16)),'Référentiel entourage'!$A$3,""),IF(ISNUMBER(SEARCH('Référentiel entourage'!$B$4,O16)),'Référentiel entourage'!$A$4,""),IF(ISNUMBER(SEARCH('Référentiel entourage'!$B$5,O16)),'Référentiel entourage'!$A$5,""),IF(ISNUMBER(SEARCH('Référentiel entourage'!$B$6,O16)),'Référentiel entourage'!$A$6,""),IF(ISNUMBER(SEARCH('Référentiel entourage'!$B$7,O16)),'Référentiel entourage'!$A$7,""),IF(ISNUMBER(SEARCH('Référentiel entourage'!$B$8,O16)),'Référentiel entourage'!$A$8,""),IF(ISNUMBER(SEARCH('Référentiel entourage'!$B$9,O16)),'Référentiel entourage'!$A$9,""),IF(ISNUMBER(SEARCH('Référentiel entourage'!$B$10,O16)),'Référentiel entourage'!$A$10,""),IF(ISNUMBER(SEARCH('Référentiel entourage'!$B$11,O16)),'Référentiel entourage'!$A$11,""),IF(ISNUMBER(SEARCH('Référentiel entourage'!$B$12,O16)),'Référentiel entourage'!$A$12,""),IF(ISNUMBER(SEARCH('Référentiel entourage'!$B$13,O16)),'Référentiel entourage'!$A$13,""),IF(ISNUMBER(SEARCH('Référentiel entourage'!$B$14,O16)),'Référentiel entourage'!$A$14,""),IF(ISNUMBER(SEARCH('Référentiel entourage'!$B$15,O16)),'Référentiel entourage'!$A$15,""),IF(ISNUMBER(SEARCH('Référentiel entourage'!$B$16,O16)),'Référentiel entourage'!$A$16,""),IF(ISNUMBER(SEARCH('Référentiel entourage'!$B$17,O16)),'Référentiel entourage'!$A$17,""),IF(ISNUMBER(SEARCH('Référentiel entourage'!$B$18,O16)),'Référentiel entourage'!$A$18,""),IF(ISNUMBER(SEARCH('Référentiel entourage'!$B$19,O16)),'Référentiel entourage'!$A$19,""),IF(ISNUMBER(SEARCH('Référentiel entourage'!$B$20,O16)),'Référentiel entourage'!$A$20,""),IF(ISNUMBER(SEARCH('Référentiel entourage'!$B$21,O16)),'Référentiel entourage'!$A$21,""),IF(ISNUMBER(SEARCH('Référentiel entourage'!$B$22,O16)),'Référentiel entourage'!$A$22,""),IF(ISNUMBER(SEARCH('Référentiel entourage'!$B$23,O16)),'Référentiel entourage'!$A$23,""),IF(ISNUMBER(SEARCH('Référentiel entourage'!$B$24,O16)),'Référentiel entourage'!$A$24,""))) -> pers-hark-bohm; pers-ingrid-caven; pers-peter-chatel; pers-lilo-pempeit; pers-michael-fengler; pers-irm-hermann; pers-kurt-raab; pers-daniel-schmid; pers-hanna-schygulla | AD16: =_xlfn.LET(_xlpm.texte,_xlfn.TEXTJOIN(" | ",TRUE,H16:N16,P16),IF(_xlpm.texte="","",_xlfn.TEXTJOIN("; ",TRUE,IF(ISNUMBER(SEARCH('Référentiel entourage'!$B$2,_xlpm.texte)),'Référentiel entourage'!$A$2,""),IF(ISNUMBER(SEARCH('Référentiel entourage'!$B$3,_xlpm.texte)),'Référentiel entourage'!$A$3,""),IF(ISNUMBER(SEARCH('Référentiel entourage'!$B$4,_xlpm.texte)),'Référentiel entourage'!$A$4,""),IF(ISNUMBER(SEARCH('Référentiel entourage'!$B$5,_xlpm.texte)),'Référentiel entourage'!$A$5,""),IF(ISNUMBER(SEARCH('Référentiel entourage'!$B$6,_xlpm.texte)),'Référentiel entourage'!$A$6,""),IF(ISNUMBER(SEARCH('Référentiel entourage'!$B$7,_xlpm.texte)),'Référentiel entourage'!$A$7,""),IF(ISNUMBER(SEARCH('Référentiel entourage'!$B$8,_xlpm.texte)),'Référentiel entourage'!$A$8,""),IF(ISNUMBER(SEARCH('Référentiel entourage'!$B$9,_xlpm.texte)),'Référentiel entourage'!$A$9,""),IF(ISNUMBER(SEARCH('Référentiel entourage'!$B$10,_xlpm.texte)),'Référentiel entourage'!$A$10,""),IF(ISNUMBER(SEARCH('Référentiel entourage'!$B$11,_xlpm.texte)),'Référentiel entourage'!$A$11,""),IF(ISNUMBER(SEARCH('Référentiel entourage'!$B$12,_xlpm.texte)),'Référentiel entourage'!$A$12,""),IF(ISNUMBER(SEARCH('Référentiel entourage'!$B$13,_xlpm.texte)),'Référentiel entourage'!$A$13,""),IF(ISNUMBER(SEARCH('Référentiel entourage'!$B$14,_xlpm.texte)),'Référentiel entourage'!$A$14,""),IF(ISNUMBER(SEARCH('Référentiel entourage'!$B$15,_xlpm.texte)),'Référentiel entourage'!$A$15,""),IF(ISNUMBER(SEARCH('Référentiel entourage'!$B$16,_xlpm.texte)),'Référentiel entourage'!$A$16,""),IF(ISNUMBER(SEARCH('Référentiel entourage'!$B$17,_xlpm.texte)),'Référentiel entourage'!$A$17,""),IF(ISNUMBER(SEARCH('Référentiel entourage'!$B$18,_xlpm.texte)),'Référentiel entourage'!$A$18,""),IF(ISNUMBER(SEARCH('Référentiel entourage'!$B$19,_xlpm.texte)),'Référentiel entourage'!$A$19,""),IF(ISNUMBER(SEARCH('Référentiel entourage'!$B$20,_xlpm.texte)),'Référentiel entourage'!$A$20,""),IF(ISNUMBER(SEARCH('Référentiel entourage'!$B$21,_xlpm.texte)),'Référentiel entourage'!$A$21,""),IF(ISNUMBER(SEARCH('Référentiel entourage'!$B$22,_xlpm.texte)),'Référentiel entourage'!$A$22,""),IF(ISNUMBER(SEARCH('Référentiel entourage'!$B$23,_xlpm.texte)),'Référentiel entourage'!$A$23,""),IF(ISNUMBER(SEARCH('Référentiel entourage'!$B$24,_xlpm.texte)),'Référentiel entourage'!$A$24,"")))) -> pers-kurt-raab
A17: rwf-1972-larmes-petra-von-kant | B17: Les Larmes amères de Petra von Kant | C17: Die bitteren Tränen der Petra von Kant | D17: 1972 | E17: Long métrage | F17: 124 | G17: RFA | H17: Rainer Werner Fassbinder | I17: Rainer Werner Fassbinder, d’après sa pièce | J17: Michael Ballhaus | K17: Thea Eymèsz | L17: Kurt Raab | N17: Filmverlag der Autoren ; Tango Film | O17: Margit Carstensen : Petra von Kant Hanna Schygulla : Karin Thimm Katrin Schaake : Sidonie von Grasenabb Eva Mattes : Gabriele von Kant Gisela Fackeldey : Valerie von Kant Irm Hermann : Marlene | P17: Costumes : Maja Lemcke Langue : allemand Genre : drame, romance Sortie : 1972 | Q17: Petra von Kant, célèbre créatrice de mode, vit avec Marlene, assistante qu’elle humilie et traite en esclave. Elle s’éprend de Karin, jeune femme d’origine modeste, qu’elle invite à partager son appartement et qu’elle aide à entrer dans le mannequinat. | U17: Films_images/Les_Larmes_ameres_de_Petra_von_Kant.jpg | X17: 1972 | Z17: Wikipédia : https://fr.wikipedia.org/wiki/Les_Larmes_am%C3%A8res_de_Petra_von_Kant | AA17: À compléter | AB17: film-1972-les-larmes-ameres-de-petra-von-kant | AC17: =IF(O17="","",_xlfn.TEXTJOIN("; ",TRUE,IF(ISNUMBER(SEARCH('Référentiel entourage'!$B$2,O17)),'Référentiel entourage'!$A$2,""),IF(ISNUMBER(SEARCH('Référentiel entourage'!$B$3,O17)),'Référentiel entourage'!$A$3,""),IF(ISNUMBER(SEARCH('Référentiel entourage'!$B$4,O17)),'Référentiel entourage'!$A$4,""),IF(ISNUMBER(SEARCH('Référentiel entourage'!$B$5,O17)),'Référentiel entourage'!$A$5,""),IF(ISNUMBER(SEARCH('Référentiel entourage'!$B$6,O17)),'Référentiel entourage'!$A$6,""),IF(ISNUMBER(SEARCH('Référentiel entourage'!$B$7,O17)),'Référentiel entourage'!$A$7,""),IF(ISNUMBER(SEARCH('Référentiel entourage'!$B$8,O17)),'Référentiel entourage'!$A$8,""),IF(ISNUMBER(SEARCH('Référentiel entourage'!$B$9,O17)),'Référentiel entourage'!$A$9,""),IF(ISNUMBER(SEARCH('Référentiel entourage'!$B$10,O17)),'Référentiel entourage'!$A$10,""),IF(ISNUMBER(SEARCH('Référentiel entourage'!$B$11,O17)),'Référentiel entourage'!$A$11,""),IF(ISNUMBER(SEARCH('Référentiel entourage'!$B$12,O17)),'Référentiel entourage'!$A$12,""),IF(ISNUMBER(SEARCH('Référentiel entourage'!$B$13,O17)),'Référentiel entourage'!$A$13,""),IF(ISNUMBER(SEARCH('Référentiel entourage'!$B$14,O17)),'Référentiel entourage'!$A$14,""),IF(ISNUMBER(SEARCH('Référentiel entourage'!$B$15,O17)),'Référentiel entourage'!$A$15,""),IF(ISNUMBER(SEARCH('Référentiel entourage'!$B$16,O17)),'Référentiel entourage'!$A$16,""),IF(ISNUMBER(SEARCH('Référentiel entourage'!$B$17,O17)),'Référentiel entourage'!$A$17,""),IF(ISNUMBER(SEARCH('Référentiel entourage'!$B$18,O17)),'Référentiel entourage'!$A$18,""),IF(ISNUMBER(SEARCH('Référentiel entourage'!$B$19,O17)),'Référentiel entourage'!$A$19,""),IF(ISNUMBER(SEARCH('Référentiel entourage'!$B$20,O17)),'Référentiel entourage'!$A$20,""),IF(ISNUMBER(SEARCH('Référentiel entourage'!$B$21,O17)),'Référentiel entourage'!$A$21,""),IF(ISNUMBER(SEARCH('Référentiel entourage'!$B$22,O17)),'Référentiel entourage'!$A$22,""),IF(ISNUMBER(SEARCH('Référentiel entourage'!$B$23,O17)),'Référentiel entourage'!$A$23,""),IF(ISNUMBER(SEARCH('Référentiel entourage'!$B$24,O17)),'Référentiel entourage'!$A$24,""))) -> pers-margit-carstensen; pers-irm-hermann; pers-hanna-schygulla | AD17: =_xlfn.LET(_xlpm.texte,_xlfn.TEXTJOIN(" | ",TRUE,H17:N17,P17),IF(_xlpm.texte="","",_xlfn.TEXTJOIN("; ",TRUE,IF(ISNUMBER(SEARCH('Référentiel entourage'!$B$2,_xlpm.texte)),'Référentiel entourage'!$A$2,""),IF(ISNUMBER(SEARCH('Référentiel entourage'!$B$3,_xlpm.texte)),'Référentiel entourage'!$A$3,""),IF(ISNUMBER(SEARCH('Référentiel entourage'!$B$4,_xlpm.texte)),'Référentiel entourage'!$A$4,""),IF(ISNUMBER(SEARCH('Référentiel entourage'!$B$5,_xlpm.texte)),'Référentiel entourage'!$A$5,""),IF(ISNUMBER(SEARCH('Référentiel entourage'!$B$6,_xlpm.texte)),'Référentiel entourage'!$A$6,""),IF(ISNUMBER(SEARCH('Référentiel entourage'!$B$7,_xlpm.texte)),'Référentiel entourage'!$A$7,""),IF(ISNUMBER(SEARCH('Référentiel entourage'!$B$8,_xlpm.texte)),'Référentiel entourage'!$A$8,""),IF(ISNUMBER(SEARCH('Référentiel entourage'!$B$9,_xlpm.texte)),'Référentiel entourage'!$A$9,""),IF(ISNUMBER(SEARCH('Référentiel entourage'!$B$10,_xlpm.texte)),'Référentiel entourage'!$A$10,""),IF(ISNUMBER(SEARCH('Référentiel entourage'!$B$11,_xlpm.texte)),'Référentiel entourage'!$A$11,""),IF(ISNUMBER(SEARCH('Référentiel entourage'!$B$12,_xlpm.texte)),'Référentiel entourage'!$A$12,""),IF(ISNUMBER(SEARCH('Référentiel entourage'!$B$13,_xlpm.texte)),'Référentiel entourage'!$A$13,""),IF(ISNUMBER(SEARCH('Référentiel entourage'!$B$14,_xlpm.texte)),'Référentiel entourage'!$A$14,""),IF(ISNUMBER(SEARCH('Référentiel entourage'!$B$15,_xlpm.texte)),'Référentiel entourage'!$A$15,""),IF(ISNUMBER(SEARCH('Référentiel entourage'!$B$16,_xlpm.texte)),'Référentiel entourage'!$A$16,""),IF(ISNUMBER(SEARCH('Référentiel entourage'!$B$17,_xlpm.texte)),'Référentiel entourage'!$A$17,""),IF(ISNUMBER(SEARCH('Référentiel entourage'!$B$18,_xlpm.texte)),'Référentiel entourage'!$A$18,""),IF(ISNUMBER(SEARCH('Référentiel entourage'!$B$19,_xlpm.texte)),'Référentiel entourage'!$A$19,""),IF(ISNUMBER(SEARCH('Référentiel entourage'!$B$20,_xlpm.texte)),'Référentiel entourage'!$A$20,""),IF(ISNUMBER(SEARCH('Référentiel entourage'!$B$21,_xlpm.texte)),'Référentiel entourage'!$A$21,""),IF(ISNUMBER(SEARCH('Référentiel entourage'!$B$22,_xlpm.texte)),'Référentiel entourage'!$A$22,""),IF(ISNUMBER(SEARCH('Référentiel entourage'!$B$23,_xlpm.texte)),'Référentiel entourage'!$A$23,""),IF(ISNUMBER(SEARCH('Référentiel entourage'!$B$24,_xlpm.texte)),'Référentiel entourage'!$A$24,"")))) -> pers-michael-ballhaus; pers-kurt-raab
A18: rwf-1972-liberte-a-breme | B18: Liberté à Brême | C18: Bremer Freiheit | D18: 1972 | E18: Téléfilm | F18: 87 | G18: RFA | H18: Rainer Werner Fassbinder | I18: Rainer Werner Fassbinder ; Dietrich Lohmann | J18: Dietrich Lohmann ; Hans Schugg ; Peter Weyrich | K18: Friedrich Niquet ; Monica Solzbacher | L18: Kurt Raab | N18: Telefilm Saar pour la SR | O18: Margit Carstensen : Geesche Ulli Lommel : Miltenberger Wolfgang Schenck : Gottfried Walter Sedlmayr : le prêtre Wolfgang Kieling : Timm Rudolf Waldemar Brem : le cousin Bohm Kurt Raab : Zimmermann Fritz Schediwy : Johann Hanna Schygulla : Luise Maurer Rainer Werner Fassbinder : Rumpf Lilo Pempeit : la mère | P18: Assistant de réalisation : Fritz Müller-Scherz Tournage : 9 jours en septembre 1972, en studio à Sarrebruck Diffusion : 27 décembre 1972 | Q18: Au début du XIXe siècle à Brême, Geesche est tyrannisée par son mari Miltenberger. | X18: 1972 | Z18: Wikipédia : https://fr.wikipedia.org/wiki/Libert%C3%A9_%C3%A0_Br%C3%AAme | AA18: À compléter | AB18: film-1972-liberte-a-breme | AC18: =IF(O18="","",_xlfn.TEXTJOIN("; ",TRUE,IF(ISNUMBER(SEARCH('Référentiel entourage'!$B$2,O18)),'Référentiel entourage'!$A$2,""),IF(ISNUMBER(SEARCH('Référentiel entourage'!$B$3,O18)),'Référentiel entourage'!$A$3,""),IF(ISNUMBER(SEARCH('Référentiel entourage'!$B$4,O18)),'Référentiel entourage'!$A$4,""),IF(ISNUMBER(SEARCH('Référentiel entourage'!$B$5,O18)),'Référentiel entourage'!$A$5,""),IF(ISNUMBER(SEARCH('Référentiel entourage'!$B$6,O18)),'Référentiel entourage'!$A$6,""),IF(ISNUMBER(SEARCH('Référentiel entourage'!$B$7,O18)),'Référentiel entourage'!$A$7,""),IF(ISNUMBER(SEARCH('Référentiel entourage'!$B$8,O18)),'Référentiel entourage'!$A$8,""),IF(ISNUMBER(SEARCH('Référentiel entourage'!$B$9,O18)),'Référentiel entourage'!$A$9,""),IF(ISNUMBER(SEARCH('Référentiel entourage'!$B$10,O18)),'Référentiel entourage'!$A$10,""),IF(ISNUMBER(SEARCH('Référentiel entourage'!$B$11,O18)),'Référentiel entourage'!$A$11,""),IF(ISNUMBER(SEARCH('Référentiel entourage'!$B$12,O18)),'Référentiel entourage'!$A$12,""),IF(ISNUMBER(SEARCH('Référentiel entourage'!$B$13,O18)),'Référentiel entourage'!$A$13,""),IF(ISNUMBER(SEARCH('Référentiel entourage'!$B$14,O18)),'Référentiel entourage'!$A$14,""),IF(ISNUMBER(SEARCH('Référentiel entourage'!$B$15,O18)),'Référentiel entourage'!$A$15,""),IF(ISNUMBER(SEARCH('Référentiel entourage'!$B$16,O18)),'Référentiel entourage'!$A$16,""),IF(ISNUMBER(SEARCH('Référentiel entourage'!$B$17,O18)),'Référentiel entourage'!$A$17,""),IF(ISNUMBER(SEARCH('Référentiel entourage'!$B$18,O18)),'Référentiel entourage'!$A$18,""),IF(ISNUMBER(SEARCH('Référentiel entourage'!$B$19,O18)),'Référentiel entourage'!$A$19,""),IF(ISNUMBER(SEARCH('Référentiel entourage'!$B$20,O18)),'Référentiel entourage'!$A$20,""),IF(ISNUMBER(SEARCH('Référentiel entourage'!$B$21,O18)),'Référentiel entourage'!$A$21,""),IF(ISNUMBER(SEARCH('Référentiel entourage'!$B$22,O18)),'Référentiel entourage'!$A$22,""),IF(ISNUMBER(SEARCH('Référentiel entourage'!$B$23,O18)),'Référentiel entourage'!$A$23,""),IF(ISNUMBER(SEARCH('Référentiel entourage'!$B$24,O18)),'Référentiel entourage'!$A$24,""))) -> pers-margit-carstensen; pers-lilo-pempeit; pers-ulli-lommel; pers-kurt-raab; pers-hanna-schygulla | AD18: =_xlfn.LET(_xlpm.texte,_xlfn.TEXTJOIN(" | ",TRUE,H18:N18,P18),IF(_xlpm.texte="","",_xlfn.TEXTJOIN("; ",TRUE,IF(ISNUMBER(SEARCH('Référentiel entourage'!$B$2,_xlpm.texte)),'Référentiel entourage'!$A$2,""),IF(ISNUMBER(SEARCH('Référentiel entourage'!$B$3,_xlpm.texte)),'Référentiel entourage'!$A$3,""),IF(ISNUMBER(SEARCH('Référentiel entourage'!$B$4,_xlpm.texte)),'Référentiel entourage'!$A$4,""),IF(ISNUMBER(SEARCH('Référentiel entourage'!$B$5,_xlpm.texte)),'Référentiel entourage'!$A$5,""),IF(ISNUMBER(SEARCH('Référentiel entourage'!$B$6,_xlpm.texte)),'Référentiel entourage'!$A$6,""),IF(ISNUMBER(SEARCH('Référentiel entourage'!$B$7,_xlpm.texte)),'Référentiel entourage'!$A$7,""),IF(ISNUMBER(SEARCH('Référentiel entourage'!$B$8,_xlpm.texte)),'Référentiel entourage'!$A$8,""),IF(ISNUMBER(SEARCH('Référentiel entourage'!$B$9,_xlpm.texte)),'Référentiel entourage'!$A$9,""),IF(ISNUMBER(SEARCH('Référentiel entourage'!$B$10,_xlpm.texte)),'Référentiel entourage'!$A$10,""),IF(ISNUMBER(SEARCH('Référentiel entourage'!$B$11,_xlpm.texte)),'Référentiel entourage'!$A$11,""),IF(ISNUMBER(SEARCH('Référentiel entourage'!$B$12,_xlpm.texte)),'Référentiel entourage'!$A$12,""),IF(ISNUMBER(SEARCH('Référentiel entourage'!$B$13,_xlpm.texte)),'Référentiel entourage'!$A$13,""),IF(ISNUMBER(SEARCH('Référentiel entourage'!$B$14,_xlpm.texte)),'Référentiel entourage'!$A$14,""),IF(ISNUMBER(SEARCH('Référentiel entourage'!$B$15,_xlpm.texte)),'Référentiel entourage'!$A$15,""),IF(ISNUMBER(SEARCH('Référentiel entourage'!$B$16,_xlpm.texte)),'Référentiel entourage'!$A$16,""),IF(ISNUMBER(SEARCH('Référentiel entourage'!$B$17,_xlpm.texte)),'Référentiel entourage'!$A$17,""),IF(ISNUMBER(SEARCH('Référentiel entourage'!$B$18,_xlpm.texte)),'Référentiel entourage'!$A$18,""),IF(ISNUMBER(SEARCH('Référentiel entourage'!$B$19,_xlpm.texte)),'Référentiel entourage'!$A$19,""),IF(ISNUMBER(SEARCH('Référentiel entourage'!$B$20,_xlpm.texte)),'Référentiel entourage'!$A$20,""),IF(ISNUMBER(SEARCH('Référentiel entourage'!$B$21,_xlpm.texte)),'Référentiel entourage'!$A$21,""),IF(ISNUMBER(SEARCH('Référentiel entourage'!$B$22,_xlpm.texte)),'Référentiel entourage'!$A$22,""),IF(ISNUMBER(SEARCH('Référentiel entourage'!$B$23,_xlpm.texte)),'Référentiel entourage'!$A$23,""),IF(ISNUMBER(SEARCH('Référentiel entourage'!$B$24,_xlpm.texte)),'Référentiel entourage'!$A$24,"")))) -> pers-kurt-raab
A19: rwf-1972-huit-heures | B19: Huit heures ne font pas un jour | C19: Acht Stunden sind kein Tag | D19: 1972 | E19: Série télévisée | F19: 467 | G19: RFA | H19: Rainer Werner Fassbinder | I19: Rainer Werner Fassbinder | J19: Dietrich Lohmann | K19: Marie Anne Gerhardt | L19: Kurt Raab | N19: WDR | O19: Gottfried John : Jochen Hanna Schygulla : Marion Luise Ullrich : Grand-mère Werner Finck : Gregor Anita Bucher : Käthe Wolfried Lier : Wolf Christine Oesterlein : Klara Renate Roland : Monika Kurt Raab : Harald Andrea Schober : Sylvia Thorsten Massinger : Manni Irm Hermann : Irmgard Erlkönig Wolfgang Zerlett : Manfred Wolfgang Schenck : Franz Herb Andress : Rüdiger Rudolf Waldemar Brem : Rolf Hans Hirschmüller : Jürgen Peter Gauhe : Ernst Grigorios Karpidis : Giuseppe Karl Scheydt : Peter | P19: Assistants de réalisation : Renate Leiffer, Eberhard Schubert Format : 16 mm, couleur Tournage : 105 jours (avril-août 1972), Cologne et environs de Mönchengladbach Diffusion initiale : 29 octobre 1972 – 18 mars 1973 | Q19: Feuilleton en cinq épisodes consacré aux amours, aux relations familiales et aux problèmes quotidiens d’un groupe de familles ouvrières. La série suit notamment Jochen et Marion, Grand-mère et Gregor, ainsi que les luttes collectives menées dans l’usine. | X19: 1971|1972|1973 | Y19: monde ouvrier|famille|travail|autogestion|solidarité|télévision | Z19: RWF_Notes sur les films.docx | AA19: Documenté | AB19: film-1972-huit-heures-ne-font-pas-un-jour | AC19: =IF(O19="","",_xlfn.TEXTJOIN("; ",TRUE,IF(ISNUMBER(SEARCH('Référentiel entourage'!$B$2,O19)),'Référentiel entourage'!$A$2,""),IF(ISNUMBER(SEARCH('Référentiel entourage'!$B$3,O19)),'Référentiel entourage'!$A$3,""),IF(ISNUMBER(SEARCH('Référentiel entourage'!$B$4,O19)),'Référentiel entourage'!$A$4,""),IF(ISNUMBER(SEARCH('Référentiel entourage'!$B$5,O19)),'Référentiel entourage'!$A$5,""),IF(ISNUMBER(SEARCH('Référentiel entourage'!$B$6,O19)),'Référentiel entourage'!$A$6,""),IF(ISNUMBER(SEARCH('Référentiel entourage'!$B$7,O19)),'Référentiel entourage'!$A$7,""),IF(ISNUMBER(SEARCH('Référentiel entourage'!$B$8,O19)),'Référentiel entourage'!$A$8,""),IF(ISNUMBER(SEARCH('Référentiel entourage'!$B$9,O19)),'Référentiel entourage'!$A$9,""),IF(ISNUMBER(SEARCH('Référentiel entourage'!$B$10,O19)),'Référentiel entourage'!$A$10,""),IF(ISNUMBER(SEARCH('Référentiel entourage'!$B$11,O19)),'Référentiel entourage'!$A$11,""),IF(ISNUMBER(SEARCH('Référentiel entourage'!$B$12,O19)),'Référentiel entourage'!$A$12,""),IF(ISNUMBER(SEARCH('Référentiel entourage'!$B$13,O19)),'Référentiel entourage'!$A$13,""),IF(ISNUMBER(SEARCH('Référentiel entourage'!$B$14,O19)),'Référentiel entourage'!$A$14,""),IF(ISNUMBER(SEARCH('Référentiel entourage'!$B$15,O19)),'Référentiel entourage'!$A$15,""),IF(ISNUMBER(SEARCH('Référentiel entourage'!$B$16,O19)),'Référentiel entourage'!$A$16,""),IF(ISNUMBER(SEARCH('Référentiel entourage'!$B$17,O19)),'Référentiel entourage'!$A$17,""),IF(ISNUMBER(SEARCH('Référentiel entourage'!$B$18,O19)),'Référentiel entourage'!$A$18,""),IF(ISNUMBER(SEARCH('Référentiel entourage'!$B$19,O19)),'Référentiel entourage'!$A$19,""),IF(ISNUMBER(SEARCH('Référentiel entourage'!$B$20,O19)),'Référentiel entourage'!$A$20,""),IF(ISNUMBER(SEARCH('Référentiel entourage'!$B$21,O19)),'Référentiel entourage'!$A$21,""),IF(ISNUMBER(SEARCH('Référentiel entourage'!$B$22,O19)),'Référentiel entourage'!$A$22,""),IF(ISNUMBER(SEARCH('Référentiel entourage'!$B$23,O19)),'Référentiel entourage'!$A$23,""),IF(ISNUMBER(SEARCH('Référentiel entourage'!$B$24,O19)),'Référentiel entourage'!$A$24,""))) -> pers-gottfried-john; pers-irm-hermann; pers-kurt-raab; pers-hanna-schygulla | AD19: =_xlfn.LET(_xlpm.texte,_xlfn.TEXTJOIN(" | ",TRUE,H19:N19,P19),IF(_xlpm.texte="","",_xlfn.TEXTJOIN("; ",TRUE,IF(ISNUMBER(SEARCH('Référentiel entourage'!$B$2,_xlpm.texte)),'Référentiel entourage'!$A$2,""),IF(ISNUMBER(SEARCH('Référentiel entourage'!$B$3,_xlpm.texte)),'Référentiel entourage'!$A$3,""),IF(ISNUMBER(SEARCH('Référentiel entourage'!$B$4,_xlpm.texte)),'Référentiel entourage'!$A$4,""),IF(ISNUMBER(SEARCH('Référentiel entourage'!$B$5,_xlpm.texte)),'Référentiel entourage'!$A$5,""),IF(ISNUMBER(SEARCH('Référentiel entourage'!$B$6,_xlpm.texte)),'Référentiel entourage'!$A$6,""),IF(ISNUMBER(SEARCH('Référentiel entourage'!$B$7,_xlpm.texte)),'Référentiel entourage'!$A$7,""),IF(ISNUMBER(SEARCH('Référentiel entourage'!$B$8,_xlpm.texte)),'Référentiel entourage'!$A$8,""),IF(ISNUMBER(SEARCH('Référentiel entourage'!$B$9,_xlpm.texte)),'Référentiel entourage'!$A$9,""),IF(ISNUMBER(SEARCH('Référentiel entourage'!$B$10,_xlpm.texte)),'Référentiel entourage'!$A$10,""),IF(ISNUMBER(SEARCH('Référentiel entourage'!$B$11,_xlpm.texte)),'Référentiel entourage'!$A$11,""),IF(ISNUMBER(SEARCH('Référentiel entourage'!$B$12,_xlpm.texte)),'Référentiel entourage'!$A$12,""),IF(ISNUMBER(SEARCH('Référentiel entourage'!$B$13,_xlpm.texte)),'Référentiel entourage'!$A$13,""),IF(ISNUMBER(SEARCH('Référentiel entourage'!$B$14,_xlpm.texte)),'Référentiel entourage'!$A$14,""),IF(ISNUMBER(SEARCH('Référentiel entourage'!$B$15,_xlpm.texte)),'Référentiel entourage'!$A$15,""),IF(ISNUMBER(SEARCH('Référentiel entourage'!$B$16,_xlpm.texte)),'Référentiel entourage'!$A$16,""),IF(ISNUMBER(SEARCH('Référentiel entourage'!$B$17,_xlpm.texte)),'Référentiel entourage'!$A$17,""),IF(ISNUMBER(SEARCH('Référentiel entourage'!$B$18,_xlpm.texte)),'Référentiel entourage'!$A$18,""),IF(ISNUMBER(SEARCH('Référentiel entourage'!$B$19,_xlpm.texte)),'Référentiel entourage'!$A$19,""),IF(ISNUMBER(SEARCH('Référentiel entourage'!$B$20,_xlpm.texte)),'Référentiel entourage'!$A$20,""),IF(ISNUMBER(SEARCH('Référentiel entourage'!$B$21,_xlpm.texte)),'Référentiel entourage'!$A$21,""),IF(ISNUMBER(SEARCH('Référentiel entourage'!$B$22,_xlpm.texte)),'Référentiel entourage'!$A$22,""),IF(ISNUMBER(SEARCH('Référentiel entourage'!$B$23,_xlpm.texte)),'Référentiel entourage'!$A$23,""),IF(ISNUMBER(SEARCH('Référentiel entourage'!$B$24,_xlpm.texte)),'Référentiel entourage'!$A$24,"")))) -> pers-kurt-raab
A20: rwf-1973-gibier-de-passage | B20: Gibier de passage | C20: Wildwechsel | D20: 1973 | E20: Téléfilm | F20: 102 | G20: RFA | H20: Rainer Werner Fassbinder | I20: Rainer Werner Fassbinder, d’après la pièce de Franz Xaver Kroetz | J20: Dietrich Lohmann | K20: Thea Eymèsz | L20: Kurt Raab | M20: Ludwig van Beethoven | N20: Intertel ; Sender Freies Berlin | O20: Jörg von Liebenfels : Erwin Ruth Drexel : Hilda Eva Mattes : Hanni Harry Baer : Franz Rudolf Waldemar Brem : Dieter Hanna Schygulla : le médecin Kurt Raab : le chef Karl Scheydt : un policier Klaus Löwitsch : un policier Irm Hermann : une fonctionnaire de police Marquard Bohm : un fonctionnaire de police El Hedi ben Salem : un ami | P20: Assistante de réalisation : Irm Hermann Producteur exécutif : Gerhard Freund Format : couleur, 35 mm Diffusion : 9 janvier 1973 | Q20: Hanni, mineure issue d’un couple bourgeois, rencontre Franz, ouvrier de dix-neuf ans, et couche avec lui. Dénoncé par un camarade, Franz est condamné pour détournement de mineure. | X20: 1973 | Z20: Wikipédia : https://fr.wikipedia.org/wiki/Gibier_de_passage | AA20: À compléter | AB20: film-1973-gibier-de-passage | AC20: =IF(O20="","",_xlfn.TEXTJOIN("; ",TRUE,IF(ISNUMBER(SEARCH('Référentiel entourage'!$B$2,O20)),'Référentiel entourage'!$A$2,""),IF(ISNUMBER(SEARCH('Référentiel entourage'!$B$3,O20)),'Référentiel entourage'!$A$3,""),IF(ISNUMBER(SEARCH('Référentiel entourage'!$B$4,O20)),'Référentiel entourage'!$A$4,""),IF(ISNUMBER(SEARCH('Référentiel entourage'!$B$5,O20)),'Référentiel entourage'!$A$5,""),IF(ISNUMBER(SEARCH('Référentiel entourage'!$B$6,O20)),'Référentiel entourage'!$A$6,""),IF(ISNUMBER(SEARCH('Référentiel entourage'!$B$7,O20)),'Référentiel entourage'!$A$7,""),IF(ISNUMBER(SEARCH('Référentiel entourage'!$B$8,O20)),'Référentiel entourage'!$A$8,""),IF(ISNUMBER(SEARCH('Référentiel entourage'!$B$9,O20)),'Référentiel entourage'!$A$9,""),IF(ISNUMBER(SEARCH('Référentiel entourage'!$B$10,O20)),'Référentiel entourage'!$A$10,""),IF(ISNUMBER(SEARCH('Référentiel entourage'!$B$11,O20)),'Référentiel entourage'!$A$11,""),IF(ISNUMBER(SEARCH('Référentiel entourage'!$B$12,O20)),'Référentiel entourage'!$A$12,""),IF(ISNUMBER(SEARCH('Référentiel entourage'!$B$13,O20)),'Référentiel entourage'!$A$13,""),IF(ISNUMBER(SEARCH('Référentiel entourage'!$B$14,O20)),'Référentiel entourage'!$A$14,""),IF(ISNUMBER(SEARCH('Référentiel entourage'!$B$15,O20)),'Référentiel entourage'!$A$15,""),IF(ISNUMBER(SEARCH('Référentiel entourage'!$B$16,O20)),'Référentiel entourage'!$A$16,""),IF(ISNUMBER(SEARCH('Référentiel entourage'!$B$17,O20)),'Référentiel entourage'!$A$17,""),IF(ISNUMBER(SEARCH('Référentiel entourage'!$B$18,O20)),'Référentiel entourage'!$A$18,""),IF(ISNUMBER(SEARCH('Référentiel entourage'!$B$19,O20)),'Référentiel entourage'!$A$19,""),IF(ISNUMBER(SEARCH('Référentiel entourage'!$B$20,O20)),'Référentiel entourage'!$A$20,""),IF(ISNUMBER(SEARCH('Référentiel entourage'!$B$21,O20)),'Référentiel entourage'!$A$21,""),IF(ISNUMBER(SEARCH('Référentiel entourage'!$B$22,O20)),'Référentiel entourage'!$A$22,""),IF(ISNUMBER(SEARCH('Référentiel entourage'!$B$23,O20)),'Référentiel entourage'!$A$23,""),IF(ISNUMBER(SEARCH('Référentiel entourage'!$B$24,O20)),'Référentiel entourage'!$A$24,""))) -> pers-el-hedi-ben-salem; pers-irm-hermann; pers-kurt-raab; pers-hanna-schygulla | AD20: =_xlfn.LET(_xlpm.texte,_xlfn.TEXTJOIN(" | ",TRUE,H20:N20,P20),IF(_xlpm.texte="","",_xlfn.TEXTJOIN("; ",TRUE,IF(ISNUMBER(SEARCH('Référentiel entourage'!$B$2,_xlpm.texte)),'Référentiel entourage'!$A$2,""),IF(ISNUMBER(SEARCH('Référentiel entourage'!$B$3,_xlpm.texte)),'Référentiel entourage'!$A$3,""),IF(ISNUMBER(SEARCH('Référentiel entourage'!$B$4,_xlpm.texte)),'Référentiel entourage'!$A$4,""),IF(ISNUMBER(SEARCH('Référentiel entourage'!$B$5,_xlpm.texte)),'Référentiel entourage'!$A$5,""),IF(ISNUMBER(SEARCH('Référentiel entourage'!$B$6,_xlpm.texte)),'Référentiel entourage'!$A$6,""),IF(ISNUMBER(SEARCH('Référentiel entourage'!$B$7,_xlpm.texte)),'Référentiel entourage'!$A$7,""),IF(ISNUMBER(SEARCH('Référentiel entourage'!$B$8,_xlpm.texte)),'Référentiel entourage'!$A$8,""),IF(ISNUMBER(SEARCH('Référentiel entourage'!$B$9,_xlpm.texte)),'Référentiel entourage'!$A$9,""),IF(ISNUMBER(SEARCH('Référentiel entourage'!$B$10,_xlpm.texte)),'Référentiel entourage'!$A$10,""),IF(ISNUMBER(SEARCH('Référentiel entourage'!$B$11,_xlpm.texte)),'Référentiel entourage'!$A$11,""),IF(ISNUMBER(SEARCH('Référentiel entourage'!$B$12,_xlpm.texte)),'Référentiel entourage'!$A$12,""),IF(ISNUMBER(SEARCH('Référentiel entourage'!$B$13,_xlpm.texte)),'Référentiel entourage'!$A$13,""),IF(ISNUMBER(SEARCH('Référentiel entourage'!$B$14,_xlpm.texte)),'Référentiel entourage'!$A$14,""),IF(ISNUMBER(SEARCH('Référentiel entourage'!$B$15,_xlpm.texte)),'Référentiel entourage'!$A$15,""),IF(ISNUMBER(SEARCH('Référentiel entourage'!$B$16,_xlpm.texte)),'Référentiel entourage'!$A$16,""),IF(ISNUMBER(SEARCH('Référentiel entourage'!$B$17,_xlpm.texte)),'Référentiel entourage'!$A$17,""),IF(ISNUMBER(SEARCH('Référentiel entourage'!$B$18,_xlpm.texte)),'Référentiel entourage'!$A$18,""),IF(ISNUMBER(SEARCH('Référentiel entourage'!$B$19,_xlpm.texte)),'Référentiel entourage'!$A$19,""),IF(ISNUMBER(SEARCH('Référentiel entourage'!$B$20,_xlpm.texte)),'Référentiel entourage'!$A$20,""),IF(ISNUMBER(SEARCH('Référentiel entourage'!$B$21,_xlpm.texte)),'Référentiel entourage'!$A$21,""),IF(ISNUMBER(SEARCH('Référentiel entourage'!$B$22,_xlpm.texte)),'Référentiel entourage'!$A$22,""),IF(ISNUMBER(SEARCH('Référentiel entourage'!$B$23,_xlpm.texte)),'Référentiel entourage'!$A$23,""),IF(ISNUMBER(SEARCH('Référentiel entourage'!$B$24,_xlpm.texte)),'Référentiel entourage'!$A$24,"")))) -> pers-irm-hermann; pers-kurt-raab
A21: rwf-1973-monde-sur-fil | B21: Le Monde sur un fil | C21: Welt am Draht | D21: 1973 | E21: Téléfilm en deux parties | F21: 212 | G21: RFA | H21: Rainer Werner Fassbinder | I21: Rainer Werner Fassbinder, d’après Simulacron 3 de Daniel F. Galouye | N21: WDR | P21: Diffusion initiale : 14 et 16 octobre 1973 Production télévisuelle de la Westdeutscher Rundfunk (WDR) | Q21: À l’Institut de cybernétique et des sciences à venir, le Simulacron simule un monde peuplé d’unités humaines. Après la mort mystérieuse du professeur Vollmer et la disparition de Gunther Lause, Fred Stiller enquête. Il découvre progressivement que son propre monde pourrait lui aussi n’être qu’une simulation. | T21: Daniel F. Galouye, Simulacron 3 | U21: Films_images/Le_Monde_sur_un_fil.jpg | X21: 1973 | Y21: science-fiction|simulation|réalité virtuelle|identité|cybernétique|télévision | Z21: RWF_Notes sur les films.docx | AA21: Partiellement documenté | AB21: film-1973-le-monde-sur-un-fil | AC21: =IF(O21="","",_xlfn.TEXTJOIN("; ",TRUE,IF(ISNUMBER(SEARCH('Référentiel entourage'!$B$2,O21)),'Référentiel entourage'!$A$2,""),IF(ISNUMBER(SEARCH('Référentiel entourage'!$B$3,O21)),'Référentiel entourage'!$A$3,""),IF(ISNUMBER(SEARCH('Référentiel entourage'!$B$4,O21)),'Référentiel entourage'!$A$4,""),IF(ISNUMBER(SEARCH('Référentiel entourage'!$B$5,O21)),'Référentiel entourage'!$A$5,""),IF(ISNUMBER(SEARCH('Référentiel entourage'!$B$6,O21)),'Référentiel entourage'!$A$6,""),IF(ISNUMBER(SEARCH('Référentiel entourage'!$B$7,O21)),'Référentiel entourage'!$A$7,""),IF(ISNUMBER(SEARCH('Référentiel entourage'!$B$8,O21)),'Référentiel entourage'!$A$8,""),IF(ISNUMBER(SEARCH('Référentiel entourage'!$B$9,O21)),'Référentiel entourage'!$A$9,""),IF(ISNUMBER(SEARCH('Référentiel entourage'!$B$10,O21)),'Référentiel entourage'!$A$10,""),IF(ISNUMBER(SEARCH('Référentiel entourage'!$B$11,O21)),'Référentiel entourage'!$A$11,""),IF(ISNUMBER(SEARCH('Référentiel entourage'!$B$12,O21)),'Référentiel entourage'!$A$12,""),IF(ISNUMBER(SEARCH('Référentiel entourage'!$B$13,O21)),'Référentiel entourage'!$A$13,""),IF(ISNUMBER(SEARCH('Référentiel entourage'!$B$14,O21)),'Référentiel entourage'!$A$14,""),IF(ISNUMBER(SEARCH('Référentiel entourage'!$B$15,O21)),'Référentiel entourage'!$A$15,""),IF(ISNUMBER(SEARCH('Référentiel entourage'!$B$16,O21)),'Référentiel entourage'!$A$16,""),IF(ISNUMBER(SEARCH('Référentiel entourage'!$B$17,O21)),'Référentiel entourage'!$A$17,""),IF(ISNUMBER(SEARCH('Référentiel entourage'!$B$18,O21)),'Référentiel entourage'!$A$18,""),IF(ISNUMBER(SEARCH('Référentiel entourage'!$B$19,O21)),'Référentiel entourage'!$A$19,""),IF(ISNUMBER(SEARCH('Référentiel entourage'!$B$20,O21)),'Référentiel entourage'!$A$20,""),IF(ISNUMBER(SEARCH('Référentiel entourage'!$B$21,O21)),'Référentiel entourage'!$A$21,""),IF(ISNUMBER(SEARCH('Référentiel entourage'!$B$22,O21)),'Référentiel entourage'!$A$22,""),IF(ISNUMBER(SEARCH('Référentiel entourage'!$B$23,O21)),'Référentiel entourage'!$A$23,""),IF(ISNUMBER(SEARCH('Référentiel entourage'!$B$24,O21)),'Référentiel entourage'!$A$24,""))) | AD21: =_xlfn.LET(_xlpm.texte,_xlfn.TEXTJOIN(" | ",TRUE,H21:N21,P21),IF(_xlpm.texte="","",_xlfn.TEXTJOIN("; ",TRUE,IF(ISNUMBER(SEARCH('Référentiel entourage'!$B$2,_xlpm.texte)),'Référentiel entourage'!$A$2,""),IF(ISNUMBER(SEARCH('Référentiel entourage'!$B$3,_xlpm.texte)),'Référentiel entourage'!$A$3,""),IF(ISNUMBER(SEARCH('Référentiel entourage'!$B$4,_xlpm.texte)),'Référentiel entourage'!$A$4,""),IF(ISNUMBER(SEARCH('Référentiel entourage'!$B$5,_xlpm.texte)),'Référentiel entourage'!$A$5,""),IF(ISNUMBER(SEARCH('Référentiel entourage'!$B$6,_xlpm.texte)),'Référentiel entourage'!$A$6,""),IF(ISNUMBER(SEARCH('Référentiel entourage'!$B$7,_xlpm.texte)),'Référentiel entourage'!$A$7,""),IF(ISNUMBER(SEARCH('Référentiel entourage'!$B$8,_xlpm.texte)),'Référentiel entourage'!$A$8,""),IF(ISNUMBER(SEARCH('Référentiel entourage'!$B$9,_xlpm.texte)),'Référentiel entourage'!$A$9,""),IF(ISNUMBER(SEARCH('Référentiel entourage'!$B$10,_xlpm.texte)),'Référentiel entourage'!$A$10,""),IF(ISNUMBER(SEARCH('Référentiel entourage'!$B$11,_xlpm.texte)),'Référentiel entourage'!$A$11,""),IF(ISNUMBER(SEARCH('Référentiel entourage'!$B$12,_xlpm.texte)),'Référentiel entourage'!$A$12,""),IF(ISNUMBER(SEARCH('Référentiel entourage'!$B$13,_xlpm.texte)),'Référentiel entourage'!$A$13,""),IF(ISNUMBER(SEARCH('Référentiel entourage'!$B$14,_xlpm.texte)),'Référentiel entourage'!$A$14,""),IF(ISNUMBER(SEARCH('Référentiel entourage'!$B$15,_xlpm.texte)),'Référentiel entourage'!$A$15,""),IF(ISNUMBER(SEARCH('Référentiel entourage'!$B$16,_xlpm.texte)),'Référentiel entourage'!$A$16,""),IF(ISNUMBER(SEARCH('Référentiel entourage'!$B$17,_xlpm.texte)),'Référentiel entourage'!$A$17,""),IF(ISNUMBER(SEARCH('Référentiel entourage'!$B$18,_xlpm.texte)),'Référentiel entourage'!$A$18,""),IF(ISNUMBER(SEARCH('Référentiel entourage'!$B$19,_xlpm.texte)),'Référentiel entourage'!$A$19,""),IF(ISNUMBER(SEARCH('Référentiel entourage'!$B$20,_xlpm.texte)),'Référentiel entourage'!$A$20,""),IF(ISNUMBER(SEARCH('Référentiel entourage'!$B$21,_xlpm.texte)),'Référentiel entourage'!$A$21,""),IF(ISNUMBER(SEARCH('Référentiel entourage'!$B$22,_xlpm.texte)),'Référentiel entourage'!$A$22,""),IF(ISNUMBER(SEARCH('Référentiel entourage'!$B$23,_xlpm.texte)),'Référentiel entourage'!$A$23,""),IF(ISNUMBER(SEARCH('Référentiel entourage'!$B$24,_xlpm.texte)),'Référentiel entourage'!$A$24,""))))
A22: rwf-1974-tous-autres-ali | B22: Tous les autres s’appellent Ali | C22: Angst essen Seele auf | D22: 1974 | E22: Long métrage | F22: 93 | G22: RFA | H22: Rainer Werner Fassbinder | I22: Rainer Werner Fassbinder | O22: Brigitte Mira : Emmi Kurowski El Hedi ben Salem : Ali Barbara Valentin : Barbara Irm Hermann : Krista Rainer Werner Fassbinder : Eugen Karl Scheydt : Albert Elma Karlowa : Mlle Kargus Anita Bucher : Mlle Ellis Gusti Kreissl : Paula Doris Mattes : Mlle Angermeyer Margit Symo : Hedwig Katharina Herberg : fille du bar Lilo Pempeit : Mlle Munchmeyer Peter Chatel : Bruno | P22: Langues originales : allemand, arabe Sortie RFA : 5 mars 1974 Sortie États-Unis : 31 octobre 1974 | Q22: Dans l’Allemagne de l’Ouest des années 1970, Emmi, veuve âgée, et Ali, travailleur immigré marocain, tombent amoureux puis se marient. Leur couple affronte le racisme, les préjugés et l’hostilité de l’entourage. Lorsque cette hostilité s’atténue par intérêt, de nouvelles tensions apparaissent au sein du couple. | U22: Films_images/Tous_les_autres_s_appellent_Ali.jpg | X22: 1974 | Y22: racisme|immigration|amour|solitude|classe sociale|Douglas Sirk | Z22: RWF_Notes sur les films.docx | AA22: Documenté | AB22: film-1974-tous-les-autres-s-appellent-ali | AC22: =IF(O22="","",_xlfn.TEXTJOIN("; ",TRUE,IF(ISNUMBER(SEARCH('Référentiel entourage'!$B$2,O22)),'Référentiel entourage'!$A$2,""),IF(ISNUMBER(SEARCH('Référentiel entourage'!$B$3,O22)),'Référentiel entourage'!$A$3,""),IF(ISNUMBER(SEARCH('Référentiel entourage'!$B$4,O22)),'Référentiel entourage'!$A$4,""),IF(ISNUMBER(SEARCH('Référentiel entourage'!$B$5,O22)),'Référentiel entourage'!$A$5,""),IF(ISNUMBER(SEARCH('Référentiel entourage'!$B$6,O22)),'Référentiel entourage'!$A$6,""),IF(ISNUMBER(SEARCH('Référentiel entourage'!$B$7,O22)),'Référentiel entourage'!$A$7,""),IF(ISNUMBER(SEARCH('Référentiel entourage'!$B$8,O22)),'Référentiel entourage'!$A$8,""),IF(ISNUMBER(SEARCH('Référentiel entourage'!$B$9,O22)),'Référentiel entourage'!$A$9,""),IF(ISNUMBER(SEARCH('Référentiel entourage'!$B$10,O22)),'Référentiel entourage'!$A$10,""),IF(ISNUMBER(SEARCH('Référentiel entourage'!$B$11,O22)),'Référentiel entourage'!$A$11,""),IF(ISNUMBER(SEARCH('Référentiel entourage'!$B$12,O22)),'Référentiel entourage'!$A$12,""),IF(ISNUMBER(SEARCH('Référentiel entourage'!$B$13,O22)),'Référentiel entourage'!$A$13,""),IF(ISNUMBER(SEARCH('Référentiel entourage'!$B$14,O22)),'Référentiel entourage'!$A$14,""),IF(ISNUMBER(SEARCH('Référentiel entourage'!$B$15,O22)),'Référentiel entourage'!$A$15,""),IF(ISNUMBER(SEARCH('Référentiel entourage'!$B$16,O22)),'Référentiel entourage'!$A$16,""),IF(ISNUMBER(SEARCH('Référentiel entourage'!$B$17,O22)),'Référentiel entourage'!$A$17,""),IF(ISNUMBER(SEARCH('Référentiel entourage'!$B$18,O22)),'Référentiel entourage'!$A$18,""),IF(ISNUMBER(SEARCH('Référentiel entourage'!$B$19,O22)),'Référentiel entourage'!$A$19,""),IF(ISNUMBER(SEARCH('Référentiel entourage'!$B$20,O22)),'Référentiel entourage'!$A$20,""),IF(ISNUMBER(SEARCH('Référentiel entourage'!$B$21,O22)),'Référentiel entourage'!$A$21,""),IF(ISNUMBER(SEARCH('Référentiel entourage'!$B$22,O22)),'Référentiel entourage'!$A$22,""),IF(ISNUMBER(SEARCH('Référentiel entourage'!$B$23,O22)),'Référentiel entourage'!$A$23,""),IF(ISNUMBER(SEARCH('Référentiel entourage'!$B$24,O22)),'Référentiel entourage'!$A$24,""))) -> pers-el-hedi-ben-salem; pers-peter-chatel; pers-lilo-pempeit; pers-irm-hermann; pers-brigitte-mira | AD22: =_xlfn.LET(_xlpm.texte,_xlfn.TEXTJOIN(" | ",TRUE,H22:N22,P22),IF(_xlpm.texte="","",_xlfn.TEXTJOIN("; ",TRUE,IF(ISNUMBER(SEARCH('Référentiel entourage'!$B$2,_xlpm.texte)),'Référentiel entourage'!$A$2,""),IF(ISNUMBER(SEARCH('Référentiel entourage'!$B$3,_xlpm.texte)),'Référentiel entourage'!$A$3,""),IF(ISNUMBER(SEARCH('Référentiel entourage'!$B$4,_xlpm.texte)),'Référentiel entourage'!$A$4,""),IF(ISNUMBER(SEARCH('Référentiel entourage'!$B$5,_xlpm.texte)),'Référentiel entourage'!$A$5,""),IF(ISNUMBER(SEARCH('Référentiel entourage'!$B$6,_xlpm.texte)),'Référentiel entourage'!$A$6,""),IF(ISNUMBER(SEARCH('Référentiel entourage'!$B$7,_xlpm.texte)),'Référentiel entourage'!$A$7,""),IF(ISNUMBER(SEARCH('Référentiel entourage'!$B$8,_xlpm.texte)),'Référentiel entourage'!$A$8,""),IF(ISNUMBER(SEARCH('Référentiel entourage'!$B$9,_xlpm.texte)),'Référentiel entourage'!$A$9,""),IF(ISNUMBER(SEARCH('Référentiel entourage'!$B$10,_xlpm.texte)),'Référentiel entourage'!$A$10,""),IF(ISNUMBER(SEARCH('Référentiel entourage'!$B$11,_xlpm.texte)),'Référentiel entourage'!$A$11,""),IF(ISNUMBER(SEARCH('Référentiel entourage'!$B$12,_xlpm.texte)),'Référentiel entourage'!$A$12,""),IF(ISNUMBER(SEARCH('Référentiel entourage'!$B$13,_xlpm.texte)),'Référentiel entourage'!$A$13,""),IF(ISNUMBER(SEARCH('Référentiel entourage'!$B$14,_xlpm.texte)),'Référentiel entourage'!$A$14,""),IF(ISNUMBER(SEARCH('Référentiel entourage'!$B$15,_xlpm.texte)),'Référentiel entourage'!$A$15,""),IF(ISNUMBER(SEARCH('Référentiel entourage'!$B$16,_xlpm.texte)),'Référentiel entourage'!$A$16,""),IF(ISNUMBER(SEARCH('Référentiel entourage'!$B$17,_xlpm.texte)),'Référentiel entourage'!$A$17,""),IF(ISNUMBER(SEARCH('Référentiel entourage'!$B$18,_xlpm.texte)),'Référentiel entourage'!$A$18,""),IF(ISNUMBER(SEARCH('Référentiel entourage'!$B$19,_xlpm.texte)),'Référentiel entourage'!$A$19,""),IF(ISNUMBER(SEARCH('Référentiel entourage'!$B$20,_xlpm.texte)),'Référentiel entourage'!$A$20,""),IF(ISNUMBER(SEARCH('Référentiel entourage'!$B$21,_xlpm.texte)),'Référentiel entourage'!$A$21,""),IF(ISNUMBER(SEARCH('Référentiel entourage'!$B$22,_xlpm.texte)),'Référentiel entourage'!$A$22,""),IF(ISNUMBER(SEARCH('Référentiel entourage'!$B$23,_xlpm.texte)),'Référentiel entourage'!$A$23,""),IF(ISNUMBER(SEARCH('Référentiel entourage'!$B$24,_xlpm.texte)),'Référentiel entourage'!$A$24,""))))
A23: rwf-1974-effi-briest | B23: Effi Briest | C23: Fontane Effi Briest | D23: 1974 | E23: Long métrage | F23: 140 | G23: RFA | H23: Rainer Werner Fassbinder | I23: Rainer Werner Fassbinder, d’après le roman de Theodor Fontane | J23: Jürgen Jürges ; Dietrich Lohmann | K23: Thea Eymèsz | L23: Kurt Raab | N23: Rainer Werner Fassbinder | O23: Hanna Schygulla : Effi Briest Wolfgang Schenck : baron Geert von Innstetten Ulli Lommel : major Crampas Lilo Pempeit : Louise von Briest Herbert Steinmetz : M. Briest Ursula Strätz : Roswitha Irm Hermann : Johanna Karlheinz Böhm : conseiller Wüllersdorf Barbara Lass : la cuisinière polonaise Hark Bohm : Gieshübler Rudolf Lenz : conseiller Rummschüttel Barbara Valentin : Marietta Tripelli Karl Scheydt : Kruse Theo Tecklenburg : pasteur Niemeyer Eva Mattes : Hilda Andrea Schober : Annie | P23: Noir et blanc, 1,37:1, mono Genre : drame Sortie : 1974 | Q23: À la fin du XIXe siècle, Effi Briest, dix-sept ans, épouse le baron von Innstetten, ancien prétendant de sa mère. Isolée dans une demeure provinciale et enfermée dans les conventions de son milieu, elle entretient une liaison avec le major Crampas. Des années plus tard, la découverte de leurs lettres déclenche duel, répudiation et exclusion sociale. | T23: Theodor Fontane, Effi Briest | U23: Films_images/Effi_Briest.jpg | X23: 1974 | Y23: adaptation littéraire|mariage|conventions sociales|patriarcat|Theodor Fontane|noir et blanc | Z23: RWF_Notes sur les films.docx | AA23: Documenté | AB23: film-1974-effi-briest | AC23: =IF(O23="","",_xlfn.TEXTJOIN("; ",TRUE,IF(ISNUMBER(SEARCH('Référentiel entourage'!$B$2,O23)),'Référentiel entourage'!$A$2,""),IF(ISNUMBER(SEARCH('Référentiel entourage'!$B$3,O23)),'Référentiel entourage'!$A$3,""),IF(ISNUMBER(SEARCH('Référentiel entourage'!$B$4,O23)),'Référentiel entourage'!$A$4,""),IF(ISNUMBER(SEARCH('Référentiel entourage'!$B$5,O23)),'Référentiel entourage'!$A$5,""),IF(ISNUMBER(SEARCH('Référentiel entourage'!$B$6,O23)),'Référentiel entourage'!$A$6,""),IF(ISNUMBER(SEARCH('Référentiel entourage'!$B$7,O23)),'Référentiel entourage'!$A$7,""),IF(ISNUMBER(SEARCH('Référentiel entourage'!$B$8,O23)),'Référentiel entourage'!$A$8,""),IF(ISNUMBER(SEARCH('Référentiel entourage'!$B$9,O23)),'Référentiel entourage'!$A$9,""),IF(ISNUMBER(SEARCH('Référentiel entourage'!$B$10,O23)),'Référentiel entourage'!$A$10,""),IF(ISNUMBER(SEARCH('Référentiel entourage'!$B$11,O23)),'Référentiel entourage'!$A$11,""),IF(ISNUMBER(SEARCH('Référentiel entourage'!$B$12,O23)),'Référentiel entourage'!$A$12,""),IF(ISNUMBER(SEARCH('Référentiel entourage'!$B$13,O23)),'Référentiel entourage'!$A$13,""),IF(ISNUMBER(SEARCH('Référentiel entourage'!$B$14,O23)),'Référentiel entourage'!$A$14,""),IF(ISNUMBER(SEARCH('Référentiel entourage'!$B$15,O23)),'Référentiel entourage'!$A$15,""),IF(ISNUMBER(SEARCH('Référentiel entourage'!$B$16,O23)),'Référentiel entourage'!$A$16,""),IF(ISNUMBER(SEARCH('Référentiel entourage'!$B$17,O23)),'Référentiel entourage'!$A$17,""),IF(ISNUMBER(SEARCH('Référentiel entourage'!$B$18,O23)),'Référentiel entourage'!$A$18,""),IF(ISNUMBER(SEARCH('Référentiel entourage'!$B$19,O23)),'Référentiel entourage'!$A$19,""),IF(ISNUMBER(SEARCH('Référentiel entourage'!$B$20,O23)),'Référentiel entourage'!$A$20,""),IF(ISNUMBER(SEARCH('Référentiel entourage'!$B$21,O23)),'Référentiel entourage'!$A$21,""),IF(ISNUMBER(SEARCH('Référentiel entourage'!$B$22,O23)),'Référentiel entourage'!$A$22,""),IF(ISNUMBER(SEARCH('Référentiel entourage'!$B$23,O23)),'Référentiel entourage'!$A$23,""),IF(ISNUMBER(SEARCH('Référentiel entourage'!$B$24,O23)),'Référentiel entourage'!$A$24,""))) -> pers-karlheinz-bohm; pers-hark-bohm; pers-lilo-pempeit; pers-irm-hermann; pers-ulli-lommel; pers-hanna-schygulla; pers-ursula-stratz | AD23: =_xlfn.LET(_xlpm.texte,_xlfn.TEXTJOIN(" | ",TRUE,H23:N23,P23),IF(_xlpm.texte="","",_xlfn.TEXTJOIN("; ",TRUE,IF(ISNUMBER(SEARCH('Référentiel entourage'!$B$2,_xlpm.texte)),'Référentiel entourage'!$A$2,""),IF(ISNUMBER(SEARCH('Référentiel entourage'!$B$3,_xlpm.texte)),'Référentiel entourage'!$A$3,""),IF(ISNUMBER(SEARCH('Référentiel entourage'!$B$4,_xlpm.texte)),'Référentiel entourage'!$A$4,""),IF(ISNUMBER(SEARCH('Référentiel entourage'!$B$5,_xlpm.texte)),'Référentiel entourage'!$A$5,""),IF(ISNUMBER(SEARCH('Référentiel entourage'!$B$6,_xlpm.texte)),'Référentiel entourage'!$A$6,""),IF(ISNUMBER(SEARCH('Référentiel entourage'!$B$7,_xlpm.texte)),'Référentiel entourage'!$A$7,""),IF(ISNUMBER(SEARCH('Référentiel entourage'!$B$8,_xlpm.texte)),'Référentiel entourage'!$A$8,""),IF(ISNUMBER(SEARCH('Référentiel entourage'!$B$9,_xlpm.texte)),'Référentiel entourage'!$A$9,""),IF(ISNUMBER(SEARCH('Référentiel entourage'!$B$10,_xlpm.texte)),'Référentiel entourage'!$A$10,""),IF(ISNUMBER(SEARCH('Référentiel entourage'!$B$11,_xlpm.texte)),'Référentiel entourage'!$A$11,""),IF(ISNUMBER(SEARCH('Référentiel entourage'!$B$12,_xlpm.texte)),'Référentiel entourage'!$A$12,""),IF(ISNUMBER(SEARCH('Référentiel entourage'!$B$13,_xlpm.texte)),'Référentiel entourage'!$A$13,""),IF(ISNUMBER(SEARCH('Référentiel entourage'!$B$14,_xlpm.texte)),'Référentiel entourage'!$A$14,""),IF(ISNUMBER(SEARCH('Référentiel entourage'!$B$15,_xlpm.texte)),'Référentiel entourage'!$A$15,""),IF(ISNUMBER(SEARCH('Référentiel entourage'!$B$16,_xlpm.texte)),'Référentiel entourage'!$A$16,""),IF(ISNUMBER(SEARCH('Référentiel entourage'!$B$17,_xlpm.texte)),'Référentiel entourage'!$A$17,""),IF(ISNUMBER(SEARCH('Référentiel entourage'!$B$18,_xlpm.texte)),'Référentiel entourage'!$A$18,""),IF(ISNUMBER(SEARCH('Référentiel entourage'!$B$19,_xlpm.texte)),'Référentiel entourage'!$A$19,""),IF(ISNUMBER(SEARCH('Référentiel entourage'!$B$20,_xlpm.texte)),'Référentiel entourage'!$A$20,""),IF(ISNUMBER(SEARCH('Référentiel entourage'!$B$21,_xlpm.texte)),'Référentiel entourage'!$A$21,""),IF(ISNUMBER(SEARCH('Référentiel entourage'!$B$22,_xlpm.texte)),'Référentiel entourage'!$A$22,""),IF(ISNUMBER(SEARCH('Référentiel entourage'!$B$23,_xlpm.texte)),'Référentiel entourage'!$A$23,""),IF(ISNUMBER(SEARCH('Référentiel entourage'!$B$24,_xlpm.texte)),'Référentiel entourage'!$A$24,"")))) -> pers-kurt-raab
A24: rwf-1974-nora-helmer | B24: Nora Helmer | D24: 1974 | E24: Téléfilm | F24: 101 | G24: RFA | H24: Rainer Werner Fassbinder | I24: D’après Une maison de poupée d’Henrik Ibsen, texte allemand de Bernhard Schulze | J24: Willi Raber ; Wilfried Mier ; Peter Weyrich ; Gisela Loew ; Hans Schugg | K24: Anne-Marie Bornheimer ; Friedrich Niquet | L24: Friedhelm Boehm | N24: Telefilm Saar pour la SR | O24: Margit Carstensen : Nora Joachim Hansen : Torvald Barbara Valentin : Mme Linde Ulli Lommel : Krogstad Klaus Löwitsch : Dr Rank Lilo Pempeit : Marie Irm Hermann : Helene | P24: Assistants de réalisation : Fritz Müller-Scherz ; Rainer Langhans Format : vidéo 2 pouces, couleur Tournage : 21 jours en mai 1973, studio de Sarrebruck Diffusion : 3 février 1974 | Q24: Nora, jeune femme au foyer, tente d’obtenir de son mari davantage d’argent afin de préparer leurs vacances, mais l’entreprise s’avère plus compliquée que prévu. | X24: 1974 | Z24: Wikipédia : https://fr.wikipedia.org/wiki/Nora_Helmer | AA24: À compléter | AB24: film-1974-nora-helmer | AC24: =IF(O24="","",_xlfn.TEXTJOIN("; ",TRUE,IF(ISNUMBER(SEARCH('Référentiel entourage'!$B$2,O24)),'Référentiel entourage'!$A$2,""),IF(ISNUMBER(SEARCH('Référentiel entourage'!$B$3,O24)),'Référentiel entourage'!$A$3,""),IF(ISNUMBER(SEARCH('Référentiel entourage'!$B$4,O24)),'Référentiel entourage'!$A$4,""),IF(ISNUMBER(SEARCH('Référentiel entourage'!$B$5,O24)),'Référentiel entourage'!$A$5,""),IF(ISNUMBER(SEARCH('Référentiel entourage'!$B$6,O24)),'Référentiel entourage'!$A$6,""),IF(ISNUMBER(SEARCH('Référentiel entourage'!$B$7,O24)),'Référentiel entourage'!$A$7,""),IF(ISNUMBER(SEARCH('Référentiel entourage'!$B$8,O24)),'Référentiel entourage'!$A$8,""),IF(ISNUMBER(SEARCH('Référentiel entourage'!$B$9,O24)),'Référentiel entourage'!$A$9,""),IF(ISNUMBER(SEARCH('Référentiel entourage'!$B$10,O24)),'Référentiel entourage'!$A$10,""),IF(ISNUMBER(SEARCH('Référentiel entourage'!$B$11,O24)),'Référentiel entourage'!$A$11,""),IF(ISNUMBER(SEARCH('Référentiel entourage'!$B$12,O24)),'Référentiel entourage'!$A$12,""),IF(ISNUMBER(SEARCH('Référentiel entourage'!$B$13,O24)),'Référentiel entourage'!$A$13,""),IF(ISNUMBER(SEARCH('Référentiel entourage'!$B$14,O24)),'Référentiel entourage'!$A$14,""),IF(ISNUMBER(SEARCH('Référentiel entourage'!$B$15,O24)),'Référentiel entourage'!$A$15,""),IF(ISNUMBER(SEARCH('Référentiel entourage'!$B$16,O24)),'Référentiel entourage'!$A$16,""),IF(ISNUMBER(SEARCH('Référentiel entourage'!$B$17,O24)),'Référentiel entourage'!$A$17,""),IF(ISNUMBER(SEARCH('Référentiel entourage'!$B$18,O24)),'Référentiel entourage'!$A$18,""),IF(ISNUMBER(SEARCH('Référentiel entourage'!$B$19,O24)),'Référentiel entourage'!$A$19,""),IF(ISNUMBER(SEARCH('Référentiel entourage'!$B$20,O24)),'Référentiel entourage'!$A$20,""),IF(ISNUMBER(SEARCH('Référentiel entourage'!$B$21,O24)),'Référentiel entourage'!$A$21,""),IF(ISNUMBER(SEARCH('Référentiel entourage'!$B$22,O24)),'Référentiel entourage'!$A$22,""),IF(ISNUMBER(SEARCH('Référentiel entourage'!$B$23,O24)),'Référentiel entourage'!$A$23,""),IF(ISNUMBER(SEARCH('Référentiel entourage'!$B$24,O24)),'Référentiel entourage'!$A$24,""))) -> pers-margit-carstensen; pers-lilo-pempeit; pers-irm-hermann; pers-ulli-lommel | AD24: =_xlfn.LET(_xlpm.texte,_xlfn.TEXTJOIN(" | ",TRUE,H24:N24,P24),IF(_xlpm.texte="","",_xlfn.TEXTJOIN("; ",TRUE,IF(ISNUMBER(SEARCH('Référentiel entourage'!$B$2,_xlpm.texte)),'Référentiel entourage'!$A$2,""),IF(ISNUMBER(SEARCH('Référentiel entourage'!$B$3,_xlpm.texte)),'Référentiel entourage'!$A$3,""),IF(ISNUMBER(SEARCH('Référentiel entourage'!$B$4,_xlpm.texte)),'Référentiel entourage'!$A$4,""),IF(ISNUMBER(SEARCH('Référentiel entourage'!$B$5,_xlpm.texte)),'Référentiel entourage'!$A$5,""),IF(ISNUMBER(SEARCH('Référentiel entourage'!$B$6,_xlpm.texte)),'Référentiel entourage'!$A$6,""),IF(ISNUMBER(SEARCH('Référentiel entourage'!$B$7,_xlpm.texte)),'Référentiel entourage'!$A$7,""),IF(ISNUMBER(SEARCH('Référentiel entourage'!$B$8,_xlpm.texte)),'Référentiel entourage'!$A$8,""),IF(ISNUMBER(SEARCH('Référentiel entourage'!$B$9,_xlpm.texte)),'Référentiel entourage'!$A$9,""),IF(ISNUMBER(SEARCH('Référentiel entourage'!$B$10,_xlpm.texte)),'Référentiel entourage'!$A$10,""),IF(ISNUMBER(SEARCH('Référentiel entourage'!$B$11,_xlpm.texte)),'Référentiel entourage'!$A$11,""),IF(ISNUMBER(SEARCH('Référentiel entourage'!$B$12,_xlpm.texte)),'Référentiel entourage'!$A$12,""),IF(ISNUMBER(SEARCH('Référentiel entourage'!$B$13,_xlpm.texte)),'Référentiel entourage'!$A$13,""),IF(ISNUMBER(SEARCH('Référentiel entourage'!$B$14,_xlpm.texte)),'Référentiel entourage'!$A$14,""),IF(ISNUMBER(SEARCH('Référentiel entourage'!$B$15,_xlpm.texte)),'Référentiel entourage'!$A$15,""),IF(ISNUMBER(SEARCH('Référentiel entourage'!$B$16,_xlpm.texte)),'Référentiel entourage'!$A$16,""),IF(ISNUMBER(SEARCH('Référentiel entourage'!$B$17,_xlpm.texte)),'Référentiel entourage'!$A$17,""),IF(ISNUMBER(SEARCH('Référentiel entourage'!$B$18,_xlpm.texte)),'Référentiel entourage'!$A$18,""),IF(ISNUMBER(SEARCH('Référentiel entourage'!$B$19,_xlpm.texte)),'Référentiel entourage'!$A$19,""),IF(ISNUMBER(SEARCH('Référentiel entourage'!$B$20,_xlpm.texte)),'Référentiel entourage'!$A$20,""),IF(ISNUMBER(SEARCH('Référentiel entourage'!$B$21,_xlpm.texte)),'Référentiel entourage'!$A$21,""),IF(ISNUMBER(SEARCH('Référentiel entourage'!$B$22,_xlpm.texte)),'Référentiel entourage'!$A$22,""),IF(ISNUMBER(SEARCH('Référentiel entourage'!$B$23,_xlpm.texte)),'Référentiel entourage'!$A$23,""),IF(ISNUMBER(SEARCH('Référentiel entourage'!$B$24,_xlpm.texte)),'Référentiel entourage'!$A$24,""))))
A25: rwf-1974-martha | B25: Martha | C25: Martha | D25: 1974 | E25: Téléfilm | F25: 116 | G25: RFA | H25: Rainer Werner Fassbinder | I25: Rainer Werner Fassbinder, d’après Cornell Woolrich | J25: Michael Ballhaus | K25: Liesgret Schmitt-Klink | L25: Kurt Raab | N25: Peter Märthesheimer | O25: Margit Carstensen : Martha Salomon, née Heyer Karlheinz Böhm : Helmut Salomon Barbara Valentin : Marianne Peter Chatel : Kaiser Kurt Raab : le secrétaire d’ambassade Karl Scheydt : un convive à la table de mariage Ingrid Caven : Ilse El Hedi ben Salem : le Libyen à Rome Gisela Fackeldey : la mère Adrian Hoven : le père | P25: Format : couleurs, 1,33:1, mono Date de diffusion : 1974 | Q25: Martha, jeune bibliothécaire, rencontre Helmut Salomon à Rome. Après leur mariage, l’apparence attentionnée de Helmut laisse place à une domination psychologique et physique méthodique. Lorsque Martha tente de fuir, un accident la rend paraplégique et la replace entièrement sous son contrôle. | S25: Étude de la médiatisation de l’intime et de la géométrie du pouvoir. Le film associe le mélodrame sirkien à une mise en scène de la claustration : travelling circulaire à 360°, surcadrages, miroirs et obstacles visuels matérialisent le piège conjugal. Le jeu de Margit Carstensen transforme le corps de Martha en lieu d’inscription de la soumission. Cette esthétique préfigure plusieurs motifs de la Trilogie RFA : circularité historique, externalisation des affects et héroïne devenue « femme-image ». | T25: Cornell Woolrich, source littéraire adaptée | X25: 1974 | Y25: mélodrame|violence conjugale|domination|claustration|Douglas Sirk|Michael Ballhaus | Z25: RWF_Notes sur les films.docx | AA25: Documenté | AB25: film-1974-martha | AC25: =IF(O25="","",_xlfn.TEXTJOIN("; ",TRUE,IF(ISNUMBER(SEARCH('Référentiel entourage'!$B$2,O25)),'Référentiel entourage'!$A$2,""),IF(ISNUMBER(SEARCH('Référentiel entourage'!$B$3,O25)),'Référentiel entourage'!$A$3,""),IF(ISNUMBER(SEARCH('Référentiel entourage'!$B$4,O25)),'Référentiel entourage'!$A$4,""),IF(ISNUMBER(SEARCH('Référentiel entourage'!$B$5,O25)),'Référentiel entourage'!$A$5,""),IF(ISNUMBER(SEARCH('Référentiel entourage'!$B$6,O25)),'Référentiel entourage'!$A$6,""),IF(ISNUMBER(SEARCH('Référentiel entourage'!$B$7,O25)),'Référentiel entourage'!$A$7,""),IF(ISNUMBER(SEARCH('Référentiel entourage'!$B$8,O25)),'Référentiel entourage'!$A$8,""),IF(ISNUMBER(SEARCH('Référentiel entourage'!$B$9,O25)),'Référentiel entourage'!$A$9,""),IF(ISNUMBER(SEARCH('Référentiel entourage'!$B$10,O25)),'Référentiel entourage'!$A$10,""),IF(ISNUMBER(SEARCH('Référentiel entourage'!$B$11,O25)),'Référentiel entourage'!$A$11,""),IF(ISNUMBER(SEARCH('Référentiel entourage'!$B$12,O25)),'Référentiel entourage'!$A$12,""),IF(ISNUMBER(SEARCH('Référentiel entourage'!$B$13,O25)),'Référentiel entourage'!$A$13,""),IF(ISNUMBER(SEARCH('Référentiel entourage'!$B$14,O25)),'Référentiel entourage'!$A$14,""),IF(ISNUMBER(SEARCH('Référentiel entourage'!$B$15,O25)),'Référentiel entourage'!$A$15,""),IF(ISNUMBER(SEARCH('Référentiel entourage'!$B$16,O25)),'Référentiel entourage'!$A$16,""),IF(ISNUMBER(SEARCH('Référentiel entourage'!$B$17,O25)),'Référentiel entourage'!$A$17,""),IF(ISNUMBER(SEARCH('Référentiel entourage'!$B$18,O25)),'Référentiel entourage'!$A$18,""),IF(ISNUMBER(SEARCH('Référentiel entourage'!$B$19,O25)),'Référentiel entourage'!$A$19,""),IF(ISNUMBER(SEARCH('Référentiel entourage'!$B$20,O25)),'Référentiel entourage'!$A$20,""),IF(ISNUMBER(SEARCH('Référentiel entourage'!$B$21,O25)),'Référentiel entourage'!$A$21,""),IF(ISNUMBER(SEARCH('Référentiel entourage'!$B$22,O25)),'Référentiel entourage'!$A$22,""),IF(ISNUMBER(SEARCH('Référentiel entourage'!$B$23,O25)),'Référentiel entourage'!$A$23,""),IF(ISNUMBER(SEARCH('Référentiel entourage'!$B$24,O25)),'Référentiel entourage'!$A$24,""))) -> pers-el-hedi-ben-salem; pers-karlheinz-bohm; pers-margit-carstensen; pers-ingrid-caven; pers-peter-chatel; pers-kurt-raab | AD25: =_xlfn.LET(_xlpm.texte,_xlfn.TEXTJOIN(" | ",TRUE,H25:N25,P25),IF(_xlpm.texte="","",_xlfn.TEXTJOIN("; ",TRUE,IF(ISNUMBER(SEARCH('Référentiel entourage'!$B$2,_xlpm.texte)),'Référentiel entourage'!$A$2,""),IF(ISNUMBER(SEARCH('Référentiel entourage'!$B$3,_xlpm.texte)),'Référentiel entourage'!$A$3,""),IF(ISNUMBER(SEARCH('Référentiel entourage'!$B$4,_xlpm.texte)),'Référentiel entourage'!$A$4,""),IF(ISNUMBER(SEARCH('Référentiel entourage'!$B$5,_xlpm.texte)),'Référentiel entourage'!$A$5,""),IF(ISNUMBER(SEARCH('Référentiel entourage'!$B$6,_xlpm.texte)),'Référentiel entourage'!$A$6,""),IF(ISNUMBER(SEARCH('Référentiel entourage'!$B$7,_xlpm.texte)),'Référentiel entourage'!$A$7,""),IF(ISNUMBER(SEARCH('Référentiel entourage'!$B$8,_xlpm.texte)),'Référentiel entourage'!$A$8,""),IF(ISNUMBER(SEARCH('Référentiel entourage'!$B$9,_xlpm.texte)),'Référentiel entourage'!$A$9,""),IF(ISNUMBER(SEARCH('Référentiel entourage'!$B$10,_xlpm.texte)),'Référentiel entourage'!$A$10,""),IF(ISNUMBER(SEARCH('Référentiel entourage'!$B$11,_xlpm.texte)),'Référentiel entourage'!$A$11,""),IF(ISNUMBER(SEARCH('Référentiel entourage'!$B$12,_xlpm.texte)),'Référentiel entourage'!$A$12,""),IF(ISNUMBER(SEARCH('Référentiel entourage'!$B$13,_xlpm.texte)),'Référentiel entourage'!$A$13,""),IF(ISNUMBER(SEARCH('Référentiel entourage'!$B$14,_xlpm.texte)),'Référentiel entourage'!$A$14,""),IF(ISNUMBER(SEARCH('Référentiel entourage'!$B$15,_xlpm.texte)),'Référentiel entourage'!$A$15,""),IF(ISNUMBER(SEARCH('Référentiel entourage'!$B$16,_xlpm.texte)),'Référentiel entourage'!$A$16,""),IF(ISNUMBER(SEARCH('Référentiel entourage'!$B$17,_xlpm.texte)),'Référentiel entourage'!$A$17,""),IF(ISNUMBER(SEARCH('Référentiel entourage'!$B$18,_xlpm.texte)),'Référentiel entourage'!$A$18,""),IF(ISNUMBER(SEARCH('Référentiel entourage'!$B$19,_xlpm.texte)),'Référentiel entourage'!$A$19,""),IF(ISNUMBER(SEARCH('Référentiel entourage'!$B$20,_xlpm.texte)),'Référentiel entourage'!$A$20,""),IF(ISNUMBER(SEARCH('Référentiel entourage'!$B$21,_xlpm.texte)),'Référentiel entourage'!$A$21,""),IF(ISNUMBER(SEARCH('Référentiel entourage'!$B$22,_xlpm.texte)),'Référentiel entourage'!$A$22,""),IF(ISNUMBER(SEARCH('Référentiel entourage'!$B$23,_xlpm.texte)),'Référentiel entourage'!$A$23,""),IF(ISNUMBER(SEARCH('Référentiel entourage'!$B$24,_xlpm.texte)),'Référentiel entourage'!$A$24,"")))) -> pers-michael-ballhaus; pers-kurt-raab
A26: rwf-1975-droit-plus-fort | B26: Le Droit du plus fort | C26: Faustrecht der Freiheit | D26: 1975 | E26: Long métrage | F26: 123 | G26: RFA | H26: Rainer Werner Fassbinder | I26: Rainer Werner Fassbinder et Christian Hohoff | J26: Michael Ballhaus | K26: Thea Eymèsz | M26: Peer Raben | N26: Rainer Werner Fassbinder ; City Film ; Tango Film | O26: Rainer Werner Fassbinder : Franz Biberkopf, dit Fox Peter Chatel : Eugen Thiess Karlheinz Böhm : Max Adrian Hoven : le père d’Eugen Ulla Jacobsson : la mère d’Eugen Harry Baer : Philip Irm Hermann : Mme Chérie Brigitte Mira : une commerçante Rudolf Lenz : l’avocat Karl Scheydt : Klaus Hans Zander : Springer Kurt Raab : Wodka-Peter Peter Kern : le fleuriste Ingrid Caven : la chanteuse du bar Barbara Valentin : la femme de Max El Hedi ben Salem : l’homme de Marrakech | P26: Format : Eastmancolor, 1,66:1, mono Langues : allemand, français et anglais Sortie RFA : 6 juin 1975 Sortie France : 17 septembre 1975 | Q26: Fox, ouvrier de fête foraine sans argent, gagne à la loterie. Il tombe amoureux d’Eugen, bourgeois raffiné dont la famille traverse une crise financière. Introduit dans ce milieu, Fox est progressivement dépouillé de son argent, de ses biens et de son identité sociale. | S26: Le film articule mélodrame, lutte des classes et exploitation affective. Le gain à la loterie ouvre un cycle provisoire de bonheur qui se referme sur la dépossession et la mort de Fox. La relation amoureuse ne supprime pas les rapports de domination : le capital culturel et les codes bourgeois transforment l’intimité en mécanisme d’exploitation. | U26: Films_images/Le_Droit_du_plus_fort.jpg | X26: 1975 | Y26: homosexualité|classe sociale|argent|exploitation|mélodrame|bourgeoisie | Z26: RWF_Notes sur les films.docx | AA26: Documenté | AB26: film-1975-le-droit-du-plus-fort | AC26: =IF(O26="","",_xlfn.TEXTJOIN("; ",TRUE,IF(ISNUMBER(SEARCH('Référentiel entourage'!$B$2,O26)),'Référentiel entourage'!$A$2,""),IF(ISNUMBER(SEARCH('Référentiel entourage'!$B$3,O26)),'Référentiel entourage'!$A$3,""),IF(ISNUMBER(SEARCH('Référentiel entourage'!$B$4,O26)),'Référentiel entourage'!$A$4,""),IF(ISNUMBER(SEARCH('Référentiel entourage'!$B$5,O26)),'Référentiel entourage'!$A$5,""),IF(ISNUMBER(SEARCH('Référentiel entourage'!$B$6,O26)),'Référentiel entourage'!$A$6,""),IF(ISNUMBER(SEARCH('Référentiel entourage'!$B$7,O26)),'Référentiel entourage'!$A$7,""),IF(ISNUMBER(SEARCH('Référentiel entourage'!$B$8,O26)),'Référentiel entourage'!$A$8,""),IF(ISNUMBER(SEARCH('Référentiel entourage'!$B$9,O26)),'Référentiel entourage'!$A$9,""),IF(ISNUMBER(SEARCH('Référentiel entourage'!$B$10,O26)),'Référentiel entourage'!$A$10,""),IF(ISNUMBER(SEARCH('Référentiel entourage'!$B$11,O26)),'Référentiel entourage'!$A$11,""),IF(ISNUMBER(SEARCH('Référentiel entourage'!$B$12,O26)),'Référentiel entourage'!$A$12,""),IF(ISNUMBER(SEARCH('Référentiel entourage'!$B$13,O26)),'Référentiel entourage'!$A$13,""),IF(ISNUMBER(SEARCH('Référentiel entourage'!$B$14,O26)),'Référentiel entourage'!$A$14,""),IF(ISNUMBER(SEARCH('Référentiel entourage'!$B$15,O26)),'Référentiel entourage'!$A$15,""),IF(ISNUMBER(SEARCH('Référentiel entourage'!$B$16,O26)),'Référentiel entourage'!$A$16,""),IF(ISNUMBER(SEARCH('Référentiel entourage'!$B$17,O26)),'Référentiel entourage'!$A$17,""),IF(ISNUMBER(SEARCH('Référentiel entourage'!$B$18,O26)),'Référentiel entourage'!$A$18,""),IF(ISNUMBER(SEARCH('Référentiel entourage'!$B$19,O26)),'Référentiel entourage'!$A$19,""),IF(ISNUMBER(SEARCH('Référentiel entourage'!$B$20,O26)),'Référentiel entourage'!$A$20,""),IF(ISNUMBER(SEARCH('Référentiel entourage'!$B$21,O26)),'Référentiel entourage'!$A$21,""),IF(ISNUMBER(SEARCH('Référentiel entourage'!$B$22,O26)),'Référentiel entourage'!$A$22,""),IF(ISNUMBER(SEARCH('Référentiel entourage'!$B$23,O26)),'Référentiel entourage'!$A$23,""),IF(ISNUMBER(SEARCH('Référentiel entourage'!$B$24,O26)),'Référentiel entourage'!$A$24,""))) -> pers-el-hedi-ben-salem; pers-karlheinz-bohm; pers-ingrid-caven; pers-peter-chatel; pers-irm-hermann; pers-brigitte-mira; pers-kurt-raab | AD26: =_xlfn.LET(_xlpm.texte,_xlfn.TEXTJOIN(" | ",TRUE,H26:N26,P26),IF(_xlpm.texte="","",_xlfn.TEXTJOIN("; ",TRUE,IF(ISNUMBER(SEARCH('Référentiel entourage'!$B$2,_xlpm.texte)),'Référentiel entourage'!$A$2,""),IF(ISNUMBER(SEARCH('Référentiel entourage'!$B$3,_xlpm.texte)),'Référentiel entourage'!$A$3,""),IF(ISNUMBER(SEARCH('Référentiel entourage'!$B$4,_xlpm.texte)),'Référentiel entourage'!$A$4,""),IF(ISNUMBER(SEARCH('Référentiel entourage'!$B$5,_xlpm.texte)),'Référentiel entourage'!$A$5,""),IF(ISNUMBER(SEARCH('Référentiel entourage'!$B$6,_xlpm.texte)),'Référentiel entourage'!$A$6,""),IF(ISNUMBER(SEARCH('Référentiel entourage'!$B$7,_xlpm.texte)),'Référentiel entourage'!$A$7,""),IF(ISNUMBER(SEARCH('Référentiel entourage'!$B$8,_xlpm.texte)),'Référentiel entourage'!$A$8,""),IF(ISNUMBER(SEARCH('Référentiel entourage'!$B$9,_xlpm.texte)),'Référentiel entourage'!$A$9,""),IF(ISNUMBER(SEARCH('Référentiel entourage'!$B$10,_xlpm.texte)),'Référentiel entourage'!$A$10,""),IF(ISNUMBER(SEARCH('Référentiel entourage'!$B$11,_xlpm.texte)),'Référentiel entourage'!$A$11,""),IF(ISNUMBER(SEARCH('Référentiel entourage'!$B$12,_xlpm.texte)),'Référentiel entourage'!$A$12,""),IF(ISNUMBER(SEARCH('Référentiel entourage'!$B$13,_xlpm.texte)),'Référentiel entourage'!$A$13,""),IF(ISNUMBER(SEARCH('Référentiel entourage'!$B$14,_xlpm.texte)),'Référentiel entourage'!$A$14,""),IF(ISNUMBER(SEARCH('Référentiel entourage'!$B$15,_xlpm.texte)),'Référentiel entourage'!$A$15,""),IF(ISNUMBER(SEARCH('Référentiel entourage'!$B$16,_xlpm.texte)),'Référentiel entourage'!$A$16,""),IF(ISNUMBER(SEARCH('Référentiel entourage'!$B$17,_xlpm.texte)),'Référentiel entourage'!$A$17,""),IF(ISNUMBER(SEARCH('Référentiel entourage'!$B$18,_xlpm.texte)),'Référentiel entourage'!$A$18,""),IF(ISNUMBER(SEARCH('Référentiel entourage'!$B$19,_xlpm.texte)),'Référentiel entourage'!$A$19,""),IF(ISNUMBER(SEARCH('Référentiel entourage'!$B$20,_xlpm.texte)),'Référentiel entourage'!$A$20,""),IF(ISNUMBER(SEARCH('Référentiel entourage'!$B$21,_xlpm.texte)),'Référentiel entourage'!$A$21,""),IF(ISNUMBER(SEARCH('Référentiel entourage'!$B$22,_xlpm.texte)),'Référentiel entourage'!$A$22,""),IF(ISNUMBER(SEARCH('Référentiel entourage'!$B$23,_xlpm.texte)),'Référentiel entourage'!$A$23,""),IF(ISNUMBER(SEARCH('Référentiel entourage'!$B$24,_xlpm.texte)),'Référentiel entourage'!$A$24,"")))) -> pers-michael-ballhaus; pers-peer-raben
A27: rwf-1975-maman-kusters | B27: Maman Küsters s’en va au ciel | C27: Mutter Küsters' Fahrt zum Himmel | D27: 1975 | E27: Long métrage | F27: 120 | G27: RFA | H27: Rainer Werner Fassbinder | I27: Rainer Werner Fassbinder, Kurt Raab et Heinrich Zille | J27: Michael Ballhaus | K27: Thea Eymèsz | L27: Kurt Raab | M27: Peer Raben | N27: Filmverlag der Autoren ; Tango Film | O27: Brigitte Mira : Emma Küsters Ingrid Caven : Corinna Margit Carstensen : Mme Thälmann Karlheinz Böhm : Thälmann Irm Hermann : Helene Gottfried John : Niemeyer Peter Kern : propriétaire du night-club Kurt Raab : Gustav Gustav Holzapfel : Herr Holzapfel Lilo Pempeit : secrétaire Peter Chatel : photographe Vitus Zeplichal : journaliste Volker Spengler : photographe Y Sa Lo : terroriste Armin Meier : Ernst Matthias Fuchs : Knab | P27: Direction artistique : Ruediger Schmid Assistant réalisateur : Renate Leiffer Maquillage : Jo Braun Son : Wolfgang Hoffmann Format : couleurs, 1,37:1, mono Sortie RFA : 7 juillet 1975 Sortie France : 19 janvier 1977 | Q27: Après que son mari ouvrier a tué son patron puis s’est suicidé, Emma Küsters cherche à défendre sa mémoire contre la presse à sensation. Délaissée par ses enfants, elle se rapproche d’abord de militants communistes, puis d’un groupe anarchiste qui transforme son combat en action politique. | S27: La fin allemande remplace le dénouement spectaculaire par des cartons reprenant les dernières pages du scénario. Ce refus du pathos produit une distanciation brechtienne : le personnage disparaît de l’image et devient littéralement un objet de discours et de récupération politique. Une fin alternative, tournée pour le marché américain, offre au contraire une consolation volontairement artificielle. | T27: Mutter Krausens Fahrt ins Glück (1929), film-source mentionné | U27: Films_images/Maman_Kusters_s_en_va_au_ciel.jpg | X27: 1975 | Y27: presse|classe ouvrière|communisme|anarchisme|distanciation|Brecht|RFA | Z27: RWF_Notes sur les films.docx | AA27: Documenté | AB27: film-1975-maman-kusters-s-en-va-au-ciel | AC27: =IF(O27="","",_xlfn.TEXTJOIN("; ",TRUE,IF(ISNUMBER(SEARCH('Référentiel entourage'!$B$2,O27)),'Référentiel entourage'!$A$2,""),IF(ISNUMBER(SEARCH('Référentiel entourage'!$B$3,O27)),'Référentiel entourage'!$A$3,""),IF(ISNUMBER(SEARCH('Référentiel entourage'!$B$4,O27)),'Référentiel entourage'!$A$4,""),IF(ISNUMBER(SEARCH('Référentiel entourage'!$B$5,O27)),'Référentiel entourage'!$A$5,""),IF(ISNUMBER(SEARCH('Référentiel entourage'!$B$6,O27)),'Référentiel entourage'!$A$6,""),IF(ISNUMBER(SEARCH('Référentiel entourage'!$B$7,O27)),'Référentiel entourage'!$A$7,""),IF(ISNUMBER(SEARCH('Référentiel entourage'!$B$8,O27)),'Référentiel entourage'!$A$8,""),IF(ISNUMBER(SEARCH('Référentiel entourage'!$B$9,O27)),'Référentiel entourage'!$A$9,""),IF(ISNUMBER(SEARCH('Référentiel entourage'!$B$10,O27)),'Référentiel entourage'!$A$10,""),IF(ISNUMBER(SEARCH('Référentiel entourage'!$B$11,O27)),'Référentiel entourage'!$A$11,""),IF(ISNUMBER(SEARCH('Référentiel entourage'!$B$12,O27)),'Référentiel entourage'!$A$12,""),IF(ISNUMBER(SEARCH('Référentiel entourage'!$B$13,O27)),'Référentiel entourage'!$A$13,""),IF(ISNUMBER(SEARCH('Référentiel entourage'!$B$14,O27)),'Référentiel entourage'!$A$14,""),IF(ISNUMBER(SEARCH('Référentiel entourage'!$B$15,O27)),'Référentiel entourage'!$A$15,""),IF(ISNUMBER(SEARCH('Référentiel entourage'!$B$16,O27)),'Référentiel entourage'!$A$16,""),IF(ISNUMBER(SEARCH('Référentiel entourage'!$B$17,O27)),'Référentiel entourage'!$A$17,""),IF(ISNUMBER(SEARCH('Référentiel entourage'!$B$18,O27)),'Référentiel entourage'!$A$18,""),IF(ISNUMBER(SEARCH('Référentiel entourage'!$B$19,O27)),'Référentiel entourage'!$A$19,""),IF(ISNUMBER(SEARCH('Référentiel entourage'!$B$20,O27)),'Référentiel entourage'!$A$20,""),IF(ISNUMBER(SEARCH('Référentiel entourage'!$B$21,O27)),'Référentiel entourage'!$A$21,""),IF(ISNUMBER(SEARCH('Référentiel entourage'!$B$22,O27)),'Référentiel entourage'!$A$22,""),IF(ISNUMBER(SEARCH('Référentiel entourage'!$B$23,O27)),'Référentiel entourage'!$A$23,""),IF(ISNUMBER(SEARCH('Référentiel entourage'!$B$24,O27)),'Référentiel entourage'!$A$24,""))) -> pers-karlheinz-bohm; pers-margit-carstensen; pers-ingrid-caven; pers-peter-chatel; pers-lilo-pempeit; pers-gottfried-john; pers-irm-hermann; pers-armin-meier; pers-brigitte-mira; pers-kurt-raab | AD27: =_xlfn.LET(_xlpm.texte,_xlfn.TEXTJOIN(" | ",TRUE,H27:N27,P27),IF(_xlpm.texte="","",_xlfn.TEXTJOIN("; ",TRUE,IF(ISNUMBER(SEARCH('Référentiel entourage'!$B$2,_xlpm.texte)),'Référentiel entourage'!$A$2,""),IF(ISNUMBER(SEARCH('Référentiel entourage'!$B$3,_xlpm.texte)),'Référentiel entourage'!$A$3,""),IF(ISNUMBER(SEARCH('Référentiel entourage'!$B$4,_xlpm.texte)),'Référentiel entourage'!$A$4,""),IF(ISNUMBER(SEARCH('Référentiel entourage'!$B$5,_xlpm.texte)),'Référentiel entourage'!$A$5,""),IF(ISNUMBER(SEARCH('Référentiel entourage'!$B$6,_xlpm.texte)),'Référentiel entourage'!$A$6,""),IF(ISNUMBER(SEARCH('Référentiel entourage'!$B$7,_xlpm.texte)),'Référentiel entourage'!$A$7,""),IF(ISNUMBER(SEARCH('Référentiel entourage'!$B$8,_xlpm.texte)),'Référentiel entourage'!$A$8,""),IF(ISNUMBER(SEARCH('Référentiel entourage'!$B$9,_xlpm.texte)),'Référentiel entourage'!$A$9,""),IF(ISNUMBER(SEARCH('Référentiel entourage'!$B$10,_xlpm.texte)),'Référentiel entourage'!$A$10,""),IF(ISNUMBER(SEARCH('Référentiel entourage'!$B$11,_xlpm.texte)),'Référentiel entourage'!$A$11,""),IF(ISNUMBER(SEARCH('Référentiel entourage'!$B$12,_xlpm.texte)),'Référentiel entourage'!$A$12,""),IF(ISNUMBER(SEARCH('Référentiel entourage'!$B$13,_xlpm.texte)),'Référentiel entourage'!$A$13,""),IF(ISNUMBER(SEARCH('Référentiel entourage'!$B$14,_xlpm.texte)),'Référentiel entourage'!$A$14,""),IF(ISNUMBER(SEARCH('Référentiel entourage'!$B$15,_xlpm.texte)),'Référentiel entourage'!$A$15,""),IF(ISNUMBER(SEARCH('Référentiel entourage'!$B$16,_xlpm.texte)),'Référentiel entourage'!$A$16,""),IF(ISNUMBER(SEARCH('Référentiel entourage'!$B$17,_xlpm.texte)),'Référentiel entourage'!$A$17,""),IF(ISNUMBER(SEARCH('Référentiel entourage'!$B$18,_xlpm.texte)),'Référentiel entourage'!$A$18,""),IF(ISNUMBER(SEARCH('Référentiel entourage'!$B$19,_xlpm.texte)),'Référentiel entourage'!$A$19,""),IF(ISNUMBER(SEARCH('Référentiel entourage'!$B$20,_xlpm.texte)),'Référentiel entourage'!$A$20,""),IF(ISNUMBER(SEARCH('Référentiel entourage'!$B$21,_xlpm.texte)),'Référentiel entourage'!$A$21,""),IF(ISNUMBER(SEARCH('Référentiel entourage'!$B$22,_xlpm.texte)),'Référentiel entourage'!$A$22,""),IF(ISNUMBER(SEARCH('Référentiel entourage'!$B$23,_xlpm.texte)),'Référentiel entourage'!$A$23,""),IF(ISNUMBER(SEARCH('Référentiel entourage'!$B$24,_xlpm.texte)),'Référentiel entourage'!$A$24,"")))) -> pers-michael-ballhaus; pers-kurt-raab; pers-peer-raben
A28: rwf-1975-comme-un-oiseau-sur-le-fil | B28: Comme un oiseau sur le fil | C28: Wie ein Vogel auf dem Draht | D28: 1975 | E28: Téléfilm | F28: 44 | G28: RFA | H28: Rainer Werner Fassbinder | I28: Rainer Werner Fassbinder ; Christian Hohoff | J28: Erhard Spandel | L28: Kurt Raab | M28: Ingfried Hoffmann ; orchestre Kurt Edelhagen | N28: WDR | O28: Brigitte Mira Evelyn Künneke Ingfried Hoffmann : le pianiste du bar El Hedi ben Salem : le culturiste | P28: Textes des chansons : Anja Hauptmann Format : vidéo 2 pouces, couleur Tournage : six jours en juillet 1974 à Cologne Diffusion : 5 mai 1975 | Q28: Brigitte Mira se souvient de ses différents mariages à travers plusieurs chansons. | X28: 1975 | Z28: Wikipédia : https://fr.wikipedia.org/wiki/Comme_un_oiseau_sur_le_fil | AA28: À compléter | AB28: film-1975-comme-un-oiseau-sur-le-fil | AC28: =IF(O28="","",_xlfn.TEXTJOIN("; ",TRUE,IF(ISNUMBER(SEARCH('Référentiel entourage'!$B$2,O28)),'Référentiel entourage'!$A$2,""),IF(ISNUMBER(SEARCH('Référentiel entourage'!$B$3,O28)),'Référentiel entourage'!$A$3,""),IF(ISNUMBER(SEARCH('Référentiel entourage'!$B$4,O28)),'Référentiel entourage'!$A$4,""),IF(ISNUMBER(SEARCH('Référentiel entourage'!$B$5,O28)),'Référentiel entourage'!$A$5,""),IF(ISNUMBER(SEARCH('Référentiel entourage'!$B$6,O28)),'Référentiel entourage'!$A$6,""),IF(ISNUMBER(SEARCH('Référentiel entourage'!$B$7,O28)),'Référentiel entourage'!$A$7,""),IF(ISNUMBER(SEARCH('Référentiel entourage'!$B$8,O28)),'Référentiel entourage'!$A$8,""),IF(ISNUMBER(SEARCH('Référentiel entourage'!$B$9,O28)),'Référentiel entourage'!$A$9,""),IF(ISNUMBER(SEARCH('Référentiel entourage'!$B$10,O28)),'Référentiel entourage'!$A$10,""),IF(ISNUMBER(SEARCH('Référentiel entourage'!$B$11,O28)),'Référentiel entourage'!$A$11,""),IF(ISNUMBER(SEARCH('Référentiel entourage'!$B$12,O28)),'Référentiel entourage'!$A$12,""),IF(ISNUMBER(SEARCH('Référentiel entourage'!$B$13,O28)),'Référentiel entourage'!$A$13,""),IF(ISNUMBER(SEARCH('Référentiel entourage'!$B$14,O28)),'Référentiel entourage'!$A$14,""),IF(ISNUMBER(SEARCH('Référentiel entourage'!$B$15,O28)),'Référentiel entourage'!$A$15,""),IF(ISNUMBER(SEARCH('Référentiel entourage'!$B$16,O28)),'Référentiel entourage'!$A$16,""),IF(ISNUMBER(SEARCH('Référentiel entourage'!$B$17,O28)),'Référentiel entourage'!$A$17,""),IF(ISNUMBER(SEARCH('Référentiel entourage'!$B$18,O28)),'Référentiel entourage'!$A$18,""),IF(ISNUMBER(SEARCH('Référentiel entourage'!$B$19,O28)),'Référentiel entourage'!$A$19,""),IF(ISNUMBER(SEARCH('Référentiel entourage'!$B$20,O28)),'Référentiel entourage'!$A$20,""),IF(ISNUMBER(SEARCH('Référentiel entourage'!$B$21,O28)),'Référentiel entourage'!$A$21,""),IF(ISNUMBER(SEARCH('Référentiel entourage'!$B$22,O28)),'Référentiel entourage'!$A$22,""),IF(ISNUMBER(SEARCH('Référentiel entourage'!$B$23,O28)),'Référentiel entourage'!$A$23,""),IF(ISNUMBER(SEARCH('Référentiel entourage'!$B$24,O28)),'Référentiel entourage'!$A$24,""))) -> pers-el-hedi-ben-salem; pers-brigitte-mira | AD28: =_xlfn.LET(_xlpm.texte,_xlfn.TEXTJOIN(" | ",TRUE,H28:N28,P28),IF(_xlpm.texte="","",_xlfn.TEXTJOIN("; ",TRUE,IF(ISNUMBER(SEARCH('Référentiel entourage'!$B$2,_xlpm.texte)),'Référentiel entourage'!$A$2,""),IF(ISNUMBER(SEARCH('Référentiel entourage'!$B$3,_xlpm.texte)),'Référentiel entourage'!$A$3,""),IF(ISNUMBER(SEARCH('Référentiel entourage'!$B$4,_xlpm.texte)),'Référentiel entourage'!$A$4,""),IF(ISNUMBER(SEARCH('Référentiel entourage'!$B$5,_xlpm.texte)),'Référentiel entourage'!$A$5,""),IF(ISNUMBER(SEARCH('Référentiel entourage'!$B$6,_xlpm.texte)),'Référentiel entourage'!$A$6,""),IF(ISNUMBER(SEARCH('Référentiel entourage'!$B$7,_xlpm.texte)),'Référentiel entourage'!$A$7,""),IF(ISNUMBER(SEARCH('Référentiel entourage'!$B$8,_xlpm.texte)),'Référentiel entourage'!$A$8,""),IF(ISNUMBER(SEARCH('Référentiel entourage'!$B$9,_xlpm.texte)),'Référentiel entourage'!$A$9,""),IF(ISNUMBER(SEARCH('Référentiel entourage'!$B$10,_xlpm.texte)),'Référentiel entourage'!$A$10,""),IF(ISNUMBER(SEARCH('Référentiel entourage'!$B$11,_xlpm.texte)),'Référentiel entourage'!$A$11,""),IF(ISNUMBER(SEARCH('Référentiel entourage'!$B$12,_xlpm.texte)),'Référentiel entourage'!$A$12,""),IF(ISNUMBER(SEARCH('Référentiel entourage'!$B$13,_xlpm.texte)),'Référentiel entourage'!$A$13,""),IF(ISNUMBER(SEARCH('Référentiel entourage'!$B$14,_xlpm.texte)),'Référentiel entourage'!$A$14,""),IF(ISNUMBER(SEARCH('Référentiel entourage'!$B$15,_xlpm.texte)),'Référentiel entourage'!$A$15,""),IF(ISNUMBER(SEARCH('Référentiel entourage'!$B$16,_xlpm.texte)),'Référentiel entourage'!$A$16,""),IF(ISNUMBER(SEARCH('Référentiel entourage'!$B$17,_xlpm.texte)),'Référentiel entourage'!$A$17,""),IF(ISNUMBER(SEARCH('Référentiel entourage'!$B$18,_xlpm.texte)),'Référentiel entourage'!$A$18,""),IF(ISNUMBER(SEARCH('Référentiel entourage'!$B$19,_xlpm.texte)),'Référentiel entourage'!$A$19,""),IF(ISNUMBER(SEARCH('Référentiel entourage'!$B$20,_xlpm.texte)),'Référentiel entourage'!$A$20,""),IF(ISNUMBER(SEARCH('Référentiel entourage'!$B$21,_xlpm.texte)),'Référentiel entourage'!$A$21,""),IF(ISNUMBER(SEARCH('Référentiel entourage'!$B$22,_xlpm.texte)),'Référentiel entourage'!$A$22,""),IF(ISNUMBER(SEARCH('Référentiel entourage'!$B$23,_xlpm.texte)),'Référentiel entourage'!$A$23,""),IF(ISNUMBER(SEARCH('Référentiel entourage'!$B$24,_xlpm.texte)),'Référentiel entourage'!$A$24,"")))) -> pers-kurt-raab
A29: rwf-1975-peur-de-la-peur | B29: Peur de la peur | C29: Angst vor der Angst | D29: 1975 | E29: Téléfilm | F29: 88 | G29: RFA | H29: Rainer Werner Fassbinder | I29: Rainer Werner Fassbinder, sur une idée d’Asta Scheib | J29: Jürgen Jürges ; Ulrich Prinz | K29: Liesgret Schmitt-Klink ; Beate Fischer-Weiskirsh | L29: Kurt Raab | M29: Peer Raben | N29: Peter Märthesheimer ; WDR | O29: Margit Carstensen : Margot Staudte Ulrich Faulhaber : Kurt Brigitte Mira : la mère Irm Hermann : Lore Armin Meier : Karli Adrian Hoven : Dr Merck Kurt Raab : M. Bauer Ingrid Caven : Edda Lilo Pempeit : Mme Schaal Helga Märthesheimer : Mme le Dr von Unruh Herbert Steinmetz : Dr Auer Hark Bohm : Dr Rozenbaum Constance Haas : Bibi | P29: Format : 16 mm, couleur Tournage : 25 jours en avril-mai 1975 à Cologne et Bonn Diffusion : 8 juillet 1975 | Q29: Margot, jeune mère de famille, se trouve doublement isolée par sa dépression, l’angoisse qui l’accompagne et l’incompréhension de son entourage. | X29: 1975 | Z29: Wikipédia : https://fr.wikipedia.org/wiki/Peur_de_la_peur | AA29: À compléter | AB29: film-1975-peur-de-la-peur | AC29: =IF(O29="","",_xlfn.TEXTJOIN("; ",TRUE,IF(ISNUMBER(SEARCH('Référentiel entourage'!$B$2,O29)),'Référentiel entourage'!$A$2,""),IF(ISNUMBER(SEARCH('Référentiel entourage'!$B$3,O29)),'Référentiel entourage'!$A$3,""),IF(ISNUMBER(SEARCH('Référentiel entourage'!$B$4,O29)),'Référentiel entourage'!$A$4,""),IF(ISNUMBER(SEARCH('Référentiel entourage'!$B$5,O29)),'Référentiel entourage'!$A$5,""),IF(ISNUMBER(SEARCH('Référentiel entourage'!$B$6,O29)),'Référentiel entourage'!$A$6,""),IF(ISNUMBER(SEARCH('Référentiel entourage'!$B$7,O29)),'Référentiel entourage'!$A$7,""),IF(ISNUMBER(SEARCH('Référentiel entourage'!$B$8,O29)),'Référentiel entourage'!$A$8,""),IF(ISNUMBER(SEARCH('Référentiel entourage'!$B$9,O29)),'Référentiel entourage'!$A$9,""),IF(ISNUMBER(SEARCH('Référentiel entourage'!$B$10,O29)),'Référentiel entourage'!$A$10,""),IF(ISNUMBER(SEARCH('Référentiel entourage'!$B$11,O29)),'Référentiel entourage'!$A$11,""),IF(ISNUMBER(SEARCH('Référentiel entourage'!$B$12,O29)),'Référentiel entourage'!$A$12,""),IF(ISNUMBER(SEARCH('Référentiel entourage'!$B$13,O29)),'Référentiel entourage'!$A$13,""),IF(ISNUMBER(SEARCH('Référentiel entourage'!$B$14,O29)),'Référentiel entourage'!$A$14,""),IF(ISNUMBER(SEARCH('Référentiel entourage'!$B$15,O29)),'Référentiel entourage'!$A$15,""),IF(ISNUMBER(SEARCH('Référentiel entourage'!$B$16,O29)),'Référentiel entourage'!$A$16,""),IF(ISNUMBER(SEARCH('Référentiel entourage'!$B$17,O29)),'Référentiel entourage'!$A$17,""),IF(ISNUMBER(SEARCH('Référentiel entourage'!$B$18,O29)),'Référentiel entourage'!$A$18,""),IF(ISNUMBER(SEARCH('Référentiel entourage'!$B$19,O29)),'Référentiel entourage'!$A$19,""),IF(ISNUMBER(SEARCH('Référentiel entourage'!$B$20,O29)),'Référentiel entourage'!$A$20,""),IF(ISNUMBER(SEARCH('Référentiel entourage'!$B$21,O29)),'Référentiel entourage'!$A$21,""),IF(ISNUMBER(SEARCH('Référentiel entourage'!$B$22,O29)),'Référentiel entourage'!$A$22,""),IF(ISNUMBER(SEARCH('Référentiel entourage'!$B$23,O29)),'Référentiel entourage'!$A$23,""),IF(ISNUMBER(SEARCH('Référentiel entourage'!$B$24,O29)),'Référentiel entourage'!$A$24,""))) -> pers-hark-bohm; pers-margit-carstensen; pers-ingrid-caven; pers-lilo-pempeit; pers-irm-hermann; pers-armin-meier; pers-brigitte-mira; pers-kurt-raab | AD29: =_xlfn.LET(_xlpm.texte,_xlfn.TEXTJOIN(" | ",TRUE,H29:N29,P29),IF(_xlpm.texte="","",_xlfn.TEXTJOIN("; ",TRUE,IF(ISNUMBER(SEARCH('Référentiel entourage'!$B$2,_xlpm.texte)),'Référentiel entourage'!$A$2,""),IF(ISNUMBER(SEARCH('Référentiel entourage'!$B$3,_xlpm.texte)),'Référentiel entourage'!$A$3,""),IF(ISNUMBER(SEARCH('Référentiel entourage'!$B$4,_xlpm.texte)),'Référentiel entourage'!$A$4,""),IF(ISNUMBER(SEARCH('Référentiel entourage'!$B$5,_xlpm.texte)),'Référentiel entourage'!$A$5,""),IF(ISNUMBER(SEARCH('Référentiel entourage'!$B$6,_xlpm.texte)),'Référentiel entourage'!$A$6,""),IF(ISNUMBER(SEARCH('Référentiel entourage'!$B$7,_xlpm.texte)),'Référentiel entourage'!$A$7,""),IF(ISNUMBER(SEARCH('Référentiel entourage'!$B$8,_xlpm.texte)),'Référentiel entourage'!$A$8,""),IF(ISNUMBER(SEARCH('Référentiel entourage'!$B$9,_xlpm.texte)),'Référentiel entourage'!$A$9,""),IF(ISNUMBER(SEARCH('Référentiel entourage'!$B$10,_xlpm.texte)),'Référentiel entourage'!$A$10,""),IF(ISNUMBER(SEARCH('Référentiel entourage'!$B$11,_xlpm.texte)),'Référentiel entourage'!$A$11,""),IF(ISNUMBER(SEARCH('Référentiel entourage'!$B$12,_xlpm.texte)),'Référentiel entourage'!$A$12,""),IF(ISNUMBER(SEARCH('Référentiel entourage'!$B$13,_xlpm.texte)),'Référentiel entourage'!$A$13,""),IF(ISNUMBER(SEARCH('Référentiel entourage'!$B$14,_xlpm.texte)),'Référentiel entourage'!$A$14,""),IF(ISNUMBER(SEARCH('Référentiel entourage'!$B$15,_xlpm.texte)),'Référentiel entourage'!$A$15,""),IF(ISNUMBER(SEARCH('Référentiel entourage'!$B$16,_xlpm.texte)),'Référentiel entourage'!$A$16,""),IF(ISNUMBER(SEARCH('Référentiel entourage'!$B$17,_xlpm.texte)),'Référentiel entourage'!$A$17,""),IF(ISNUMBER(SEARCH('Référentiel entourage'!$B$18,_xlpm.texte)),'Référentiel entourage'!$A$18,""),IF(ISNUMBER(SEARCH('Référentiel entourage'!$B$19,_xlpm.texte)),'Référentiel entourage'!$A$19,""),IF(ISNUMBER(SEARCH('Référentiel entourage'!$B$20,_xlpm.texte)),'Référentiel entourage'!$A$20,""),IF(ISNUMBER(SEARCH('Référentiel entourage'!$B$21,_xlpm.texte)),'Référentiel entourage'!$A$21,""),IF(ISNUMBER(SEARCH('Référentiel entourage'!$B$22,_xlpm.texte)),'Référentiel entourage'!$A$22,""),IF(ISNUMBER(SEARCH('Référentiel entourage'!$B$23,_xlpm.texte)),'Référentiel entourage'!$A$23,""),IF(ISNUMBER(SEARCH('Référentiel entourage'!$B$24,_xlpm.texte)),'Référentiel entourage'!$A$24,"")))) -> pers-kurt-raab; pers-peer-raben
A30: rwf-1976-lombre-des-anges | B30: L’Ombre des anges | C30: Schatten der Engel | D30: 1976 | E30: Long métrage | F30: 101 | G30: RFA | H30: Daniel Schmid | I30: Daniel Schmid ; Rainer Werner Fassbinder, d’après la pièce de Fassbinder | J30: Renato Berta | K30: Ila von Hasperg | M30: Gottfried Hüngsberg ; Peer Raben | N30: Michael Fengler ; Jordan Bojilov | O30: Ingrid Caven : Lily Brest Rainer Werner Fassbinder : Raoul Klaus Löwitsch : le spéculateur, dit « le Juif riche » Anne-Marie Düringer : Luise Müller Adrian Hoven : Herr Müller Boy Gobert : le chef de la police Ulli Lommel : le Petit Prince Jean-Claude Dreyfus : le nain Alexander Allerson : Hans von Gluck | P30: Format : couleur, mono Genre : drame Sortie : 1976 | Q30: Lily, prostituée désabusée, rencontre un riche spéculateur juif qui la paie pour l’écouter. Tous deux sont pris dans un univers urbain de violence, d’exploitation et de solitude. | U30: Films_images/L_Ombre_des_anges.jpg | X30: 1976 | Z30: Wikipédia : https://fr.wikipedia.org/wiki/L%27Ombre_des_anges | AA30: À compléter | AB30: film-1976-l-ombre-des-anges | AC30: =IF(O30="","",_xlfn.TEXTJOIN("; ",TRUE,IF(ISNUMBER(SEARCH('Référentiel entourage'!$B$2,O30)),'Référentiel entourage'!$A$2,""),IF(ISNUMBER(SEARCH('Référentiel entourage'!$B$3,O30)),'Référentiel entourage'!$A$3,""),IF(ISNUMBER(SEARCH('Référentiel entourage'!$B$4,O30)),'Référentiel entourage'!$A$4,""),IF(ISNUMBER(SEARCH('Référentiel entourage'!$B$5,O30)),'Référentiel entourage'!$A$5,""),IF(ISNUMBER(SEARCH('Référentiel entourage'!$B$6,O30)),'Référentiel entourage'!$A$6,""),IF(ISNUMBER(SEARCH('Référentiel entourage'!$B$7,O30)),'Référentiel entourage'!$A$7,""),IF(ISNUMBER(SEARCH('Référentiel entourage'!$B$8,O30)),'Référentiel entourage'!$A$8,""),IF(ISNUMBER(SEARCH('Référentiel entourage'!$B$9,O30)),'Référentiel entourage'!$A$9,""),IF(ISNUMBER(SEARCH('Référentiel entourage'!$B$10,O30)),'Référentiel entourage'!$A$10,""),IF(ISNUMBER(SEARCH('Référentiel entourage'!$B$11,O30)),'Référentiel entourage'!$A$11,""),IF(ISNUMBER(SEARCH('Référentiel entourage'!$B$12,O30)),'Référentiel entourage'!$A$12,""),IF(ISNUMBER(SEARCH('Référentiel entourage'!$B$13,O30)),'Référentiel entourage'!$A$13,""),IF(ISNUMBER(SEARCH('Référentiel entourage'!$B$14,O30)),'Référentiel entourage'!$A$14,""),IF(ISNUMBER(SEARCH('Référentiel entourage'!$B$15,O30)),'Référentiel entourage'!$A$15,""),IF(ISNUMBER(SEARCH('Référentiel entourage'!$B$16,O30)),'Référentiel entourage'!$A$16,""),IF(ISNUMBER(SEARCH('Référentiel entourage'!$B$17,O30)),'Référentiel entourage'!$A$17,""),IF(ISNUMBER(SEARCH('Référentiel entourage'!$B$18,O30)),'Référentiel entourage'!$A$18,""),IF(ISNUMBER(SEARCH('Référentiel entourage'!$B$19,O30)),'Référentiel entourage'!$A$19,""),IF(ISNUMBER(SEARCH('Référentiel entourage'!$B$20,O30)),'Référentiel entourage'!$A$20,""),IF(ISNUMBER(SEARCH('Référentiel entourage'!$B$21,O30)),'Référentiel entourage'!$A$21,""),IF(ISNUMBER(SEARCH('Référentiel entourage'!$B$22,O30)),'Référentiel entourage'!$A$22,""),IF(ISNUMBER(SEARCH('Référentiel entourage'!$B$23,O30)),'Référentiel entourage'!$A$23,""),IF(ISNUMBER(SEARCH('Référentiel entourage'!$B$24,O30)),'Référentiel entourage'!$A$24,""))) -> pers-ingrid-caven; pers-ulli-lommel | AD30: =_xlfn.LET(_xlpm.texte,_xlfn.TEXTJOIN(" | ",TRUE,H30:N30,P30),IF(_xlpm.texte="","",_xlfn.TEXTJOIN("; ",TRUE,IF(ISNUMBER(SEARCH('Référentiel entourage'!$B$2,_xlpm.texte)),'Référentiel entourage'!$A$2,""),IF(ISNUMBER(SEARCH('Référentiel entourage'!$B$3,_xlpm.texte)),'Référentiel entourage'!$A$3,""),IF(ISNUMBER(SEARCH('Référentiel entourage'!$B$4,_xlpm.texte)),'Référentiel entourage'!$A$4,""),IF(ISNUMBER(SEARCH('Référentiel entourage'!$B$5,_xlpm.texte)),'Référentiel entourage'!$A$5,""),IF(ISNUMBER(SEARCH('Référentiel entourage'!$B$6,_xlpm.texte)),'Référentiel entourage'!$A$6,""),IF(ISNUMBER(SEARCH('Référentiel entourage'!$B$7,_xlpm.texte)),'Référentiel entourage'!$A$7,""),IF(ISNUMBER(SEARCH('Référentiel entourage'!$B$8,_xlpm.texte)),'Référentiel entourage'!$A$8,""),IF(ISNUMBER(SEARCH('Référentiel entourage'!$B$9,_xlpm.texte)),'Référentiel entourage'!$A$9,""),IF(ISNUMBER(SEARCH('Référentiel entourage'!$B$10,_xlpm.texte)),'Référentiel entourage'!$A$10,""),IF(ISNUMBER(SEARCH('Référentiel entourage'!$B$11,_xlpm.texte)),'Référentiel entourage'!$A$11,""),IF(ISNUMBER(SEARCH('Référentiel entourage'!$B$12,_xlpm.texte)),'Référentiel entourage'!$A$12,""),IF(ISNUMBER(SEARCH('Référentiel entourage'!$B$13,_xlpm.texte)),'Référentiel entourage'!$A$13,""),IF(ISNUMBER(SEARCH('Référentiel entourage'!$B$14,_xlpm.texte)),'Référentiel entourage'!$A$14,""),IF(ISNUMBER(SEARCH('Référentiel entourage'!$B$15,_xlpm.texte)),'Référentiel entourage'!$A$15,""),IF(ISNUMBER(SEARCH('Référentiel entourage'!$B$16,_xlpm.texte)),'Référentiel entourage'!$A$16,""),IF(ISNUMBER(SEARCH('Référentiel entourage'!$B$17,_xlpm.texte)),'Référentiel entourage'!$A$17,""),IF(ISNUMBER(SEARCH('Référentiel entourage'!$B$18,_xlpm.texte)),'Référentiel entourage'!$A$18,""),IF(ISNUMBER(SEARCH('Référentiel entourage'!$B$19,_xlpm.texte)),'Référentiel entourage'!$A$19,""),IF(ISNUMBER(SEARCH('Référentiel entourage'!$B$20,_xlpm.texte)),'Référentiel entourage'!$A$20,""),IF(ISNUMBER(SEARCH('Référentiel entourage'!$B$21,_xlpm.texte)),'Référentiel entourage'!$A$21,""),IF(ISNUMBER(SEARCH('Référentiel entourage'!$B$22,_xlpm.texte)),'Référentiel entourage'!$A$22,""),IF(ISNUMBER(SEARCH('Référentiel entourage'!$B$23,_xlpm.texte)),'Référentiel entourage'!$A$23,""),IF(ISNUMBER(SEARCH('Référentiel entourage'!$B$24,_xlpm.texte)),'Référentiel entourage'!$A$24,"")))) -> pers-michael-fengler; pers-peer-raben; pers-daniel-schmid
A31: rwf-1976-roti-satan | B31: Le Rôti de Satan | C31: Satansbraten | D31: 1976 | E31: Long métrage | F31: 112 | G31: RFA | H31: Rainer Werner Fassbinder | I31: Rainer Werner Fassbinder | J31: Michael Ballhaus et Jürgen Jürges | K31: Thea Eymèsz | M31: Peer Raben | N31: Hanns Eckelkamp et Michael Fengler | O31: Kurt Raab : Walter Kranz Margit Carstensen : Andrée Helen Vita : Luise Kranz Volker Spengler : Ernst Kranz Ingrid Caven : Lisa Marquard Bohm : le mari de Lilly Y Sa Lo : Lana von Meyerbeer Ulli Lommel : inspecteur Lauf Brigitte Mira : mère de Walter Armin Meier : un prostitué Vitus Zeplichal : Urs Dieter Schidor : Willy Peter Chatel : Eugen Adrian Hoven : le médecin | P31: Format : couleurs, 1,37:1, mono Genre : comédie noire Sortie : 1976 | Q31: Walter Kranz, poète autrefois révolutionnaire, est en panne d’inspiration et d’argent. Convaincu d’être la réincarnation du poète Stefan George, il multiplie mensonges, violences, plagiats et manipulations dans une quête grotesque de reconnaissance et de financement. | S31: L’exergue est tirée d’Héliogabale ou l’anarchiste couronné d’Antonin Artaud. Le film place la crise du sujet créateur sous le signe de la cruauté, du grotesque et de la défiguration. Walter Kranz préfigure le naufrage identitaire de Despair : la folie créatrice devient une forme de désintégration du sujet. | T31: Antonin Artaud, Héliogabale ou l’anarchiste couronné (1934) Stefan George Thomas Elsaesser, analyses sur Fassbinder et Despair | U31: Films_images/Le_Roti_de_Satan.jpg | X31: 1976 | Y31: artiste|folie|grotesque|Antonin Artaud|Stefan George|création|comédie noire | Z31: RWF_Notes sur les films.docx | AA31: Documenté | AB31: film-1976-le-roti-de-satan | AC31: =IF(O31="","",_xlfn.TEXTJOIN("; ",TRUE,IF(ISNUMBER(SEARCH('Référentiel entourage'!$B$2,O31)),'Référentiel entourage'!$A$2,""),IF(ISNUMBER(SEARCH('Référentiel entourage'!$B$3,O31)),'Référentiel entourage'!$A$3,""),IF(ISNUMBER(SEARCH('Référentiel entourage'!$B$4,O31)),'Référentiel entourage'!$A$4,""),IF(ISNUMBER(SEARCH('Référentiel entourage'!$B$5,O31)),'Référentiel entourage'!$A$5,""),IF(ISNUMBER(SEARCH('Référentiel entourage'!$B$6,O31)),'Référentiel entourage'!$A$6,""),IF(ISNUMBER(SEARCH('Référentiel entourage'!$B$7,O31)),'Référentiel entourage'!$A$7,""),IF(ISNUMBER(SEARCH('Référentiel entourage'!$B$8,O31)),'Référentiel entourage'!$A$8,""),IF(ISNUMBER(SEARCH('Référentiel entourage'!$B$9,O31)),'Référentiel entourage'!$A$9,""),IF(ISNUMBER(SEARCH('Référentiel entourage'!$B$10,O31)),'Référentiel entourage'!$A$10,""),IF(ISNUMBER(SEARCH('Référentiel entourage'!$B$11,O31)),'Référentiel entourage'!$A$11,""),IF(ISNUMBER(SEARCH('Référentiel entourage'!$B$12,O31)),'Référentiel entourage'!$A$12,""),IF(ISNUMBER(SEARCH('Référentiel entourage'!$B$13,O31)),'Référentiel entourage'!$A$13,""),IF(ISNUMBER(SEARCH('Référentiel entourage'!$B$14,O31)),'Référentiel entourage'!$A$14,""),IF(ISNUMBER(SEARCH('Référentiel entourage'!$B$15,O31)),'Référentiel entourage'!$A$15,""),IF(ISNUMBER(SEARCH('Référentiel entourage'!$B$16,O31)),'Référentiel entourage'!$A$16,""),IF(ISNUMBER(SEARCH('Référentiel entourage'!$B$17,O31)),'Référentiel entourage'!$A$17,""),IF(ISNUMBER(SEARCH('Référentiel entourage'!$B$18,O31)),'Référentiel entourage'!$A$18,""),IF(ISNUMBER(SEARCH('Référentiel entourage'!$B$19,O31)),'Référentiel entourage'!$A$19,""),IF(ISNUMBER(SEARCH('Référentiel entourage'!$B$20,O31)),'Référentiel entourage'!$A$20,""),IF(ISNUMBER(SEARCH('Référentiel entourage'!$B$21,O31)),'Référentiel entourage'!$A$21,""),IF(ISNUMBER(SEARCH('Référentiel entourage'!$B$22,O31)),'Référentiel entourage'!$A$22,""),IF(ISNUMBER(SEARCH('Référentiel entourage'!$B$23,O31)),'Référentiel entourage'!$A$23,""),IF(ISNUMBER(SEARCH('Référentiel entourage'!$B$24,O31)),'Référentiel entourage'!$A$24,""))) -> pers-margit-carstensen; pers-ingrid-caven; pers-peter-chatel; pers-ulli-lommel; pers-armin-meier; pers-brigitte-mira; pers-kurt-raab | AD31: =_xlfn.LET(_xlpm.texte,_xlfn.TEXTJOIN(" | ",TRUE,H31:N31,P31),IF(_xlpm.texte="","",_xlfn.TEXTJOIN("; ",TRUE,IF(ISNUMBER(SEARCH('Référentiel entourage'!$B$2,_xlpm.texte)),'Référentiel entourage'!$A$2,""),IF(ISNUMBER(SEARCH('Référentiel entourage'!$B$3,_xlpm.texte)),'Référentiel entourage'!$A$3,""),IF(ISNUMBER(SEARCH('Référentiel entourage'!$B$4,_xlpm.texte)),'Référentiel entourage'!$A$4,""),IF(ISNUMBER(SEARCH('Référentiel entourage'!$B$5,_xlpm.texte)),'Référentiel entourage'!$A$5,""),IF(ISNUMBER(SEARCH('Référentiel entourage'!$B$6,_xlpm.texte)),'Référentiel entourage'!$A$6,""),IF(ISNUMBER(SEARCH('Référentiel entourage'!$B$7,_xlpm.texte)),'Référentiel entourage'!$A$7,""),IF(ISNUMBER(SEARCH('Référentiel entourage'!$B$8,_xlpm.texte)),'Référentiel entourage'!$A$8,""),IF(ISNUMBER(SEARCH('Référentiel entourage'!$B$9,_xlpm.texte)),'Référentiel entourage'!$A$9,""),IF(ISNUMBER(SEARCH('Référentiel entourage'!$B$10,_xlpm.texte)),'Référentiel entourage'!$A$10,""),IF(ISNUMBER(SEARCH('Référentiel entourage'!$B$11,_xlpm.texte)),'Référentiel entourage'!$A$11,""),IF(ISNUMBER(SEARCH('Référentiel entourage'!$B$12,_xlpm.texte)),'Référentiel entourage'!$A$12,""),IF(ISNUMBER(SEARCH('Référentiel entourage'!$B$13,_xlpm.texte)),'Référentiel entourage'!$A$13,""),IF(ISNUMBER(SEARCH('Référentiel entourage'!$B$14,_xlpm.texte)),'Référentiel entourage'!$A$14,""),IF(ISNUMBER(SEARCH('Référentiel entourage'!$B$15,_xlpm.texte)),'Référentiel entourage'!$A$15,""),IF(ISNUMBER(SEARCH('Référentiel entourage'!$B$16,_xlpm.texte)),'Référentiel entourage'!$A$16,""),IF(ISNUMBER(SEARCH('Référentiel entourage'!$B$17,_xlpm.texte)),'Référentiel entourage'!$A$17,""),IF(ISNUMBER(SEARCH('Référentiel entourage'!$B$18,_xlpm.texte)),'Référentiel entourage'!$A$18,""),IF(ISNUMBER(SEARCH('Référentiel entourage'!$B$19,_xlpm.texte)),'Référentiel entourage'!$A$19,""),IF(ISNUMBER(SEARCH('Référentiel entourage'!$B$20,_xlpm.texte)),'Référentiel entourage'!$A$20,""),IF(ISNUMBER(SEARCH('Référentiel entourage'!$B$21,_xlpm.texte)),'Référentiel entourage'!$A$21,""),IF(ISNUMBER(SEARCH('Référentiel entourage'!$B$22,_xlpm.texte)),'Référentiel entourage'!$A$22,""),IF(ISNUMBER(SEARCH('Référentiel entourage'!$B$23,_xlpm.texte)),'Référentiel entourage'!$A$23,""),IF(ISNUMBER(SEARCH('Référentiel entourage'!$B$24,_xlpm.texte)),'Référentiel entourage'!$A$24,"")))) -> pers-michael-ballhaus; pers-michael-fengler; pers-peer-raben
A32: rwf-1976-roulette-chinoise | B32: Roulette chinoise | C32: Chinesisches Roulette | D32: 1976 | E32: Long métrage | F32: 96 | G32: RFA / France | H32: Rainer Werner Fassbinder | I32: Rainer Werner Fassbinder | J32: Michael Ballhaus | K32: Ila von Hasperg | M32: Peer Raben | N32: Michael Fengler ; Barbet Schroeder | O32: Anna Karina : Irene Cartis Margit Carstensen : Ariane Christ Brigitte Mira : Kast Ulli Lommel : Kolbe Alexander Allerson : Gerhard Christ Volker Spengler : Gabriel Kast Andrea Schober : Angela Christ Macha Méril : Traunitz, la gouvernante muette Armin Meier : le pompiste Roland Henschke : le mendiant | P32: Format : couleurs, 1,66:1, mono Genre : drame, thriller Sortie : 1976 | Q32: Un riche industriel et sa femme partent séparément passer le week-end avec leurs amants dans leur château de campagne, chacun croyant l’autre absent. La rencontre imprévue des deux couples est bientôt aggravée par l’arrivée de leur fille Angela, handicapée, et de sa gouvernante. Angela organise une « roulette chinoise » qui transforme le jeu mondain en règlement de comptes familial. | S32: Le château devient un huis clos où vitrines, miroirs, meubles transparents, surcadrages et travellings circulaires enferment les personnages dans un réseau de regards et recomposent sans cesse les alliances. Angela utilise le jeu pour rendre visibles les mensonges, la haine familiale et la violence exercée sur l’enfant handicapée. Les allusions au IIIe Reich font affleurer, sous la respectabilité bourgeoise, une mémoire refoulée dont la violence éclate sans produire de résolution. | U32: Films_images/Roulette_chinoise.jpg | X32: 1976 | Y32: famille|adultère|huis clos|jeu|cruauté|handicap|nazisme|mémoire|miroirs|surcadrage | Z32: RWF_Notes sur les films.docx | AA32: Documenté | AB32: film-1976-roulette-chinoise | AC32: =IF(O32="","",_xlfn.TEXTJOIN("; ",TRUE,IF(ISNUMBER(SEARCH('Référentiel entourage'!$B$2,O32)),'Référentiel entourage'!$A$2,""),IF(ISNUMBER(SEARCH('Référentiel entourage'!$B$3,O32)),'Référentiel entourage'!$A$3,""),IF(ISNUMBER(SEARCH('Référentiel entourage'!$B$4,O32)),'Référentiel entourage'!$A$4,""),IF(ISNUMBER(SEARCH('Référentiel entourage'!$B$5,O32)),'Référentiel entourage'!$A$5,""),IF(ISNUMBER(SEARCH('Référentiel entourage'!$B$6,O32)),'Référentiel entourage'!$A$6,""),IF(ISNUMBER(SEARCH('Référentiel entourage'!$B$7,O32)),'Référentiel entourage'!$A$7,""),IF(ISNUMBER(SEARCH('Référentiel entourage'!$B$8,O32)),'Référentiel entourage'!$A$8,""),IF(ISNUMBER(SEARCH('Référentiel entourage'!$B$9,O32)),'Référentiel entourage'!$A$9,""),IF(ISNUMBER(SEARCH('Référentiel entourage'!$B$10,O32)),'Référentiel entourage'!$A$10,""),IF(ISNUMBER(SEARCH('Référentiel entourage'!$B$11,O32)),'Référentiel entourage'!$A$11,""),IF(ISNUMBER(SEARCH('Référentiel entourage'!$B$12,O32)),'Référentiel entourage'!$A$12,""),IF(ISNUMBER(SEARCH('Référentiel entourage'!$B$13,O32)),'Référentiel entourage'!$A$13,""),IF(ISNUMBER(SEARCH('Référentiel entourage'!$B$14,O32)),'Référentiel entourage'!$A$14,""),IF(ISNUMBER(SEARCH('Référentiel entourage'!$B$15,O32)),'Référentiel entourage'!$A$15,""),IF(ISNUMBER(SEARCH('Référentiel entourage'!$B$16,O32)),'Référentiel entourage'!$A$16,""),IF(ISNUMBER(SEARCH('Référentiel entourage'!$B$17,O32)),'Référentiel entourage'!$A$17,""),IF(ISNUMBER(SEARCH('Référentiel entourage'!$B$18,O32)),'Référentiel entourage'!$A$18,""),IF(ISNUMBER(SEARCH('Référentiel entourage'!$B$19,O32)),'Référentiel entourage'!$A$19,""),IF(ISNUMBER(SEARCH('Référentiel entourage'!$B$20,O32)),'Référentiel entourage'!$A$20,""),IF(ISNUMBER(SEARCH('Référentiel entourage'!$B$21,O32)),'Référentiel entourage'!$A$21,""),IF(ISNUMBER(SEARCH('Référentiel entourage'!$B$22,O32)),'Référentiel entourage'!$A$22,""),IF(ISNUMBER(SEARCH('Référentiel entourage'!$B$23,O32)),'Référentiel entourage'!$A$23,""),IF(ISNUMBER(SEARCH('Référentiel entourage'!$B$24,O32)),'Référentiel entourage'!$A$24,""))) -> pers-margit-carstensen; pers-ulli-lommel; pers-armin-meier; pers-brigitte-mira | AD32: =_xlfn.LET(_xlpm.texte,_xlfn.TEXTJOIN(" | ",TRUE,H32:N32,P32),IF(_xlpm.texte="","",_xlfn.TEXTJOIN("; ",TRUE,IF(ISNUMBER(SEARCH('Référentiel entourage'!$B$2,_xlpm.texte)),'Référentiel entourage'!$A$2,""),IF(ISNUMBER(SEARCH('Référentiel entourage'!$B$3,_xlpm.texte)),'Référentiel entourage'!$A$3,""),IF(ISNUMBER(SEARCH('Référentiel entourage'!$B$4,_xlpm.texte)),'Référentiel entourage'!$A$4,""),IF(ISNUMBER(SEARCH('Référentiel entourage'!$B$5,_xlpm.texte)),'Référentiel entourage'!$A$5,""),IF(ISNUMBER(SEARCH('Référentiel entourage'!$B$6,_xlpm.texte)),'Référentiel entourage'!$A$6,""),IF(ISNUMBER(SEARCH('Référentiel entourage'!$B$7,_xlpm.texte)),'Référentiel entourage'!$A$7,""),IF(ISNUMBER(SEARCH('Référentiel entourage'!$B$8,_xlpm.texte)),'Référentiel entourage'!$A$8,""),IF(ISNUMBER(SEARCH('Référentiel entourage'!$B$9,_xlpm.texte)),'Référentiel entourage'!$A$9,""),IF(ISNUMBER(SEARCH('Référentiel entourage'!$B$10,_xlpm.texte)),'Référentiel entourage'!$A$10,""),IF(ISNUMBER(SEARCH('Référentiel entourage'!$B$11,_xlpm.texte)),'Référentiel entourage'!$A$11,""),IF(ISNUMBER(SEARCH('Référentiel entourage'!$B$12,_xlpm.texte)),'Référentiel entourage'!$A$12,""),IF(ISNUMBER(SEARCH('Référentiel entourage'!$B$13,_xlpm.texte)),'Référentiel entourage'!$A$13,""),IF(ISNUMBER(SEARCH('Référentiel entourage'!$B$14,_xlpm.texte)),'Référentiel entourage'!$A$14,""),IF(ISNUMBER(SEARCH('Référentiel entourage'!$B$15,_xlpm.texte)),'Référentiel entourage'!$A$15,""),IF(ISNUMBER(SEARCH('Référentiel entourage'!$B$16,_xlpm.texte)),'Référentiel entourage'!$A$16,""),IF(ISNUMBER(SEARCH('Référentiel entourage'!$B$17,_xlpm.texte)),'Référentiel entourage'!$A$17,""),IF(ISNUMBER(SEARCH('Référentiel entourage'!$B$18,_xlpm.texte)),'Référentiel entourage'!$A$18,""),IF(ISNUMBER(SEARCH('Référentiel entourage'!$B$19,_xlpm.texte)),'Référentiel entourage'!$A$19,""),IF(ISNUMBER(SEARCH('Référentiel entourage'!$B$20,_xlpm.texte)),'Référentiel entourage'!$A$20,""),IF(ISNUMBER(SEARCH('Référentiel entourage'!$B$21,_xlpm.texte)),'Référentiel entourage'!$A$21,""),IF(ISNUMBER(SEARCH('Référentiel entourage'!$B$22,_xlpm.texte)),'Référentiel entourage'!$A$22,""),IF(ISNUMBER(SEARCH('Référentiel entourage'!$B$23,_xlpm.texte)),'Référentiel entourage'!$A$23,""),IF(ISNUMBER(SEARCH('Référentiel entourage'!$B$24,_xlpm.texte)),'Référentiel entourage'!$A$24,"")))) -> pers-michael-ballhaus; pers-michael-fengler; pers-peer-raben
A33: rwf-1976-je-veux-seulement-que-vous-maimiez | B33: Je veux seulement que vous m’aimiez | C33: Ich will doch nur, daß ihr mich liebt | D33: 1976 | E33: Téléfilm | F33: 104 | G33: RFA | H33: Rainer Werner Fassbinder | J33: Michael Ballhaus | K33: Liesgret Schmitt-Klink | L33: Kurt Raab | M33: Peer Raben | N33: Bavaria Atelier GmbH pour la WDR | O33: Vitus Zeplichal : Peter Elke Aberle : Erika Alexander Allerson : le père Erni Mangold : la mère Johanna Hofer : la grand-mère Katharina Buchhammer : Ulla Wolfgang Hess : le chef de chantier Armin Meier : le contremaître Erika Runge : la psychologue Ulrich Radke : le père d’Erika Annemarie Wendl : la mère d’Erika Janos Gönczöl : le tenancier Edith Volkmann : la tenancière Robert Naegele : l’huissier Axel Ganz : le concierge Inge Schulz : Mme Emmerich Heinz H. Bernstein : le vendeur de meubles Helga Bender : la vendeuse dans la boutique Adi Gruber : l’employé des postes Ingrid Caven : la vendeuse de machines à tricoter Sonja Neudorres : la bijoutière Reinhard Brex : l’entrepreneur Lilo Pempeit : la dame à la poste | P33: Adaptation : d’après une histoire tirée de Lebenslänglich — Protokolle aus der Haft de Klaus Antes et Christiane Ehrhardt Assistants à la réalisation : Renate Leiffer ; Christian Hohoff Production exécutive : Peter Märthesheimer Son : Karsten Ullrich Format : 16 mm, couleur Genre : drame Tournage : 25 jours, novembre-décembre 1975, Munich et environs Diffusion : 23 mars 1976 (ARD) | Q33: Peter Trepper, condamné à dix ans de prison pour homicide, raconte son histoire à une psychologue. Privé d’affection par ses parents, il cherche à gagner l’amour de son épouse Erika par son travail, les cadeaux et une consommation à crédit qui l’endette toujours davantage. Épuisé par le surtravail et incapable de demander de l’aide, il finit par tuer un cafetier qui maltraite un jeune homme. | S33: Peter tente d’acheter par son travail et ses cadeaux une affection dont il a été privé : chez Fassbinder, l’argent, les objets et les sentiments sont incommensurables. L’engrenage du crédit et du surtravail inscrit sa détresse dans le « miracle économique » ouest-allemand, construit au prix des relations humaines. Les retours en arrière, les brefs aperçus anticipés, les fleurs et les miroirs empruntent au mélodrame tout en révélant les origines quotidiennes de la violence et de la folie. | U33: Films_images/Je_veux_seulement_que_vous_m_aimiez.jpg | X33: 1976 | Y33: amour|famille|travail|argent|crédit|consommation|surtravail|violence|folie|mélodrame|fleurs|miroirs | Z33: RWF_Notes sur les films.docx | AA33: Documenté | AB33: film-1976-je-veux-seulement-que-vous-m-aimiez | AC33: =IF(O33="","",_xlfn.TEXTJOIN("; ",TRUE,IF(ISNUMBER(SEARCH('Référentiel entourage'!$B$2,O33)),'Référentiel entourage'!$A$2,""),IF(ISNUMBER(SEARCH('Référentiel entourage'!$B$3,O33)),'Référentiel entourage'!$A$3,""),IF(ISNUMBER(SEARCH('Référentiel entourage'!$B$4,O33)),'Référentiel entourage'!$A$4,""),IF(ISNUMBER(SEARCH('Référentiel entourage'!$B$5,O33)),'Référentiel entourage'!$A$5,""),IF(ISNUMBER(SEARCH('Référentiel entourage'!$B$6,O33)),'Référentiel entourage'!$A$6,""),IF(ISNUMBER(SEARCH('Référentiel entourage'!$B$7,O33)),'Référentiel entourage'!$A$7,""),IF(ISNUMBER(SEARCH('Référentiel entourage'!$B$8,O33)),'Référentiel entourage'!$A$8,""),IF(ISNUMBER(SEARCH('Référentiel entourage'!$B$9,O33)),'Référentiel entourage'!$A$9,""),IF(ISNUMBER(SEARCH('Référentiel entourage'!$B$10,O33)),'Référentiel entourage'!$A$10,""),IF(ISNUMBER(SEARCH('Référentiel entourage'!$B$11,O33)),'Référentiel entourage'!$A$11,""),IF(ISNUMBER(SEARCH('Référentiel entourage'!$B$12,O33)),'Référentiel entourage'!$A$12,""),IF(ISNUMBER(SEARCH('Référentiel entourage'!$B$13,O33)),'Référentiel entourage'!$A$13,""),IF(ISNUMBER(SEARCH('Référentiel entourage'!$B$14,O33)),'Référentiel entourage'!$A$14,""),IF(ISNUMBER(SEARCH('Référentiel entourage'!$B$15,O33)),'Référentiel entourage'!$A$15,""),IF(ISNUMBER(SEARCH('Référentiel entourage'!$B$16,O33)),'Référentiel entourage'!$A$16,""),IF(ISNUMBER(SEARCH('Référentiel entourage'!$B$17,O33)),'Référentiel entourage'!$A$17,""),IF(ISNUMBER(SEARCH('Référentiel entourage'!$B$18,O33)),'Référentiel entourage'!$A$18,""),IF(ISNUMBER(SEARCH('Référentiel entourage'!$B$19,O33)),'Référentiel entourage'!$A$19,""),IF(ISNUMBER(SEARCH('Référentiel entourage'!$B$20,O33)),'Référentiel entourage'!$A$20,""),IF(ISNUMBER(SEARCH('Référentiel entourage'!$B$21,O33)),'Référentiel entourage'!$A$21,""),IF(ISNUMBER(SEARCH('Référentiel entourage'!$B$22,O33)),'Référentiel entourage'!$A$22,""),IF(ISNUMBER(SEARCH('Référentiel entourage'!$B$23,O33)),'Référentiel entourage'!$A$23,""),IF(ISNUMBER(SEARCH('Référentiel entourage'!$B$24,O33)),'Référentiel entourage'!$A$24,""))) -> pers-ingrid-caven; pers-lilo-pempeit; pers-armin-meier | AD33: =_xlfn.LET(_xlpm.texte,_xlfn.TEXTJOIN(" | ",TRUE,H33:N33,P33),IF(_xlpm.texte="","",_xlfn.TEXTJOIN("; ",TRUE,IF(ISNUMBER(SEARCH('Référentiel entourage'!$B$2,_xlpm.texte)),'Référentiel entourage'!$A$2,""),IF(ISNUMBER(SEARCH('Référentiel entourage'!$B$3,_xlpm.texte)),'Référentiel entourage'!$A$3,""),IF(ISNUMBER(SEARCH('Référentiel entourage'!$B$4,_xlpm.texte)),'Référentiel entourage'!$A$4,""),IF(ISNUMBER(SEARCH('Référentiel entourage'!$B$5,_xlpm.texte)),'Référentiel entourage'!$A$5,""),IF(ISNUMBER(SEARCH('Référentiel entourage'!$B$6,_xlpm.texte)),'Référentiel entourage'!$A$6,""),IF(ISNUMBER(SEARCH('Référentiel entourage'!$B$7,_xlpm.texte)),'Référentiel entourage'!$A$7,""),IF(ISNUMBER(SEARCH('Référentiel entourage'!$B$8,_xlpm.texte)),'Référentiel entourage'!$A$8,""),IF(ISNUMBER(SEARCH('Référentiel entourage'!$B$9,_xlpm.texte)),'Référentiel entourage'!$A$9,""),IF(ISNUMBER(SEARCH('Référentiel entourage'!$B$10,_xlpm.texte)),'Référentiel entourage'!$A$10,""),IF(ISNUMBER(SEARCH('Référentiel entourage'!$B$11,_xlpm.texte)),'Référentiel entourage'!$A$11,""),IF(ISNUMBER(SEARCH('Référentiel entourage'!$B$12,_xlpm.texte)),'Référentiel entourage'!$A$12,""),IF(ISNUMBER(SEARCH('Référentiel entourage'!$B$13,_xlpm.texte)),'Référentiel entourage'!$A$13,""),IF(ISNUMBER(SEARCH('Référentiel entourage'!$B$14,_xlpm.texte)),'Référentiel entourage'!$A$14,""),IF(ISNUMBER(SEARCH('Référentiel entourage'!$B$15,_xlpm.texte)),'Référentiel entourage'!$A$15,""),IF(ISNUMBER(SEARCH('Référentiel entourage'!$B$16,_xlpm.texte)),'Référentiel entourage'!$A$16,""),IF(ISNUMBER(SEARCH('Référentiel entourage'!$B$17,_xlpm.texte)),'Référentiel entourage'!$A$17,""),IF(ISNUMBER(SEARCH('Référentiel entourage'!$B$18,_xlpm.texte)),'Référentiel entourage'!$A$18,""),IF(ISNUMBER(SEARCH('Référentiel entourage'!$B$19,_xlpm.texte)),'Référentiel entourage'!$A$19,""),IF(ISNUMBER(SEARCH('Référentiel entourage'!$B$20,_xlpm.texte)),'Référentiel entourage'!$A$20,""),IF(ISNUMBER(SEARCH('Référentiel entourage'!$B$21,_xlpm.texte)),'Référentiel entourage'!$A$21,""),IF(ISNUMBER(SEARCH('Référentiel entourage'!$B$22,_xlpm.texte)),'Référentiel entourage'!$A$22,""),IF(ISNUMBER(SEARCH('Référentiel entourage'!$B$23,_xlpm.texte)),'Référentiel entourage'!$A$23,""),IF(ISNUMBER(SEARCH('Référentiel entourage'!$B$24,_xlpm.texte)),'Référentiel entourage'!$A$24,"")))) -> pers-michael-ballhaus; pers-kurt-raab; pers-peer-raben
A34: rwf-1977-femmes-a-new-york | B34: Femmes à New York | C34: Frauen in New York | D34: 1977 | E34: Téléfilm | F34: 111 | G34: RFA | H34: Rainer Werner Fassbinder | I34: Nora Gray, d’après la pièce de Clare Boothe Luce | J34: Michael Ballhaus | K34: Wolfgang Kerhutt | L34: Rolf Glittenberg | O34: Christa Berndl : Mary Haines Margit Carstensen : Sylvia Fowler Anne-Marie Kuster : Peggy Day Eva Mattes : Edith Potter Angela Schmid : Nancy Blake / la princesse Tamara / Miss Trimmerback Barbara Sukowa : Chrystal Allen Heide Grübl : Jane / la professeure de gymnastique / une jeune fille Ehmi Bessel : Mrs Wagstaff / Ingrid / une directrice / Miss Watts / une dame Suzanne Werht : une vendeuse / une coiffeuse / une jeune fille Carola Schwarz : une vendeuse / une coiffeuse / Helene Irm Hermann : Olga / Miriam Adelheid Müther : Euphie / un mannequin / la cigarettière Ilse Bally : la dame au masque de boue / une directrice / une dame Andrea Grosske : Miss Fordyce / Luca / Maggie / une veuve Christina Prior : Klein-Mary Gisela Uhlen : Mrs Moorehead / la comtesse de Lage Henny Zschoppe : une infirmière / Sadie Sabine Wegener : la débutante | P34: Format : couleur, mono Genre : comédie Diffusion : 1977 | Q34: Dans le New York des années 1930, plusieurs femmes fortunées se retrouvent et discutent de leur vie quotidienne. | X34: 1977 | Z34: Wikipédia : https://fr.wikipedia.org/wiki/Femmes_%C3%A0_New_York | AA34: À compléter | AB34: film-1977-femmes-a-new-york | AC34: =IF(O34="","",_xlfn.TEXTJOIN("; ",TRUE,IF(ISNUMBER(SEARCH('Référentiel entourage'!$B$2,O34)),'Référentiel entourage'!$A$2,""),IF(ISNUMBER(SEARCH('Référentiel entourage'!$B$3,O34)),'Référentiel entourage'!$A$3,""),IF(ISNUMBER(SEARCH('Référentiel entourage'!$B$4,O34)),'Référentiel entourage'!$A$4,""),IF(ISNUMBER(SEARCH('Référentiel entourage'!$B$5,O34)),'Référentiel entourage'!$A$5,""),IF(ISNUMBER(SEARCH('Référentiel entourage'!$B$6,O34)),'Référentiel entourage'!$A$6,""),IF(ISNUMBER(SEARCH('Référentiel entourage'!$B$7,O34)),'Référentiel entourage'!$A$7,""),IF(ISNUMBER(SEARCH('Référentiel entourage'!$B$8,O34)),'Référentiel entourage'!$A$8,""),IF(ISNUMBER(SEARCH('Référentiel entourage'!$B$9,O34)),'Référentiel entourage'!$A$9,""),IF(ISNUMBER(SEARCH('Référentiel entourage'!$B$10,O34)),'Référentiel entourage'!$A$10,""),IF(ISNUMBER(SEARCH('Référentiel entourage'!$B$11,O34)),'Référentiel entourage'!$A$11,""),IF(ISNUMBER(SEARCH('Référentiel entourage'!$B$12,O34)),'Référentiel entourage'!$A$12,""),IF(ISNUMBER(SEARCH('Référentiel entourage'!$B$13,O34)),'Référentiel entourage'!$A$13,""),IF(ISNUMBER(SEARCH('Référentiel entourage'!$B$14,O34)),'Référentiel entourage'!$A$14,""),IF(ISNUMBER(SEARCH('Référentiel entourage'!$B$15,O34)),'Référentiel entourage'!$A$15,""),IF(ISNUMBER(SEARCH('Référentiel entourage'!$B$16,O34)),'Référentiel entourage'!$A$16,""),IF(ISNUMBER(SEARCH('Référentiel entourage'!$B$17,O34)),'Référentiel entourage'!$A$17,""),IF(ISNUMBER(SEARCH('Référentiel entourage'!$B$18,O34)),'Référentiel entourage'!$A$18,""),IF(ISNUMBER(SEARCH('Référentiel entourage'!$B$19,O34)),'Référentiel entourage'!$A$19,""),IF(ISNUMBER(SEARCH('Référentiel entourage'!$B$20,O34)),'Référentiel entourage'!$A$20,""),IF(ISNUMBER(SEARCH('Référentiel entourage'!$B$21,O34)),'Référentiel entourage'!$A$21,""),IF(ISNUMBER(SEARCH('Référentiel entourage'!$B$22,O34)),'Référentiel entourage'!$A$22,""),IF(ISNUMBER(SEARCH('Référentiel entourage'!$B$23,O34)),'Référentiel entourage'!$A$23,""),IF(ISNUMBER(SEARCH('Référentiel entourage'!$B$24,O34)),'Référentiel entourage'!$A$24,""))) -> pers-margit-carstensen; pers-irm-hermann | AD34: =_xlfn.LET(_xlpm.texte,_xlfn.TEXTJOIN(" | ",TRUE,H34:N34,P34),IF(_xlpm.texte="","",_xlfn.TEXTJOIN("; ",TRUE,IF(ISNUMBER(SEARCH('Référentiel entourage'!$B$2,_xlpm.texte)),'Référentiel entourage'!$A$2,""),IF(ISNUMBER(SEARCH('Référentiel entourage'!$B$3,_xlpm.texte)),'Référentiel entourage'!$A$3,""),IF(ISNUMBER(SEARCH('Référentiel entourage'!$B$4,_xlpm.texte)),'Référentiel entourage'!$A$4,""),IF(ISNUMBER(SEARCH('Référentiel entourage'!$B$5,_xlpm.texte)),'Référentiel entourage'!$A$5,""),IF(ISNUMBER(SEARCH('Référentiel entourage'!$B$6,_xlpm.texte)),'Référentiel entourage'!$A$6,""),IF(ISNUMBER(SEARCH('Référentiel entourage'!$B$7,_xlpm.texte)),'Référentiel entourage'!$A$7,""),IF(ISNUMBER(SEARCH('Référentiel entourage'!$B$8,_xlpm.texte)),'Référentiel entourage'!$A$8,""),IF(ISNUMBER(SEARCH('Référentiel entourage'!$B$9,_xlpm.texte)),'Référentiel entourage'!$A$9,""),IF(ISNUMBER(SEARCH('Référentiel entourage'!$B$10,_xlpm.texte)),'Référentiel entourage'!$A$10,""),IF(ISNUMBER(SEARCH('Référentiel entourage'!$B$11,_xlpm.texte)),'Référentiel entourage'!$A$11,""),IF(ISNUMBER(SEARCH('Référentiel entourage'!$B$12,_xlpm.texte)),'Référentiel entourage'!$A$12,""),IF(ISNUMBER(SEARCH('Référentiel entourage'!$B$13,_xlpm.texte)),'Référentiel entourage'!$A$13,""),IF(ISNUMBER(SEARCH('Référentiel entourage'!$B$14,_xlpm.texte)),'Référentiel entourage'!$A$14,""),IF(ISNUMBER(SEARCH('Référentiel entourage'!$B$15,_xlpm.texte)),'Référentiel entourage'!$A$15,""),IF(ISNUMBER(SEARCH('Référentiel entourage'!$B$16,_xlpm.texte)),'Référentiel entourage'!$A$16,""),IF(ISNUMBER(SEARCH('Référentiel entourage'!$B$17,_xlpm.texte)),'Référentiel entourage'!$A$17,""),IF(ISNUMBER(SEARCH('Référentiel entourage'!$B$18,_xlpm.texte)),'Référentiel entourage'!$A$18,""),IF(ISNUMBER(SEARCH('Référentiel entourage'!$B$19,_xlpm.texte)),'Référentiel entourage'!$A$19,""),IF(ISNUMBER(SEARCH('Référentiel entourage'!$B$20,_xlpm.texte)),'Référentiel entourage'!$A$20,""),IF(ISNUMBER(SEARCH('Référentiel entourage'!$B$21,_xlpm.texte)),'Référentiel entourage'!$A$21,""),IF(ISNUMBER(SEARCH('Référentiel entourage'!$B$22,_xlpm.texte)),'Référentiel entourage'!$A$22,""),IF(ISNUMBER(SEARCH('Référentiel entourage'!$B$23,_xlpm.texte)),'Référentiel entourage'!$A$23,""),IF(ISNUMBER(SEARCH('Référentiel entourage'!$B$24,_xlpm.texte)),'Référentiel entourage'!$A$24,"")))) -> pers-michael-ballhaus
A35: rwf-1977-la-femme-du-chef-de-gare | B35: La Femme du chef de gare | C35: Bolwieser | D35: 1977 | E35: Téléfilm | F35: 201 | G35: RFA | H35: Rainer Werner Fassbinder | I35: Rainer Werner Fassbinder, d’après le roman d’Oskar Maria Graf | J35: Michael Ballhaus | M35: Peer Raben | N35: Herbert Knopp ; Willi Segler ; Harry R. Sokal ; Bavaria Film | O35: Elisabeth Trissenaar : Hanni Bolwieser Kurt Raab : Xaver Ferdinand Maria Bolwieser Karl Scheydt : un gardien de prison Armin Meier : Scherber Bernhard Helfrich : Franz Merkl Karl-Heinz von Hassel : Windegger Volker Spengler : Mangst Gustl Bayrhammer : Neidhard Udo Kier : Schafftaler | P35: Format : couleur, 1,66:1, mono Genre : drame Diffusion : 1977 | Q35: Xaver Bolwieser, chef de gare, découvre que sa femme le trompe avec un boucher puis avec un coiffeur. | X35: 1977 | Z35: Wikipédia : https://fr.wikipedia.org/wiki/La_Femme_du_chef_de_gare | AA35: À compléter | AB35: film-1977-la-femme-du-chef-de-gare | AC35: =IF(O35="","",_xlfn.TEXTJOIN("; ",TRUE,IF(ISNUMBER(SEARCH('Référentiel entourage'!$B$2,O35)),'Référentiel entourage'!$A$2,""),IF(ISNUMBER(SEARCH('Référentiel entourage'!$B$3,O35)),'Référentiel entourage'!$A$3,""),IF(ISNUMBER(SEARCH('Référentiel entourage'!$B$4,O35)),'Référentiel entourage'!$A$4,""),IF(ISNUMBER(SEARCH('Référentiel entourage'!$B$5,O35)),'Référentiel entourage'!$A$5,""),IF(ISNUMBER(SEARCH('Référentiel entourage'!$B$6,O35)),'Référentiel entourage'!$A$6,""),IF(ISNUMBER(SEARCH('Référentiel entourage'!$B$7,O35)),'Référentiel entourage'!$A$7,""),IF(ISNUMBER(SEARCH('Référentiel entourage'!$B$8,O35)),'Référentiel entourage'!$A$8,""),IF(ISNUMBER(SEARCH('Référentiel entourage'!$B$9,O35)),'Référentiel entourage'!$A$9,""),IF(ISNUMBER(SEARCH('Référentiel entourage'!$B$10,O35)),'Référentiel entourage'!$A$10,""),IF(ISNUMBER(SEARCH('Référentiel entourage'!$B$11,O35)),'Référentiel entourage'!$A$11,""),IF(ISNUMBER(SEARCH('Référentiel entourage'!$B$12,O35)),'Référentiel entourage'!$A$12,""),IF(ISNUMBER(SEARCH('Référentiel entourage'!$B$13,O35)),'Référentiel entourage'!$A$13,""),IF(ISNUMBER(SEARCH('Référentiel entourage'!$B$14,O35)),'Référentiel entourage'!$A$14,""),IF(ISNUMBER(SEARCH('Référentiel entourage'!$B$15,O35)),'Référentiel entourage'!$A$15,""),IF(ISNUMBER(SEARCH('Référentiel entourage'!$B$16,O35)),'Référentiel entourage'!$A$16,""),IF(ISNUMBER(SEARCH('Référentiel entourage'!$B$17,O35)),'Référentiel entourage'!$A$17,""),IF(ISNUMBER(SEARCH('Référentiel entourage'!$B$18,O35)),'Référentiel entourage'!$A$18,""),IF(ISNUMBER(SEARCH('Référentiel entourage'!$B$19,O35)),'Référentiel entourage'!$A$19,""),IF(ISNUMBER(SEARCH('Référentiel entourage'!$B$20,O35)),'Référentiel entourage'!$A$20,""),IF(ISNUMBER(SEARCH('Référentiel entourage'!$B$21,O35)),'Référentiel entourage'!$A$21,""),IF(ISNUMBER(SEARCH('Référentiel entourage'!$B$22,O35)),'Référentiel entourage'!$A$22,""),IF(ISNUMBER(SEARCH('Référentiel entourage'!$B$23,O35)),'Référentiel entourage'!$A$23,""),IF(ISNUMBER(SEARCH('Référentiel entourage'!$B$24,O35)),'Référentiel entourage'!$A$24,""))) -> pers-armin-meier; pers-kurt-raab; pers-elisabeth-trissenaar | AD35: =_xlfn.LET(_xlpm.texte,_xlfn.TEXTJOIN(" | ",TRUE,H35:N35,P35),IF(_xlpm.texte="","",_xlfn.TEXTJOIN("; ",TRUE,IF(ISNUMBER(SEARCH('Référentiel entourage'!$B$2,_xlpm.texte)),'Référentiel entourage'!$A$2,""),IF(ISNUMBER(SEARCH('Référentiel entourage'!$B$3,_xlpm.texte)),'Référentiel entourage'!$A$3,""),IF(ISNUMBER(SEARCH('Référentiel entourage'!$B$4,_xlpm.texte)),'Référentiel entourage'!$A$4,""),IF(ISNUMBER(SEARCH('Référentiel entourage'!$B$5,_xlpm.texte)),'Référentiel entourage'!$A$5,""),IF(ISNUMBER(SEARCH('Référentiel entourage'!$B$6,_xlpm.texte)),'Référentiel entourage'!$A$6,""),IF(ISNUMBER(SEARCH('Référentiel entourage'!$B$7,_xlpm.texte)),'Référentiel entourage'!$A$7,""),IF(ISNUMBER(SEARCH('Référentiel entourage'!$B$8,_xlpm.texte)),'Référentiel entourage'!$A$8,""),IF(ISNUMBER(SEARCH('Référentiel entourage'!$B$9,_xlpm.texte)),'Référentiel entourage'!$A$9,""),IF(ISNUMBER(SEARCH('Référentiel entourage'!$B$10,_xlpm.texte)),'Référentiel entourage'!$A$10,""),IF(ISNUMBER(SEARCH('Référentiel entourage'!$B$11,_xlpm.texte)),'Référentiel entourage'!$A$11,""),IF(ISNUMBER(SEARCH('Référentiel entourage'!$B$12,_xlpm.texte)),'Référentiel entourage'!$A$12,""),IF(ISNUMBER(SEARCH('Référentiel entourage'!$B$13,_xlpm.texte)),'Référentiel entourage'!$A$13,""),IF(ISNUMBER(SEARCH('Référentiel entourage'!$B$14,_xlpm.texte)),'Référentiel entourage'!$A$14,""),IF(ISNUMBER(SEARCH('Référentiel entourage'!$B$15,_xlpm.texte)),'Référentiel entourage'!$A$15,""),IF(ISNUMBER(SEARCH('Référentiel entourage'!$B$16,_xlpm.texte)),'Référentiel entourage'!$A$16,""),IF(ISNUMBER(SEARCH('Référentiel entourage'!$B$17,_xlpm.texte)),'Référentiel entourage'!$A$17,""),IF(ISNUMBER(SEARCH('Référentiel entourage'!$B$18,_xlpm.texte)),'Référentiel entourage'!$A$18,""),IF(ISNUMBER(SEARCH('Référentiel entourage'!$B$19,_xlpm.texte)),'Référentiel entourage'!$A$19,""),IF(ISNUMBER(SEARCH('Référentiel entourage'!$B$20,_xlpm.texte)),'Référentiel entourage'!$A$20,""),IF(ISNUMBER(SEARCH('Référentiel entourage'!$B$21,_xlpm.texte)),'Référentiel entourage'!$A$21,""),IF(ISNUMBER(SEARCH('Référentiel entourage'!$B$22,_xlpm.texte)),'Référentiel entourage'!$A$22,""),IF(ISNUMBER(SEARCH('Référentiel entourage'!$B$23,_xlpm.texte)),'Référentiel entourage'!$A$23,""),IF(ISNUMBER(SEARCH('Référentiel entourage'!$B$24,_xlpm.texte)),'Référentiel entourage'!$A$24,"")))) -> pers-michael-ballhaus; pers-peer-raben
A36: rwf-1978-l-allemagne-en-automne | B36: L’Allemagne en automne | D36: 1978 | E36: Film collectif | F36: 119 | G36: RFA | H36: Rainer Werner Fassbinder | P36: Film collectif : Alf Brustellin ; Bernhard Sinkel ; Rainer Werner Fassbinder ; Alexander Kluge ; Maximiliane Mainka ; Edgar Reitz ; Beate Mainka-Jellinghaus ; Peter Schubert ; Hans Peter Cloos ; Katja Rupé ; Volker Schlöndorff Format : 1,66:1, mono Genre : drame, documentaire Sortie : mars 1978 | Q36: Premier film consacré à la Fraction armée rouge, L’Allemagne en automne réunit plusieurs cinéastes du Nouveau cinéma allemand. Dans son segment autofictionnel, Fassbinder met en scène son travail, son couple et sa mère pour confronter l’artiste et la société allemande aux événements de l’automne 1977, à la question de l’engagement et au poids de la mémoire historique. | S36: Fassbinder expose la contradiction entre son analyse politique et un comportement intime ambivalent, violent et irrationnel, notamment dans sa relation avec Armin Meier. Armin et la mère du cinéaste incarnent deux formes de « bon sens » allemand où la défense de la démocratie coexiste avec l’acceptation de la violence policière et le désir d’autorité. Le huis clos obscur, les cadres serrés et les surcadrages composent ainsi l’autoportrait crépusculaire d’un artiste impuissant, où l’intime, le politique et la création demeurent indissociables. | U36: Films_images/L_Allemagne_en_automne.jpg | X36: 1978 | Y36: Fraction armée rouge|terrorisme|autofiction|engagement|démocratie|autorité|mémoire|couple|autoportrait|intime|politique|huis clos | Z36: RWF_Notes sur les films.docx | AA36: Documenté | AB36: film-1978-l-allemagne-en-automne | AC36: =IF(O36="","",_xlfn.TEXTJOIN("; ",TRUE,IF(ISNUMBER(SEARCH('Référentiel entourage'!$B$2,O36)),'Référentiel entourage'!$A$2,""),IF(ISNUMBER(SEARCH('Référentiel entourage'!$B$3,O36)),'Référentiel entourage'!$A$3,""),IF(ISNUMBER(SEARCH('Référentiel entourage'!$B$4,O36)),'Référentiel entourage'!$A$4,""),IF(ISNUMBER(SEARCH('Référentiel entourage'!$B$5,O36)),'Référentiel entourage'!$A$5,""),IF(ISNUMBER(SEARCH('Référentiel entourage'!$B$6,O36)),'Référentiel entourage'!$A$6,""),IF(ISNUMBER(SEARCH('Référentiel entourage'!$B$7,O36)),'Référentiel entourage'!$A$7,""),IF(ISNUMBER(SEARCH('Référentiel entourage'!$B$8,O36)),'Référentiel entourage'!$A$8,""),IF(ISNUMBER(SEARCH('Référentiel entourage'!$B$9,O36)),'Référentiel entourage'!$A$9,""),IF(ISNUMBER(SEARCH('Référentiel entourage'!$B$10,O36)),'Référentiel entourage'!$A$10,""),IF(ISNUMBER(SEARCH('Référentiel entourage'!$B$11,O36)),'Référentiel entourage'!$A$11,""),IF(ISNUMBER(SEARCH('Référentiel entourage'!$B$12,O36)),'Référentiel entourage'!$A$12,""),IF(ISNUMBER(SEARCH('Référentiel entourage'!$B$13,O36)),'Référentiel entourage'!$A$13,""),IF(ISNUMBER(SEARCH('Référentiel entourage'!$B$14,O36)),'Référentiel entourage'!$A$14,""),IF(ISNUMBER(SEARCH('Référentiel entourage'!$B$15,O36)),'Référentiel entourage'!$A$15,""),IF(ISNUMBER(SEARCH('Référentiel entourage'!$B$16,O36)),'Référentiel entourage'!$A$16,""),IF(ISNUMBER(SEARCH('Référentiel entourage'!$B$17,O36)),'Référentiel entourage'!$A$17,""),IF(ISNUMBER(SEARCH('Référentiel entourage'!$B$18,O36)),'Référentiel entourage'!$A$18,""),IF(ISNUMBER(SEARCH('Référentiel entourage'!$B$19,O36)),'Référentiel entourage'!$A$19,""),IF(ISNUMBER(SEARCH('Référentiel entourage'!$B$20,O36)),'Référentiel entourage'!$A$20,""),IF(ISNUMBER(SEARCH('Référentiel entourage'!$B$21,O36)),'Référentiel entourage'!$A$21,""),IF(ISNUMBER(SEARCH('Référentiel entourage'!$B$22,O36)),'Référentiel entourage'!$A$22,""),IF(ISNUMBER(SEARCH('Référentiel entourage'!$B$23,O36)),'Référentiel entourage'!$A$23,""),IF(ISNUMBER(SEARCH('Référentiel entourage'!$B$24,O36)),'Référentiel entourage'!$A$24,""))) | AD36: =_xlfn.LET(_xlpm.texte,_xlfn.TEXTJOIN(" | ",TRUE,H36:N36,P36),IF(_xlpm.texte="","",_xlfn.TEXTJOIN("; ",TRUE,IF(ISNUMBER(SEARCH('Référentiel entourage'!$B$2,_xlpm.texte)),'Référentiel entourage'!$A$2,""),IF(ISNUMBER(SEARCH('Référentiel entourage'!$B$3,_xlpm.texte)),'Référentiel entourage'!$A$3,""),IF(ISNUMBER(SEARCH('Référentiel entourage'!$B$4,_xlpm.texte)),'Référentiel entourage'!$A$4,""),IF(ISNUMBER(SEARCH('Référentiel entourage'!$B$5,_xlpm.texte)),'Référentiel entourage'!$A$5,""),IF(ISNUMBER(SEARCH('Référentiel entourage'!$B$6,_xlpm.texte)),'Référentiel entourage'!$A$6,""),IF(ISNUMBER(SEARCH('Référentiel entourage'!$B$7,_xlpm.texte)),'Référentiel entourage'!$A$7,""),IF(ISNUMBER(SEARCH('Référentiel entourage'!$B$8,_xlpm.texte)),'Référentiel entourage'!$A$8,""),IF(ISNUMBER(SEARCH('Référentiel entourage'!$B$9,_xlpm.texte)),'Référentiel entourage'!$A$9,""),IF(ISNUMBER(SEARCH('Référentiel entourage'!$B$10,_xlpm.texte)),'Référentiel entourage'!$A$10,""),IF(ISNUMBER(SEARCH('Référentiel entourage'!$B$11,_xlpm.texte)),'Référentiel entourage'!$A$11,""),IF(ISNUMBER(SEARCH('Référentiel entourage'!$B$12,_xlpm.texte)),'Référentiel entourage'!$A$12,""),IF(ISNUMBER(SEARCH('Référentiel entourage'!$B$13,_xlpm.texte)),'Référentiel entourage'!$A$13,""),IF(ISNUMBER(SEARCH('Référentiel entourage'!$B$14,_xlpm.texte)),'Référentiel entourage'!$A$14,""),IF(ISNUMBER(SEARCH('Référentiel entourage'!$B$15,_xlpm.texte)),'Référentiel entourage'!$A$15,""),IF(ISNUMBER(SEARCH('Référentiel entourage'!$B$16,_xlpm.texte)),'Référentiel entourage'!$A$16,""),IF(ISNUMBER(SEARCH('Référentiel entourage'!$B$17,_xlpm.texte)),'Référentiel entourage'!$A$17,""),IF(ISNUMBER(SEARCH('Référentiel entourage'!$B$18,_xlpm.texte)),'Référentiel entourage'!$A$18,""),IF(ISNUMBER(SEARCH('Référentiel entourage'!$B$19,_xlpm.texte)),'Référentiel entourage'!$A$19,""),IF(ISNUMBER(SEARCH('Référentiel entourage'!$B$20,_xlpm.texte)),'Référentiel entourage'!$A$20,""),IF(ISNUMBER(SEARCH('Référentiel entourage'!$B$21,_xlpm.texte)),'Référentiel entourage'!$A$21,""),IF(ISNUMBER(SEARCH('Référentiel entourage'!$B$22,_xlpm.texte)),'Référentiel entourage'!$A$22,""),IF(ISNUMBER(SEARCH('Référentiel entourage'!$B$23,_xlpm.texte)),'Référentiel entourage'!$A$23,""),IF(ISNUMBER(SEARCH('Référentiel entourage'!$B$24,_xlpm.texte)),'Référentiel entourage'!$A$24,""))))
A37: rwf-1978-despair | B37: Despair | C37: Despair – Eine Reise ins Licht | D37: 1978 | E37: Long métrage | F37: 119 | G37: RFA / France | H37: Rainer Werner Fassbinder | I37: Tom Stoppard, d’après La Méprise de Vladimir Nabokov | O37: Dirk Bogarde : Hermann Hermann Andréa Ferréol : Lydia Klaus Löwitsch : Felix Weber Volker Spengler : Ardalion Peter Kern : Müller Alexander Allerson : Mayer Gottfried John : Perebrodov Hark Bohm : le docteur Bernhard Wicki : Orlovius Isolde Barth Ingrid Caven : la réceptionniste de l’hôtel Adrian Hoven : l’inspecteur Schelling Roger Fritz : l’inspecteur Braun Voli Geiller : Madame Hans Zander : le frère de Müller | P37: Langue : anglais Format : couleur Sortie : 19 mai 1978 | Q37: Dans l’Allemagne des années 1930, Hermann Hermann, magnat du chocolat et émigré russe, s’enfonce lentement dans la folie. | S37: En adaptant Nabokov, Fassbinder transforme le récit du double en crise de l’identification : vitres, miroirs, zooms et décalages spatiaux rendent la perception instable et empêchent Hermann de s’inscrire dans un espace classique. Le récit labyrinthique repose sur des répétitions, des échos et des identités flottantes, jusqu’à la rupture finale de la fiction face à la caméra. La folie du bourgeois, l’impuissance sexuelle et le rêve de fusion se nouent à l’ascension du nazisme et à une lecture du fascisme comme forme extrême du capitalisme de monopole. | U37: Films_images/Despair.jpg | X37: 1978 | Y37: double|folie|identité|perception|labyrinthe|miroirs|nazisme|capitalisme|homosexualité|adaptation|Nabokov|cinéma | Z37: RWF_Notes sur les films.docx | AA37: Documenté | AB37: film-1978-despair | AC37: =IF(O37="","",_xlfn.TEXTJOIN("; ",TRUE,IF(ISNUMBER(SEARCH('Référentiel entourage'!$B$2,O37)),'Référentiel entourage'!$A$2,""),IF(ISNUMBER(SEARCH('Référentiel entourage'!$B$3,O37)),'Référentiel entourage'!$A$3,""),IF(ISNUMBER(SEARCH('Référentiel entourage'!$B$4,O37)),'Référentiel entourage'!$A$4,""),IF(ISNUMBER(SEARCH('Référentiel entourage'!$B$5,O37)),'Référentiel entourage'!$A$5,""),IF(ISNUMBER(SEARCH('Référentiel entourage'!$B$6,O37)),'Référentiel entourage'!$A$6,""),IF(ISNUMBER(SEARCH('Référentiel entourage'!$B$7,O37)),'Référentiel entourage'!$A$7,""),IF(ISNUMBER(SEARCH('Référentiel entourage'!$B$8,O37)),'Référentiel entourage'!$A$8,""),IF(ISNUMBER(SEARCH('Référentiel entourage'!$B$9,O37)),'Référentiel entourage'!$A$9,""),IF(ISNUMBER(SEARCH('Référentiel entourage'!$B$10,O37)),'Référentiel entourage'!$A$10,""),IF(ISNUMBER(SEARCH('Référentiel entourage'!$B$11,O37)),'Référentiel entourage'!$A$11,""),IF(ISNUMBER(SEARCH('Référentiel entourage'!$B$12,O37)),'Référentiel entourage'!$A$12,""),IF(ISNUMBER(SEARCH('Référentiel entourage'!$B$13,O37)),'Référentiel entourage'!$A$13,""),IF(ISNUMBER(SEARCH('Référentiel entourage'!$B$14,O37)),'Référentiel entourage'!$A$14,""),IF(ISNUMBER(SEARCH('Référentiel entourage'!$B$15,O37)),'Référentiel entourage'!$A$15,""),IF(ISNUMBER(SEARCH('Référentiel entourage'!$B$16,O37)),'Référentiel entourage'!$A$16,""),IF(ISNUMBER(SEARCH('Référentiel entourage'!$B$17,O37)),'Référentiel entourage'!$A$17,""),IF(ISNUMBER(SEARCH('Référentiel entourage'!$B$18,O37)),'Référentiel entourage'!$A$18,""),IF(ISNUMBER(SEARCH('Référentiel entourage'!$B$19,O37)),'Référentiel entourage'!$A$19,""),IF(ISNUMBER(SEARCH('Référentiel entourage'!$B$20,O37)),'Référentiel entourage'!$A$20,""),IF(ISNUMBER(SEARCH('Référentiel entourage'!$B$21,O37)),'Référentiel entourage'!$A$21,""),IF(ISNUMBER(SEARCH('Référentiel entourage'!$B$22,O37)),'Référentiel entourage'!$A$22,""),IF(ISNUMBER(SEARCH('Référentiel entourage'!$B$23,O37)),'Référentiel entourage'!$A$23,""),IF(ISNUMBER(SEARCH('Référentiel entourage'!$B$24,O37)),'Référentiel entourage'!$A$24,""))) -> pers-hark-bohm; pers-ingrid-caven; pers-gottfried-john | AD37: =_xlfn.LET(_xlpm.texte,_xlfn.TEXTJOIN(" | ",TRUE,H37:N37,P37),IF(_xlpm.texte="","",_xlfn.TEXTJOIN("; ",TRUE,IF(ISNUMBER(SEARCH('Référentiel entourage'!$B$2,_xlpm.texte)),'Référentiel entourage'!$A$2,""),IF(ISNUMBER(SEARCH('Référentiel entourage'!$B$3,_xlpm.texte)),'Référentiel entourage'!$A$3,""),IF(ISNUMBER(SEARCH('Référentiel entourage'!$B$4,_xlpm.texte)),'Référentiel entourage'!$A$4,""),IF(ISNUMBER(SEARCH('Référentiel entourage'!$B$5,_xlpm.texte)),'Référentiel entourage'!$A$5,""),IF(ISNUMBER(SEARCH('Référentiel entourage'!$B$6,_xlpm.texte)),'Référentiel entourage'!$A$6,""),IF(ISNUMBER(SEARCH('Référentiel entourage'!$B$7,_xlpm.texte)),'Référentiel entourage'!$A$7,""),IF(ISNUMBER(SEARCH('Référentiel entourage'!$B$8,_xlpm.texte)),'Référentiel entourage'!$A$8,""),IF(ISNUMBER(SEARCH('Référentiel entourage'!$B$9,_xlpm.texte)),'Référentiel entourage'!$A$9,""),IF(ISNUMBER(SEARCH('Référentiel entourage'!$B$10,_xlpm.texte)),'Référentiel entourage'!$A$10,""),IF(ISNUMBER(SEARCH('Référentiel entourage'!$B$11,_xlpm.texte)),'Référentiel entourage'!$A$11,""),IF(ISNUMBER(SEARCH('Référentiel entourage'!$B$12,_xlpm.texte)),'Référentiel entourage'!$A$12,""),IF(ISNUMBER(SEARCH('Référentiel entourage'!$B$13,_xlpm.texte)),'Référentiel entourage'!$A$13,""),IF(ISNUMBER(SEARCH('Référentiel entourage'!$B$14,_xlpm.texte)),'Référentiel entourage'!$A$14,""),IF(ISNUMBER(SEARCH('Référentiel entourage'!$B$15,_xlpm.texte)),'Référentiel entourage'!$A$15,""),IF(ISNUMBER(SEARCH('Référentiel entourage'!$B$16,_xlpm.texte)),'Référentiel entourage'!$A$16,""),IF(ISNUMBER(SEARCH('Référentiel entourage'!$B$17,_xlpm.texte)),'Référentiel entourage'!$A$17,""),IF(ISNUMBER(SEARCH('Référentiel entourage'!$B$18,_xlpm.texte)),'Référentiel entourage'!$A$18,""),IF(ISNUMBER(SEARCH('Référentiel entourage'!$B$19,_xlpm.texte)),'Référentiel entourage'!$A$19,""),IF(ISNUMBER(SEARCH('Référentiel entourage'!$B$20,_xlpm.texte)),'Référentiel entourage'!$A$20,""),IF(ISNUMBER(SEARCH('Référentiel entourage'!$B$21,_xlpm.texte)),'Référentiel entourage'!$A$21,""),IF(ISNUMBER(SEARCH('Référentiel entourage'!$B$22,_xlpm.texte)),'Référentiel entourage'!$A$22,""),IF(ISNUMBER(SEARCH('Référentiel entourage'!$B$23,_xlpm.texte)),'Référentiel entourage'!$A$23,""),IF(ISNUMBER(SEARCH('Référentiel entourage'!$B$24,_xlpm.texte)),'Référentiel entourage'!$A$24,""))))
