Workbook

Sheet Périodes
A1: ID période | B1: Titre période | C1: question directrice | D1: Événement histoire et politique | E1: Contexte culturel | F1: Biographie de Fassbinder | G1: Œuvres | H1: ID films - Œuvres | I1: Analyse et réception critique | J1: Liens | K1: Citation | L1: Image | M1: Legende | N1: Notion
A2: 1945-1946 | B2: Les ruines l'Heure zéro | C2: Le "point zéro" de l'histoire de l'Allemagne d'après-guerre est-il un point zéro pour la vie et l'œuvre de RWF ? | D2: Capitulation du Troisième Reich (mai). L'Allemagne est en ruines (Année Zéro). Début de l'occupation alliée et de l'amnésie collective sur le passé nazi. Le pays et berlin sont partagés en zone sous contrôle des différentes forces alliées. | E2: Le cinéma est en ruines. Période des films de décombres ( Trümmerfilme ) comme Les assassins sont parmi nous (Staudte, 1946). | F2: Naissance de Rainer Werner Fassbinder le 31 mai à Bad Wörishofen, Bavière. | H2: =IF(G2="","",_xlfn.TEXTJOIN("; ",TRUE(),IF(ISNUMBER(SEARCH(SUBSTITUTE('Référentiel films'!$A$2,"’","'"),SUBSTITUTE(G2,"’","'"))),'Référentiel films'!$B$2,""),IF(ISNUMBER(SEARCH(SUBSTITUTE('Référentiel films'!$A$3,"’","'"),SUBSTITUTE(G2,"’","'"))),'Référentiel films'!$B$3,""),IF(ISNUMBER(SEARCH(SUBSTITUTE('Référentiel films'!$A$4,"’","'"),SUBSTITUTE(G2,"’","'"))),'Référentiel films'!$B$4,""),IF(ISNUMBER(SEARCH(SUBSTITUTE('Référentiel films'!$A$5,"’","'"),SUBSTITUTE(G2,"’","'"))),'Référentiel films'!$B$5,""),IF(ISNUMBER(SEARCH(SUBSTITUTE('Référentiel films'!$A$6,"’","'"),SUBSTITUTE(G2,"’","'"))),'Référentiel films'!$B$6,""),IF(ISNUMBER(SEARCH(SUBSTITUTE('Référentiel films'!$A$7,"’","'"),SUBSTITUTE(G2,"’","'"))),'Référentiel films'!$B$7,""),IF(ISNUMBER(SEARCH(SUBSTITUTE('Référentiel films'!$A$8,"’","'"),SUBSTITUTE(G2,"’","'"))),'Référentiel films'!$B$8,""),IF(ISNUMBER(SEARCH(SUBSTITUTE('Référentiel films'!$A$9,"’","'"),SUBSTITUTE(G2,"’","'"))),'Référentiel films'!$B$9,""),IF(ISNUMBER(SEARCH(SUBSTITUTE('Référentiel films'!$A$10,"’","'"),SUBSTITUTE(G2,"’","'"))),'Référentiel films'!$B$10,""),IF(ISNUMBER(SEARCH(SUBSTITUTE('Référentiel films'!$A$11,"’","'"),SUBSTITUTE(G2,"’","'"))),'Référentiel films'!$B$11,""),IF(ISNUMBER(SEARCH(SUBSTITUTE('Référentiel films'!$A$12,"’","'"),SUBSTITUTE(G2,"’","'"))),'Référentiel films'!$B$12,""),IF(ISNUMBER(SEARCH(SUBSTITUTE('Référentiel films'!$A$13,"’","'"),SUBSTITUTE(G2,"’","'"))),'Référentiel films'!$B$13,""),IF(ISNUMBER(SEARCH(SUBSTITUTE('Référentiel films'!$A$14,"’","'"),SUBSTITUTE(G2,"’","'"))),'Référentiel films'!$B$14,""),IF(ISNUMBER(SEARCH(SUBSTITUTE('Référentiel films'!$A$15,"’","'"),SUBSTITUTE(G2,"’","'"))),'Référentiel films'!$B$15,""),IF(ISNUMBER(SEARCH(SUBSTITUTE('Référentiel films'!$A$16,"’","'"),SUBSTITUTE(G2,"’","'"))),'Référentiel films'!$B$16,""),IF(ISNUMBER(SEARCH(SUBSTITUTE('Référentiel films'!$A$17,"’","'"),SUBSTITUTE(G2,"’","'"))),'Référentiel films'!$B$17,""),IF(ISNUMBER(SEARCH(SUBSTITUTE('Référentiel films'!$A$18,"’","'"),SUBSTITUTE(G2,"’","'"))),'Référentiel films'!$B$18,""),IF(ISNUMBER(SEARCH(SUBSTITUTE('Référentiel films'!$A$19,"’","'"),SUBSTITUTE(G2,"’","'"))),'Référentiel films'!$B$19,""),IF(ISNUMBER(SEARCH(SUBSTITUTE('Référentiel films'!$A$20,"’","'"),SUBSTITUTE(G2,"’","'"))),'Référentiel films'!$B$20,""),IF(ISNUMBER(SEARCH(SUBSTITUTE('Référentiel films'!$A$21,"’","'"),SUBSTITUTE(G2,"’","'"))),'Référentiel films'!$B$21,""),IF(ISNUMBER(SEARCH(SUBSTITUTE('Référentiel films'!$A$22,"’","'"),SUBSTITUTE(G2,"’","'"))),'Référentiel films'!$B$22,""),IF(ISNUMBER(SEARCH(SUBSTITUTE('Référentiel films'!$A$23,"’","'"),SUBSTITUTE(G2,"’","'"))),'Référentiel films'!$B$23,""),IF(ISNUMBER(SEARCH(SUBSTITUTE('Référentiel films'!$A$24,"’","'"),SUBSTITUTE(G2,"’","'"))),'Référentiel films'!$B$24,""),IF(ISNUMBER(SEARCH(SUBSTITUTE('Référentiel films'!$A$25,"’","'"),SUBSTITUTE(G2,"’","'"))),'Référentiel films'!$B$25,""),IF(ISNUMBER(SEARCH(SUBSTITUTE('Référentiel films'!$A$26,"’","'"),SUBSTITUTE(G2,"’","'"))),'Référentiel films'!$B$26,""),IF(ISNUMBER(SEARCH(SUBSTITUTE('Référentiel films'!$A$27,"’","'"),SUBSTITUTE(G2,"’","'"))),'Référentiel films'!$B$27,""),IF(ISNUMBER(SEARCH(SUBSTITUTE('Référentiel films'!$A$28,"’","'"),SUBSTITUTE(G2,"’","'"))),'Référentiel films'!$B$28,""),IF(ISNUMBER(SEARCH(SUBSTITUTE('Référentiel films'!$A$29,"’","'"),SUBSTITUTE(G2,"’","'"))),'Référentiel films'!$B$29,""),IF(ISNUMBER(SEARCH(SUBSTITUTE('Référentiel films'!$A$30,"’","'"),SUBSTITUTE(G2,"’","'"))),'Référentiel films'!$B$30,""),IF(ISNUMBER(SEARCH(SUBSTITUTE('Référentiel films'!$A$31,"’","'"),SUBSTITUTE(G2,"’","'"))),'Référentiel films'!$B$31,""),IF(ISNUMBER(SEARCH(SUBSTITUTE('Référentiel films'!$A$32,"’","'"),SUBSTITUTE(G2,"’","'"))),'Référentiel films'!$B$32,""),IF(ISNUMBER(SEARCH(SUBSTITUTE('Référentiel films'!$A$33,"’","'"),SUBSTITUTE(G2,"’","'"))),'Référentiel films'!$B$33,""),IF(ISNUMBER(SEARCH(SUBSTITUTE('Référentiel films'!$A$34,"’","'"),SUBSTITUTE(G2,"’","'"))),'Référentiel films'!$B$34,""),IF(ISNUMBER(SEARCH(SUBSTITUTE('Référentiel films'!$A$35,"’","'"),SUBSTITUTE(G2,"’","'"))),'Référentiel films'!$B$35,""),IF(ISNUMBER(SEARCH(SUBSTITUTE('Référentiel films'!$A$36,"’","'"),SUBSTITUTE(G2,"’","'"))),'Référentiel films'!$B$36,""),IF(ISNUMBER(SEARCH(SUBSTITUTE('Référentiel films'!$A$37,"’","'"),SUBSTITUTE(G2,"’","'"))),'Référentiel films'!$B$37,""),IF(ISNUMBER(SEARCH(SUBSTITUTE('Référentiel films'!$A$38,"’","'"),SUBSTITUTE(G2,"’","'"))),'Référentiel films'!$B$38,""),IF(ISNUMBER(SEARCH(SUBSTITUTE('Référentiel films'!$A$39,"’","'"),SUBSTITUTE(G2,"’","'"))),'Référentiel films'!$B$39,""),IF(ISNUMBER(SEARCH(SUBSTITUTE('Référentiel films'!$A$40,"’","'"),SUBSTITUTE(G2,"’","'"))),'Référentiel films'!$B$40,""),IF(ISNUMBER(SEARCH(SUBSTITUTE('Référentiel films'!$A$41,"’","'"),SUBSTITUTE(G2,"’","'"))),'Référentiel films'!$B$41,""))) | I2: L'œuvre de Fassbinder proposera plus tard une radiographie critique de ce "point zéro" de la nouvelle Allemagne, notamment dans Le mariage de Maria Braun | J2: Les génériques de Fassbinder | K2: "Nous devons nous débarrasser du passé pour construire l'avenir". Konrad Adenauer | L2: Adenauer.jpeg | M2: Adénauer
A3: 1947-1960 | B3: Le miracle économique | C3: Comment l'Allemagne de l'ouest a-t-elle pu devenir une des premières nations industrielles capitalistes et une démocratie alors même qu'elle était marquée par le provincialisme, l'absence de morale et l'hypocrisie ? | D3: Création de la RFA (1949). Ère Adenauer. Miracle économique ( Wirtschaftswunder ) entre 1950 et 1965 l'économie ouest-allemande croît de 8,2% en moyenne (contre 5% en France pendant les 30 glorieuses). La coccinelle de Wolkswagen devient l'emblème du "miracle économique". Les entreprise de taille moyenne constituent la colonne vertébrale de la puissance économique allemande en fournissant les outils spécialisés nécessaires à l'industrie. Parallèmement, l'état développe une politique sociale conservatrice. Réarmement de la RFA (1955). | E3: Domination du "cinéma de papa" ( Papas Kino ) : films de terroir ( Heimatfilm ), comédies légères dépolitisées, films en costumes , comédies musicales obitennent toujours les faveurs du public. Ces genres nés dans les années 10 et 20 ont été très exploités par les nazis. Freddy Quinn, Rocco Granata ou Catharina Valente sont les stars de la culture populaire allemande. Il n'existe presque aucun film allemand des années 50 et 60 qui traite des camps de concentration nazis. Le cinéma allemand de la période s'intéresse peu à l'histoire. | F3: Enfance marquée par le divorce de ses parents (1951) et l'absence du père. Passion précoce pour le cinéma (refuge). Première lecture de Berlin Alexanderplatz vers 14 ans. | H3: =IF(G3="","",_xlfn.TEXTJOIN("; ",TRUE(),IF(ISNUMBER(SEARCH(SUBSTITUTE('Référentiel films'!$A$2,"’","'"),SUBSTITUTE(G3,"’","'"))),'Référentiel films'!$B$2,""),IF(ISNUMBER(SEARCH(SUBSTITUTE('Référentiel films'!$A$3,"’","'"),SUBSTITUTE(G3,"’","'"))),'Référentiel films'!$B$3,""),IF(ISNUMBER(SEARCH(SUBSTITUTE('Référentiel films'!$A$4,"’","'"),SUBSTITUTE(G3,"’","'"))),'Référentiel films'!$B$4,""),IF(ISNUMBER(SEARCH(SUBSTITUTE('Référentiel films'!$A$5,"’","'"),SUBSTITUTE(G3,"’","'"))),'Référentiel films'!$B$5,""),IF(ISNUMBER(SEARCH(SUBSTITUTE('Référentiel films'!$A$6,"’","'"),SUBSTITUTE(G3,"’","'"))),'Référentiel films'!$B$6,""),IF(ISNUMBER(SEARCH(SUBSTITUTE('Référentiel films'!$A$7,"’","'"),SUBSTITUTE(G3,"’","'"))),'Référentiel films'!$B$7,""),IF(ISNUMBER(SEARCH(SUBSTITUTE('Référentiel films'!$A$8,"’","'"),SUBSTITUTE(G3,"’","'"))),'Référentiel films'!$B$8,""),IF(ISNUMBER(SEARCH(SUBSTITUTE('Référentiel films'!$A$9,"’","'"),SUBSTITUTE(G3,"’","'"))),'Référentiel films'!$B$9,""),IF(ISNUMBER(SEARCH(SUBSTITUTE('Référentiel films'!$A$10,"’","'"),SUBSTITUTE(G3,"’","'"))),'Référentiel films'!$B$10,""),IF(ISNUMBER(SEARCH(SUBSTITUTE('Référentiel films'!$A$11,"’","'"),SUBSTITUTE(G3,"’","'"))),'Référentiel films'!$B$11,""),IF(ISNUMBER(SEARCH(SUBSTITUTE('Référentiel films'!$A$12,"’","'"),SUBSTITUTE(G3,"’","'"))),'Référentiel films'!$B$12,""),IF(ISNUMBER(SEARCH(SUBSTITUTE('Référentiel films'!$A$13,"’","'"),SUBSTITUTE(G3,"’","'"))),'Référentiel films'!$B$13,""),IF(ISNUMBER(SEARCH(SUBSTITUTE('Référentiel films'!$A$14,"’","'"),SUBSTITUTE(G3,"’","'"))),'Référentiel films'!$B$14,""),IF(ISNUMBER(SEARCH(SUBSTITUTE('Référentiel films'!$A$15,"’","'"),SUBSTITUTE(G3,"’","'"))),'Référentiel films'!$B$15,""),IF(ISNUMBER(SEARCH(SUBSTITUTE('Référentiel films'!$A$16,"’","'"),SUBSTITUTE(G3,"’","'"))),'Référentiel films'!$B$16,""),IF(ISNUMBER(SEARCH(SUBSTITUTE('Référentiel films'!$A$17,"’","'"),SUBSTITUTE(G3,"’","'"))),'Référentiel films'!$B$17,""),IF(ISNUMBER(SEARCH(SUBSTITUTE('Référentiel films'!$A$18,"’","'"),SUBSTITUTE(G3,"’","'"))),'Référentiel films'!$B$18,""),IF(ISNUMBER(SEARCH(SUBSTITUTE('Référentiel films'!$A$19,"’","'"),SUBSTITUTE(G3,"’","'"))),'Référentiel films'!$B$19,""),IF(ISNUMBER(SEARCH(SUBSTITUTE('Référentiel films'!$A$20,"’","'"),SUBSTITUTE(G3,"’","'"))),'Référentiel films'!$B$20,""),IF(ISNUMBER(SEARCH(SUBSTITUTE('Référentiel films'!$A$21,"’","'"),SUBSTITUTE(G3,"’","'"))),'Référentiel films'!$B$21,""),IF(ISNUMBER(SEARCH(SUBSTITUTE('Référentiel films'!$A$22,"’","'"),SUBSTITUTE(G3,"’","'"))),'Référentiel films'!$B$22,""),IF(ISNUMBER(SEARCH(SUBSTITUTE('Référentiel films'!$A$23,"’","'"),SUBSTITUTE(G3,"’","'"))),'Référentiel films'!$B$23,""),IF(ISNUMBER(SEARCH(SUBSTITUTE('Référentiel films'!$A$24,"’","'"),SUBSTITUTE(G3,"’","'"))),'Référentiel films'!$B$24,""),IF(ISNUMBER(SEARCH(SUBSTITUTE('Référentiel films'!$A$25,"’","'"),SUBSTITUTE(G3,"’","'"))),'Référentiel films'!$B$25,""),IF(ISNUMBER(SEARCH(SUBSTITUTE('Référentiel films'!$A$26,"’","'"),SUBSTITUTE(G3,"’","'"))),'Référentiel films'!$B$26,""),IF(ISNUMBER(SEARCH(SUBSTITUTE('Référentiel films'!$A$27,"’","'"),SUBSTITUTE(G3,"’","'"))),'Référentiel films'!$B$27,""),IF(ISNUMBER(SEARCH(SUBSTITUTE('Référentiel films'!$A$28,"’","'"),SUBSTITUTE(G3,"’","'"))),'Référentiel films'!$B$28,""),IF(ISNUMBER(SEARCH(SUBSTITUTE('Référentiel films'!$A$29,"’","'"),SUBSTITUTE(G3,"’","'"))),'Référentiel films'!$B$29,""),IF(ISNUMBER(SEARCH(SUBSTITUTE('Référentiel films'!$A$30,"’","'"),SUBSTITUTE(G3,"’","'"))),'Référentiel films'!$B$30,""),IF(ISNUMBER(SEARCH(SUBSTITUTE('Référentiel films'!$A$31,"’","'"),SUBSTITUTE(G3,"’","'"))),'Référentiel films'!$B$31,""),IF(ISNUMBER(SEARCH(SUBSTITUTE('Référentiel films'!$A$32,"’","'"),SUBSTITUTE(G3,"’","'"))),'Référentiel films'!$B$32,""),IF(ISNUMBER(SEARCH(SUBSTITUTE('Référentiel films'!$A$33,"’","'"),SUBSTITUTE(G3,"’","'"))),'Référentiel films'!$B$33,""),IF(ISNUMBER(SEARCH(SUBSTITUTE('Référentiel films'!$A$34,"’","'"),SUBSTITUTE(G3,"’","'"))),'Référentiel films'!$B$34,""),IF(ISNUMBER(SEARCH(SUBSTITUTE('Référentiel films'!$A$35,"’","'"),SUBSTITUTE(G3,"’","'"))),'Référentiel films'!$B$35,""),IF(ISNUMBER(SEARCH(SUBSTITUTE('Référentiel films'!$A$36,"’","'"),SUBSTITUTE(G3,"’","'"))),'Référentiel films'!$B$36,""),IF(ISNUMBER(SEARCH(SUBSTITUTE('Référentiel films'!$A$37,"’","'"),SUBSTITUTE(G3,"’","'"))),'Référentiel films'!$B$37,""),IF(ISNUMBER(SEARCH(SUBSTITUTE('Référentiel films'!$A$38,"’","'"),SUBSTITUTE(G3,"’","'"))),'Référentiel films'!$B$38,""),IF(ISNUMBER(SEARCH(SUBSTITUTE('Référentiel films'!$A$39,"’","'"),SUBSTITUTE(G3,"’","'"))),'Référentiel films'!$B$39,""),IF(ISNUMBER(SEARCH(SUBSTITUTE('Référentiel films'!$A$40,"’","'"),SUBSTITUTE(G3,"’","'"))),'Référentiel films'!$B$40,""),IF(ISNUMBER(SEARCH(SUBSTITUTE('Référentiel films'!$A$41,"’","'"),SUBSTITUTE(G3,"’","'"))),'Référentiel films'!$B$41,""))) | I3: Jochen et ses collègues, dans Huit heures ne font pas un jour, incarnent les ouvriers hautement qualifiés qui font la réussite économique de la RFA. L'œuvre de Fassbinder analyse rétrospectivement cette période en mettant à distance le consensus social de la prospérité des années 50 et 60 et en révélant les mensonges du miracle économique. Mais il met aussi en exergue l'optimisme et la vitalité anarchique de cette période où tout est possible (la garderie dans Huit heures ne font pas un jour, l'ascension de Maria Braun) | J3: De l’année zéro au miracle économique|https://youtu.be/BC4BffkWyY8?si=e80MWCLF0K9Fgiub; Jalousie de Catharina Valente|https://youtu.be/-ugDTj7UFtU?si=vzGNySrsaYGKZW0k | L3: l-industrie-de-l-industrie-automobile-l-usine-volkswagen-vue-de-l-interieur-usine-wolfsburg-vers-1950.jpg
A4: 1961-1966 | B4: naissance du Nouveau cinéma allemand | C4: Que serait un cinéma nouveau prenant à bras le corps l'histoire de l'Allemagne et du cinéma, tout en s'en détachant ? | D4: Construction du Mur de Berlin (1961). Procès d'Auschwitz à Francfort (1963-1965). Démission d'Adenauer. Grande Coalition (1966). | E4: Manifeste d'Oberhausen (1962) : naissance du Nouveau Cinéma Allemand. Une nouvelle génération de cinéastes s'affirme et conquiert son indépendance notamment par la création de structures de production indépendantes. Fondation de l'école de cinéma DFFB à Berlin (1966). Cette génération incarne le phénomène de la "société sans père" et "la crise du patriarcat". L'absence ou la défaillance des pères devient un thème récurrent du Nouveau Cinéma allemand. | F4: Échec au concours d'entrée de la DFFB. Rencontre Hanna Schygulla et Irm Hermann dans un cours d'art dramatique. Rejoint l'Action-Theater (1967). | G4: Réalise ses premiers courts métrages : This Night (1966) et Le Clochard (1966). Confrontation de la mémoire de la Shoah. | H4: =IF(G4="","",_xlfn.TEXTJOIN("; ",TRUE(),IF(ISNUMBER(SEARCH(SUBSTITUTE('Référentiel films'!$A$2,"’","'"),SUBSTITUTE(G4,"’","'"))),'Référentiel films'!$B$2,""),IF(ISNUMBER(SEARCH(SUBSTITUTE('Référentiel films'!$A$3,"’","'"),SUBSTITUTE(G4,"’","'"))),'Référentiel films'!$B$3,""),IF(ISNUMBER(SEARCH(SUBSTITUTE('Référentiel films'!$A$4,"’","'"),SUBSTITUTE(G4,"’","'"))),'Référentiel films'!$B$4,""),IF(ISNUMBER(SEARCH(SUBSTITUTE('Référentiel films'!$A$5,"’","'"),SUBSTITUTE(G4,"’","'"))),'Référentiel films'!$B$5,""),IF(ISNUMBER(SEARCH(SUBSTITUTE('Référentiel films'!$A$6,"’","'"),SUBSTITUTE(G4,"’","'"))),'Référentiel films'!$B$6,""),IF(ISNUMBER(SEARCH(SUBSTITUTE('Référentiel films'!$A$7,"’","'"),SUBSTITUTE(G4,"’","'"))),'Référentiel films'!$B$7,""),IF(ISNUMBER(SEARCH(SUBSTITUTE('Référentiel films'!$A$8,"’","'"),SUBSTITUTE(G4,"’","'"))),'Référentiel films'!$B$8,""),IF(ISNUMBER(SEARCH(SUBSTITUTE('Référentiel films'!$A$9,"’","'"),SUBSTITUTE(G4,"’","'"))),'Référentiel films'!$B$9,""),IF(ISNUMBER(SEARCH(SUBSTITUTE('Référentiel films'!$A$10,"’","'"),SUBSTITUTE(G4,"’","'"))),'Référentiel films'!$B$10,""),IF(ISNUMBER(SEARCH(SUBSTITUTE('Référentiel films'!$A$11,"’","'"),SUBSTITUTE(G4,"’","'"))),'Référentiel films'!$B$11,""),IF(ISNUMBER(SEARCH(SUBSTITUTE('Référentiel films'!$A$12,"’","'"),SUBSTITUTE(G4,"’","'"))),'Référentiel films'!$B$12,""),IF(ISNUMBER(SEARCH(SUBSTITUTE('Référentiel films'!$A$13,"’","'"),SUBSTITUTE(G4,"’","'"))),'Référentiel films'!$B$13,""),IF(ISNUMBER(SEARCH(SUBSTITUTE('Référentiel films'!$A$14,"’","'"),SUBSTITUTE(G4,"’","'"))),'Référentiel films'!$B$14,""),IF(ISNUMBER(SEARCH(SUBSTITUTE('Référentiel films'!$A$15,"’","'"),SUBSTITUTE(G4,"’","'"))),'Référentiel films'!$B$15,""),IF(ISNUMBER(SEARCH(SUBSTITUTE('Référentiel films'!$A$16,"’","'"),SUBSTITUTE(G4,"’","'"))),'Référentiel films'!$B$16,""),IF(ISNUMBER(SEARCH(SUBSTITUTE('Référentiel films'!$A$17,"’","'"),SUBSTITUTE(G4,"’","'"))),'Référentiel films'!$B$17,""),IF(ISNUMBER(SEARCH(SUBSTITUTE('Référentiel films'!$A$18,"’","'"),SUBSTITUTE(G4,"’","'"))),'Référentiel films'!$B$18,""),IF(ISNUMBER(SEARCH(SUBSTITUTE('Référentiel films'!$A$19,"’","'"),SUBSTITUTE(G4,"’","'"))),'Référentiel films'!$B$19,""),IF(ISNUMBER(SEARCH(SUBSTITUTE('Référentiel films'!$A$20,"’","'"),SUBSTITUTE(G4,"’","'"))),'Référentiel films'!$B$20,""),IF(ISNUMBER(SEARCH(SUBSTITUTE('Référentiel films'!$A$21,"’","'"),SUBSTITUTE(G4,"’","'"))),'Référentiel films'!$B$21,""),IF(ISNUMBER(SEARCH(SUBSTITUTE('Référentiel films'!$A$22,"’","'"),SUBSTITUTE(G4,"’","'"))),'Référentiel films'!$B$22,""),IF(ISNUMBER(SEARCH(SUBSTITUTE('Référentiel films'!$A$23,"’","'"),SUBSTITUTE(G4,"’","'"))),'Référentiel films'!$B$23,""),IF(ISNUMBER(SEARCH(SUBSTITUTE('Référentiel films'!$A$24,"’","'"),SUBSTITUTE(G4,"’","'"))),'Référentiel films'!$B$24,""),IF(ISNUMBER(SEARCH(SUBSTITUTE('Référentiel films'!$A$25,"’","'"),SUBSTITUTE(G4,"’","'"))),'Référentiel films'!$B$25,""),IF(ISNUMBER(SEARCH(SUBSTITUTE('Référentiel films'!$A$26,"’","'"),SUBSTITUTE(G4,"’","'"))),'Référentiel films'!$B$26,""),IF(ISNUMBER(SEARCH(SUBSTITUTE('Référentiel films'!$A$27,"’","'"),SUBSTITUTE(G4,"’","'"))),'Référentiel films'!$B$27,""),IF(ISNUMBER(SEARCH(SUBSTITUTE('Référentiel films'!$A$28,"’","'"),SUBSTITUTE(G4,"’","'"))),'Référentiel films'!$B$28,""),IF(ISNUMBER(SEARCH(SUBSTITUTE('Référentiel films'!$A$29,"’","'"),SUBSTITUTE(G4,"’","'"))),'Référentiel films'!$B$29,""),IF(ISNUMBER(SEARCH(SUBSTITUTE('Référentiel films'!$A$30,"’","'"),SUBSTITUTE(G4,"’","'"))),'Référentiel films'!$B$30,""),IF(ISNUMBER(SEARCH(SUBSTITUTE('Référentiel films'!$A$31,"’","'"),SUBSTITUTE(G4,"’","'"))),'Référentiel films'!$B$31,""),IF(ISNUMBER(SEARCH(SUBSTITUTE('Référentiel films'!$A$32,"’","'"),SUBSTITUTE(G4,"’","'"))),'Référentiel films'!$B$32,""),IF(ISNUMBER(SEARCH(SUBSTITUTE('Référentiel films'!$A$33,"’","'"),SUBSTITUTE(G4,"’","'"))),'Référentiel films'!$B$33,""),IF(ISNUMBER(SEARCH(SUBSTITUTE('Référentiel films'!$A$34,"’","'"),SUBSTITUTE(G4,"’","'"))),'Référentiel films'!$B$34,""),IF(ISNUMBER(SEARCH(SUBSTITUTE('Référentiel films'!$A$35,"’","'"),SUBSTITUTE(G4,"’","'"))),'Référentiel films'!$B$35,""),IF(ISNUMBER(SEARCH(SUBSTITUTE('Référentiel films'!$A$36,"’","'"),SUBSTITUTE(G4,"’","'"))),'Référentiel films'!$B$36,""),IF(ISNUMBER(SEARCH(SUBSTITUTE('Référentiel films'!$A$37,"’","'"),SUBSTITUTE(G4,"’","'"))),'Référentiel films'!$B$37,""),IF(ISNUMBER(SEARCH(SUBSTITUTE('Référentiel films'!$A$38,"’","'"),SUBSTITUTE(G4,"’","'"))),'Référentiel films'!$B$38,""),IF(ISNUMBER(SEARCH(SUBSTITUTE('Référentiel films'!$A$39,"’","'"),SUBSTITUTE(G4,"’","'"))),'Référentiel films'!$B$39,""),IF(ISNUMBER(SEARCH(SUBSTITUTE('Référentiel films'!$A$40,"’","'"),SUBSTITUTE(G4,"’","'"))),'Référentiel films'!$B$40,""),IF(ISNUMBER(SEARCH(SUBSTITUTE('Référentiel films'!$A$41,"’","'"),SUBSTITUTE(G4,"’","'"))),'Référentiel films'!$B$41,""))) | J4: Documentaire sur le nouveau cinéma allemand | K4: "Le cinéma de Papa est mort. Nous croyons au nouveau cinéma " Manifeste d'Oberhausen (1962) « Toute une génération exorcisa son enfance déjà presque oubliée en soulignant sans répit combien étaient encombrantes et dévastatrices les ombres que le passé des parents avaient jetées sur le présent de leurs enfants ».Thomas Elsaesser, RWF un cinéaste d'Allemagne (2005) p.201
A5: 1967-1970 | B5: Antitheater et politisation | C5: Qu'-est-ce qu'un cinéaste engagé ? | D5: Mouvements étudiants de 1968. Tentative d'assassinat contre Rudi Dutschke. Victoire de Willy Brandt (SPD, 1969). Abrogation partielle de l'article 175 (homosexualité). | F5: Fonde l' antiteater (1968). Collaboration intense avec sa "troupe" (Schygulla, Hermann, Raab, Baer, Lommel). Mariage avec Ingrid Caven (1970). | G5: L'amour est plus froid que la mort (1969), Le Bouc (1969) | H5: =IF(G5="","",_xlfn.TEXTJOIN("; ",TRUE(),IF(ISNUMBER(SEARCH(SUBSTITUTE('Référentiel films'!$A$2,"’","'"),SUBSTITUTE(G5,"’","'"))),'Référentiel films'!$B$2,""),IF(ISNUMBER(SEARCH(SUBSTITUTE('Référentiel films'!$A$3,"’","'"),SUBSTITUTE(G5,"’","'"))),'Référentiel films'!$B$3,""),IF(ISNUMBER(SEARCH(SUBSTITUTE('Référentiel films'!$A$4,"’","'"),SUBSTITUTE(G5,"’","'"))),'Référentiel films'!$B$4,""),IF(ISNUMBER(SEARCH(SUBSTITUTE('Référentiel films'!$A$5,"’","'"),SUBSTITUTE(G5,"’","'"))),'Référentiel films'!$B$5,""),IF(ISNUMBER(SEARCH(SUBSTITUTE('Référentiel films'!$A$6,"’","'"),SUBSTITUTE(G5,"’","'"))),'Référentiel films'!$B$6,""),IF(ISNUMBER(SEARCH(SUBSTITUTE('Référentiel films'!$A$7,"’","'"),SUBSTITUTE(G5,"’","'"))),'Référentiel films'!$B$7,""),IF(ISNUMBER(SEARCH(SUBSTITUTE('Référentiel films'!$A$8,"’","'"),SUBSTITUTE(G5,"’","'"))),'Référentiel films'!$B$8,""),IF(ISNUMBER(SEARCH(SUBSTITUTE('Référentiel films'!$A$9,"’","'"),SUBSTITUTE(G5,"’","'"))),'Référentiel films'!$B$9,""),IF(ISNUMBER(SEARCH(SUBSTITUTE('Référentiel films'!$A$10,"’","'"),SUBSTITUTE(G5,"’","'"))),'Référentiel films'!$B$10,""),IF(ISNUMBER(SEARCH(SUBSTITUTE('Référentiel films'!$A$11,"’","'"),SUBSTITUTE(G5,"’","'"))),'Référentiel films'!$B$11,""),IF(ISNUMBER(SEARCH(SUBSTITUTE('Référentiel films'!$A$12,"’","'"),SUBSTITUTE(G5,"’","'"))),'Référentiel films'!$B$12,""),IF(ISNUMBER(SEARCH(SUBSTITUTE('Référentiel films'!$A$13,"’","'"),SUBSTITUTE(G5,"’","'"))),'Référentiel films'!$B$13,""),IF(ISNUMBER(SEARCH(SUBSTITUTE('Référentiel films'!$A$14,"’","'"),SUBSTITUTE(G5,"’","'"))),'Référentiel films'!$B$14,""),IF(ISNUMBER(SEARCH(SUBSTITUTE('Référentiel films'!$A$15,"’","'"),SUBSTITUTE(G5,"’","'"))),'Référentiel films'!$B$15,""),IF(ISNUMBER(SEARCH(SUBSTITUTE('Référentiel films'!$A$16,"’","'"),SUBSTITUTE(G5,"’","'"))),'Référentiel films'!$B$16,""),IF(ISNUMBER(SEARCH(SUBSTITUTE('Référentiel films'!$A$17,"’","'"),SUBSTITUTE(G5,"’","'"))),'Référentiel films'!$B$17,""),IF(ISNUMBER(SEARCH(SUBSTITUTE('Référentiel films'!$A$18,"’","'"),SUBSTITUTE(G5,"’","'"))),'Référentiel films'!$B$18,""),IF(ISNUMBER(SEARCH(SUBSTITUTE('Référentiel films'!$A$19,"’","'"),SUBSTITUTE(G5,"’","'"))),'Référentiel films'!$B$19,""),IF(ISNUMBER(SEARCH(SUBSTITUTE('Référentiel films'!$A$20,"’","'"),SUBSTITUTE(G5,"’","'"))),'Référentiel films'!$B$20,""),IF(ISNUMBER(SEARCH(SUBSTITUTE('Référentiel films'!$A$21,"’","'"),SUBSTITUTE(G5,"’","'"))),'Référentiel films'!$B$21,""),IF(ISNUMBER(SEARCH(SUBSTITUTE('Référentiel films'!$A$22,"’","'"),SUBSTITUTE(G5,"’","'"))),'Référentiel films'!$B$22,""),IF(ISNUMBER(SEARCH(SUBSTITUTE('Référentiel films'!$A$23,"’","'"),SUBSTITUTE(G5,"’","'"))),'Référentiel films'!$B$23,""),IF(ISNUMBER(SEARCH(SUBSTITUTE('Référentiel films'!$A$24,"’","'"),SUBSTITUTE(G5,"’","'"))),'Référentiel films'!$B$24,""),IF(ISNUMBER(SEARCH(SUBSTITUTE('Référentiel films'!$A$25,"’","'"),SUBSTITUTE(G5,"’","'"))),'Référentiel films'!$B$25,""),IF(ISNUMBER(SEARCH(SUBSTITUTE('Référentiel films'!$A$26,"’","'"),SUBSTITUTE(G5,"’","'"))),'Référentiel films'!$B$26,""),IF(ISNUMBER(SEARCH(SUBSTITUTE('Référentiel films'!$A$27,"’","'"),SUBSTITUTE(G5,"’","'"))),'Référentiel films'!$B$27,""),IF(ISNUMBER(SEARCH(SUBSTITUTE('Référentiel films'!$A$28,"’","'"),SUBSTITUTE(G5,"’","'"))),'Référentiel films'!$B$28,""),IF(ISNUMBER(SEARCH(SUBSTITUTE('Référentiel films'!$A$29,"’","'"),SUBSTITUTE(G5,"’","'"))),'Référentiel films'!$B$29,""),IF(ISNUMBER(SEARCH(SUBSTITUTE('Référentiel films'!$A$30,"’","'"),SUBSTITUTE(G5,"’","'"))),'Référentiel films'!$B$30,""),IF(ISNUMBER(SEARCH(SUBSTITUTE('Référentiel films'!$A$31,"’","'"),SUBSTITUTE(G5,"’","'"))),'Référentiel films'!$B$31,""),IF(ISNUMBER(SEARCH(SUBSTITUTE('Référentiel films'!$A$32,"’","'"),SUBSTITUTE(G5,"’","'"))),'Référentiel films'!$B$32,""),IF(ISNUMBER(SEARCH(SUBSTITUTE('Référentiel films'!$A$33,"’","'"),SUBSTITUTE(G5,"’","'"))),'Référentiel films'!$B$33,""),IF(ISNUMBER(SEARCH(SUBSTITUTE('Référentiel films'!$A$34,"’","'"),SUBSTITUTE(G5,"’","'"))),'Référentiel films'!$B$34,""),IF(ISNUMBER(SEARCH(SUBSTITUTE('Référentiel films'!$A$35,"’","'"),SUBSTITUTE(G5,"’","'"))),'Référentiel films'!$B$35,""),IF(ISNUMBER(SEARCH(SUBSTITUTE('Référentiel films'!$A$36,"’","'"),SUBSTITUTE(G5,"’","'"))),'Référentiel films'!$B$36,""),IF(ISNUMBER(SEARCH(SUBSTITUTE('Référentiel films'!$A$37,"’","'"),SUBSTITUTE(G5,"’","'"))),'Référentiel films'!$B$37,""),IF(ISNUMBER(SEARCH(SUBSTITUTE('Référentiel films'!$A$38,"’","'"),SUBSTITUTE(G5,"’","'"))),'Référentiel films'!$B$38,""),IF(ISNUMBER(SEARCH(SUBSTITUTE('Référentiel films'!$A$39,"’","'"),SUBSTITUTE(G5,"’","'"))),'Référentiel films'!$B$39,""),IF(ISNUMBER(SEARCH(SUBSTITUTE('Référentiel films'!$A$40,"’","'"),SUBSTITUTE(G5,"’","'"))),'Référentiel films'!$B$40,""),IF(ISNUMBER(SEARCH(SUBSTITUTE('Référentiel films'!$A$41,"’","'"),SUBSTITUTE(G5,"’","'"))),'Référentiel films'!$B$41,""))) -> film-1969-l-amour-est-plus-froid-que-la-mort; film-1969-le-bouc | I5: Le bouc est un tournant tant en termes de reconnaissance que du point de vue économique. Le film aborde des problématiques contemporaines (sort des travailleurs immigrés) et des thématiques chères à RWF (l'univers étriqué de la bourgeoisie, en particulière bavaroise).
A6: 1971-1974 | B6: Terrorisme et mélodrame | C6: Comment faire du cinéma allemand hollywoodien, qui attire et séduise le public le plus large tout en l'amenant à l'analyse et à la réflexion, sans didactisme ? | D6: Terrorisme de la RAF (arrestations en 1972). Attentat des JO de Munich (1972). Démission de Willy Brandt (1974) suite à l'affaire Guillaume. | E6: Fondation du Filmverlag der Autoren (1971). Accords Film-Télévision (1974) favorisant les coproductions (WDR). Plusieurs cinéastes allemands ( Schlöndorff, Herzog notamment) réalisent des charges politiques violentes contre la politique et la société allemande. Pourtant l'amnnésie historique se poursuit dans le cinéma allemand de fiction. Seuls des documentaires s'emparent de l'histoire du nazisme. A parti de 1968 l'industrie du cinéma commercial allemand agonise | F6: Découverte des mélodrames de Douglas Sirk grâce à Peer Raben .Liaison avec El Hedi ben Salem. Direction du TAT à Francfort. Collaboration avec le caméraman Michael Ballhaus. Succès international. Les films de RWF deviennent incontournables dans les grands festivals internationaux (Cannes, Venise, Berlin). | G6: Période Sirkienne : Le Marchand des quatre saisons (1971). Tous les autres s'appellent Ali (1974, succès mondial à Cannes) : critique du racisme ordinaire. Martha (1974). | H6: =IF(G6="","",_xlfn.TEXTJOIN("; ",TRUE(),IF(ISNUMBER(SEARCH(SUBSTITUTE('Référentiel films'!$A$2,"’","'"),SUBSTITUTE(G6,"’","'"))),'Référentiel films'!$B$2,""),IF(ISNUMBER(SEARCH(SUBSTITUTE('Référentiel films'!$A$3,"’","'"),SUBSTITUTE(G6,"’","'"))),'Référentiel films'!$B$3,""),IF(ISNUMBER(SEARCH(SUBSTITUTE('Référentiel films'!$A$4,"’","'"),SUBSTITUTE(G6,"’","'"))),'Référentiel films'!$B$4,""),IF(ISNUMBER(SEARCH(SUBSTITUTE('Référentiel films'!$A$5,"’","'"),SUBSTITUTE(G6,"’","'"))),'Référentiel films'!$B$5,""),IF(ISNUMBER(SEARCH(SUBSTITUTE('Référentiel films'!$A$6,"’","'"),SUBSTITUTE(G6,"’","'"))),'Référentiel films'!$B$6,""),IF(ISNUMBER(SEARCH(SUBSTITUTE('Référentiel films'!$A$7,"’","'"),SUBSTITUTE(G6,"’","'"))),'Référentiel films'!$B$7,""),IF(ISNUMBER(SEARCH(SUBSTITUTE('Référentiel films'!$A$8,"’","'"),SUBSTITUTE(G6,"’","'"))),'Référentiel films'!$B$8,""),IF(ISNUMBER(SEARCH(SUBSTITUTE('Référentiel films'!$A$9,"’","'"),SUBSTITUTE(G6,"’","'"))),'Référentiel films'!$B$9,""),IF(ISNUMBER(SEARCH(SUBSTITUTE('Référentiel films'!$A$10,"’","'"),SUBSTITUTE(G6,"’","'"))),'Référentiel films'!$B$10,""),IF(ISNUMBER(SEARCH(SUBSTITUTE('Référentiel films'!$A$11,"’","'"),SUBSTITUTE(G6,"’","'"))),'Référentiel films'!$B$11,""),IF(ISNUMBER(SEARCH(SUBSTITUTE('Référentiel films'!$A$12,"’","'"),SUBSTITUTE(G6,"’","'"))),'Référentiel films'!$B$12,""),IF(ISNUMBER(SEARCH(SUBSTITUTE('Référentiel films'!$A$13,"’","'"),SUBSTITUTE(G6,"’","'"))),'Référentiel films'!$B$13,""),IF(ISNUMBER(SEARCH(SUBSTITUTE('Référentiel films'!$A$14,"’","'"),SUBSTITUTE(G6,"’","'"))),'Référentiel films'!$B$14,""),IF(ISNUMBER(SEARCH(SUBSTITUTE('Référentiel films'!$A$15,"’","'"),SUBSTITUTE(G6,"’","'"))),'Référentiel films'!$B$15,""),IF(ISNUMBER(SEARCH(SUBSTITUTE('Référentiel films'!$A$16,"’","'"),SUBSTITUTE(G6,"’","'"))),'Référentiel films'!$B$16,""),IF(ISNUMBER(SEARCH(SUBSTITUTE('Référentiel films'!$A$17,"’","'"),SUBSTITUTE(G6,"’","'"))),'Référentiel films'!$B$17,""),IF(ISNUMBER(SEARCH(SUBSTITUTE('Référentiel films'!$A$18,"’","'"),SUBSTITUTE(G6,"’","'"))),'Référentiel films'!$B$18,""),IF(ISNUMBER(SEARCH(SUBSTITUTE('Référentiel films'!$A$19,"’","'"),SUBSTITUTE(G6,"’","'"))),'Référentiel films'!$B$19,""),IF(ISNUMBER(SEARCH(SUBSTITUTE('Référentiel films'!$A$20,"’","'"),SUBSTITUTE(G6,"’","'"))),'Référentiel films'!$B$20,""),IF(ISNUMBER(SEARCH(SUBSTITUTE('Référentiel films'!$A$21,"’","'"),SUBSTITUTE(G6,"’","'"))),'Référentiel films'!$B$21,""),IF(ISNUMBER(SEARCH(SUBSTITUTE('Référentiel films'!$A$22,"’","'"),SUBSTITUTE(G6,"’","'"))),'Référentiel films'!$B$22,""),IF(ISNUMBER(SEARCH(SUBSTITUTE('Référentiel films'!$A$23,"’","'"),SUBSTITUTE(G6,"’","'"))),'Référentiel films'!$B$23,""),IF(ISNUMBER(SEARCH(SUBSTITUTE('Référentiel films'!$A$24,"’","'"),SUBSTITUTE(G6,"’","'"))),'Référentiel films'!$B$24,""),IF(ISNUMBER(SEARCH(SUBSTITUTE('Référentiel films'!$A$25,"’","'"),SUBSTITUTE(G6,"’","'"))),'Référentiel films'!$B$25,""),IF(ISNUMBER(SEARCH(SUBSTITUTE('Référentiel films'!$A$26,"’","'"),SUBSTITUTE(G6,"’","'"))),'Référentiel films'!$B$26,""),IF(ISNUMBER(SEARCH(SUBSTITUTE('Référentiel films'!$A$27,"’","'"),SUBSTITUTE(G6,"’","'"))),'Référentiel films'!$B$27,""),IF(ISNUMBER(SEARCH(SUBSTITUTE('Référentiel films'!$A$28,"’","'"),SUBSTITUTE(G6,"’","'"))),'Référentiel films'!$B$28,""),IF(ISNUMBER(SEARCH(SUBSTITUTE('Référentiel films'!$A$29,"’","'"),SUBSTITUTE(G6,"’","'"))),'Référentiel films'!$B$29,""),IF(ISNUMBER(SEARCH(SUBSTITUTE('Référentiel films'!$A$30,"’","'"),SUBSTITUTE(G6,"’","'"))),'Référentiel films'!$B$30,""),IF(ISNUMBER(SEARCH(SUBSTITUTE('Référentiel films'!$A$31,"’","'"),SUBSTITUTE(G6,"’","'"))),'Référentiel films'!$B$31,""),IF(ISNUMBER(SEARCH(SUBSTITUTE('Référentiel films'!$A$32,"’","'"),SUBSTITUTE(G6,"’","'"))),'Référentiel films'!$B$32,""),IF(ISNUMBER(SEARCH(SUBSTITUTE('Référentiel films'!$A$33,"’","'"),SUBSTITUTE(G6,"’","'"))),'Référentiel films'!$B$33,""),IF(ISNUMBER(SEARCH(SUBSTITUTE('Référentiel films'!$A$34,"’","'"),SUBSTITUTE(G6,"’","'"))),'Référentiel films'!$B$34,""),IF(ISNUMBER(SEARCH(SUBSTITUTE('Référentiel films'!$A$35,"’","'"),SUBSTITUTE(G6,"’","'"))),'Référentiel films'!$B$35,""),IF(ISNUMBER(SEARCH(SUBSTITUTE('Référentiel films'!$A$36,"’","'"),SUBSTITUTE(G6,"’","'"))),'Référentiel films'!$B$36,""),IF(ISNUMBER(SEARCH(SUBSTITUTE('Référentiel films'!$A$37,"’","'"),SUBSTITUTE(G6,"’","'"))),'Référentiel films'!$B$37,""),IF(ISNUMBER(SEARCH(SUBSTITUTE('Référentiel films'!$A$38,"’","'"),SUBSTITUTE(G6,"’","'"))),'Référentiel films'!$B$38,""),IF(ISNUMBER(SEARCH(SUBSTITUTE('Référentiel films'!$A$39,"’","'"),SUBSTITUTE(G6,"’","'"))),'Référentiel films'!$B$39,""),IF(ISNUMBER(SEARCH(SUBSTITUTE('Référentiel films'!$A$40,"’","'"),SUBSTITUTE(G6,"’","'"))),'Référentiel films'!$B$40,""),IF(ISNUMBER(SEARCH(SUBSTITUTE('Référentiel films'!$A$41,"’","'"),SUBSTITUTE(G6,"’","'"))),'Référentiel films'!$B$41,""))) -> film-1972-le-marchand-des-quatre-saisons; film-1974-tous-les-autres-s-appellent-ali; film-1974-martha | I6: Dans les mélodrames de RWF , les personnages tentent en vain de s'affranchir des positions aliénantes produites par la famille, le couple, au sein du système capitaliste et de la classe bourgeoise. Une analogie s'établit alors entre famille et Allemagne. Le mélodrame fassbindérien met en scène des crises identitaires du sujet, comme crises de la perception (du regard), qui se traduisent par une mise en crise de l'image (image de soi et image du film). Les films font dialoguer subjectivité et affects avec mécanismes sociaux, évitant ainsi toute lecture simpliste et figées de type psychologique ou idéologique. Le mélodrame, en interpénétrant le privé et le public, l'individuel et le collectif, joue d'un trouble qui participe à son caractère critique et progressiste : il est potentiellement facteur de changement pour un spectateur constamment soumis à la réflexion.
A7: 1975-1976 | C7: Comment le rapport dominant/dominé structure-t-il toute relation, affective ou sociale ? | D7: Tensions sociales et crises du logement (Westend). Débats sur la visibilité des minorités. Lois limitant les libertés civiles. | E7: Développement du "film amphibie" (cinéma/TV). Le cinéma devient un outil de critique sociale directe. | F7: Scandale théâtral autour de la pièce L'Ordure, la ville et la mort (accusations d'antisémitisme). Liaison avec Armin Meier. | G7: Maman Küsters s'en va au ciel (1975). Le Droit du plus fort (1975) : | H7: =IF(G7="","",_xlfn.TEXTJOIN("; ",TRUE(),IF(ISNUMBER(SEARCH(SUBSTITUTE('Référentiel films'!$A$2,"’","'"),SUBSTITUTE(G7,"’","'"))),'Référentiel films'!$B$2,""),IF(ISNUMBER(SEARCH(SUBSTITUTE('Référentiel films'!$A$3,"’","'"),SUBSTITUTE(G7,"’","'"))),'Référentiel films'!$B$3,""),IF(ISNUMBER(SEARCH(SUBSTITUTE('Référentiel films'!$A$4,"’","'"),SUBSTITUTE(G7,"’","'"))),'Référentiel films'!$B$4,""),IF(ISNUMBER(SEARCH(SUBSTITUTE('Référentiel films'!$A$5,"’","'"),SUBSTITUTE(G7,"’","'"))),'Référentiel films'!$B$5,""),IF(ISNUMBER(SEARCH(SUBSTITUTE('Référentiel films'!$A$6,"’","'"),SUBSTITUTE(G7,"’","'"))),'Référentiel films'!$B$6,""),IF(ISNUMBER(SEARCH(SUBSTITUTE('Référentiel films'!$A$7,"’","'"),SUBSTITUTE(G7,"’","'"))),'Référentiel films'!$B$7,""),IF(ISNUMBER(SEARCH(SUBSTITUTE('Référentiel films'!$A$8,"’","'"),SUBSTITUTE(G7,"’","'"))),'Référentiel films'!$B$8,""),IF(ISNUMBER(SEARCH(SUBSTITUTE('Référentiel films'!$A$9,"’","'"),SUBSTITUTE(G7,"’","'"))),'Référentiel films'!$B$9,""),IF(ISNUMBER(SEARCH(SUBSTITUTE('Référentiel films'!$A$10,"’","'"),SUBSTITUTE(G7,"’","'"))),'Référentiel films'!$B$10,""),IF(ISNUMBER(SEARCH(SUBSTITUTE('Référentiel films'!$A$11,"’","'"),SUBSTITUTE(G7,"’","'"))),'Référentiel films'!$B$11,""),IF(ISNUMBER(SEARCH(SUBSTITUTE('Référentiel films'!$A$12,"’","'"),SUBSTITUTE(G7,"’","'"))),'Référentiel films'!$B$12,""),IF(ISNUMBER(SEARCH(SUBSTITUTE('Référentiel films'!$A$13,"’","'"),SUBSTITUTE(G7,"’","'"))),'Référentiel films'!$B$13,""),IF(ISNUMBER(SEARCH(SUBSTITUTE('Référentiel films'!$A$14,"’","'"),SUBSTITUTE(G7,"’","'"))),'Référentiel films'!$B$14,""),IF(ISNUMBER(SEARCH(SUBSTITUTE('Référentiel films'!$A$15,"’","'"),SUBSTITUTE(G7,"’","'"))),'Référentiel films'!$B$15,""),IF(ISNUMBER(SEARCH(SUBSTITUTE('Référentiel films'!$A$16,"’","'"),SUBSTITUTE(G7,"’","'"))),'Référentiel films'!$B$16,""),IF(ISNUMBER(SEARCH(SUBSTITUTE('Référentiel films'!$A$17,"’","'"),SUBSTITUTE(G7,"’","'"))),'Référentiel films'!$B$17,""),IF(ISNUMBER(SEARCH(SUBSTITUTE('Référentiel films'!$A$18,"’","'"),SUBSTITUTE(G7,"’","'"))),'Référentiel films'!$B$18,""),IF(ISNUMBER(SEARCH(SUBSTITUTE('Référentiel films'!$A$19,"’","'"),SUBSTITUTE(G7,"’","'"))),'Référentiel films'!$B$19,""),IF(ISNUMBER(SEARCH(SUBSTITUTE('Référentiel films'!$A$20,"’","'"),SUBSTITUTE(G7,"’","'"))),'Référentiel films'!$B$20,""),IF(ISNUMBER(SEARCH(SUBSTITUTE('Référentiel films'!$A$21,"’","'"),SUBSTITUTE(G7,"’","'"))),'Référentiel films'!$B$21,""),IF(ISNUMBER(SEARCH(SUBSTITUTE('Référentiel films'!$A$22,"’","'"),SUBSTITUTE(G7,"’","'"))),'Référentiel films'!$B$22,""),IF(ISNUMBER(SEARCH(SUBSTITUTE('Référentiel films'!$A$23,"’","'"),SUBSTITUTE(G7,"’","'"))),'Référentiel films'!$B$23,""),IF(ISNUMBER(SEARCH(SUBSTITUTE('Référentiel films'!$A$24,"’","'"),SUBSTITUTE(G7,"’","'"))),'Référentiel films'!$B$24,""),IF(ISNUMBER(SEARCH(SUBSTITUTE('Référentiel films'!$A$25,"’","'"),SUBSTITUTE(G7,"’","'"))),'Référentiel films'!$B$25,""),IF(ISNUMBER(SEARCH(SUBSTITUTE('Référentiel films'!$A$26,"’","'"),SUBSTITUTE(G7,"’","'"))),'Référentiel films'!$B$26,""),IF(ISNUMBER(SEARCH(SUBSTITUTE('Référentiel films'!$A$27,"’","'"),SUBSTITUTE(G7,"’","'"))),'Référentiel films'!$B$27,""),IF(ISNUMBER(SEARCH(SUBSTITUTE('Référentiel films'!$A$28,"’","'"),SUBSTITUTE(G7,"’","'"))),'Référentiel films'!$B$28,""),IF(ISNUMBER(SEARCH(SUBSTITUTE('Référentiel films'!$A$29,"’","'"),SUBSTITUTE(G7,"’","'"))),'Référentiel films'!$B$29,""),IF(ISNUMBER(SEARCH(SUBSTITUTE('Référentiel films'!$A$30,"’","'"),SUBSTITUTE(G7,"’","'"))),'Référentiel films'!$B$30,""),IF(ISNUMBER(SEARCH(SUBSTITUTE('Référentiel films'!$A$31,"’","'"),SUBSTITUTE(G7,"’","'"))),'Référentiel films'!$B$31,""),IF(ISNUMBER(SEARCH(SUBSTITUTE('Référentiel films'!$A$32,"’","'"),SUBSTITUTE(G7,"’","'"))),'Référentiel films'!$B$32,""),IF(ISNUMBER(SEARCH(SUBSTITUTE('Référentiel films'!$A$33,"’","'"),SUBSTITUTE(G7,"’","'"))),'Référentiel films'!$B$33,""),IF(ISNUMBER(SEARCH(SUBSTITUTE('Référentiel films'!$A$34,"’","'"),SUBSTITUTE(G7,"’","'"))),'Référentiel films'!$B$34,""),IF(ISNUMBER(SEARCH(SUBSTITUTE('Référentiel films'!$A$35,"’","'"),SUBSTITUTE(G7,"’","'"))),'Référentiel films'!$B$35,""),IF(ISNUMBER(SEARCH(SUBSTITUTE('Référentiel films'!$A$36,"’","'"),SUBSTITUTE(G7,"’","'"))),'Référentiel films'!$B$36,""),IF(ISNUMBER(SEARCH(SUBSTITUTE('Référentiel films'!$A$37,"’","'"),SUBSTITUTE(G7,"’","'"))),'Référentiel films'!$B$37,""),IF(ISNUMBER(SEARCH(SUBSTITUTE('Référentiel films'!$A$38,"’","'"),SUBSTITUTE(G7,"’","'"))),'Référentiel films'!$B$38,""),IF(ISNUMBER(SEARCH(SUBSTITUTE('Référentiel films'!$A$39,"’","'"),SUBSTITUTE(G7,"’","'"))),'Référentiel films'!$B$39,""),IF(ISNUMBER(SEARCH(SUBSTITUTE('Référentiel films'!$A$40,"’","'"),SUBSTITUTE(G7,"’","'"))),'Référentiel films'!$B$40,""),IF(ISNUMBER(SEARCH(SUBSTITUTE('Référentiel films'!$A$41,"’","'"),SUBSTITUTE(G7,"’","'"))),'Référentiel films'!$B$41,""))) -> film-1975-le-droit-du-plus-fort; film-1975-maman-kusters-s-en-va-au-ciel | I7: Fassbinder y joue un rôle principal, assumant une visibilité politique de son homosexualité.
A8: 1977-1979 | B8: Le retour de l'histoire | C8: Jusqu'à quel point les femmes de la trilogie RFA sont-elles une allégorie de la nation allemande ? Quelle distance RWF prend-il avec la critique historique de son pays ? | D8: Automne Allemand (1977) : enlèvement de Schleyer, détournement du Landshut, morts à Stammheim. | E8: Le cinéma allemand s'empare de son histoire passée et récente et réfléchit aux problèmes de représentation qu'elle pose. Film collectif L'Allemagne en automne (1978). La diffusion de la série Holocaust de Marvin J. Chomsky (1979) à la télévision allemande suscite des débats importants, auxquels participent des cinéastes comme Syberberg ou Edgard Reitz. Le mouvement du Nouveau Cinéma allemand atteint son apogée thématique et politique. | F8: Suicide d'Armin Meier (31 mai 1978). Début de la collaboration avec Juliane Lorenz. Fassbinder se filme en crise, exposant son angoisse face à l'État. | G8: L'Année des treize lunes (1978) : œuvre radicale sur le désespoir. Le Mariage de Maria Braun (1979) : triomphe international, allégorie de la reconstruction. | H8: =IF(G8="","",_xlfn.TEXTJOIN("; ",TRUE(),IF(ISNUMBER(SEARCH(SUBSTITUTE('Référentiel films'!$A$2,"’","'"),SUBSTITUTE(G8,"’","'"))),'Référentiel films'!$B$2,""),IF(ISNUMBER(SEARCH(SUBSTITUTE('Référentiel films'!$A$3,"’","'"),SUBSTITUTE(G8,"’","'"))),'Référentiel films'!$B$3,""),IF(ISNUMBER(SEARCH(SUBSTITUTE('Référentiel films'!$A$4,"’","'"),SUBSTITUTE(G8,"’","'"))),'Référentiel films'!$B$4,""),IF(ISNUMBER(SEARCH(SUBSTITUTE('Référentiel films'!$A$5,"’","'"),SUBSTITUTE(G8,"’","'"))),'Référentiel films'!$B$5,""),IF(ISNUMBER(SEARCH(SUBSTITUTE('Référentiel films'!$A$6,"’","'"),SUBSTITUTE(G8,"’","'"))),'Référentiel films'!$B$6,""),IF(ISNUMBER(SEARCH(SUBSTITUTE('Référentiel films'!$A$7,"’","'"),SUBSTITUTE(G8,"’","'"))),'Référentiel films'!$B$7,""),IF(ISNUMBER(SEARCH(SUBSTITUTE('Référentiel films'!$A$8,"’","'"),SUBSTITUTE(G8,"’","'"))),'Référentiel films'!$B$8,""),IF(ISNUMBER(SEARCH(SUBSTITUTE('Référentiel films'!$A$9,"’","'"),SUBSTITUTE(G8,"’","'"))),'Référentiel films'!$B$9,""),IF(ISNUMBER(SEARCH(SUBSTITUTE('Référentiel films'!$A$10,"’","'"),SUBSTITUTE(G8,"’","'"))),'Référentiel films'!$B$10,""),IF(ISNUMBER(SEARCH(SUBSTITUTE('Référentiel films'!$A$11,"’","'"),SUBSTITUTE(G8,"’","'"))),'Référentiel films'!$B$11,""),IF(ISNUMBER(SEARCH(SUBSTITUTE('Référentiel films'!$A$12,"’","'"),SUBSTITUTE(G8,"’","'"))),'Référentiel films'!$B$12,""),IF(ISNUMBER(SEARCH(SUBSTITUTE('Référentiel films'!$A$13,"’","'"),SUBSTITUTE(G8,"’","'"))),'Référentiel films'!$B$13,""),IF(ISNUMBER(SEARCH(SUBSTITUTE('Référentiel films'!$A$14,"’","'"),SUBSTITUTE(G8,"’","'"))),'Référentiel films'!$B$14,""),IF(ISNUMBER(SEARCH(SUBSTITUTE('Référentiel films'!$A$15,"’","'"),SUBSTITUTE(G8,"’","'"))),'Référentiel films'!$B$15,""),IF(ISNUMBER(SEARCH(SUBSTITUTE('Référentiel films'!$A$16,"’","'"),SUBSTITUTE(G8,"’","'"))),'Référentiel films'!$B$16,""),IF(ISNUMBER(SEARCH(SUBSTITUTE('Référentiel films'!$A$17,"’","'"),SUBSTITUTE(G8,"’","'"))),'Référentiel films'!$B$17,""),IF(ISNUMBER(SEARCH(SUBSTITUTE('Référentiel films'!$A$18,"’","'"),SUBSTITUTE(G8,"’","'"))),'Référentiel films'!$B$18,""),IF(ISNUMBER(SEARCH(SUBSTITUTE('Référentiel films'!$A$19,"’","'"),SUBSTITUTE(G8,"’","'"))),'Référentiel films'!$B$19,""),IF(ISNUMBER(SEARCH(SUBSTITUTE('Référentiel films'!$A$20,"’","'"),SUBSTITUTE(G8,"’","'"))),'Référentiel films'!$B$20,""),IF(ISNUMBER(SEARCH(SUBSTITUTE('Référentiel films'!$A$21,"’","'"),SUBSTITUTE(G8,"’","'"))),'Référentiel films'!$B$21,""),IF(ISNUMBER(SEARCH(SUBSTITUTE('Référentiel films'!$A$22,"’","'"),SUBSTITUTE(G8,"’","'"))),'Référentiel films'!$B$22,""),IF(ISNUMBER(SEARCH(SUBSTITUTE('Référentiel films'!$A$23,"’","'"),SUBSTITUTE(G8,"’","'"))),'Référentiel films'!$B$23,""),IF(ISNUMBER(SEARCH(SUBSTITUTE('Référentiel films'!$A$24,"’","'"),SUBSTITUTE(G8,"’","'"))),'Référentiel films'!$B$24,""),IF(ISNUMBER(SEARCH(SUBSTITUTE('Référentiel films'!$A$25,"’","'"),SUBSTITUTE(G8,"’","'"))),'Référentiel films'!$B$25,""),IF(ISNUMBER(SEARCH(SUBSTITUTE('Référentiel films'!$A$26,"’","'"),SUBSTITUTE(G8,"’","'"))),'Référentiel films'!$B$26,""),IF(ISNUMBER(SEARCH(SUBSTITUTE('Référentiel films'!$A$27,"’","'"),SUBSTITUTE(G8,"’","'"))),'Référentiel films'!$B$27,""),IF(ISNUMBER(SEARCH(SUBSTITUTE('Référentiel films'!$A$28,"’","'"),SUBSTITUTE(G8,"’","'"))),'Référentiel films'!$B$28,""),IF(ISNUMBER(SEARCH(SUBSTITUTE('Référentiel films'!$A$29,"’","'"),SUBSTITUTE(G8,"’","'"))),'Référentiel films'!$B$29,""),IF(ISNUMBER(SEARCH(SUBSTITUTE('Référentiel films'!$A$30,"’","'"),SUBSTITUTE(G8,"’","'"))),'Référentiel films'!$B$30,""),IF(ISNUMBER(SEARCH(SUBSTITUTE('Référentiel films'!$A$31,"’","'"),SUBSTITUTE(G8,"’","'"))),'Référentiel films'!$B$31,""),IF(ISNUMBER(SEARCH(SUBSTITUTE('Référentiel films'!$A$32,"’","'"),SUBSTITUTE(G8,"’","'"))),'Référentiel films'!$B$32,""),IF(ISNUMBER(SEARCH(SUBSTITUTE('Référentiel films'!$A$33,"’","'"),SUBSTITUTE(G8,"’","'"))),'Référentiel films'!$B$33,""),IF(ISNUMBER(SEARCH(SUBSTITUTE('Référentiel films'!$A$34,"’","'"),SUBSTITUTE(G8,"’","'"))),'Référentiel films'!$B$34,""),IF(ISNUMBER(SEARCH(SUBSTITUTE('Référentiel films'!$A$35,"’","'"),SUBSTITUTE(G8,"’","'"))),'Référentiel films'!$B$35,""),IF(ISNUMBER(SEARCH(SUBSTITUTE('Référentiel films'!$A$36,"’","'"),SUBSTITUTE(G8,"’","'"))),'Référentiel films'!$B$36,""),IF(ISNUMBER(SEARCH(SUBSTITUTE('Référentiel films'!$A$37,"’","'"),SUBSTITUTE(G8,"’","'"))),'Référentiel films'!$B$37,""),IF(ISNUMBER(SEARCH(SUBSTITUTE('Référentiel films'!$A$38,"’","'"),SUBSTITUTE(G8,"’","'"))),'Référentiel films'!$B$38,""),IF(ISNUMBER(SEARCH(SUBSTITUTE('Référentiel films'!$A$39,"’","'"),SUBSTITUTE(G8,"’","'"))),'Référentiel films'!$B$39,""),IF(ISNUMBER(SEARCH(SUBSTITUTE('Référentiel films'!$A$40,"’","'"),SUBSTITUTE(G8,"’","'"))),'Référentiel films'!$B$40,""),IF(ISNUMBER(SEARCH(SUBSTITUTE('Référentiel films'!$A$41,"’","'"),SUBSTITUTE(G8,"’","'"))),'Référentiel films'!$B$41,""))) -> film-1978-l-annee-des-treize-lunes; film-1978-le-mariage-de-maria-braun | K8: le cinéaste Edgar Reitz affirme la nécessité " de films, de livres, d'images qui nous fassent reprendre connaissance et rétablissent nos réflexes", Medium, 5/1979, p.21 | N8: mélodrame
A9: 1980-1981 | B9: La fin d'un ère | C9: Quelles ambitions pour la série télévisuelle ? | D9: Fondation des Verts (1980). Manifestations écologistes. Fin de l'ère sociale-libérale. | F9: Travaille frénétiquement. Réalise son projet de vie : l'adaptation de Döblin. Épuisement physique dû aux excès. | G9: Monumental Berlin Alexanderplatz (1980, 15h). Suite de la Trilogie de la RFA : Lola, une femme allemande (1981) et Lili Marleen (1981). | H9: =IF(G9="","",_xlfn.TEXTJOIN("; ",TRUE(),IF(ISNUMBER(SEARCH(SUBSTITUTE('Référentiel films'!$A$2,"’","'"),SUBSTITUTE(G9,"’","'"))),'Référentiel films'!$B$2,""),IF(ISNUMBER(SEARCH(SUBSTITUTE('Référentiel films'!$A$3,"’","'"),SUBSTITUTE(G9,"’","'"))),'Référentiel films'!$B$3,""),IF(ISNUMBER(SEARCH(SUBSTITUTE('Référentiel films'!$A$4,"’","'"),SUBSTITUTE(G9,"’","'"))),'Référentiel films'!$B$4,""),IF(ISNUMBER(SEARCH(SUBSTITUTE('Référentiel films'!$A$5,"’","'"),SUBSTITUTE(G9,"’","'"))),'Référentiel films'!$B$5,""),IF(ISNUMBER(SEARCH(SUBSTITUTE('Référentiel films'!$A$6,"’","'"),SUBSTITUTE(G9,"’","'"))),'Référentiel films'!$B$6,""),IF(ISNUMBER(SEARCH(SUBSTITUTE('Référentiel films'!$A$7,"’","'"),SUBSTITUTE(G9,"’","'"))),'Référentiel films'!$B$7,""),IF(ISNUMBER(SEARCH(SUBSTITUTE('Référentiel films'!$A$8,"’","'"),SUBSTITUTE(G9,"’","'"))),'Référentiel films'!$B$8,""),IF(ISNUMBER(SEARCH(SUBSTITUTE('Référentiel films'!$A$9,"’","'"),SUBSTITUTE(G9,"’","'"))),'Référentiel films'!$B$9,""),IF(ISNUMBER(SEARCH(SUBSTITUTE('Référentiel films'!$A$10,"’","'"),SUBSTITUTE(G9,"’","'"))),'Référentiel films'!$B$10,""),IF(ISNUMBER(SEARCH(SUBSTITUTE('Référentiel films'!$A$11,"’","'"),SUBSTITUTE(G9,"’","'"))),'Référentiel films'!$B$11,""),IF(ISNUMBER(SEARCH(SUBSTITUTE('Référentiel films'!$A$12,"’","'"),SUBSTITUTE(G9,"’","'"))),'Référentiel films'!$B$12,""),IF(ISNUMBER(SEARCH(SUBSTITUTE('Référentiel films'!$A$13,"’","'"),SUBSTITUTE(G9,"’","'"))),'Référentiel films'!$B$13,""),IF(ISNUMBER(SEARCH(SUBSTITUTE('Référentiel films'!$A$14,"’","'"),SUBSTITUTE(G9,"’","'"))),'Référentiel films'!$B$14,""),IF(ISNUMBER(SEARCH(SUBSTITUTE('Référentiel films'!$A$15,"’","'"),SUBSTITUTE(G9,"’","'"))),'Référentiel films'!$B$15,""),IF(ISNUMBER(SEARCH(SUBSTITUTE('Référentiel films'!$A$16,"’","'"),SUBSTITUTE(G9,"’","'"))),'Référentiel films'!$B$16,""),IF(ISNUMBER(SEARCH(SUBSTITUTE('Référentiel films'!$A$17,"’","'"),SUBSTITUTE(G9,"’","'"))),'Référentiel films'!$B$17,""),IF(ISNUMBER(SEARCH(SUBSTITUTE('Référentiel films'!$A$18,"’","'"),SUBSTITUTE(G9,"’","'"))),'Référentiel films'!$B$18,""),IF(ISNUMBER(SEARCH(SUBSTITUTE('Référentiel films'!$A$19,"’","'"),SUBSTITUTE(G9,"’","'"))),'Référentiel films'!$B$19,""),IF(ISNUMBER(SEARCH(SUBSTITUTE('Référentiel films'!$A$20,"’","'"),SUBSTITUTE(G9,"’","'"))),'Référentiel films'!$B$20,""),IF(ISNUMBER(SEARCH(SUBSTITUTE('Référentiel films'!$A$21,"’","'"),SUBSTITUTE(G9,"’","'"))),'Référentiel films'!$B$21,""),IF(ISNUMBER(SEARCH(SUBSTITUTE('Référentiel films'!$A$22,"’","'"),SUBSTITUTE(G9,"’","'"))),'Référentiel films'!$B$22,""),IF(ISNUMBER(SEARCH(SUBSTITUTE('Référentiel films'!$A$23,"’","'"),SUBSTITUTE(G9,"’","'"))),'Référentiel films'!$B$23,""),IF(ISNUMBER(SEARCH(SUBSTITUTE('Référentiel films'!$A$24,"’","'"),SUBSTITUTE(G9,"’","'"))),'Référentiel films'!$B$24,""),IF(ISNUMBER(SEARCH(SUBSTITUTE('Référentiel films'!$A$25,"’","'"),SUBSTITUTE(G9,"’","'"))),'Référentiel films'!$B$25,""),IF(ISNUMBER(SEARCH(SUBSTITUTE('Référentiel films'!$A$26,"’","'"),SUBSTITUTE(G9,"’","'"))),'Référentiel films'!$B$26,""),IF(ISNUMBER(SEARCH(SUBSTITUTE('Référentiel films'!$A$27,"’","'"),SUBSTITUTE(G9,"’","'"))),'Référentiel films'!$B$27,""),IF(ISNUMBER(SEARCH(SUBSTITUTE('Référentiel films'!$A$28,"’","'"),SUBSTITUTE(G9,"’","'"))),'Référentiel films'!$B$28,""),IF(ISNUMBER(SEARCH(SUBSTITUTE('Référentiel films'!$A$29,"’","'"),SUBSTITUTE(G9,"’","'"))),'Référentiel films'!$B$29,""),IF(ISNUMBER(SEARCH(SUBSTITUTE('Référentiel films'!$A$30,"’","'"),SUBSTITUTE(G9,"’","'"))),'Référentiel films'!$B$30,""),IF(ISNUMBER(SEARCH(SUBSTITUTE('Référentiel films'!$A$31,"’","'"),SUBSTITUTE(G9,"’","'"))),'Référentiel films'!$B$31,""),IF(ISNUMBER(SEARCH(SUBSTITUTE('Référentiel films'!$A$32,"’","'"),SUBSTITUTE(G9,"’","'"))),'Référentiel films'!$B$32,""),IF(ISNUMBER(SEARCH(SUBSTITUTE('Référentiel films'!$A$33,"’","'"),SUBSTITUTE(G9,"’","'"))),'Référentiel films'!$B$33,""),IF(ISNUMBER(SEARCH(SUBSTITUTE('Référentiel films'!$A$34,"’","'"),SUBSTITUTE(G9,"’","'"))),'Référentiel films'!$B$34,""),IF(ISNUMBER(SEARCH(SUBSTITUTE('Référentiel films'!$A$35,"’","'"),SUBSTITUTE(G9,"’","'"))),'Référentiel films'!$B$35,""),IF(ISNUMBER(SEARCH(SUBSTITUTE('Référentiel films'!$A$36,"’","'"),SUBSTITUTE(G9,"’","'"))),'Référentiel films'!$B$36,""),IF(ISNUMBER(SEARCH(SUBSTITUTE('Référentiel films'!$A$37,"’","'"),SUBSTITUTE(G9,"’","'"))),'Référentiel films'!$B$37,""),IF(ISNUMBER(SEARCH(SUBSTITUTE('Référentiel films'!$A$38,"’","'"),SUBSTITUTE(G9,"’","'"))),'Référentiel films'!$B$38,""),IF(ISNUMBER(SEARCH(SUBSTITUTE('Référentiel films'!$A$39,"’","'"),SUBSTITUTE(G9,"’","'"))),'Référentiel films'!$B$39,""),IF(ISNUMBER(SEARCH(SUBSTITUTE('Référentiel films'!$A$40,"’","'"),SUBSTITUTE(G9,"’","'"))),'Référentiel films'!$B$40,""),IF(ISNUMBER(SEARCH(SUBSTITUTE('Référentiel films'!$A$41,"’","'"),SUBSTITUTE(G9,"’","'"))),'Référentiel films'!$B$41,""))) -> film-1980-berlin-alexanderplatz; film-1981-lili-marleen; film-1981-lola-une-femme-allemande
A10: 1982 | B10: La mort du Maître | C10: RWF, figure du collectif politique des années 60 et 70 ou d'héritier de la figure du génie romantique et du poète maudit ? Auteur ou cinéaste populaire ? | D10: Victoire d'Helmut Kohl (CDU) en octobre. Fin d'une époque artistique et politique radicale. | E10: Mort de Fassbinder marquant symboliquement la fin du Nouveau Cinéma Allemand. | F10: Décès de Fassbinder le 10 juin à Munich, à l'âge de 37 ans (épuisement et overdose). | G10: Le Secret de Veronika Voss (Ours d'Or à Berlin). Querelle (œuvre posthume). Fassbinder laisse un héritage de plus de 40 films. | H10: =IF(G10="","",_xlfn.TEXTJOIN("; ",TRUE(),IF(ISNUMBER(SEARCH(SUBSTITUTE('Référentiel films'!$A$2,"’","'"),SUBSTITUTE(G10,"’","'"))),'Référentiel films'!$B$2,""),IF(ISNUMBER(SEARCH(SUBSTITUTE('Référentiel films'!$A$3,"’","'"),SUBSTITUTE(G10,"’","'"))),'Référentiel films'!$B$3,""),IF(ISNUMBER(SEARCH(SUBSTITUTE('Référentiel films'!$A$4,"’","'"),SUBSTITUTE(G10,"’","'"))),'Référentiel films'!$B$4,""),IF(ISNUMBER(SEARCH(SUBSTITUTE('Référentiel films'!$A$5,"’","'"),SUBSTITUTE(G10,"’","'"))),'Référentiel films'!$B$5,""),IF(ISNUMBER(SEARCH(SUBSTITUTE('Référentiel films'!$A$6,"’","'"),SUBSTITUTE(G10,"’","'"))),'Référentiel films'!$B$6,""),IF(ISNUMBER(SEARCH(SUBSTITUTE('Référentiel films'!$A$7,"’","'"),SUBSTITUTE(G10,"’","'"))),'Référentiel films'!$B$7,""),IF(ISNUMBER(SEARCH(SUBSTITUTE('Référentiel films'!$A$8,"’","'"),SUBSTITUTE(G10,"’","'"))),'Référentiel films'!$B$8,""),IF(ISNUMBER(SEARCH(SUBSTITUTE('Référentiel films'!$A$9,"’","'"),SUBSTITUTE(G10,"’","'"))),'Référentiel films'!$B$9,""),IF(ISNUMBER(SEARCH(SUBSTITUTE('Référentiel films'!$A$10,"’","'"),SUBSTITUTE(G10,"’","'"))),'Référentiel films'!$B$10,""),IF(ISNUMBER(SEARCH(SUBSTITUTE('Référentiel films'!$A$11,"’","'"),SUBSTITUTE(G10,"’","'"))),'Référentiel films'!$B$11,""),IF(ISNUMBER(SEARCH(SUBSTITUTE('Référentiel films'!$A$12,"’","'"),SUBSTITUTE(G10,"’","'"))),'Référentiel films'!$B$12,""),IF(ISNUMBER(SEARCH(SUBSTITUTE('Référentiel films'!$A$13,"’","'"),SUBSTITUTE(G10,"’","'"))),'Référentiel films'!$B$13,""),IF(ISNUMBER(SEARCH(SUBSTITUTE('Référentiel films'!$A$14,"’","'"),SUBSTITUTE(G10,"’","'"))),'Référentiel films'!$B$14,""),IF(ISNUMBER(SEARCH(SUBSTITUTE('Référentiel films'!$A$15,"’","'"),SUBSTITUTE(G10,"’","'"))),'Référentiel films'!$B$15,""),IF(ISNUMBER(SEARCH(SUBSTITUTE('Référentiel films'!$A$16,"’","'"),SUBSTITUTE(G10,"’","'"))),'Référentiel films'!$B$16,""),IF(ISNUMBER(SEARCH(SUBSTITUTE('Référentiel films'!$A$17,"’","'"),SUBSTITUTE(G10,"’","'"))),'Référentiel films'!$B$17,""),IF(ISNUMBER(SEARCH(SUBSTITUTE('Référentiel films'!$A$18,"’","'"),SUBSTITUTE(G10,"’","'"))),'Référentiel films'!$B$18,""),IF(ISNUMBER(SEARCH(SUBSTITUTE('Référentiel films'!$A$19,"’","'"),SUBSTITUTE(G10,"’","'"))),'Référentiel films'!$B$19,""),IF(ISNUMBER(SEARCH(SUBSTITUTE('Référentiel films'!$A$20,"’","'"),SUBSTITUTE(G10,"’","'"))),'Référentiel films'!$B$20,""),IF(ISNUMBER(SEARCH(SUBSTITUTE('Référentiel films'!$A$21,"’","'"),SUBSTITUTE(G10,"’","'"))),'Référentiel films'!$B$21,""),IF(ISNUMBER(SEARCH(SUBSTITUTE('Référentiel films'!$A$22,"’","'"),SUBSTITUTE(G10,"’","'"))),'Référentiel films'!$B$22,""),IF(ISNUMBER(SEARCH(SUBSTITUTE('Référentiel films'!$A$23,"’","'"),SUBSTITUTE(G10,"’","'"))),'Référentiel films'!$B$23,""),IF(ISNUMBER(SEARCH(SUBSTITUTE('Référentiel films'!$A$24,"’","'"),SUBSTITUTE(G10,"’","'"))),'Référentiel films'!$B$24,""),IF(ISNUMBER(SEARCH(SUBSTITUTE('Référentiel films'!$A$25,"’","'"),SUBSTITUTE(G10,"’","'"))),'Référentiel films'!$B$25,""),IF(ISNUMBER(SEARCH(SUBSTITUTE('Référentiel films'!$A$26,"’","'"),SUBSTITUTE(G10,"’","'"))),'Référentiel films'!$B$26,""),IF(ISNUMBER(SEARCH(SUBSTITUTE('Référentiel films'!$A$27,"’","'"),SUBSTITUTE(G10,"’","'"))),'Référentiel films'!$B$27,""),IF(ISNUMBER(SEARCH(SUBSTITUTE('Référentiel films'!$A$28,"’","'"),SUBSTITUTE(G10,"’","'"))),'Référentiel films'!$B$28,""),IF(ISNUMBER(SEARCH(SUBSTITUTE('Référentiel films'!$A$29,"’","'"),SUBSTITUTE(G10,"’","'"))),'Référentiel films'!$B$29,""),IF(ISNUMBER(SEARCH(SUBSTITUTE('Référentiel films'!$A$30,"’","'"),SUBSTITUTE(G10,"’","'"))),'Référentiel films'!$B$30,""),IF(ISNUMBER(SEARCH(SUBSTITUTE('Référentiel films'!$A$31,"’","'"),SUBSTITUTE(G10,"’","'"))),'Référentiel films'!$B$31,""),IF(ISNUMBER(SEARCH(SUBSTITUTE('Référentiel films'!$A$32,"’","'"),SUBSTITUTE(G10,"’","'"))),'Référentiel films'!$B$32,""),IF(ISNUMBER(SEARCH(SUBSTITUTE('Référentiel films'!$A$33,"’","'"),SUBSTITUTE(G10,"’","'"))),'Référentiel films'!$B$33,""),IF(ISNUMBER(SEARCH(SUBSTITUTE('Référentiel films'!$A$34,"’","'"),SUBSTITUTE(G10,"’","'"))),'Référentiel films'!$B$34,""),IF(ISNUMBER(SEARCH(SUBSTITUTE('Référentiel films'!$A$35,"’","'"),SUBSTITUTE(G10,"’","'"))),'Référentiel films'!$B$35,""),IF(ISNUMBER(SEARCH(SUBSTITUTE('Référentiel films'!$A$36,"’","'"),SUBSTITUTE(G10,"’","'"))),'Référentiel films'!$B$36,""),IF(ISNUMBER(SEARCH(SUBSTITUTE('Référentiel films'!$A$37,"’","'"),SUBSTITUTE(G10,"’","'"))),'Référentiel films'!$B$37,""),IF(ISNUMBER(SEARCH(SUBSTITUTE('Référentiel films'!$A$38,"’","'"),SUBSTITUTE(G10,"’","'"))),'Référentiel films'!$B$38,""),IF(ISNUMBER(SEARCH(SUBSTITUTE('Référentiel films'!$A$39,"’","'"),SUBSTITUTE(G10,"’","'"))),'Référentiel films'!$B$39,""),IF(ISNUMBER(SEARCH(SUBSTITUTE('Référentiel films'!$A$40,"’","'"),SUBSTITUTE(G10,"’","'"))),'Référentiel films'!$B$40,""),IF(ISNUMBER(SEARCH(SUBSTITUTE('Référentiel films'!$A$41,"’","'"),SUBSTITUTE(G10,"’","'"))),'Référentiel films'!$B$41,""))) -> film-1981-le-secret-de-veronika-voss; film-1982-querelle

Sheet Années
A1: Année | B1: ID période | C1: Événement histoire et politique | D1: Contexte culturel | E1: Biographie de Fassbinder | F1: Œuvres | G1: Analyse et Réception critique | H1: Liens | I1: Extraits | J1: Description de l'extrait | K1: Consigne d'analyse | L1: Citation | M1: Image 1 | N1: Légende 1 | O1: Image 2 | P1: Légende 2 | Q1: Image 3 | R1: Légende 3 | S1: Notion | T1: Source | U1: IDs films — Œuvres
A2: 1945 | B2: 1945-1946 | C2: Les alliés aident à la relance de médias d'information et promeuvent une nouvelle politique éducative. Les alliés organisent un vaste programme de démocratisation, décartellisation, démilatarisation et dénazification | D2: Le cinéma est en ruines. Premières projection des Moulins de la mort (Todesmühen), un documentaire sur les camps de concentration. | E2: Naissance de Rainer Werner Fassbinder le 31 mai à Bad Wörishofen, Bavière. Père médecin généraliste, mère traductrice. Première année passée chez son oncle paternel | H2: Les génériques de Fassbinder | U2: =IF(F2="","",_xlfn.TEXTJOIN("; ",TRUE(),IF(ISNUMBER(SEARCH(SUBSTITUTE('Référentiel films'!$A$2,"’","'"),SUBSTITUTE(F2,"’","'"))),'Référentiel films'!$B$2,""),IF(ISNUMBER(SEARCH(SUBSTITUTE('Référentiel films'!$A$3,"’","'"),SUBSTITUTE(F2,"’","'"))),'Référentiel films'!$B$3,""),IF(ISNUMBER(SEARCH(SUBSTITUTE('Référentiel films'!$A$4,"’","'"),SUBSTITUTE(F2,"’","'"))),'Référentiel films'!$B$4,""),IF(ISNUMBER(SEARCH(SUBSTITUTE('Référentiel films'!$A$5,"’","'"),SUBSTITUTE(F2,"’","'"))),'Référentiel films'!$B$5,""),IF(ISNUMBER(SEARCH(SUBSTITUTE('Référentiel films'!$A$6,"’","'"),SUBSTITUTE(F2,"’","'"))),'Référentiel films'!$B$6,""),IF(ISNUMBER(SEARCH(SUBSTITUTE('Référentiel films'!$A$7,"’","'"),SUBSTITUTE(F2,"’","'"))),'Référentiel films'!$B$7,""),IF(ISNUMBER(SEARCH(SUBSTITUTE('Référentiel films'!$A$8,"’","'"),SUBSTITUTE(F2,"’","'"))),'Référentiel films'!$B$8,""),IF(ISNUMBER(SEARCH(SUBSTITUTE('Référentiel films'!$A$9,"’","'"),SUBSTITUTE(F2,"’","'"))),'Référentiel films'!$B$9,""),IF(ISNUMBER(SEARCH(SUBSTITUTE('Référentiel films'!$A$10,"’","'"),SUBSTITUTE(F2,"’","'"))),'Référentiel films'!$B$10,""),IF(ISNUMBER(SEARCH(SUBSTITUTE('Référentiel films'!$A$11,"’","'"),SUBSTITUTE(F2,"’","'"))),'Référentiel films'!$B$11,""),IF(ISNUMBER(SEARCH(SUBSTITUTE('Référentiel films'!$A$12,"’","'"),SUBSTITUTE(F2,"’","'"))),'Référentiel films'!$B$12,""),IF(ISNUMBER(SEARCH(SUBSTITUTE('Référentiel films'!$A$13,"’","'"),SUBSTITUTE(F2,"’","'"))),'Référentiel films'!$B$13,""),IF(ISNUMBER(SEARCH(SUBSTITUTE('Référentiel films'!$A$14,"’","'"),SUBSTITUTE(F2,"’","'"))),'Référentiel films'!$B$14,""),IF(ISNUMBER(SEARCH(SUBSTITUTE('Référentiel films'!$A$15,"’","'"),SUBSTITUTE(F2,"’","'"))),'Référentiel films'!$B$15,""),IF(ISNUMBER(SEARCH(SUBSTITUTE('Référentiel films'!$A$16,"’","'"),SUBSTITUTE(F2,"’","'"))),'Référentiel films'!$B$16,""),IF(ISNUMBER(SEARCH(SUBSTITUTE('Référentiel films'!$A$17,"’","'"),SUBSTITUTE(F2,"’","'"))),'Référentiel films'!$B$17,""),IF(ISNUMBER(SEARCH(SUBSTITUTE('Référentiel films'!$A$18,"’","'"),SUBSTITUTE(F2,"’","'"))),'Référentiel films'!$B$18,""),IF(ISNUMBER(SEARCH(SUBSTITUTE('Référentiel films'!$A$19,"’","'"),SUBSTITUTE(F2,"’","'"))),'Référentiel films'!$B$19,""),IF(ISNUMBER(SEARCH(SUBSTITUTE('Référentiel films'!$A$20,"’","'"),SUBSTITUTE(F2,"’","'"))),'Référentiel films'!$B$20,""),IF(ISNUMBER(SEARCH(SUBSTITUTE('Référentiel films'!$A$21,"’","'"),SUBSTITUTE(F2,"’","'"))),'Référentiel films'!$B$21,""),IF(ISNUMBER(SEARCH(SUBSTITUTE('Référentiel films'!$A$22,"’","'"),SUBSTITUTE(F2,"’","'"))),'Référentiel films'!$B$22,""),IF(ISNUMBER(SEARCH(SUBSTITUTE('Référentiel films'!$A$23,"’","'"),SUBSTITUTE(F2,"’","'"))),'Référentiel films'!$B$23,""),IF(ISNUMBER(SEARCH(SUBSTITUTE('Référentiel films'!$A$24,"’","'"),SUBSTITUTE(F2,"’","'"))),'Référentiel films'!$B$24,""),IF(ISNUMBER(SEARCH(SUBSTITUTE('Référentiel films'!$A$25,"’","'"),SUBSTITUTE(F2,"’","'"))),'Référentiel films'!$B$25,""),IF(ISNUMBER(SEARCH(SUBSTITUTE('Référentiel films'!$A$26,"’","'"),SUBSTITUTE(F2,"’","'"))),'Référentiel films'!$B$26,""),IF(ISNUMBER(SEARCH(SUBSTITUTE('Référentiel films'!$A$27,"’","'"),SUBSTITUTE(F2,"’","'"))),'Référentiel films'!$B$27,""),IF(ISNUMBER(SEARCH(SUBSTITUTE('Référentiel films'!$A$28,"’","'"),SUBSTITUTE(F2,"’","'"))),'Référentiel films'!$B$28,""),IF(ISNUMBER(SEARCH(SUBSTITUTE('Référentiel films'!$A$29,"’","'"),SUBSTITUTE(F2,"’","'"))),'Référentiel films'!$B$29,""),IF(ISNUMBER(SEARCH(SUBSTITUTE('Référentiel films'!$A$30,"’","'"),SUBSTITUTE(F2,"’","'"))),'Référentiel films'!$B$30,""),IF(ISNUMBER(SEARCH(SUBSTITUTE('Référentiel films'!$A$31,"’","'"),SUBSTITUTE(F2,"’","'"))),'Référentiel films'!$B$31,""),IF(ISNUMBER(SEARCH(SUBSTITUTE('Référentiel films'!$A$32,"’","'"),SUBSTITUTE(F2,"’","'"))),'Référentiel films'!$B$32,""),IF(ISNUMBER(SEARCH(SUBSTITUTE('Référentiel films'!$A$33,"’","'"),SUBSTITUTE(F2,"’","'"))),'Référentiel films'!$B$33,""),IF(ISNUMBER(SEARCH(SUBSTITUTE('Référentiel films'!$A$34,"’","'"),SUBSTITUTE(F2,"’","'"))),'Référentiel films'!$B$34,""),IF(ISNUMBER(SEARCH(SUBSTITUTE('Référentiel films'!$A$35,"’","'"),SUBSTITUTE(F2,"’","'"))),'Référentiel films'!$B$35,""),IF(ISNUMBER(SEARCH(SUBSTITUTE('Référentiel films'!$A$36,"’","'"),SUBSTITUTE(F2,"’","'"))),'Référentiel films'!$B$36,""),IF(ISNUMBER(SEARCH(SUBSTITUTE('Référentiel films'!$A$37,"’","'"),SUBSTITUTE(F2,"’","'"))),'Référentiel films'!$B$37,""),IF(ISNUMBER(SEARCH(SUBSTITUTE('Référentiel films'!$A$38,"’","'"),SUBSTITUTE(F2,"’","'"))),'Référentiel films'!$B$38,""),IF(ISNUMBER(SEARCH(SUBSTITUTE('Référentiel films'!$A$39,"’","'"),SUBSTITUTE(F2,"’","'"))),'Référentiel films'!$B$39,""),IF(ISNUMBER(SEARCH(SUBSTITUTE('Référentiel films'!$A$40,"’","'"),SUBSTITUTE(F2,"’","'"))),'Référentiel films'!$B$40,""),IF(ISNUMBER(SEARCH(SUBSTITUTE('Référentiel films'!$A$41,"’","'"),SUBSTITUTE(F2,"’","'"))),'Référentiel films'!$B$41,"")))
A3: 1946 | B3: 1945-1946 | C3: Premières élections municipales dans la zone américaine. La « loi d'élimination du national-socialisme et du militarisme » du 5 mars 1946 définit dans son article 4 les niveaux de responsabilité : Hauptschuldige (principaux coupables), Belastete (charges importantes), Minderbelastete (charges mineures), Mitläufer (suivistes), Entlastete (libérés, les procès en dénazification pouvant déclarer les prévenus nicht betroffen, « non concernés » par cette loi). Procès de Nuremberg : 12 des 24 accusés sont condamnés à mort pour crimes de guerre. | D3: Fondation de la DEFA (Deutsch Film AG) à Berlin Est. Premières productions de films allemands de fiction depuis la fin de la guerre. Vogue de l'évocation mélancolique de la patrie dans la chanson de variété allemande avec "Möwe, di fliegst in die Heimat" de Magda Hein. | E3: Le couple Fassbinder prend l'enfant avec eux à Munich. Une partie de la famille vit dans le même appartement, notamment la grand-mère de Rainer. | H3: Le procès de Nuremberg | U3: =IF(F3="","",_xlfn.TEXTJOIN("; ",TRUE(),IF(ISNUMBER(SEARCH(SUBSTITUTE('Référentiel films'!$A$2,"’","'"),SUBSTITUTE(F3,"’","'"))),'Référentiel films'!$B$2,""),IF(ISNUMBER(SEARCH(SUBSTITUTE('Référentiel films'!$A$3,"’","'"),SUBSTITUTE(F3,"’","'"))),'Référentiel films'!$B$3,""),IF(ISNUMBER(SEARCH(SUBSTITUTE('Référentiel films'!$A$4,"’","'"),SUBSTITUTE(F3,"’","'"))),'Référentiel films'!$B$4,""),IF(ISNUMBER(SEARCH(SUBSTITUTE('Référentiel films'!$A$5,"’","'"),SUBSTITUTE(F3,"’","'"))),'Référentiel films'!$B$5,""),IF(ISNUMBER(SEARCH(SUBSTITUTE('Référentiel films'!$A$6,"’","'"),SUBSTITUTE(F3,"’","'"))),'Référentiel films'!$B$6,""),IF(ISNUMBER(SEARCH(SUBSTITUTE('Référentiel films'!$A$7,"’","'"),SUBSTITUTE(F3,"’","'"))),'Référentiel films'!$B$7,""),IF(ISNUMBER(SEARCH(SUBSTITUTE('Référentiel films'!$A$8,"’","'"),SUBSTITUTE(F3,"’","'"))),'Référentiel films'!$B$8,""),IF(ISNUMBER(SEARCH(SUBSTITUTE('Référentiel films'!$A$9,"’","'"),SUBSTITUTE(F3,"’","'"))),'Référentiel films'!$B$9,""),IF(ISNUMBER(SEARCH(SUBSTITUTE('Référentiel films'!$A$10,"’","'"),SUBSTITUTE(F3,"’","'"))),'Référentiel films'!$B$10,""),IF(ISNUMBER(SEARCH(SUBSTITUTE('Référentiel films'!$A$11,"’","'"),SUBSTITUTE(F3,"’","'"))),'Référentiel films'!$B$11,""),IF(ISNUMBER(SEARCH(SUBSTITUTE('Référentiel films'!$A$12,"’","'"),SUBSTITUTE(F3,"’","'"))),'Référentiel films'!$B$12,""),IF(ISNUMBER(SEARCH(SUBSTITUTE('Référentiel films'!$A$13,"’","'"),SUBSTITUTE(F3,"’","'"))),'Référentiel films'!$B$13,""),IF(ISNUMBER(SEARCH(SUBSTITUTE('Référentiel films'!$A$14,"’","'"),SUBSTITUTE(F3,"’","'"))),'Référentiel films'!$B$14,""),IF(ISNUMBER(SEARCH(SUBSTITUTE('Référentiel films'!$A$15,"’","'"),SUBSTITUTE(F3,"’","'"))),'Référentiel films'!$B$15,""),IF(ISNUMBER(SEARCH(SUBSTITUTE('Référentiel films'!$A$16,"’","'"),SUBSTITUTE(F3,"’","'"))),'Référentiel films'!$B$16,""),IF(ISNUMBER(SEARCH(SUBSTITUTE('Référentiel films'!$A$17,"’","'"),SUBSTITUTE(F3,"’","'"))),'Référentiel films'!$B$17,""),IF(ISNUMBER(SEARCH(SUBSTITUTE('Référentiel films'!$A$18,"’","'"),SUBSTITUTE(F3,"’","'"))),'Référentiel films'!$B$18,""),IF(ISNUMBER(SEARCH(SUBSTITUTE('Référentiel films'!$A$19,"’","'"),SUBSTITUTE(F3,"’","'"))),'Référentiel films'!$B$19,""),IF(ISNUMBER(SEARCH(SUBSTITUTE('Référentiel films'!$A$20,"’","'"),SUBSTITUTE(F3,"’","'"))),'Référentiel films'!$B$20,""),IF(ISNUMBER(SEARCH(SUBSTITUTE('Référentiel films'!$A$21,"’","'"),SUBSTITUTE(F3,"’","'"))),'Référentiel films'!$B$21,""),IF(ISNUMBER(SEARCH(SUBSTITUTE('Référentiel films'!$A$22,"’","'"),SUBSTITUTE(F3,"’","'"))),'Référentiel films'!$B$22,""),IF(ISNUMBER(SEARCH(SUBSTITUTE('Référentiel films'!$A$23,"’","'"),SUBSTITUTE(F3,"’","'"))),'Référentiel films'!$B$23,""),IF(ISNUMBER(SEARCH(SUBSTITUTE('Référentiel films'!$A$24,"’","'"),SUBSTITUTE(F3,"’","'"))),'Référentiel films'!$B$24,""),IF(ISNUMBER(SEARCH(SUBSTITUTE('Référentiel films'!$A$25,"’","'"),SUBSTITUTE(F3,"’","'"))),'Référentiel films'!$B$25,""),IF(ISNUMBER(SEARCH(SUBSTITUTE('Référentiel films'!$A$26,"’","'"),SUBSTITUTE(F3,"’","'"))),'Référentiel films'!$B$26,""),IF(ISNUMBER(SEARCH(SUBSTITUTE('Référentiel films'!$A$27,"’","'"),SUBSTITUTE(F3,"’","'"))),'Référentiel films'!$B$27,""),IF(ISNUMBER(SEARCH(SUBSTITUTE('Référentiel films'!$A$28,"’","'"),SUBSTITUTE(F3,"’","'"))),'Référentiel films'!$B$28,""),IF(ISNUMBER(SEARCH(SUBSTITUTE('Référentiel films'!$A$29,"’","'"),SUBSTITUTE(F3,"’","'"))),'Référentiel films'!$B$29,""),IF(ISNUMBER(SEARCH(SUBSTITUTE('Référentiel films'!$A$30,"’","'"),SUBSTITUTE(F3,"’","'"))),'Référentiel films'!$B$30,""),IF(ISNUMBER(SEARCH(SUBSTITUTE('Référentiel films'!$A$31,"’","'"),SUBSTITUTE(F3,"’","'"))),'Référentiel films'!$B$31,""),IF(ISNUMBER(SEARCH(SUBSTITUTE('Référentiel films'!$A$32,"’","'"),SUBSTITUTE(F3,"’","'"))),'Référentiel films'!$B$32,""),IF(ISNUMBER(SEARCH(SUBSTITUTE('Référentiel films'!$A$33,"’","'"),SUBSTITUTE(F3,"’","'"))),'Référentiel films'!$B$33,""),IF(ISNUMBER(SEARCH(SUBSTITUTE('Référentiel films'!$A$34,"’","'"),SUBSTITUTE(F3,"’","'"))),'Référentiel films'!$B$34,""),IF(ISNUMBER(SEARCH(SUBSTITUTE('Référentiel films'!$A$35,"’","'"),SUBSTITUTE(F3,"’","'"))),'Référentiel films'!$B$35,""),IF(ISNUMBER(SEARCH(SUBSTITUTE('Référentiel films'!$A$36,"’","'"),SUBSTITUTE(F3,"’","'"))),'Référentiel films'!$B$36,""),IF(ISNUMBER(SEARCH(SUBSTITUTE('Référentiel films'!$A$37,"’","'"),SUBSTITUTE(F3,"’","'"))),'Référentiel films'!$B$37,""),IF(ISNUMBER(SEARCH(SUBSTITUTE('Référentiel films'!$A$38,"’","'"),SUBSTITUTE(F3,"’","'"))),'Référentiel films'!$B$38,""),IF(ISNUMBER(SEARCH(SUBSTITUTE('Référentiel films'!$A$39,"’","'"),SUBSTITUTE(F3,"’","'"))),'Référentiel films'!$B$39,""),IF(ISNUMBER(SEARCH(SUBSTITUTE('Référentiel films'!$A$40,"’","'"),SUBSTITUTE(F3,"’","'"))),'Référentiel films'!$B$40,""),IF(ISNUMBER(SEARCH(SUBSTITUTE('Référentiel films'!$A$41,"’","'"),SUBSTITUTE(F3,"’","'"))),'Référentiel films'!$B$41,"")))
A4: 1947 | B4: 1947-1960 | C4: Période de disette la plus terrible depuis la fin de la guerre. Les Trümmerfrauen (les femmes des ruines) constituent un des piliers de la reconstruction. | D4: A l'initiative de Hans Werner Richter, fondation du Groupe 47 qui réunit l'avant-garde littéraire allemande dont Gunter Grass et Heinrich Böll. Le Groupe cherche à constituer une élite exemplairement démocratique dans le domaine des lettres et à développer de nouvelles formes d'écriture pour permettre aux lettres allemandes d'exprimer au mieux des enjeux esthétiques et politiques en adéquation avec la société d'après-guerre. | T4: Elsaesser, Wikipedia | U4: =IF(F4="","",_xlfn.TEXTJOIN("; ",TRUE(),IF(ISNUMBER(SEARCH(SUBSTITUTE('Référentiel films'!$A$2,"’","'"),SUBSTITUTE(F4,"’","'"))),'Référentiel films'!$B$2,""),IF(ISNUMBER(SEARCH(SUBSTITUTE('Référentiel films'!$A$3,"’","'"),SUBSTITUTE(F4,"’","'"))),'Référentiel films'!$B$3,""),IF(ISNUMBER(SEARCH(SUBSTITUTE('Référentiel films'!$A$4,"’","'"),SUBSTITUTE(F4,"’","'"))),'Référentiel films'!$B$4,""),IF(ISNUMBER(SEARCH(SUBSTITUTE('Référentiel films'!$A$5,"’","'"),SUBSTITUTE(F4,"’","'"))),'Référentiel films'!$B$5,""),IF(ISNUMBER(SEARCH(SUBSTITUTE('Référentiel films'!$A$6,"’","'"),SUBSTITUTE(F4,"’","'"))),'Référentiel films'!$B$6,""),IF(ISNUMBER(SEARCH(SUBSTITUTE('Référentiel films'!$A$7,"’","'"),SUBSTITUTE(F4,"’","'"))),'Référentiel films'!$B$7,""),IF(ISNUMBER(SEARCH(SUBSTITUTE('Référentiel films'!$A$8,"’","'"),SUBSTITUTE(F4,"’","'"))),'Référentiel films'!$B$8,""),IF(ISNUMBER(SEARCH(SUBSTITUTE('Référentiel films'!$A$9,"’","'"),SUBSTITUTE(F4,"’","'"))),'Référentiel films'!$B$9,""),IF(ISNUMBER(SEARCH(SUBSTITUTE('Référentiel films'!$A$10,"’","'"),SUBSTITUTE(F4,"’","'"))),'Référentiel films'!$B$10,""),IF(ISNUMBER(SEARCH(SUBSTITUTE('Référentiel films'!$A$11,"’","'"),SUBSTITUTE(F4,"’","'"))),'Référentiel films'!$B$11,""),IF(ISNUMBER(SEARCH(SUBSTITUTE('Référentiel films'!$A$12,"’","'"),SUBSTITUTE(F4,"’","'"))),'Référentiel films'!$B$12,""),IF(ISNUMBER(SEARCH(SUBSTITUTE('Référentiel films'!$A$13,"’","'"),SUBSTITUTE(F4,"’","'"))),'Référentiel films'!$B$13,""),IF(ISNUMBER(SEARCH(SUBSTITUTE('Référentiel films'!$A$14,"’","'"),SUBSTITUTE(F4,"’","'"))),'Référentiel films'!$B$14,""),IF(ISNUMBER(SEARCH(SUBSTITUTE('Référentiel films'!$A$15,"’","'"),SUBSTITUTE(F4,"’","'"))),'Référentiel films'!$B$15,""),IF(ISNUMBER(SEARCH(SUBSTITUTE('Référentiel films'!$A$16,"’","'"),SUBSTITUTE(F4,"’","'"))),'Référentiel films'!$B$16,""),IF(ISNUMBER(SEARCH(SUBSTITUTE('Référentiel films'!$A$17,"’","'"),SUBSTITUTE(F4,"’","'"))),'Référentiel films'!$B$17,""),IF(ISNUMBER(SEARCH(SUBSTITUTE('Référentiel films'!$A$18,"’","'"),SUBSTITUTE(F4,"’","'"))),'Référentiel films'!$B$18,""),IF(ISNUMBER(SEARCH(SUBSTITUTE('Référentiel films'!$A$19,"’","'"),SUBSTITUTE(F4,"’","'"))),'Référentiel films'!$B$19,""),IF(ISNUMBER(SEARCH(SUBSTITUTE('Référentiel films'!$A$20,"’","'"),SUBSTITUTE(F4,"’","'"))),'Référentiel films'!$B$20,""),IF(ISNUMBER(SEARCH(SUBSTITUTE('Référentiel films'!$A$21,"’","'"),SUBSTITUTE(F4,"’","'"))),'Référentiel films'!$B$21,""),IF(ISNUMBER(SEARCH(SUBSTITUTE('Référentiel films'!$A$22,"’","'"),SUBSTITUTE(F4,"’","'"))),'Référentiel films'!$B$22,""),IF(ISNUMBER(SEARCH(SUBSTITUTE('Référentiel films'!$A$23,"’","'"),SUBSTITUTE(F4,"’","'"))),'Référentiel films'!$B$23,""),IF(ISNUMBER(SEARCH(SUBSTITUTE('Référentiel films'!$A$24,"’","'"),SUBSTITUTE(F4,"’","'"))),'Référentiel films'!$B$24,""),IF(ISNUMBER(SEARCH(SUBSTITUTE('Référentiel films'!$A$25,"’","'"),SUBSTITUTE(F4,"’","'"))),'Référentiel films'!$B$25,""),IF(ISNUMBER(SEARCH(SUBSTITUTE('Référentiel films'!$A$26,"’","'"),SUBSTITUTE(F4,"’","'"))),'Référentiel films'!$B$26,""),IF(ISNUMBER(SEARCH(SUBSTITUTE('Référentiel films'!$A$27,"’","'"),SUBSTITUTE(F4,"’","'"))),'Référentiel films'!$B$27,""),IF(ISNUMBER(SEARCH(SUBSTITUTE('Référentiel films'!$A$28,"’","'"),SUBSTITUTE(F4,"’","'"))),'Référentiel films'!$B$28,""),IF(ISNUMBER(SEARCH(SUBSTITUTE('Référentiel films'!$A$29,"’","'"),SUBSTITUTE(F4,"’","'"))),'Référentiel films'!$B$29,""),IF(ISNUMBER(SEARCH(SUBSTITUTE('Référentiel films'!$A$30,"’","'"),SUBSTITUTE(F4,"’","'"))),'Référentiel films'!$B$30,""),IF(ISNUMBER(SEARCH(SUBSTITUTE('Référentiel films'!$A$31,"’","'"),SUBSTITUTE(F4,"’","'"))),'Référentiel films'!$B$31,""),IF(ISNUMBER(SEARCH(SUBSTITUTE('Référentiel films'!$A$32,"’","'"),SUBSTITUTE(F4,"’","'"))),'Référentiel films'!$B$32,""),IF(ISNUMBER(SEARCH(SUBSTITUTE('Référentiel films'!$A$33,"’","'"),SUBSTITUTE(F4,"’","'"))),'Référentiel films'!$B$33,""),IF(ISNUMBER(SEARCH(SUBSTITUTE('Référentiel films'!$A$34,"’","'"),SUBSTITUTE(F4,"’","'"))),'Référentiel films'!$B$34,""),IF(ISNUMBER(SEARCH(SUBSTITUTE('Référentiel films'!$A$35,"’","'"),SUBSTITUTE(F4,"’","'"))),'Référentiel films'!$B$35,""),IF(ISNUMBER(SEARCH(SUBSTITUTE('Référentiel films'!$A$36,"’","'"),SUBSTITUTE(F4,"’","'"))),'Référentiel films'!$B$36,""),IF(ISNUMBER(SEARCH(SUBSTITUTE('Référentiel films'!$A$37,"’","'"),SUBSTITUTE(F4,"’","'"))),'Référentiel films'!$B$37,""),IF(ISNUMBER(SEARCH(SUBSTITUTE('Référentiel films'!$A$38,"’","'"),SUBSTITUTE(F4,"’","'"))),'Référentiel films'!$B$38,""),IF(ISNUMBER(SEARCH(SUBSTITUTE('Référentiel films'!$A$39,"’","'"),SUBSTITUTE(F4,"’","'"))),'Référentiel films'!$B$39,""),IF(ISNUMBER(SEARCH(SUBSTITUTE('Référentiel films'!$A$40,"’","'"),SUBSTITUTE(F4,"’","'"))),'Référentiel films'!$B$40,""),IF(ISNUMBER(SEARCH(SUBSTITUTE('Référentiel films'!$A$41,"’","'"),SUBSTITUTE(F4,"’","'"))),'Référentiel films'!$B$41,"")))
A5: 1948 | B5: 1947-1960 | C5: Réforme monétaire de l'Allemagne de l'Ouest, acte fondateur du "miracle économique" comme de la séparation entre blocs est et ouest. Ludwig Erhard, professeur d'économie, développe l'économie sociale de marché. Le Plan Marshall participe à la relance de l'économie ouest-allemande. Blocus de Berlin par les soviétiques, l'une des premières crises de la Guerre Froide. Un pont aérien est mise en place à l'initiative des Etats-Unis et de la Grande-Bretagne. | D5: Le film de Rossellini Allemagne année zéro offre une vision réaliste et critique de l'Allemagne en ruine | H5: Le blocus de Berlin en 3 minutes | I5: Allemagne_annee_0_Reichstag.mp4 | J5: Allemagne année zéro de Rossellini (1948) ) Le protagoniste Edmund tente de vendre un enregistrement d'un discours d'Hitler sur disque à des soldats alliés. La voix du Fürher se met à résonner dans les ruines du Reichstag, siège du parlement incendié en 1933 | K5: Comment Rossellini traduit-il une relation complexe avec l'Histoire, entre fascination, terreur, et hantise ? | U5: =IF(F5="","",_xlfn.TEXTJOIN("; ",TRUE(),IF(ISNUMBER(SEARCH(SUBSTITUTE('Référentiel films'!$A$2,"’","'"),SUBSTITUTE(F5,"’","'"))),'Référentiel films'!$B$2,""),IF(ISNUMBER(SEARCH(SUBSTITUTE('Référentiel films'!$A$3,"’","'"),SUBSTITUTE(F5,"’","'"))),'Référentiel films'!$B$3,""),IF(ISNUMBER(SEARCH(SUBSTITUTE('Référentiel films'!$A$4,"’","'"),SUBSTITUTE(F5,"’","'"))),'Référentiel films'!$B$4,""),IF(ISNUMBER(SEARCH(SUBSTITUTE('Référentiel films'!$A$5,"’","'"),SUBSTITUTE(F5,"’","'"))),'Référentiel films'!$B$5,""),IF(ISNUMBER(SEARCH(SUBSTITUTE('Référentiel films'!$A$6,"’","'"),SUBSTITUTE(F5,"’","'"))),'Référentiel films'!$B$6,""),IF(ISNUMBER(SEARCH(SUBSTITUTE('Référentiel films'!$A$7,"’","'"),SUBSTITUTE(F5,"’","'"))),'Référentiel films'!$B$7,""),IF(ISNUMBER(SEARCH(SUBSTITUTE('Référentiel films'!$A$8,"’","'"),SUBSTITUTE(F5,"’","'"))),'Référentiel films'!$B$8,""),IF(ISNUMBER(SEARCH(SUBSTITUTE('Référentiel films'!$A$9,"’","'"),SUBSTITUTE(F5,"’","'"))),'Référentiel films'!$B$9,""),IF(ISNUMBER(SEARCH(SUBSTITUTE('Référentiel films'!$A$10,"’","'"),SUBSTITUTE(F5,"’","'"))),'Référentiel films'!$B$10,""),IF(ISNUMBER(SEARCH(SUBSTITUTE('Référentiel films'!$A$11,"’","'"),SUBSTITUTE(F5,"’","'"))),'Référentiel films'!$B$11,""),IF(ISNUMBER(SEARCH(SUBSTITUTE('Référentiel films'!$A$12,"’","'"),SUBSTITUTE(F5,"’","'"))),'Référentiel films'!$B$12,""),IF(ISNUMBER(SEARCH(SUBSTITUTE('Référentiel films'!$A$13,"’","'"),SUBSTITUTE(F5,"’","'"))),'Référentiel films'!$B$13,""),IF(ISNUMBER(SEARCH(SUBSTITUTE('Référentiel films'!$A$14,"’","'"),SUBSTITUTE(F5,"’","'"))),'Référentiel films'!$B$14,""),IF(ISNUMBER(SEARCH(SUBSTITUTE('Référentiel films'!$A$15,"’","'"),SUBSTITUTE(F5,"’","'"))),'Référentiel films'!$B$15,""),IF(ISNUMBER(SEARCH(SUBSTITUTE('Référentiel films'!$A$16,"’","'"),SUBSTITUTE(F5,"’","'"))),'Référentiel films'!$B$16,""),IF(ISNUMBER(SEARCH(SUBSTITUTE('Référentiel films'!$A$17,"’","'"),SUBSTITUTE(F5,"’","'"))),'Référentiel films'!$B$17,""),IF(ISNUMBER(SEARCH(SUBSTITUTE('Référentiel films'!$A$18,"’","'"),SUBSTITUTE(F5,"’","'"))),'Référentiel films'!$B$18,""),IF(ISNUMBER(SEARCH(SUBSTITUTE('Référentiel films'!$A$19,"’","'"),SUBSTITUTE(F5,"’","'"))),'Référentiel films'!$B$19,""),IF(ISNUMBER(SEARCH(SUBSTITUTE('Référentiel films'!$A$20,"’","'"),SUBSTITUTE(F5,"’","'"))),'Référentiel films'!$B$20,""),IF(ISNUMBER(SEARCH(SUBSTITUTE('Référentiel films'!$A$21,"’","'"),SUBSTITUTE(F5,"’","'"))),'Référentiel films'!$B$21,""),IF(ISNUMBER(SEARCH(SUBSTITUTE('Référentiel films'!$A$22,"’","'"),SUBSTITUTE(F5,"’","'"))),'Référentiel films'!$B$22,""),IF(ISNUMBER(SEARCH(SUBSTITUTE('Référentiel films'!$A$23,"’","'"),SUBSTITUTE(F5,"’","'"))),'Référentiel films'!$B$23,""),IF(ISNUMBER(SEARCH(SUBSTITUTE('Référentiel films'!$A$24,"’","'"),SUBSTITUTE(F5,"’","'"))),'Référentiel films'!$B$24,""),IF(ISNUMBER(SEARCH(SUBSTITUTE('Référentiel films'!$A$25,"’","'"),SUBSTITUTE(F5,"’","'"))),'Référentiel films'!$B$25,""),IF(ISNUMBER(SEARCH(SUBSTITUTE('Référentiel films'!$A$26,"’","'"),SUBSTITUTE(F5,"’","'"))),'Référentiel films'!$B$26,""),IF(ISNUMBER(SEARCH(SUBSTITUTE('Référentiel films'!$A$27,"’","'"),SUBSTITUTE(F5,"’","'"))),'Référentiel films'!$B$27,""),IF(ISNUMBER(SEARCH(SUBSTITUTE('Référentiel films'!$A$28,"’","'"),SUBSTITUTE(F5,"’","'"))),'Référentiel films'!$B$28,""),IF(ISNUMBER(SEARCH(SUBSTITUTE('Référentiel films'!$A$29,"’","'"),SUBSTITUTE(F5,"’","'"))),'Référentiel films'!$B$29,""),IF(ISNUMBER(SEARCH(SUBSTITUTE('Référentiel films'!$A$30,"’","'"),SUBSTITUTE(F5,"’","'"))),'Référentiel films'!$B$30,""),IF(ISNUMBER(SEARCH(SUBSTITUTE('Référentiel films'!$A$31,"’","'"),SUBSTITUTE(F5,"’","'"))),'Référentiel films'!$B$31,""),IF(ISNUMBER(SEARCH(SUBSTITUTE('Référentiel films'!$A$32,"’","'"),SUBSTITUTE(F5,"’","'"))),'Référentiel films'!$B$32,""),IF(ISNUMBER(SEARCH(SUBSTITUTE('Référentiel films'!$A$33,"’","'"),SUBSTITUTE(F5,"’","'"))),'Référentiel films'!$B$33,""),IF(ISNUMBER(SEARCH(SUBSTITUTE('Référentiel films'!$A$34,"’","'"),SUBSTITUTE(F5,"’","'"))),'Référentiel films'!$B$34,""),IF(ISNUMBER(SEARCH(SUBSTITUTE('Référentiel films'!$A$35,"’","'"),SUBSTITUTE(F5,"’","'"))),'Référentiel films'!$B$35,""),IF(ISNUMBER(SEARCH(SUBSTITUTE('Référentiel films'!$A$36,"’","'"),SUBSTITUTE(F5,"’","'"))),'Référentiel films'!$B$36,""),IF(ISNUMBER(SEARCH(SUBSTITUTE('Référentiel films'!$A$37,"’","'"),SUBSTITUTE(F5,"’","'"))),'Référentiel films'!$B$37,""),IF(ISNUMBER(SEARCH(SUBSTITUTE('Référentiel films'!$A$38,"’","'"),SUBSTITUTE(F5,"’","'"))),'Référentiel films'!$B$38,""),IF(ISNUMBER(SEARCH(SUBSTITUTE('Référentiel films'!$A$39,"’","'"),SUBSTITUTE(F5,"’","'"))),'Référentiel films'!$B$39,""),IF(ISNUMBER(SEARCH(SUBSTITUTE('Référentiel films'!$A$40,"’","'"),SUBSTITUTE(F5,"’","'"))),'Référentiel films'!$B$40,""),IF(ISNUMBER(SEARCH(SUBSTITUTE('Référentiel films'!$A$41,"’","'"),SUBSTITUTE(F5,"’","'"))),'Référentiel films'!$B$41,"")))
A6: 1949 | B6: 1947-1960 | C6: Création de l'OTAN. Création de la RFA. Konrad Adenauer est élu chancelier fédéral avec une courte majorité. La division de l'Allemande en deux états indépendants est reconnue par la communauté internationale. | D6: Avec sa femme Helene Weigel, Brecht fonde le Berliner Ensemble à Berlin-Est, où il crée Mère courage et ses enfants. Thomas Mann donne des conférences en Allemagne de l'ouest et en République démocratique (voir le film de Pavec Pwalikoscki Fatherland (2026)) | H6: Bande Annonce de Fatherland de Pavel Pawlikoski | M6: Adenauer.jpeg | N6: Portrait d'Adenauer | U6: =IF(F6="","",_xlfn.TEXTJOIN("; ",TRUE(),IF(ISNUMBER(SEARCH(SUBSTITUTE('Référentiel films'!$A$2,"’","'"),SUBSTITUTE(F6,"’","'"))),'Référentiel films'!$B$2,""),IF(ISNUMBER(SEARCH(SUBSTITUTE('Référentiel films'!$A$3,"’","'"),SUBSTITUTE(F6,"’","'"))),'Référentiel films'!$B$3,""),IF(ISNUMBER(SEARCH(SUBSTITUTE('Référentiel films'!$A$4,"’","'"),SUBSTITUTE(F6,"’","'"))),'Référentiel films'!$B$4,""),IF(ISNUMBER(SEARCH(SUBSTITUTE('Référentiel films'!$A$5,"’","'"),SUBSTITUTE(F6,"’","'"))),'Référentiel films'!$B$5,""),IF(ISNUMBER(SEARCH(SUBSTITUTE('Référentiel films'!$A$6,"’","'"),SUBSTITUTE(F6,"’","'"))),'Référentiel films'!$B$6,""),IF(ISNUMBER(SEARCH(SUBSTITUTE('Référentiel films'!$A$7,"’","'"),SUBSTITUTE(F6,"’","'"))),'Référentiel films'!$B$7,""),IF(ISNUMBER(SEARCH(SUBSTITUTE('Référentiel films'!$A$8,"’","'"),SUBSTITUTE(F6,"’","'"))),'Référentiel films'!$B$8,""),IF(ISNUMBER(SEARCH(SUBSTITUTE('Référentiel films'!$A$9,"’","'"),SUBSTITUTE(F6,"’","'"))),'Référentiel films'!$B$9,""),IF(ISNUMBER(SEARCH(SUBSTITUTE('Référentiel films'!$A$10,"’","'"),SUBSTITUTE(F6,"’","'"))),'Référentiel films'!$B$10,""),IF(ISNUMBER(SEARCH(SUBSTITUTE('Référentiel films'!$A$11,"’","'"),SUBSTITUTE(F6,"’","'"))),'Référentiel films'!$B$11,""),IF(ISNUMBER(SEARCH(SUBSTITUTE('Référentiel films'!$A$12,"’","'"),SUBSTITUTE(F6,"’","'"))),'Référentiel films'!$B$12,""),IF(ISNUMBER(SEARCH(SUBSTITUTE('Référentiel films'!$A$13,"’","'"),SUBSTITUTE(F6,"’","'"))),'Référentiel films'!$B$13,""),IF(ISNUMBER(SEARCH(SUBSTITUTE('Référentiel films'!$A$14,"’","'"),SUBSTITUTE(F6,"’","'"))),'Référentiel films'!$B$14,""),IF(ISNUMBER(SEARCH(SUBSTITUTE('Référentiel films'!$A$15,"’","'"),SUBSTITUTE(F6,"’","'"))),'Référentiel films'!$B$15,""),IF(ISNUMBER(SEARCH(SUBSTITUTE('Référentiel films'!$A$16,"’","'"),SUBSTITUTE(F6,"’","'"))),'Référentiel films'!$B$16,""),IF(ISNUMBER(SEARCH(SUBSTITUTE('Référentiel films'!$A$17,"’","'"),SUBSTITUTE(F6,"’","'"))),'Référentiel films'!$B$17,""),IF(ISNUMBER(SEARCH(SUBSTITUTE('Référentiel films'!$A$18,"’","'"),SUBSTITUTE(F6,"’","'"))),'Référentiel films'!$B$18,""),IF(ISNUMBER(SEARCH(SUBSTITUTE('Référentiel films'!$A$19,"’","'"),SUBSTITUTE(F6,"’","'"))),'Référentiel films'!$B$19,""),IF(ISNUMBER(SEARCH(SUBSTITUTE('Référentiel films'!$A$20,"’","'"),SUBSTITUTE(F6,"’","'"))),'Référentiel films'!$B$20,""),IF(ISNUMBER(SEARCH(SUBSTITUTE('Référentiel films'!$A$21,"’","'"),SUBSTITUTE(F6,"’","'"))),'Référentiel films'!$B$21,""),IF(ISNUMBER(SEARCH(SUBSTITUTE('Référentiel films'!$A$22,"’","'"),SUBSTITUTE(F6,"’","'"))),'Référentiel films'!$B$22,""),IF(ISNUMBER(SEARCH(SUBSTITUTE('Référentiel films'!$A$23,"’","'"),SUBSTITUTE(F6,"’","'"))),'Référentiel films'!$B$23,""),IF(ISNUMBER(SEARCH(SUBSTITUTE('Référentiel films'!$A$24,"’","'"),SUBSTITUTE(F6,"’","'"))),'Référentiel films'!$B$24,""),IF(ISNUMBER(SEARCH(SUBSTITUTE('Référentiel films'!$A$25,"’","'"),SUBSTITUTE(F6,"’","'"))),'Référentiel films'!$B$25,""),IF(ISNUMBER(SEARCH(SUBSTITUTE('Référentiel films'!$A$26,"’","'"),SUBSTITUTE(F6,"’","'"))),'Référentiel films'!$B$26,""),IF(ISNUMBER(SEARCH(SUBSTITUTE('Référentiel films'!$A$27,"’","'"),SUBSTITUTE(F6,"’","'"))),'Référentiel films'!$B$27,""),IF(ISNUMBER(SEARCH(SUBSTITUTE('Référentiel films'!$A$28,"’","'"),SUBSTITUTE(F6,"’","'"))),'Référentiel films'!$B$28,""),IF(ISNUMBER(SEARCH(SUBSTITUTE('Référentiel films'!$A$29,"’","'"),SUBSTITUTE(F6,"’","'"))),'Référentiel films'!$B$29,""),IF(ISNUMBER(SEARCH(SUBSTITUTE('Référentiel films'!$A$30,"’","'"),SUBSTITUTE(F6,"’","'"))),'Référentiel films'!$B$30,""),IF(ISNUMBER(SEARCH(SUBSTITUTE('Référentiel films'!$A$31,"’","'"),SUBSTITUTE(F6,"’","'"))),'Référentiel films'!$B$31,""),IF(ISNUMBER(SEARCH(SUBSTITUTE('Référentiel films'!$A$32,"’","'"),SUBSTITUTE(F6,"’","'"))),'Référentiel films'!$B$32,""),IF(ISNUMBER(SEARCH(SUBSTITUTE('Référentiel films'!$A$33,"’","'"),SUBSTITUTE(F6,"’","'"))),'Référentiel films'!$B$33,""),IF(ISNUMBER(SEARCH(SUBSTITUTE('Référentiel films'!$A$34,"’","'"),SUBSTITUTE(F6,"’","'"))),'Référentiel films'!$B$34,""),IF(ISNUMBER(SEARCH(SUBSTITUTE('Référentiel films'!$A$35,"’","'"),SUBSTITUTE(F6,"’","'"))),'Référentiel films'!$B$35,""),IF(ISNUMBER(SEARCH(SUBSTITUTE('Référentiel films'!$A$36,"’","'"),SUBSTITUTE(F6,"’","'"))),'Référentiel films'!$B$36,""),IF(ISNUMBER(SEARCH(SUBSTITUTE('Référentiel films'!$A$37,"’","'"),SUBSTITUTE(F6,"’","'"))),'Référentiel films'!$B$37,""),IF(ISNUMBER(SEARCH(SUBSTITUTE('Référentiel films'!$A$38,"’","'"),SUBSTITUTE(F6,"’","'"))),'Référentiel films'!$B$38,""),IF(ISNUMBER(SEARCH(SUBSTITUTE('Référentiel films'!$A$39,"’","'"),SUBSTITUTE(F6,"’","'"))),'Référentiel films'!$B$39,""),IF(ISNUMBER(SEARCH(SUBSTITUTE('Référentiel films'!$A$40,"’","'"),SUBSTITUTE(F6,"’","'"))),'Référentiel films'!$B$40,""),IF(ISNUMBER(SEARCH(SUBSTITUTE('Référentiel films'!$A$41,"’","'"),SUBSTITUTE(F6,"’","'"))),'Référentiel films'!$B$41,"")))
A7: 1950 | B7: 1947-1960 | E7: La mère de Fassbinder Lisolette Eder, née Pempeit, dite aussi Lilo Pempeit, est hospitalisée pour cause de tuberculose. | M7: Adenauer.jpeg | N7: Portrait d'Adenauer | R7: ,,,,,,,,,,,,,,,,,,,,,,,,,,,,,,,,,,,,,,,,,,,,,,,,,,,,,,,,,,,,,,,,,,,,,,,,,,,,,,,,,,,,,,,,,,,,,,,,,,,,,,,,,,,,,,,,,,,,,,,,,,,,,,,,,,,,,,,,,,,,,,,,,,,,,,,,,,,,,,,,,,,,,,,,,,,,,,,,,,,,,,,,,,,,,,,,,,,,,,,,,,,,,,,,,,,,,,,,,,,,, | U7: =IF(F7="","",_xlfn.TEXTJOIN("; ",TRUE(),IF(ISNUMBER(SEARCH(SUBSTITUTE('Référentiel films'!$A$2,"’","'"),SUBSTITUTE(F7,"’","'"))),'Référentiel films'!$B$2,""),IF(ISNUMBER(SEARCH(SUBSTITUTE('Référentiel films'!$A$3,"’","'"),SUBSTITUTE(F7,"’","'"))),'Référentiel films'!$B$3,""),IF(ISNUMBER(SEARCH(SUBSTITUTE('Référentiel films'!$A$4,"’","'"),SUBSTITUTE(F7,"’","'"))),'Référentiel films'!$B$4,""),IF(ISNUMBER(SEARCH(SUBSTITUTE('Référentiel films'!$A$5,"’","'"),SUBSTITUTE(F7,"’","'"))),'Référentiel films'!$B$5,""),IF(ISNUMBER(SEARCH(SUBSTITUTE('Référentiel films'!$A$6,"’","'"),SUBSTITUTE(F7,"’","'"))),'Référentiel films'!$B$6,""),IF(ISNUMBER(SEARCH(SUBSTITUTE('Référentiel films'!$A$7,"’","'"),SUBSTITUTE(F7,"’","'"))),'Référentiel films'!$B$7,""),IF(ISNUMBER(SEARCH(SUBSTITUTE('Référentiel films'!$A$8,"’","'"),SUBSTITUTE(F7,"’","'"))),'Référentiel films'!$B$8,""),IF(ISNUMBER(SEARCH(SUBSTITUTE('Référentiel films'!$A$9,"’","'"),SUBSTITUTE(F7,"’","'"))),'Référentiel films'!$B$9,""),IF(ISNUMBER(SEARCH(SUBSTITUTE('Référentiel films'!$A$10,"’","'"),SUBSTITUTE(F7,"’","'"))),'Référentiel films'!$B$10,""),IF(ISNUMBER(SEARCH(SUBSTITUTE('Référentiel films'!$A$11,"’","'"),SUBSTITUTE(F7,"’","'"))),'Référentiel films'!$B$11,""),IF(ISNUMBER(SEARCH(SUBSTITUTE('Référentiel films'!$A$12,"’","'"),SUBSTITUTE(F7,"’","'"))),'Référentiel films'!$B$12,""),IF(ISNUMBER(SEARCH(SUBSTITUTE('Référentiel films'!$A$13,"’","'"),SUBSTITUTE(F7,"’","'"))),'Référentiel films'!$B$13,""),IF(ISNUMBER(SEARCH(SUBSTITUTE('Référentiel films'!$A$14,"’","'"),SUBSTITUTE(F7,"’","'"))),'Référentiel films'!$B$14,""),IF(ISNUMBER(SEARCH(SUBSTITUTE('Référentiel films'!$A$15,"’","'"),SUBSTITUTE(F7,"’","'"))),'Référentiel films'!$B$15,""),IF(ISNUMBER(SEARCH(SUBSTITUTE('Référentiel films'!$A$16,"’","'"),SUBSTITUTE(F7,"’","'"))),'Référentiel films'!$B$16,""),IF(ISNUMBER(SEARCH(SUBSTITUTE('Référentiel films'!$A$17,"’","'"),SUBSTITUTE(F7,"’","'"))),'Référentiel films'!$B$17,""),IF(ISNUMBER(SEARCH(SUBSTITUTE('Référentiel films'!$A$18,"’","'"),SUBSTITUTE(F7,"’","'"))),'Référentiel films'!$B$18,""),IF(ISNUMBER(SEARCH(SUBSTITUTE('Référentiel films'!$A$19,"’","'"),SUBSTITUTE(F7,"’","'"))),'Référentiel films'!$B$19,""),IF(ISNUMBER(SEARCH(SUBSTITUTE('Référentiel films'!$A$20,"’","'"),SUBSTITUTE(F7,"’","'"))),'Référentiel films'!$B$20,""),IF(ISNUMBER(SEARCH(SUBSTITUTE('Référentiel films'!$A$21,"’","'"),SUBSTITUTE(F7,"’","'"))),'Référentiel films'!$B$21,""),IF(ISNUMBER(SEARCH(SUBSTITUTE('Référentiel films'!$A$22,"’","'"),SUBSTITUTE(F7,"’","'"))),'Référentiel films'!$B$22,""),IF(ISNUMBER(SEARCH(SUBSTITUTE('Référentiel films'!$A$23,"’","'"),SUBSTITUTE(F7,"’","'"))),'Référentiel films'!$B$23,""),IF(ISNUMBER(SEARCH(SUBSTITUTE('Référentiel films'!$A$24,"’","'"),SUBSTITUTE(F7,"’","'"))),'Référentiel films'!$B$24,""),IF(ISNUMBER(SEARCH(SUBSTITUTE('Référentiel films'!$A$25,"’","'"),SUBSTITUTE(F7,"’","'"))),'Référentiel films'!$B$25,""),IF(ISNUMBER(SEARCH(SUBSTITUTE('Référentiel films'!$A$26,"’","'"),SUBSTITUTE(F7,"’","'"))),'Référentiel films'!$B$26,""),IF(ISNUMBER(SEARCH(SUBSTITUTE('Référentiel films'!$A$27,"’","'"),SUBSTITUTE(F7,"’","'"))),'Référentiel films'!$B$27,""),IF(ISNUMBER(SEARCH(SUBSTITUTE('Référentiel films'!$A$28,"’","'"),SUBSTITUTE(F7,"’","'"))),'Référentiel films'!$B$28,""),IF(ISNUMBER(SEARCH(SUBSTITUTE('Référentiel films'!$A$29,"’","'"),SUBSTITUTE(F7,"’","'"))),'Référentiel films'!$B$29,""),IF(ISNUMBER(SEARCH(SUBSTITUTE('Référentiel films'!$A$30,"’","'"),SUBSTITUTE(F7,"’","'"))),'Référentiel films'!$B$30,""),IF(ISNUMBER(SEARCH(SUBSTITUTE('Référentiel films'!$A$31,"’","'"),SUBSTITUTE(F7,"’","'"))),'Référentiel films'!$B$31,""),IF(ISNUMBER(SEARCH(SUBSTITUTE('Référentiel films'!$A$32,"’","'"),SUBSTITUTE(F7,"’","'"))),'Référentiel films'!$B$32,""),IF(ISNUMBER(SEARCH(SUBSTITUTE('Référentiel films'!$A$33,"’","'"),SUBSTITUTE(F7,"’","'"))),'Référentiel films'!$B$33,""),IF(ISNUMBER(SEARCH(SUBSTITUTE('Référentiel films'!$A$34,"’","'"),SUBSTITUTE(F7,"’","'"))),'Référentiel films'!$B$34,""),IF(ISNUMBER(SEARCH(SUBSTITUTE('Référentiel films'!$A$35,"’","'"),SUBSTITUTE(F7,"’","'"))),'Référentiel films'!$B$35,""),IF(ISNUMBER(SEARCH(SUBSTITUTE('Référentiel films'!$A$36,"’","'"),SUBSTITUTE(F7,"’","'"))),'Référentiel films'!$B$36,""),IF(ISNUMBER(SEARCH(SUBSTITUTE('Référentiel films'!$A$37,"’","'"),SUBSTITUTE(F7,"’","'"))),'Référentiel films'!$B$37,""),IF(ISNUMBER(SEARCH(SUBSTITUTE('Référentiel films'!$A$38,"’","'"),SUBSTITUTE(F7,"’","'"))),'Référentiel films'!$B$38,""),IF(ISNUMBER(SEARCH(SUBSTITUTE('Référentiel films'!$A$39,"’","'"),SUBSTITUTE(F7,"’","'"))),'Référentiel films'!$B$39,""),IF(ISNUMBER(SEARCH(SUBSTITUTE('Référentiel films'!$A$40,"’","'"),SUBSTITUTE(F7,"’","'"))),'Référentiel films'!$B$40,""),IF(ISNUMBER(SEARCH(SUBSTITUTE('Référentiel films'!$A$41,"’","'"),SUBSTITUTE(F7,"’","'"))),'Référentiel films'!$B$41,"")))
A8: 1951 | B8: 1947-1960 | C8: Création du Traité de "la communauté du charbon et de l'acier", début de la construction européenne autour de 6 pays. | E8: Divorce des parents. Le père de RWF, Helmut Fassbinder, s'installe à Cologne. RWF reste à Munich avec sa mère. | M8: Adenauer.jpeg | N8: Portrait d'Adenauer | U8: =IF(F8="","",_xlfn.TEXTJOIN("; ",TRUE(),IF(ISNUMBER(SEARCH(SUBSTITUTE('Référentiel films'!$A$2,"’","'"),SUBSTITUTE(F8,"’","'"))),'Référentiel films'!$B$2,""),IF(ISNUMBER(SEARCH(SUBSTITUTE('Référentiel films'!$A$3,"’","'"),SUBSTITUTE(F8,"’","'"))),'Référentiel films'!$B$3,""),IF(ISNUMBER(SEARCH(SUBSTITUTE('Référentiel films'!$A$4,"’","'"),SUBSTITUTE(F8,"’","'"))),'Référentiel films'!$B$4,""),IF(ISNUMBER(SEARCH(SUBSTITUTE('Référentiel films'!$A$5,"’","'"),SUBSTITUTE(F8,"’","'"))),'Référentiel films'!$B$5,""),IF(ISNUMBER(SEARCH(SUBSTITUTE('Référentiel films'!$A$6,"’","'"),SUBSTITUTE(F8,"’","'"))),'Référentiel films'!$B$6,""),IF(ISNUMBER(SEARCH(SUBSTITUTE('Référentiel films'!$A$7,"’","'"),SUBSTITUTE(F8,"’","'"))),'Référentiel films'!$B$7,""),IF(ISNUMBER(SEARCH(SUBSTITUTE('Référentiel films'!$A$8,"’","'"),SUBSTITUTE(F8,"’","'"))),'Référentiel films'!$B$8,""),IF(ISNUMBER(SEARCH(SUBSTITUTE('Référentiel films'!$A$9,"’","'"),SUBSTITUTE(F8,"’","'"))),'Référentiel films'!$B$9,""),IF(ISNUMBER(SEARCH(SUBSTITUTE('Référentiel films'!$A$10,"’","'"),SUBSTITUTE(F8,"’","'"))),'Référentiel films'!$B$10,""),IF(ISNUMBER(SEARCH(SUBSTITUTE('Référentiel films'!$A$11,"’","'"),SUBSTITUTE(F8,"’","'"))),'Référentiel films'!$B$11,""),IF(ISNUMBER(SEARCH(SUBSTITUTE('Référentiel films'!$A$12,"’","'"),SUBSTITUTE(F8,"’","'"))),'Référentiel films'!$B$12,""),IF(ISNUMBER(SEARCH(SUBSTITUTE('Référentiel films'!$A$13,"’","'"),SUBSTITUTE(F8,"’","'"))),'Référentiel films'!$B$13,""),IF(ISNUMBER(SEARCH(SUBSTITUTE('Référentiel films'!$A$14,"’","'"),SUBSTITUTE(F8,"’","'"))),'Référentiel films'!$B$14,""),IF(ISNUMBER(SEARCH(SUBSTITUTE('Référentiel films'!$A$15,"’","'"),SUBSTITUTE(F8,"’","'"))),'Référentiel films'!$B$15,""),IF(ISNUMBER(SEARCH(SUBSTITUTE('Référentiel films'!$A$16,"’","'"),SUBSTITUTE(F8,"’","'"))),'Référentiel films'!$B$16,""),IF(ISNUMBER(SEARCH(SUBSTITUTE('Référentiel films'!$A$17,"’","'"),SUBSTITUTE(F8,"’","'"))),'Référentiel films'!$B$17,""),IF(ISNUMBER(SEARCH(SUBSTITUTE('Référentiel films'!$A$18,"’","'"),SUBSTITUTE(F8,"’","'"))),'Référentiel films'!$B$18,""),IF(ISNUMBER(SEARCH(SUBSTITUTE('Référentiel films'!$A$19,"’","'"),SUBSTITUTE(F8,"’","'"))),'Référentiel films'!$B$19,""),IF(ISNUMBER(SEARCH(SUBSTITUTE('Référentiel films'!$A$20,"’","'"),SUBSTITUTE(F8,"’","'"))),'Référentiel films'!$B$20,""),IF(ISNUMBER(SEARCH(SUBSTITUTE('Référentiel films'!$A$21,"’","'"),SUBSTITUTE(F8,"’","'"))),'Référentiel films'!$B$21,""),IF(ISNUMBER(SEARCH(SUBSTITUTE('Référentiel films'!$A$22,"’","'"),SUBSTITUTE(F8,"’","'"))),'Référentiel films'!$B$22,""),IF(ISNUMBER(SEARCH(SUBSTITUTE('Référentiel films'!$A$23,"’","'"),SUBSTITUTE(F8,"’","'"))),'Référentiel films'!$B$23,""),IF(ISNUMBER(SEARCH(SUBSTITUTE('Référentiel films'!$A$24,"’","'"),SUBSTITUTE(F8,"’","'"))),'Référentiel films'!$B$24,""),IF(ISNUMBER(SEARCH(SUBSTITUTE('Référentiel films'!$A$25,"’","'"),SUBSTITUTE(F8,"’","'"))),'Référentiel films'!$B$25,""),IF(ISNUMBER(SEARCH(SUBSTITUTE('Référentiel films'!$A$26,"’","'"),SUBSTITUTE(F8,"’","'"))),'Référentiel films'!$B$26,""),IF(ISNUMBER(SEARCH(SUBSTITUTE('Référentiel films'!$A$27,"’","'"),SUBSTITUTE(F8,"’","'"))),'Référentiel films'!$B$27,""),IF(ISNUMBER(SEARCH(SUBSTITUTE('Référentiel films'!$A$28,"’","'"),SUBSTITUTE(F8,"’","'"))),'Référentiel films'!$B$28,""),IF(ISNUMBER(SEARCH(SUBSTITUTE('Référentiel films'!$A$29,"’","'"),SUBSTITUTE(F8,"’","'"))),'Référentiel films'!$B$29,""),IF(ISNUMBER(SEARCH(SUBSTITUTE('Référentiel films'!$A$30,"’","'"),SUBSTITUTE(F8,"’","'"))),'Référentiel films'!$B$30,""),IF(ISNUMBER(SEARCH(SUBSTITUTE('Référentiel films'!$A$31,"’","'"),SUBSTITUTE(F8,"’","'"))),'Référentiel films'!$B$31,""),IF(ISNUMBER(SEARCH(SUBSTITUTE('Référentiel films'!$A$32,"’","'"),SUBSTITUTE(F8,"’","'"))),'Référentiel films'!$B$32,""),IF(ISNUMBER(SEARCH(SUBSTITUTE('Référentiel films'!$A$33,"’","'"),SUBSTITUTE(F8,"’","'"))),'Référentiel films'!$B$33,""),IF(ISNUMBER(SEARCH(SUBSTITUTE('Référentiel films'!$A$34,"’","'"),SUBSTITUTE(F8,"’","'"))),'Référentiel films'!$B$34,""),IF(ISNUMBER(SEARCH(SUBSTITUTE('Référentiel films'!$A$35,"’","'"),SUBSTITUTE(F8,"’","'"))),'Référentiel films'!$B$35,""),IF(ISNUMBER(SEARCH(SUBSTITUTE('Référentiel films'!$A$36,"’","'"),SUBSTITUTE(F8,"’","'"))),'Référentiel films'!$B$36,""),IF(ISNUMBER(SEARCH(SUBSTITUTE('Référentiel films'!$A$37,"’","'"),SUBSTITUTE(F8,"’","'"))),'Référentiel films'!$B$37,""),IF(ISNUMBER(SEARCH(SUBSTITUTE('Référentiel films'!$A$38,"’","'"),SUBSTITUTE(F8,"’","'"))),'Référentiel films'!$B$38,""),IF(ISNUMBER(SEARCH(SUBSTITUTE('Référentiel films'!$A$39,"’","'"),SUBSTITUTE(F8,"’","'"))),'Référentiel films'!$B$39,""),IF(ISNUMBER(SEARCH(SUBSTITUTE('Référentiel films'!$A$40,"’","'"),SUBSTITUTE(F8,"’","'"))),'Référentiel films'!$B$40,""),IF(ISNUMBER(SEARCH(SUBSTITUTE('Référentiel films'!$A$41,"’","'"),SUBSTITUTE(F8,"’","'"))),'Référentiel films'!$B$41,"")))
A9: 1952 | B9: 1947-1960 | C9: Traité de réparation avec Israël signé par Adenauer. | D9: Première émission de télévision dans le nord et l'ouest de la RFA | E9: La mère de RWF l'inscrit dans une école Rudolf Steiner. Nbx séjours de la mère à l'hopital ou en sanatorium. RWF est confié à des voisins ou parents. Il commence à fréquenter assidument les salles de cinéma. | M9: Fassbinder_enfant.jpeg | N9: Fassbinder enfant | O9: Adenauer.jpeg | P9: Portrait d'Adenauer | U9: =IF(F9="","",_xlfn.TEXTJOIN("; ",TRUE(),IF(ISNUMBER(SEARCH(SUBSTITUTE('Référentiel films'!$A$2,"’","'"),SUBSTITUTE(F9,"’","'"))),'Référentiel films'!$B$2,""),IF(ISNUMBER(SEARCH(SUBSTITUTE('Référentiel films'!$A$3,"’","'"),SUBSTITUTE(F9,"’","'"))),'Référentiel films'!$B$3,""),IF(ISNUMBER(SEARCH(SUBSTITUTE('Référentiel films'!$A$4,"’","'"),SUBSTITUTE(F9,"’","'"))),'Référentiel films'!$B$4,""),IF(ISNUMBER(SEARCH(SUBSTITUTE('Référentiel films'!$A$5,"’","'"),SUBSTITUTE(F9,"’","'"))),'Référentiel films'!$B$5,""),IF(ISNUMBER(SEARCH(SUBSTITUTE('Référentiel films'!$A$6,"’","'"),SUBSTITUTE(F9,"’","'"))),'Référentiel films'!$B$6,""),IF(ISNUMBER(SEARCH(SUBSTITUTE('Référentiel films'!$A$7,"’","'"),SUBSTITUTE(F9,"’","'"))),'Référentiel films'!$B$7,""),IF(ISNUMBER(SEARCH(SUBSTITUTE('Référentiel films'!$A$8,"’","'"),SUBSTITUTE(F9,"’","'"))),'Référentiel films'!$B$8,""),IF(ISNUMBER(SEARCH(SUBSTITUTE('Référentiel films'!$A$9,"’","'"),SUBSTITUTE(F9,"’","'"))),'Référentiel films'!$B$9,""),IF(ISNUMBER(SEARCH(SUBSTITUTE('Référentiel films'!$A$10,"’","'"),SUBSTITUTE(F9,"’","'"))),'Référentiel films'!$B$10,""),IF(ISNUMBER(SEARCH(SUBSTITUTE('Référentiel films'!$A$11,"’","'"),SUBSTITUTE(F9,"’","'"))),'Référentiel films'!$B$11,""),IF(ISNUMBER(SEARCH(SUBSTITUTE('Référentiel films'!$A$12,"’","'"),SUBSTITUTE(F9,"’","'"))),'Référentiel films'!$B$12,""),IF(ISNUMBER(SEARCH(SUBSTITUTE('Référentiel films'!$A$13,"’","'"),SUBSTITUTE(F9,"’","'"))),'Référentiel films'!$B$13,""),IF(ISNUMBER(SEARCH(SUBSTITUTE('Référentiel films'!$A$14,"’","'"),SUBSTITUTE(F9,"’","'"))),'Référentiel films'!$B$14,""),IF(ISNUMBER(SEARCH(SUBSTITUTE('Référentiel films'!$A$15,"’","'"),SUBSTITUTE(F9,"’","'"))),'Référentiel films'!$B$15,""),IF(ISNUMBER(SEARCH(SUBSTITUTE('Référentiel films'!$A$16,"’","'"),SUBSTITUTE(F9,"’","'"))),'Référentiel films'!$B$16,""),IF(ISNUMBER(SEARCH(SUBSTITUTE('Référentiel films'!$A$17,"’","'"),SUBSTITUTE(F9,"’","'"))),'Référentiel films'!$B$17,""),IF(ISNUMBER(SEARCH(SUBSTITUTE('Référentiel films'!$A$18,"’","'"),SUBSTITUTE(F9,"’","'"))),'Référentiel films'!$B$18,""),IF(ISNUMBER(SEARCH(SUBSTITUTE('Référentiel films'!$A$19,"’","'"),SUBSTITUTE(F9,"’","'"))),'Référentiel films'!$B$19,""),IF(ISNUMBER(SEARCH(SUBSTITUTE('Référentiel films'!$A$20,"’","'"),SUBSTITUTE(F9,"’","'"))),'Référentiel films'!$B$20,""),IF(ISNUMBER(SEARCH(SUBSTITUTE('Référentiel films'!$A$21,"’","'"),SUBSTITUTE(F9,"’","'"))),'Référentiel films'!$B$21,""),IF(ISNUMBER(SEARCH(SUBSTITUTE('Référentiel films'!$A$22,"’","'"),SUBSTITUTE(F9,"’","'"))),'Référentiel films'!$B$22,""),IF(ISNUMBER(SEARCH(SUBSTITUTE('Référentiel films'!$A$23,"’","'"),SUBSTITUTE(F9,"’","'"))),'Référentiel films'!$B$23,""),IF(ISNUMBER(SEARCH(SUBSTITUTE('Référentiel films'!$A$24,"’","'"),SUBSTITUTE(F9,"’","'"))),'Référentiel films'!$B$24,""),IF(ISNUMBER(SEARCH(SUBSTITUTE('Référentiel films'!$A$25,"’","'"),SUBSTITUTE(F9,"’","'"))),'Référentiel films'!$B$25,""),IF(ISNUMBER(SEARCH(SUBSTITUTE('Référentiel films'!$A$26,"’","'"),SUBSTITUTE(F9,"’","'"))),'Référentiel films'!$B$26,""),IF(ISNUMBER(SEARCH(SUBSTITUTE('Référentiel films'!$A$27,"’","'"),SUBSTITUTE(F9,"’","'"))),'Référentiel films'!$B$27,""),IF(ISNUMBER(SEARCH(SUBSTITUTE('Référentiel films'!$A$28,"’","'"),SUBSTITUTE(F9,"’","'"))),'Référentiel films'!$B$28,""),IF(ISNUMBER(SEARCH(SUBSTITUTE('Référentiel films'!$A$29,"’","'"),SUBSTITUTE(F9,"’","'"))),'Référentiel films'!$B$29,""),IF(ISNUMBER(SEARCH(SUBSTITUTE('Référentiel films'!$A$30,"’","'"),SUBSTITUTE(F9,"’","'"))),'Référentiel films'!$B$30,""),IF(ISNUMBER(SEARCH(SUBSTITUTE('Référentiel films'!$A$31,"’","'"),SUBSTITUTE(F9,"’","'"))),'Référentiel films'!$B$31,""),IF(ISNUMBER(SEARCH(SUBSTITUTE('Référentiel films'!$A$32,"’","'"),SUBSTITUTE(F9,"’","'"))),'Référentiel films'!$B$32,""),IF(ISNUMBER(SEARCH(SUBSTITUTE('Référentiel films'!$A$33,"’","'"),SUBSTITUTE(F9,"’","'"))),'Référentiel films'!$B$33,""),IF(ISNUMBER(SEARCH(SUBSTITUTE('Référentiel films'!$A$34,"’","'"),SUBSTITUTE(F9,"’","'"))),'Référentiel films'!$B$34,""),IF(ISNUMBER(SEARCH(SUBSTITUTE('Référentiel films'!$A$35,"’","'"),SUBSTITUTE(F9,"’","'"))),'Référentiel films'!$B$35,""),IF(ISNUMBER(SEARCH(SUBSTITUTE('Référentiel films'!$A$36,"’","'"),SUBSTITUTE(F9,"’","'"))),'Référentiel films'!$B$36,""),IF(ISNUMBER(SEARCH(SUBSTITUTE('Référentiel films'!$A$37,"’","'"),SUBSTITUTE(F9,"’","'"))),'Référentiel films'!$B$37,""),IF(ISNUMBER(SEARCH(SUBSTITUTE('Référentiel films'!$A$38,"’","'"),SUBSTITUTE(F9,"’","'"))),'Référentiel films'!$B$38,""),IF(ISNUMBER(SEARCH(SUBSTITUTE('Référentiel films'!$A$39,"’","'"),SUBSTITUTE(F9,"’","'"))),'Référentiel films'!$B$39,""),IF(ISNUMBER(SEARCH(SUBSTITUTE('Référentiel films'!$A$40,"’","'"),SUBSTITUTE(F9,"’","'"))),'Référentiel films'!$B$40,""),IF(ISNUMBER(SEARCH(SUBSTITUTE('Référentiel films'!$A$41,"’","'"),SUBSTITUTE(F9,"’","'"))),'Référentiel films'!$B$41,"")))
A10: 1953 | B10: 1947-1960 | C10: Révolte des ouvriers berlinois est-allemands écrasée par les chars soviétiques. Adenauer est réélu chancelier avec une coalition de centre droit | D10: Premiers concerts de rock'n'roll en RFA à Hambourg et Francfort. | H10: La révolte des ouvriers est-allemands | M10: Adenauer.jpeg | N10: Portrait d'Adenauer | U10: =IF(F10="","",_xlfn.TEXTJOIN("; ",TRUE(),IF(ISNUMBER(SEARCH(SUBSTITUTE('Référentiel films'!$A$2,"’","'"),SUBSTITUTE(F10,"’","'"))),'Référentiel films'!$B$2,""),IF(ISNUMBER(SEARCH(SUBSTITUTE('Référentiel films'!$A$3,"’","'"),SUBSTITUTE(F10,"’","'"))),'Référentiel films'!$B$3,""),IF(ISNUMBER(SEARCH(SUBSTITUTE('Référentiel films'!$A$4,"’","'"),SUBSTITUTE(F10,"’","'"))),'Référentiel films'!$B$4,""),IF(ISNUMBER(SEARCH(SUBSTITUTE('Référentiel films'!$A$5,"’","'"),SUBSTITUTE(F10,"’","'"))),'Référentiel films'!$B$5,""),IF(ISNUMBER(SEARCH(SUBSTITUTE('Référentiel films'!$A$6,"’","'"),SUBSTITUTE(F10,"’","'"))),'Référentiel films'!$B$6,""),IF(ISNUMBER(SEARCH(SUBSTITUTE('Référentiel films'!$A$7,"’","'"),SUBSTITUTE(F10,"’","'"))),'Référentiel films'!$B$7,""),IF(ISNUMBER(SEARCH(SUBSTITUTE('Référentiel films'!$A$8,"’","'"),SUBSTITUTE(F10,"’","'"))),'Référentiel films'!$B$8,""),IF(ISNUMBER(SEARCH(SUBSTITUTE('Référentiel films'!$A$9,"’","'"),SUBSTITUTE(F10,"’","'"))),'Référentiel films'!$B$9,""),IF(ISNUMBER(SEARCH(SUBSTITUTE('Référentiel films'!$A$10,"’","'"),SUBSTITUTE(F10,"’","'"))),'Référentiel films'!$B$10,""),IF(ISNUMBER(SEARCH(SUBSTITUTE('Référentiel films'!$A$11,"’","'"),SUBSTITUTE(F10,"’","'"))),'Référentiel films'!$B$11,""),IF(ISNUMBER(SEARCH(SUBSTITUTE('Référentiel films'!$A$12,"’","'"),SUBSTITUTE(F10,"’","'"))),'Référentiel films'!$B$12,""),IF(ISNUMBER(SEARCH(SUBSTITUTE('Référentiel films'!$A$13,"’","'"),SUBSTITUTE(F10,"’","'"))),'Référentiel films'!$B$13,""),IF(ISNUMBER(SEARCH(SUBSTITUTE('Référentiel films'!$A$14,"’","'"),SUBSTITUTE(F10,"’","'"))),'Référentiel films'!$B$14,""),IF(ISNUMBER(SEARCH(SUBSTITUTE('Référentiel films'!$A$15,"’","'"),SUBSTITUTE(F10,"’","'"))),'Référentiel films'!$B$15,""),IF(ISNUMBER(SEARCH(SUBSTITUTE('Référentiel films'!$A$16,"’","'"),SUBSTITUTE(F10,"’","'"))),'Référentiel films'!$B$16,""),IF(ISNUMBER(SEARCH(SUBSTITUTE('Référentiel films'!$A$17,"’","'"),SUBSTITUTE(F10,"’","'"))),'Référentiel films'!$B$17,""),IF(ISNUMBER(SEARCH(SUBSTITUTE('Référentiel films'!$A$18,"’","'"),SUBSTITUTE(F10,"’","'"))),'Référentiel films'!$B$18,""),IF(ISNUMBER(SEARCH(SUBSTITUTE('Référentiel films'!$A$19,"’","'"),SUBSTITUTE(F10,"’","'"))),'Référentiel films'!$B$19,""),IF(ISNUMBER(SEARCH(SUBSTITUTE('Référentiel films'!$A$20,"’","'"),SUBSTITUTE(F10,"’","'"))),'Référentiel films'!$B$20,""),IF(ISNUMBER(SEARCH(SUBSTITUTE('Référentiel films'!$A$21,"’","'"),SUBSTITUTE(F10,"’","'"))),'Référentiel films'!$B$21,""),IF(ISNUMBER(SEARCH(SUBSTITUTE('Référentiel films'!$A$22,"’","'"),SUBSTITUTE(F10,"’","'"))),'Référentiel films'!$B$22,""),IF(ISNUMBER(SEARCH(SUBSTITUTE('Référentiel films'!$A$23,"’","'"),SUBSTITUTE(F10,"’","'"))),'Référentiel films'!$B$23,""),IF(ISNUMBER(SEARCH(SUBSTITUTE('Référentiel films'!$A$24,"’","'"),SUBSTITUTE(F10,"’","'"))),'Référentiel films'!$B$24,""),IF(ISNUMBER(SEARCH(SUBSTITUTE('Référentiel films'!$A$25,"’","'"),SUBSTITUTE(F10,"’","'"))),'Référentiel films'!$B$25,""),IF(ISNUMBER(SEARCH(SUBSTITUTE('Référentiel films'!$A$26,"’","'"),SUBSTITUTE(F10,"’","'"))),'Référentiel films'!$B$26,""),IF(ISNUMBER(SEARCH(SUBSTITUTE('Référentiel films'!$A$27,"’","'"),SUBSTITUTE(F10,"’","'"))),'Référentiel films'!$B$27,""),IF(ISNUMBER(SEARCH(SUBSTITUTE('Référentiel films'!$A$28,"’","'"),SUBSTITUTE(F10,"’","'"))),'Référentiel films'!$B$28,""),IF(ISNUMBER(SEARCH(SUBSTITUTE('Référentiel films'!$A$29,"’","'"),SUBSTITUTE(F10,"’","'"))),'Référentiel films'!$B$29,""),IF(ISNUMBER(SEARCH(SUBSTITUTE('Référentiel films'!$A$30,"’","'"),SUBSTITUTE(F10,"’","'"))),'Référentiel films'!$B$30,""),IF(ISNUMBER(SEARCH(SUBSTITUTE('Référentiel films'!$A$31,"’","'"),SUBSTITUTE(F10,"’","'"))),'Référentiel films'!$B$31,""),IF(ISNUMBER(SEARCH(SUBSTITUTE('Référentiel films'!$A$32,"’","'"),SUBSTITUTE(F10,"’","'"))),'Référentiel films'!$B$32,""),IF(ISNUMBER(SEARCH(SUBSTITUTE('Référentiel films'!$A$33,"’","'"),SUBSTITUTE(F10,"’","'"))),'Référentiel films'!$B$33,""),IF(ISNUMBER(SEARCH(SUBSTITUTE('Référentiel films'!$A$34,"’","'"),SUBSTITUTE(F10,"’","'"))),'Référentiel films'!$B$34,""),IF(ISNUMBER(SEARCH(SUBSTITUTE('Référentiel films'!$A$35,"’","'"),SUBSTITUTE(F10,"’","'"))),'Référentiel films'!$B$35,""),IF(ISNUMBER(SEARCH(SUBSTITUTE('Référentiel films'!$A$36,"’","'"),SUBSTITUTE(F10,"’","'"))),'Référentiel films'!$B$36,""),IF(ISNUMBER(SEARCH(SUBSTITUTE('Référentiel films'!$A$37,"’","'"),SUBSTITUTE(F10,"’","'"))),'Référentiel films'!$B$37,""),IF(ISNUMBER(SEARCH(SUBSTITUTE('Référentiel films'!$A$38,"’","'"),SUBSTITUTE(F10,"’","'"))),'Référentiel films'!$B$38,""),IF(ISNUMBER(SEARCH(SUBSTITUTE('Référentiel films'!$A$39,"’","'"),SUBSTITUTE(F10,"’","'"))),'Référentiel films'!$B$39,""),IF(ISNUMBER(SEARCH(SUBSTITUTE('Référentiel films'!$A$40,"’","'"),SUBSTITUTE(F10,"’","'"))),'Référentiel films'!$B$40,""),IF(ISNUMBER(SEARCH(SUBSTITUTE('Référentiel films'!$A$41,"’","'"),SUBSTITUTE(F10,"’","'"))),'Référentiel films'!$B$41,"")))
A11: 1954 | B11: 1947-1960 | C11: La RFA devient un état souverain, doté de sa propre armée. Elle est admise au sein de l'OTAN. La RFA remporte la coupe du monde de football, confirmation de son retour dans le concert des nations. Les premiers travailleurs immigrés commencent à arriver de Grèce et d'Italie pour soutenir le "miracle économique". | D11: Sissi d'Ernst Marischka avec Romy Schneider et Karlheinz Böhm, qui deviendra un acteur récurrent du cinéma de Fassbinder | H11: Bande Annonce de Sissi (1955) | M11: Bohm.jpg | N11: Karlheinz Böhm | O11: Adenauer.jpeg | P11: Portrait d'Adenauer | U11: =IF(F11="","",_xlfn.TEXTJOIN("; ",TRUE(),IF(ISNUMBER(SEARCH(SUBSTITUTE('Référentiel films'!$A$2,"’","'"),SUBSTITUTE(F11,"’","'"))),'Référentiel films'!$B$2,""),IF(ISNUMBER(SEARCH(SUBSTITUTE('Référentiel films'!$A$3,"’","'"),SUBSTITUTE(F11,"’","'"))),'Référentiel films'!$B$3,""),IF(ISNUMBER(SEARCH(SUBSTITUTE('Référentiel films'!$A$4,"’","'"),SUBSTITUTE(F11,"’","'"))),'Référentiel films'!$B$4,""),IF(ISNUMBER(SEARCH(SUBSTITUTE('Référentiel films'!$A$5,"’","'"),SUBSTITUTE(F11,"’","'"))),'Référentiel films'!$B$5,""),IF(ISNUMBER(SEARCH(SUBSTITUTE('Référentiel films'!$A$6,"’","'"),SUBSTITUTE(F11,"’","'"))),'Référentiel films'!$B$6,""),IF(ISNUMBER(SEARCH(SUBSTITUTE('Référentiel films'!$A$7,"’","'"),SUBSTITUTE(F11,"’","'"))),'Référentiel films'!$B$7,""),IF(ISNUMBER(SEARCH(SUBSTITUTE('Référentiel films'!$A$8,"’","'"),SUBSTITUTE(F11,"’","'"))),'Référentiel films'!$B$8,""),IF(ISNUMBER(SEARCH(SUBSTITUTE('Référentiel films'!$A$9,"’","'"),SUBSTITUTE(F11,"’","'"))),'Référentiel films'!$B$9,""),IF(ISNUMBER(SEARCH(SUBSTITUTE('Référentiel films'!$A$10,"’","'"),SUBSTITUTE(F11,"’","'"))),'Référentiel films'!$B$10,""),IF(ISNUMBER(SEARCH(SUBSTITUTE('Référentiel films'!$A$11,"’","'"),SUBSTITUTE(F11,"’","'"))),'Référentiel films'!$B$11,""),IF(ISNUMBER(SEARCH(SUBSTITUTE('Référentiel films'!$A$12,"’","'"),SUBSTITUTE(F11,"’","'"))),'Référentiel films'!$B$12,""),IF(ISNUMBER(SEARCH(SUBSTITUTE('Référentiel films'!$A$13,"’","'"),SUBSTITUTE(F11,"’","'"))),'Référentiel films'!$B$13,""),IF(ISNUMBER(SEARCH(SUBSTITUTE('Référentiel films'!$A$14,"’","'"),SUBSTITUTE(F11,"’","'"))),'Référentiel films'!$B$14,""),IF(ISNUMBER(SEARCH(SUBSTITUTE('Référentiel films'!$A$15,"’","'"),SUBSTITUTE(F11,"’","'"))),'Référentiel films'!$B$15,""),IF(ISNUMBER(SEARCH(SUBSTITUTE('Référentiel films'!$A$16,"’","'"),SUBSTITUTE(F11,"’","'"))),'Référentiel films'!$B$16,""),IF(ISNUMBER(SEARCH(SUBSTITUTE('Référentiel films'!$A$17,"’","'"),SUBSTITUTE(F11,"’","'"))),'Référentiel films'!$B$17,""),IF(ISNUMBER(SEARCH(SUBSTITUTE('Référentiel films'!$A$18,"’","'"),SUBSTITUTE(F11,"’","'"))),'Référentiel films'!$B$18,""),IF(ISNUMBER(SEARCH(SUBSTITUTE('Référentiel films'!$A$19,"’","'"),SUBSTITUTE(F11,"’","'"))),'Référentiel films'!$B$19,""),IF(ISNUMBER(SEARCH(SUBSTITUTE('Référentiel films'!$A$20,"’","'"),SUBSTITUTE(F11,"’","'"))),'Référentiel films'!$B$20,""),IF(ISNUMBER(SEARCH(SUBSTITUTE('Référentiel films'!$A$21,"’","'"),SUBSTITUTE(F11,"’","'"))),'Référentiel films'!$B$21,""),IF(ISNUMBER(SEARCH(SUBSTITUTE('Référentiel films'!$A$22,"’","'"),SUBSTITUTE(F11,"’","'"))),'Référentiel films'!$B$22,""),IF(ISNUMBER(SEARCH(SUBSTITUTE('Référentiel films'!$A$23,"’","'"),SUBSTITUTE(F11,"’","'"))),'Référentiel films'!$B$23,""),IF(ISNUMBER(SEARCH(SUBSTITUTE('Référentiel films'!$A$24,"’","'"),SUBSTITUTE(F11,"’","'"))),'Référentiel films'!$B$24,""),IF(ISNUMBER(SEARCH(SUBSTITUTE('Référentiel films'!$A$25,"’","'"),SUBSTITUTE(F11,"’","'"))),'Référentiel films'!$B$25,""),IF(ISNUMBER(SEARCH(SUBSTITUTE('Référentiel films'!$A$26,"’","'"),SUBSTITUTE(F11,"’","'"))),'Référentiel films'!$B$26,""),IF(ISNUMBER(SEARCH(SUBSTITUTE('Référentiel films'!$A$27,"’","'"),SUBSTITUTE(F11,"’","'"))),'Référentiel films'!$B$27,""),IF(ISNUMBER(SEARCH(SUBSTITUTE('Référentiel films'!$A$28,"’","'"),SUBSTITUTE(F11,"’","'"))),'Référentiel films'!$B$28,""),IF(ISNUMBER(SEARCH(SUBSTITUTE('Référentiel films'!$A$29,"’","'"),SUBSTITUTE(F11,"’","'"))),'Référentiel films'!$B$29,""),IF(ISNUMBER(SEARCH(SUBSTITUTE('Référentiel films'!$A$30,"’","'"),SUBSTITUTE(F11,"’","'"))),'Référentiel films'!$B$30,""),IF(ISNUMBER(SEARCH(SUBSTITUTE('Référentiel films'!$A$31,"’","'"),SUBSTITUTE(F11,"’","'"))),'Référentiel films'!$B$31,""),IF(ISNUMBER(SEARCH(SUBSTITUTE('Référentiel films'!$A$32,"’","'"),SUBSTITUTE(F11,"’","'"))),'Référentiel films'!$B$32,""),IF(ISNUMBER(SEARCH(SUBSTITUTE('Référentiel films'!$A$33,"’","'"),SUBSTITUTE(F11,"’","'"))),'Référentiel films'!$B$33,""),IF(ISNUMBER(SEARCH(SUBSTITUTE('Référentiel films'!$A$34,"’","'"),SUBSTITUTE(F11,"’","'"))),'Référentiel films'!$B$34,""),IF(ISNUMBER(SEARCH(SUBSTITUTE('Référentiel films'!$A$35,"’","'"),SUBSTITUTE(F11,"’","'"))),'Référentiel films'!$B$35,""),IF(ISNUMBER(SEARCH(SUBSTITUTE('Référentiel films'!$A$36,"’","'"),SUBSTITUTE(F11,"’","'"))),'Référentiel films'!$B$36,""),IF(ISNUMBER(SEARCH(SUBSTITUTE('Référentiel films'!$A$37,"’","'"),SUBSTITUTE(F11,"’","'"))),'Référentiel films'!$B$37,""),IF(ISNUMBER(SEARCH(SUBSTITUTE('Référentiel films'!$A$38,"’","'"),SUBSTITUTE(F11,"’","'"))),'Référentiel films'!$B$38,""),IF(ISNUMBER(SEARCH(SUBSTITUTE('Référentiel films'!$A$39,"’","'"),SUBSTITUTE(F11,"’","'"))),'Référentiel films'!$B$39,""),IF(ISNUMBER(SEARCH(SUBSTITUTE('Référentiel films'!$A$40,"’","'"),SUBSTITUTE(F11,"’","'"))),'Référentiel films'!$B$40,""),IF(ISNUMBER(SEARCH(SUBSTITUTE('Référentiel films'!$A$41,"’","'"),SUBSTITUTE(F11,"’","'"))),'Référentiel films'!$B$41,"")))
A12: 1955 | B12: 1947-1960 | E12: RWF est lycéen à Munich. | U12: =IF(F12="","",_xlfn.TEXTJOIN("; ",TRUE(),IF(ISNUMBER(SEARCH(SUBSTITUTE('Référentiel films'!$A$2,"’","'"),SUBSTITUTE(F12,"’","'"))),'Référentiel films'!$B$2,""),IF(ISNUMBER(SEARCH(SUBSTITUTE('Référentiel films'!$A$3,"’","'"),SUBSTITUTE(F12,"’","'"))),'Référentiel films'!$B$3,""),IF(ISNUMBER(SEARCH(SUBSTITUTE('Référentiel films'!$A$4,"’","'"),SUBSTITUTE(F12,"’","'"))),'Référentiel films'!$B$4,""),IF(ISNUMBER(SEARCH(SUBSTITUTE('Référentiel films'!$A$5,"’","'"),SUBSTITUTE(F12,"’","'"))),'Référentiel films'!$B$5,""),IF(ISNUMBER(SEARCH(SUBSTITUTE('Référentiel films'!$A$6,"’","'"),SUBSTITUTE(F12,"’","'"))),'Référentiel films'!$B$6,""),IF(ISNUMBER(SEARCH(SUBSTITUTE('Référentiel films'!$A$7,"’","'"),SUBSTITUTE(F12,"’","'"))),'Référentiel films'!$B$7,""),IF(ISNUMBER(SEARCH(SUBSTITUTE('Référentiel films'!$A$8,"’","'"),SUBSTITUTE(F12,"’","'"))),'Référentiel films'!$B$8,""),IF(ISNUMBER(SEARCH(SUBSTITUTE('Référentiel films'!$A$9,"’","'"),SUBSTITUTE(F12,"’","'"))),'Référentiel films'!$B$9,""),IF(ISNUMBER(SEARCH(SUBSTITUTE('Référentiel films'!$A$10,"’","'"),SUBSTITUTE(F12,"’","'"))),'Référentiel films'!$B$10,""),IF(ISNUMBER(SEARCH(SUBSTITUTE('Référentiel films'!$A$11,"’","'"),SUBSTITUTE(F12,"’","'"))),'Référentiel films'!$B$11,""),IF(ISNUMBER(SEARCH(SUBSTITUTE('Référentiel films'!$A$12,"’","'"),SUBSTITUTE(F12,"’","'"))),'Référentiel films'!$B$12,""),IF(ISNUMBER(SEARCH(SUBSTITUTE('Référentiel films'!$A$13,"’","'"),SUBSTITUTE(F12,"’","'"))),'Référentiel films'!$B$13,""),IF(ISNUMBER(SEARCH(SUBSTITUTE('Référentiel films'!$A$14,"’","'"),SUBSTITUTE(F12,"’","'"))),'Référentiel films'!$B$14,""),IF(ISNUMBER(SEARCH(SUBSTITUTE('Référentiel films'!$A$15,"’","'"),SUBSTITUTE(F12,"’","'"))),'Référentiel films'!$B$15,""),IF(ISNUMBER(SEARCH(SUBSTITUTE('Référentiel films'!$A$16,"’","'"),SUBSTITUTE(F12,"’","'"))),'Référentiel films'!$B$16,""),IF(ISNUMBER(SEARCH(SUBSTITUTE('Référentiel films'!$A$17,"’","'"),SUBSTITUTE(F12,"’","'"))),'Référentiel films'!$B$17,""),IF(ISNUMBER(SEARCH(SUBSTITUTE('Référentiel films'!$A$18,"’","'"),SUBSTITUTE(F12,"’","'"))),'Référentiel films'!$B$18,""),IF(ISNUMBER(SEARCH(SUBSTITUTE('Référentiel films'!$A$19,"’","'"),SUBSTITUTE(F12,"’","'"))),'Référentiel films'!$B$19,""),IF(ISNUMBER(SEARCH(SUBSTITUTE('Référentiel films'!$A$20,"’","'"),SUBSTITUTE(F12,"’","'"))),'Référentiel films'!$B$20,""),IF(ISNUMBER(SEARCH(SUBSTITUTE('Référentiel films'!$A$21,"’","'"),SUBSTITUTE(F12,"’","'"))),'Référentiel films'!$B$21,""),IF(ISNUMBER(SEARCH(SUBSTITUTE('Référentiel films'!$A$22,"’","'"),SUBSTITUTE(F12,"’","'"))),'Référentiel films'!$B$22,""),IF(ISNUMBER(SEARCH(SUBSTITUTE('Référentiel films'!$A$23,"’","'"),SUBSTITUTE(F12,"’","'"))),'Référentiel films'!$B$23,""),IF(ISNUMBER(SEARCH(SUBSTITUTE('Référentiel films'!$A$24,"’","'"),SUBSTITUTE(F12,"’","'"))),'Référentiel films'!$B$24,""),IF(ISNUMBER(SEARCH(SUBSTITUTE('Référentiel films'!$A$25,"’","'"),SUBSTITUTE(F12,"’","'"))),'Référentiel films'!$B$25,""),IF(ISNUMBER(SEARCH(SUBSTITUTE('Référentiel films'!$A$26,"’","'"),SUBSTITUTE(F12,"’","'"))),'Référentiel films'!$B$26,""),IF(ISNUMBER(SEARCH(SUBSTITUTE('Référentiel films'!$A$27,"’","'"),SUBSTITUTE(F12,"’","'"))),'Référentiel films'!$B$27,""),IF(ISNUMBER(SEARCH(SUBSTITUTE('Référentiel films'!$A$28,"’","'"),SUBSTITUTE(F12,"’","'"))),'Référentiel films'!$B$28,""),IF(ISNUMBER(SEARCH(SUBSTITUTE('Référentiel films'!$A$29,"’","'"),SUBSTITUTE(F12,"’","'"))),'Référentiel films'!$B$29,""),IF(ISNUMBER(SEARCH(SUBSTITUTE('Référentiel films'!$A$30,"’","'"),SUBSTITUTE(F12,"’","'"))),'Référentiel films'!$B$30,""),IF(ISNUMBER(SEARCH(SUBSTITUTE('Référentiel films'!$A$31,"’","'"),SUBSTITUTE(F12,"’","'"))),'Référentiel films'!$B$31,""),IF(ISNUMBER(SEARCH(SUBSTITUTE('Référentiel films'!$A$32,"’","'"),SUBSTITUTE(F12,"’","'"))),'Référentiel films'!$B$32,""),IF(ISNUMBER(SEARCH(SUBSTITUTE('Référentiel films'!$A$33,"’","'"),SUBSTITUTE(F12,"’","'"))),'Référentiel films'!$B$33,""),IF(ISNUMBER(SEARCH(SUBSTITUTE('Référentiel films'!$A$34,"’","'"),SUBSTITUTE(F12,"’","'"))),'Référentiel films'!$B$34,""),IF(ISNUMBER(SEARCH(SUBSTITUTE('Référentiel films'!$A$35,"’","'"),SUBSTITUTE(F12,"’","'"))),'Référentiel films'!$B$35,""),IF(ISNUMBER(SEARCH(SUBSTITUTE('Référentiel films'!$A$36,"’","'"),SUBSTITUTE(F12,"’","'"))),'Référentiel films'!$B$36,""),IF(ISNUMBER(SEARCH(SUBSTITUTE('Référentiel films'!$A$37,"’","'"),SUBSTITUTE(F12,"’","'"))),'Référentiel films'!$B$37,""),IF(ISNUMBER(SEARCH(SUBSTITUTE('Référentiel films'!$A$38,"’","'"),SUBSTITUTE(F12,"’","'"))),'Référentiel films'!$B$38,""),IF(ISNUMBER(SEARCH(SUBSTITUTE('Référentiel films'!$A$39,"’","'"),SUBSTITUTE(F12,"’","'"))),'Référentiel films'!$B$39,""),IF(ISNUMBER(SEARCH(SUBSTITUTE('Référentiel films'!$A$40,"’","'"),SUBSTITUTE(F12,"’","'"))),'Référentiel films'!$B$40,""),IF(ISNUMBER(SEARCH(SUBSTITUTE('Référentiel films'!$A$41,"’","'"),SUBSTITUTE(F12,"’","'"))),'Référentiel films'!$B$41,"")))
A13: 1956 | B13: 1947-1960 | C13: Adenauer fête ses 80 ans. Le KDP, parti communiste ouest-allemand, est interdit. | D13: Décès de Bertold Brecht Nuit et brouillard d'Alain Resnais. | E13: RWF est pensionnaire à Augsbourg, sa mère étant hospitalisée pendant près de deux ans à la suite d'une opération. Il continue à fréquenter les salles obscures. Il voit toutes sortes de film sans distinction, des films noirs américains doublés en allemand, des films pornos sans budget qui se développent à partir de 1960. Le cinéma hollywoodien est alors plutôt dénigré par la bourgeoisie. | H13: découvrir Brecht avec l'INA | M13: Adenauer.jpeg | N13: Portrait d'Adenauer | U13: =IF(F13="","",_xlfn.TEXTJOIN("; ",TRUE(),IF(ISNUMBER(SEARCH(SUBSTITUTE('Référentiel films'!$A$2,"’","'"),SUBSTITUTE(F13,"’","'"))),'Référentiel films'!$B$2,""),IF(ISNUMBER(SEARCH(SUBSTITUTE('Référentiel films'!$A$3,"’","'"),SUBSTITUTE(F13,"’","'"))),'Référentiel films'!$B$3,""),IF(ISNUMBER(SEARCH(SUBSTITUTE('Référentiel films'!$A$4,"’","'"),SUBSTITUTE(F13,"’","'"))),'Référentiel films'!$B$4,""),IF(ISNUMBER(SEARCH(SUBSTITUTE('Référentiel films'!$A$5,"’","'"),SUBSTITUTE(F13,"’","'"))),'Référentiel films'!$B$5,""),IF(ISNUMBER(SEARCH(SUBSTITUTE('Référentiel films'!$A$6,"’","'"),SUBSTITUTE(F13,"’","'"))),'Référentiel films'!$B$6,""),IF(ISNUMBER(SEARCH(SUBSTITUTE('Référentiel films'!$A$7,"’","'"),SUBSTITUTE(F13,"’","'"))),'Référentiel films'!$B$7,""),IF(ISNUMBER(SEARCH(SUBSTITUTE('Référentiel films'!$A$8,"’","'"),SUBSTITUTE(F13,"’","'"))),'Référentiel films'!$B$8,""),IF(ISNUMBER(SEARCH(SUBSTITUTE('Référentiel films'!$A$9,"’","'"),SUBSTITUTE(F13,"’","'"))),'Référentiel films'!$B$9,""),IF(ISNUMBER(SEARCH(SUBSTITUTE('Référentiel films'!$A$10,"’","'"),SUBSTITUTE(F13,"’","'"))),'Référentiel films'!$B$10,""),IF(ISNUMBER(SEARCH(SUBSTITUTE('Référentiel films'!$A$11,"’","'"),SUBSTITUTE(F13,"’","'"))),'Référentiel films'!$B$11,""),IF(ISNUMBER(SEARCH(SUBSTITUTE('Référentiel films'!$A$12,"’","'"),SUBSTITUTE(F13,"’","'"))),'Référentiel films'!$B$12,""),IF(ISNUMBER(SEARCH(SUBSTITUTE('Référentiel films'!$A$13,"’","'"),SUBSTITUTE(F13,"’","'"))),'Référentiel films'!$B$13,""),IF(ISNUMBER(SEARCH(SUBSTITUTE('Référentiel films'!$A$14,"’","'"),SUBSTITUTE(F13,"’","'"))),'Référentiel films'!$B$14,""),IF(ISNUMBER(SEARCH(SUBSTITUTE('Référentiel films'!$A$15,"’","'"),SUBSTITUTE(F13,"’","'"))),'Référentiel films'!$B$15,""),IF(ISNUMBER(SEARCH(SUBSTITUTE('Référentiel films'!$A$16,"’","'"),SUBSTITUTE(F13,"’","'"))),'Référentiel films'!$B$16,""),IF(ISNUMBER(SEARCH(SUBSTITUTE('Référentiel films'!$A$17,"’","'"),SUBSTITUTE(F13,"’","'"))),'Référentiel films'!$B$17,""),IF(ISNUMBER(SEARCH(SUBSTITUTE('Référentiel films'!$A$18,"’","'"),SUBSTITUTE(F13,"’","'"))),'Référentiel films'!$B$18,""),IF(ISNUMBER(SEARCH(SUBSTITUTE('Référentiel films'!$A$19,"’","'"),SUBSTITUTE(F13,"’","'"))),'Référentiel films'!$B$19,""),IF(ISNUMBER(SEARCH(SUBSTITUTE('Référentiel films'!$A$20,"’","'"),SUBSTITUTE(F13,"’","'"))),'Référentiel films'!$B$20,""),IF(ISNUMBER(SEARCH(SUBSTITUTE('Référentiel films'!$A$21,"’","'"),SUBSTITUTE(F13,"’","'"))),'Référentiel films'!$B$21,""),IF(ISNUMBER(SEARCH(SUBSTITUTE('Référentiel films'!$A$22,"’","'"),SUBSTITUTE(F13,"’","'"))),'Référentiel films'!$B$22,""),IF(ISNUMBER(SEARCH(SUBSTITUTE('Référentiel films'!$A$23,"’","'"),SUBSTITUTE(F13,"’","'"))),'Référentiel films'!$B$23,""),IF(ISNUMBER(SEARCH(SUBSTITUTE('Référentiel films'!$A$24,"’","'"),SUBSTITUTE(F13,"’","'"))),'Référentiel films'!$B$24,""),IF(ISNUMBER(SEARCH(SUBSTITUTE('Référentiel films'!$A$25,"’","'"),SUBSTITUTE(F13,"’","'"))),'Référentiel films'!$B$25,""),IF(ISNUMBER(SEARCH(SUBSTITUTE('Référentiel films'!$A$26,"’","'"),SUBSTITUTE(F13,"’","'"))),'Référentiel films'!$B$26,""),IF(ISNUMBER(SEARCH(SUBSTITUTE('Référentiel films'!$A$27,"’","'"),SUBSTITUTE(F13,"’","'"))),'Référentiel films'!$B$27,""),IF(ISNUMBER(SEARCH(SUBSTITUTE('Référentiel films'!$A$28,"’","'"),SUBSTITUTE(F13,"’","'"))),'Référentiel films'!$B$28,""),IF(ISNUMBER(SEARCH(SUBSTITUTE('Référentiel films'!$A$29,"’","'"),SUBSTITUTE(F13,"’","'"))),'Référentiel films'!$B$29,""),IF(ISNUMBER(SEARCH(SUBSTITUTE('Référentiel films'!$A$30,"’","'"),SUBSTITUTE(F13,"’","'"))),'Référentiel films'!$B$30,""),IF(ISNUMBER(SEARCH(SUBSTITUTE('Référentiel films'!$A$31,"’","'"),SUBSTITUTE(F13,"’","'"))),'Référentiel films'!$B$31,""),IF(ISNUMBER(SEARCH(SUBSTITUTE('Référentiel films'!$A$32,"’","'"),SUBSTITUTE(F13,"’","'"))),'Référentiel films'!$B$32,""),IF(ISNUMBER(SEARCH(SUBSTITUTE('Référentiel films'!$A$33,"’","'"),SUBSTITUTE(F13,"’","'"))),'Référentiel films'!$B$33,""),IF(ISNUMBER(SEARCH(SUBSTITUTE('Référentiel films'!$A$34,"’","'"),SUBSTITUTE(F13,"’","'"))),'Référentiel films'!$B$34,""),IF(ISNUMBER(SEARCH(SUBSTITUTE('Référentiel films'!$A$35,"’","'"),SUBSTITUTE(F13,"’","'"))),'Référentiel films'!$B$35,""),IF(ISNUMBER(SEARCH(SUBSTITUTE('Référentiel films'!$A$36,"’","'"),SUBSTITUTE(F13,"’","'"))),'Référentiel films'!$B$36,""),IF(ISNUMBER(SEARCH(SUBSTITUTE('Référentiel films'!$A$37,"’","'"),SUBSTITUTE(F13,"’","'"))),'Référentiel films'!$B$37,""),IF(ISNUMBER(SEARCH(SUBSTITUTE('Référentiel films'!$A$38,"’","'"),SUBSTITUTE(F13,"’","'"))),'Référentiel films'!$B$38,""),IF(ISNUMBER(SEARCH(SUBSTITUTE('Référentiel films'!$A$39,"’","'"),SUBSTITUTE(F13,"’","'"))),'Référentiel films'!$B$39,""),IF(ISNUMBER(SEARCH(SUBSTITUTE('Référentiel films'!$A$40,"’","'"),SUBSTITUTE(F13,"’","'"))),'Référentiel films'!$B$40,""),IF(ISNUMBER(SEARCH(SUBSTITUTE('Référentiel films'!$A$41,"’","'"),SUBSTITUTE(F13,"’","'"))),'Référentiel films'!$B$41,"")))
A14: 1957 | B14: 1947-1960 | C14: La RFA signe le traité de Rome qui institue la Communauté Européenne (CEE). Un scandale secoue le monde politique et financier : une prostituée qui comptait parmi ses clients de nombreux hommes poli-tiques ou industriels, est assassinée à Francfort. Adenauer tente d'imposer le fait que la RFA se dote de l'arme nucléaire mais se heurte à un front de protestation, notamment du monde scientifique. | D14: L'opéra de quat'sous de Brecht (1928) est diffusé à la télévision est obient un taux d'audience de 81,2%. L'appel à boycotter les pièces de Brecht est refusé par la plupart des théâtres ouest-allemands. | M14: Adenauer.jpeg | N14: Portrait d'Adenauer | U14: =IF(F14="","",_xlfn.TEXTJOIN("; ",TRUE(),IF(ISNUMBER(SEARCH(SUBSTITUTE('Référentiel films'!$A$2,"’","'"),SUBSTITUTE(F14,"’","'"))),'Référentiel films'!$B$2,""),IF(ISNUMBER(SEARCH(SUBSTITUTE('Référentiel films'!$A$3,"’","'"),SUBSTITUTE(F14,"’","'"))),'Référentiel films'!$B$3,""),IF(ISNUMBER(SEARCH(SUBSTITUTE('Référentiel films'!$A$4,"’","'"),SUBSTITUTE(F14,"’","'"))),'Référentiel films'!$B$4,""),IF(ISNUMBER(SEARCH(SUBSTITUTE('Référentiel films'!$A$5,"’","'"),SUBSTITUTE(F14,"’","'"))),'Référentiel films'!$B$5,""),IF(ISNUMBER(SEARCH(SUBSTITUTE('Référentiel films'!$A$6,"’","'"),SUBSTITUTE(F14,"’","'"))),'Référentiel films'!$B$6,""),IF(ISNUMBER(SEARCH(SUBSTITUTE('Référentiel films'!$A$7,"’","'"),SUBSTITUTE(F14,"’","'"))),'Référentiel films'!$B$7,""),IF(ISNUMBER(SEARCH(SUBSTITUTE('Référentiel films'!$A$8,"’","'"),SUBSTITUTE(F14,"’","'"))),'Référentiel films'!$B$8,""),IF(ISNUMBER(SEARCH(SUBSTITUTE('Référentiel films'!$A$9,"’","'"),SUBSTITUTE(F14,"’","'"))),'Référentiel films'!$B$9,""),IF(ISNUMBER(SEARCH(SUBSTITUTE('Référentiel films'!$A$10,"’","'"),SUBSTITUTE(F14,"’","'"))),'Référentiel films'!$B$10,""),IF(ISNUMBER(SEARCH(SUBSTITUTE('Référentiel films'!$A$11,"’","'"),SUBSTITUTE(F14,"’","'"))),'Référentiel films'!$B$11,""),IF(ISNUMBER(SEARCH(SUBSTITUTE('Référentiel films'!$A$12,"’","'"),SUBSTITUTE(F14,"’","'"))),'Référentiel films'!$B$12,""),IF(ISNUMBER(SEARCH(SUBSTITUTE('Référentiel films'!$A$13,"’","'"),SUBSTITUTE(F14,"’","'"))),'Référentiel films'!$B$13,""),IF(ISNUMBER(SEARCH(SUBSTITUTE('Référentiel films'!$A$14,"’","'"),SUBSTITUTE(F14,"’","'"))),'Référentiel films'!$B$14,""),IF(ISNUMBER(SEARCH(SUBSTITUTE('Référentiel films'!$A$15,"’","'"),SUBSTITUTE(F14,"’","'"))),'Référentiel films'!$B$15,""),IF(ISNUMBER(SEARCH(SUBSTITUTE('Référentiel films'!$A$16,"’","'"),SUBSTITUTE(F14,"’","'"))),'Référentiel films'!$B$16,""),IF(ISNUMBER(SEARCH(SUBSTITUTE('Référentiel films'!$A$17,"’","'"),SUBSTITUTE(F14,"’","'"))),'Référentiel films'!$B$17,""),IF(ISNUMBER(SEARCH(SUBSTITUTE('Référentiel films'!$A$18,"’","'"),SUBSTITUTE(F14,"’","'"))),'Référentiel films'!$B$18,""),IF(ISNUMBER(SEARCH(SUBSTITUTE('Référentiel films'!$A$19,"’","'"),SUBSTITUTE(F14,"’","'"))),'Référentiel films'!$B$19,""),IF(ISNUMBER(SEARCH(SUBSTITUTE('Référentiel films'!$A$20,"’","'"),SUBSTITUTE(F14,"’","'"))),'Référentiel films'!$B$20,""),IF(ISNUMBER(SEARCH(SUBSTITUTE('Référentiel films'!$A$21,"’","'"),SUBSTITUTE(F14,"’","'"))),'Référentiel films'!$B$21,""),IF(ISNUMBER(SEARCH(SUBSTITUTE('Référentiel films'!$A$22,"’","'"),SUBSTITUTE(F14,"’","'"))),'Référentiel films'!$B$22,""),IF(ISNUMBER(SEARCH(SUBSTITUTE('Référentiel films'!$A$23,"’","'"),SUBSTITUTE(F14,"’","'"))),'Référentiel films'!$B$23,""),IF(ISNUMBER(SEARCH(SUBSTITUTE('Référentiel films'!$A$24,"’","'"),SUBSTITUTE(F14,"’","'"))),'Référentiel films'!$B$24,""),IF(ISNUMBER(SEARCH(SUBSTITUTE('Référentiel films'!$A$25,"’","'"),SUBSTITUTE(F14,"’","'"))),'Référentiel films'!$B$25,""),IF(ISNUMBER(SEARCH(SUBSTITUTE('Référentiel films'!$A$26,"’","'"),SUBSTITUTE(F14,"’","'"))),'Référentiel films'!$B$26,""),IF(ISNUMBER(SEARCH(SUBSTITUTE('Référentiel films'!$A$27,"’","'"),SUBSTITUTE(F14,"’","'"))),'Référentiel films'!$B$27,""),IF(ISNUMBER(SEARCH(SUBSTITUTE('Référentiel films'!$A$28,"’","'"),SUBSTITUTE(F14,"’","'"))),'Référentiel films'!$B$28,""),IF(ISNUMBER(SEARCH(SUBSTITUTE('Référentiel films'!$A$29,"’","'"),SUBSTITUTE(F14,"’","'"))),'Référentiel films'!$B$29,""),IF(ISNUMBER(SEARCH(SUBSTITUTE('Référentiel films'!$A$30,"’","'"),SUBSTITUTE(F14,"’","'"))),'Référentiel films'!$B$30,""),IF(ISNUMBER(SEARCH(SUBSTITUTE('Référentiel films'!$A$31,"’","'"),SUBSTITUTE(F14,"’","'"))),'Référentiel films'!$B$31,""),IF(ISNUMBER(SEARCH(SUBSTITUTE('Référentiel films'!$A$32,"’","'"),SUBSTITUTE(F14,"’","'"))),'Référentiel films'!$B$32,""),IF(ISNUMBER(SEARCH(SUBSTITUTE('Référentiel films'!$A$33,"’","'"),SUBSTITUTE(F14,"’","'"))),'Référentiel films'!$B$33,""),IF(ISNUMBER(SEARCH(SUBSTITUTE('Référentiel films'!$A$34,"’","'"),SUBSTITUTE(F14,"’","'"))),'Référentiel films'!$B$34,""),IF(ISNUMBER(SEARCH(SUBSTITUTE('Référentiel films'!$A$35,"’","'"),SUBSTITUTE(F14,"’","'"))),'Référentiel films'!$B$35,""),IF(ISNUMBER(SEARCH(SUBSTITUTE('Référentiel films'!$A$36,"’","'"),SUBSTITUTE(F14,"’","'"))),'Référentiel films'!$B$36,""),IF(ISNUMBER(SEARCH(SUBSTITUTE('Référentiel films'!$A$37,"’","'"),SUBSTITUTE(F14,"’","'"))),'Référentiel films'!$B$37,""),IF(ISNUMBER(SEARCH(SUBSTITUTE('Référentiel films'!$A$38,"’","'"),SUBSTITUTE(F14,"’","'"))),'Référentiel films'!$B$38,""),IF(ISNUMBER(SEARCH(SUBSTITUTE('Référentiel films'!$A$39,"’","'"),SUBSTITUTE(F14,"’","'"))),'Référentiel films'!$B$39,""),IF(ISNUMBER(SEARCH(SUBSTITUTE('Référentiel films'!$A$40,"’","'"),SUBSTITUTE(F14,"’","'"))),'Référentiel films'!$B$40,""),IF(ISNUMBER(SEARCH(SUBSTITUTE('Référentiel films'!$A$41,"’","'"),SUBSTITUTE(F14,"’","'"))),'Référentiel films'!$B$41,"")))
A15: 1959 | B15: 1947-1960 | C15: Le SPD (parti social-démocrate allemand), adopte le programme de Bad-Godesberg : pour la première fois, le SPD abandonne formellement les idées d'inspiration marxiste. Il reconnaît l'économie de marché et se dit lié au peuple entier, non aux seuls travailleurs. | D15: La vogue du hula-hoop déferle sur l'Allemagne | E15: Remariage de Lilo avec un journaliste, Wolff Eder. Relations difficiles entre RWF et son beau-père. RWF revient à Munich mais vit dans un pensionnat. RWF commence à assumer ouvertement son homosexualité, fait rare pour l'époque. | G15: Les œuvres de Fassbinder témoignent de l'influence du Rock'nRoll sur la culture populaire ouest-allemande, notamment dans huit heures ne font pas un jour. | M15: Adenauer.jpeg | N15: Portrait d'Adenauer | U15: =IF(F15="","",_xlfn.TEXTJOIN("; ",TRUE(),IF(ISNUMBER(SEARCH(SUBSTITUTE('Référentiel films'!$A$2,"’","'"),SUBSTITUTE(F15,"’","'"))),'Référentiel films'!$B$2,""),IF(ISNUMBER(SEARCH(SUBSTITUTE('Référentiel films'!$A$3,"’","'"),SUBSTITUTE(F15,"’","'"))),'Référentiel films'!$B$3,""),IF(ISNUMBER(SEARCH(SUBSTITUTE('Référentiel films'!$A$4,"’","'"),SUBSTITUTE(F15,"’","'"))),'Référentiel films'!$B$4,""),IF(ISNUMBER(SEARCH(SUBSTITUTE('Référentiel films'!$A$5,"’","'"),SUBSTITUTE(F15,"’","'"))),'Référentiel films'!$B$5,""),IF(ISNUMBER(SEARCH(SUBSTITUTE('Référentiel films'!$A$6,"’","'"),SUBSTITUTE(F15,"’","'"))),'Référentiel films'!$B$6,""),IF(ISNUMBER(SEARCH(SUBSTITUTE('Référentiel films'!$A$7,"’","'"),SUBSTITUTE(F15,"’","'"))),'Référentiel films'!$B$7,""),IF(ISNUMBER(SEARCH(SUBSTITUTE('Référentiel films'!$A$8,"’","'"),SUBSTITUTE(F15,"’","'"))),'Référentiel films'!$B$8,""),IF(ISNUMBER(SEARCH(SUBSTITUTE('Référentiel films'!$A$9,"’","'"),SUBSTITUTE(F15,"’","'"))),'Référentiel films'!$B$9,""),IF(ISNUMBER(SEARCH(SUBSTITUTE('Référentiel films'!$A$10,"’","'"),SUBSTITUTE(F15,"’","'"))),'Référentiel films'!$B$10,""),IF(ISNUMBER(SEARCH(SUBSTITUTE('Référentiel films'!$A$11,"’","'"),SUBSTITUTE(F15,"’","'"))),'Référentiel films'!$B$11,""),IF(ISNUMBER(SEARCH(SUBSTITUTE('Référentiel films'!$A$12,"’","'"),SUBSTITUTE(F15,"’","'"))),'Référentiel films'!$B$12,""),IF(ISNUMBER(SEARCH(SUBSTITUTE('Référentiel films'!$A$13,"’","'"),SUBSTITUTE(F15,"’","'"))),'Référentiel films'!$B$13,""),IF(ISNUMBER(SEARCH(SUBSTITUTE('Référentiel films'!$A$14,"’","'"),SUBSTITUTE(F15,"’","'"))),'Référentiel films'!$B$14,""),IF(ISNUMBER(SEARCH(SUBSTITUTE('Référentiel films'!$A$15,"’","'"),SUBSTITUTE(F15,"’","'"))),'Référentiel films'!$B$15,""),IF(ISNUMBER(SEARCH(SUBSTITUTE('Référentiel films'!$A$16,"’","'"),SUBSTITUTE(F15,"’","'"))),'Référentiel films'!$B$16,""),IF(ISNUMBER(SEARCH(SUBSTITUTE('Référentiel films'!$A$17,"’","'"),SUBSTITUTE(F15,"’","'"))),'Référentiel films'!$B$17,""),IF(ISNUMBER(SEARCH(SUBSTITUTE('Référentiel films'!$A$18,"’","'"),SUBSTITUTE(F15,"’","'"))),'Référentiel films'!$B$18,""),IF(ISNUMBER(SEARCH(SUBSTITUTE('Référentiel films'!$A$19,"’","'"),SUBSTITUTE(F15,"’","'"))),'Référentiel films'!$B$19,""),IF(ISNUMBER(SEARCH(SUBSTITUTE('Référentiel films'!$A$20,"’","'"),SUBSTITUTE(F15,"’","'"))),'Référentiel films'!$B$20,""),IF(ISNUMBER(SEARCH(SUBSTITUTE('Référentiel films'!$A$21,"’","'"),SUBSTITUTE(F15,"’","'"))),'Référentiel films'!$B$21,""),IF(ISNUMBER(SEARCH(SUBSTITUTE('Référentiel films'!$A$22,"’","'"),SUBSTITUTE(F15,"’","'"))),'Référentiel films'!$B$22,""),IF(ISNUMBER(SEARCH(SUBSTITUTE('Référentiel films'!$A$23,"’","'"),SUBSTITUTE(F15,"’","'"))),'Référentiel films'!$B$23,""),IF(ISNUMBER(SEARCH(SUBSTITUTE('Référentiel films'!$A$24,"’","'"),SUBSTITUTE(F15,"’","'"))),'Référentiel films'!$B$24,""),IF(ISNUMBER(SEARCH(SUBSTITUTE('Référentiel films'!$A$25,"’","'"),SUBSTITUTE(F15,"’","'"))),'Référentiel films'!$B$25,""),IF(ISNUMBER(SEARCH(SUBSTITUTE('Référentiel films'!$A$26,"’","'"),SUBSTITUTE(F15,"’","'"))),'Référentiel films'!$B$26,""),IF(ISNUMBER(SEARCH(SUBSTITUTE('Référentiel films'!$A$27,"’","'"),SUBSTITUTE(F15,"’","'"))),'Référentiel films'!$B$27,""),IF(ISNUMBER(SEARCH(SUBSTITUTE('Référentiel films'!$A$28,"’","'"),SUBSTITUTE(F15,"’","'"))),'Référentiel films'!$B$28,""),IF(ISNUMBER(SEARCH(SUBSTITUTE('Référentiel films'!$A$29,"’","'"),SUBSTITUTE(F15,"’","'"))),'Référentiel films'!$B$29,""),IF(ISNUMBER(SEARCH(SUBSTITUTE('Référentiel films'!$A$30,"’","'"),SUBSTITUTE(F15,"’","'"))),'Référentiel films'!$B$30,""),IF(ISNUMBER(SEARCH(SUBSTITUTE('Référentiel films'!$A$31,"’","'"),SUBSTITUTE(F15,"’","'"))),'Référentiel films'!$B$31,""),IF(ISNUMBER(SEARCH(SUBSTITUTE('Référentiel films'!$A$32,"’","'"),SUBSTITUTE(F15,"’","'"))),'Référentiel films'!$B$32,""),IF(ISNUMBER(SEARCH(SUBSTITUTE('Référentiel films'!$A$33,"’","'"),SUBSTITUTE(F15,"’","'"))),'Référentiel films'!$B$33,""),IF(ISNUMBER(SEARCH(SUBSTITUTE('Référentiel films'!$A$34,"’","'"),SUBSTITUTE(F15,"’","'"))),'Référentiel films'!$B$34,""),IF(ISNUMBER(SEARCH(SUBSTITUTE('Référentiel films'!$A$35,"’","'"),SUBSTITUTE(F15,"’","'"))),'Référentiel films'!$B$35,""),IF(ISNUMBER(SEARCH(SUBSTITUTE('Référentiel films'!$A$36,"’","'"),SUBSTITUTE(F15,"’","'"))),'Référentiel films'!$B$36,""),IF(ISNUMBER(SEARCH(SUBSTITUTE('Référentiel films'!$A$37,"’","'"),SUBSTITUTE(F15,"’","'"))),'Référentiel films'!$B$37,""),IF(ISNUMBER(SEARCH(SUBSTITUTE('Référentiel films'!$A$38,"’","'"),SUBSTITUTE(F15,"’","'"))),'Référentiel films'!$B$38,""),IF(ISNUMBER(SEARCH(SUBSTITUTE('Référentiel films'!$A$39,"’","'"),SUBSTITUTE(F15,"’","'"))),'Référentiel films'!$B$39,""),IF(ISNUMBER(SEARCH(SUBSTITUTE('Référentiel films'!$A$40,"’","'"),SUBSTITUTE(F15,"’","'"))),'Référentiel films'!$B$40,""),IF(ISNUMBER(SEARCH(SUBSTITUTE('Référentiel films'!$A$41,"’","'"),SUBSTITUTE(F15,"’","'"))),'Référentiel films'!$B$41,"")))
A16: 1960 | B16: 1947-1960 | C16: Le constructeur automobile Volkswagen est privatisé à hauteur de 60% de son capital. 78% des ménages ouest-allemands disposent d'un réfrigérateur contre 25% en France. 42% mossèdent une voiture. La société de consommation de masse est une réalité en RFA. Adolf Eichamnn est extradé en Israel. | D16: Fin de la série télévisée Die familie Schölermann (111 épisodes depuis 1954), extrêmement populaire (70% à 90% d'audience). Elle est remplacée par un nouveau feuilleton Die Firma Hesselbach | E16: RWF commence à écrire des nouvelles et de petites pièces de théâtre | M16: Adenauer.jpeg | N16: Portrait d'Adenauer | U16: =IF(F16="","",_xlfn.TEXTJOIN("; ",TRUE(),IF(ISNUMBER(SEARCH(SUBSTITUTE('Référentiel films'!$A$2,"’","'"),SUBSTITUTE(F16,"’","'"))),'Référentiel films'!$B$2,""),IF(ISNUMBER(SEARCH(SUBSTITUTE('Référentiel films'!$A$3,"’","'"),SUBSTITUTE(F16,"’","'"))),'Référentiel films'!$B$3,""),IF(ISNUMBER(SEARCH(SUBSTITUTE('Référentiel films'!$A$4,"’","'"),SUBSTITUTE(F16,"’","'"))),'Référentiel films'!$B$4,""),IF(ISNUMBER(SEARCH(SUBSTITUTE('Référentiel films'!$A$5,"’","'"),SUBSTITUTE(F16,"’","'"))),'Référentiel films'!$B$5,""),IF(ISNUMBER(SEARCH(SUBSTITUTE('Référentiel films'!$A$6,"’","'"),SUBSTITUTE(F16,"’","'"))),'Référentiel films'!$B$6,""),IF(ISNUMBER(SEARCH(SUBSTITUTE('Référentiel films'!$A$7,"’","'"),SUBSTITUTE(F16,"’","'"))),'Référentiel films'!$B$7,""),IF(ISNUMBER(SEARCH(SUBSTITUTE('Référentiel films'!$A$8,"’","'"),SUBSTITUTE(F16,"’","'"))),'Référentiel films'!$B$8,""),IF(ISNUMBER(SEARCH(SUBSTITUTE('Référentiel films'!$A$9,"’","'"),SUBSTITUTE(F16,"’","'"))),'Référentiel films'!$B$9,""),IF(ISNUMBER(SEARCH(SUBSTITUTE('Référentiel films'!$A$10,"’","'"),SUBSTITUTE(F16,"’","'"))),'Référentiel films'!$B$10,""),IF(ISNUMBER(SEARCH(SUBSTITUTE('Référentiel films'!$A$11,"’","'"),SUBSTITUTE(F16,"’","'"))),'Référentiel films'!$B$11,""),IF(ISNUMBER(SEARCH(SUBSTITUTE('Référentiel films'!$A$12,"’","'"),SUBSTITUTE(F16,"’","'"))),'Référentiel films'!$B$12,""),IF(ISNUMBER(SEARCH(SUBSTITUTE('Référentiel films'!$A$13,"’","'"),SUBSTITUTE(F16,"’","'"))),'Référentiel films'!$B$13,""),IF(ISNUMBER(SEARCH(SUBSTITUTE('Référentiel films'!$A$14,"’","'"),SUBSTITUTE(F16,"’","'"))),'Référentiel films'!$B$14,""),IF(ISNUMBER(SEARCH(SUBSTITUTE('Référentiel films'!$A$15,"’","'"),SUBSTITUTE(F16,"’","'"))),'Référentiel films'!$B$15,""),IF(ISNUMBER(SEARCH(SUBSTITUTE('Référentiel films'!$A$16,"’","'"),SUBSTITUTE(F16,"’","'"))),'Référentiel films'!$B$16,""),IF(ISNUMBER(SEARCH(SUBSTITUTE('Référentiel films'!$A$17,"’","'"),SUBSTITUTE(F16,"’","'"))),'Référentiel films'!$B$17,""),IF(ISNUMBER(SEARCH(SUBSTITUTE('Référentiel films'!$A$18,"’","'"),SUBSTITUTE(F16,"’","'"))),'Référentiel films'!$B$18,""),IF(ISNUMBER(SEARCH(SUBSTITUTE('Référentiel films'!$A$19,"’","'"),SUBSTITUTE(F16,"’","'"))),'Référentiel films'!$B$19,""),IF(ISNUMBER(SEARCH(SUBSTITUTE('Référentiel films'!$A$20,"’","'"),SUBSTITUTE(F16,"’","'"))),'Référentiel films'!$B$20,""),IF(ISNUMBER(SEARCH(SUBSTITUTE('Référentiel films'!$A$21,"’","'"),SUBSTITUTE(F16,"’","'"))),'Référentiel films'!$B$21,""),IF(ISNUMBER(SEARCH(SUBSTITUTE('Référentiel films'!$A$22,"’","'"),SUBSTITUTE(F16,"’","'"))),'Référentiel films'!$B$22,""),IF(ISNUMBER(SEARCH(SUBSTITUTE('Référentiel films'!$A$23,"’","'"),SUBSTITUTE(F16,"’","'"))),'Référentiel films'!$B$23,""),IF(ISNUMBER(SEARCH(SUBSTITUTE('Référentiel films'!$A$24,"’","'"),SUBSTITUTE(F16,"’","'"))),'Référentiel films'!$B$24,""),IF(ISNUMBER(SEARCH(SUBSTITUTE('Référentiel films'!$A$25,"’","'"),SUBSTITUTE(F16,"’","'"))),'Référentiel films'!$B$25,""),IF(ISNUMBER(SEARCH(SUBSTITUTE('Référentiel films'!$A$26,"’","'"),SUBSTITUTE(F16,"’","'"))),'Référentiel films'!$B$26,""),IF(ISNUMBER(SEARCH(SUBSTITUTE('Référentiel films'!$A$27,"’","'"),SUBSTITUTE(F16,"’","'"))),'Référentiel films'!$B$27,""),IF(ISNUMBER(SEARCH(SUBSTITUTE('Référentiel films'!$A$28,"’","'"),SUBSTITUTE(F16,"’","'"))),'Référentiel films'!$B$28,""),IF(ISNUMBER(SEARCH(SUBSTITUTE('Référentiel films'!$A$29,"’","'"),SUBSTITUTE(F16,"’","'"))),'Référentiel films'!$B$29,""),IF(ISNUMBER(SEARCH(SUBSTITUTE('Référentiel films'!$A$30,"’","'"),SUBSTITUTE(F16,"’","'"))),'Référentiel films'!$B$30,""),IF(ISNUMBER(SEARCH(SUBSTITUTE('Référentiel films'!$A$31,"’","'"),SUBSTITUTE(F16,"’","'"))),'Référentiel films'!$B$31,""),IF(ISNUMBER(SEARCH(SUBSTITUTE('Référentiel films'!$A$32,"’","'"),SUBSTITUTE(F16,"’","'"))),'Référentiel films'!$B$32,""),IF(ISNUMBER(SEARCH(SUBSTITUTE('Référentiel films'!$A$33,"’","'"),SUBSTITUTE(F16,"’","'"))),'Référentiel films'!$B$33,""),IF(ISNUMBER(SEARCH(SUBSTITUTE('Référentiel films'!$A$34,"’","'"),SUBSTITUTE(F16,"’","'"))),'Référentiel films'!$B$34,""),IF(ISNUMBER(SEARCH(SUBSTITUTE('Référentiel films'!$A$35,"’","'"),SUBSTITUTE(F16,"’","'"))),'Référentiel films'!$B$35,""),IF(ISNUMBER(SEARCH(SUBSTITUTE('Référentiel films'!$A$36,"’","'"),SUBSTITUTE(F16,"’","'"))),'Référentiel films'!$B$36,""),IF(ISNUMBER(SEARCH(SUBSTITUTE('Référentiel films'!$A$37,"’","'"),SUBSTITUTE(F16,"’","'"))),'Référentiel films'!$B$37,""),IF(ISNUMBER(SEARCH(SUBSTITUTE('Référentiel films'!$A$38,"’","'"),SUBSTITUTE(F16,"’","'"))),'Référentiel films'!$B$38,""),IF(ISNUMBER(SEARCH(SUBSTITUTE('Référentiel films'!$A$39,"’","'"),SUBSTITUTE(F16,"’","'"))),'Référentiel films'!$B$39,""),IF(ISNUMBER(SEARCH(SUBSTITUTE('Référentiel films'!$A$40,"’","'"),SUBSTITUTE(F16,"’","'"))),'Référentiel films'!$B$40,""),IF(ISNUMBER(SEARCH(SUBSTITUTE('Référentiel films'!$A$41,"’","'"),SUBSTITUTE(F16,"’","'"))),'Référentiel films'!$B$41,"")))
A17: 1961 | B17: 1961-1966 | C17: Construction du Mur de Berlin (1961). Adenauer est rééel chancelier fédéral. Procès d'Eichmann en Israel. | E17: RWF interrompt ses études avant le baccalauréat. Il rejoint son père à Cologne. Il collecte pour lui des loyers dans des immeubles principalement occupés par des Gastarbeiters (travaillers "invités" c'est-à-dire immigrés). RWF prend des cours du soir, écrit, f'équente les bars homosexuels. | M17: Adenauer.jpeg | N17: Portrait d'Adenauer | U17: =IF(F17="","",_xlfn.TEXTJOIN("; ",TRUE(),IF(ISNUMBER(SEARCH(SUBSTITUTE('Référentiel films'!$A$2,"’","'"),SUBSTITUTE(F17,"’","'"))),'Référentiel films'!$B$2,""),IF(ISNUMBER(SEARCH(SUBSTITUTE('Référentiel films'!$A$3,"’","'"),SUBSTITUTE(F17,"’","'"))),'Référentiel films'!$B$3,""),IF(ISNUMBER(SEARCH(SUBSTITUTE('Référentiel films'!$A$4,"’","'"),SUBSTITUTE(F17,"’","'"))),'Référentiel films'!$B$4,""),IF(ISNUMBER(SEARCH(SUBSTITUTE('Référentiel films'!$A$5,"’","'"),SUBSTITUTE(F17,"’","'"))),'Référentiel films'!$B$5,""),IF(ISNUMBER(SEARCH(SUBSTITUTE('Référentiel films'!$A$6,"’","'"),SUBSTITUTE(F17,"’","'"))),'Référentiel films'!$B$6,""),IF(ISNUMBER(SEARCH(SUBSTITUTE('Référentiel films'!$A$7,"’","'"),SUBSTITUTE(F17,"’","'"))),'Référentiel films'!$B$7,""),IF(ISNUMBER(SEARCH(SUBSTITUTE('Référentiel films'!$A$8,"’","'"),SUBSTITUTE(F17,"’","'"))),'Référentiel films'!$B$8,""),IF(ISNUMBER(SEARCH(SUBSTITUTE('Référentiel films'!$A$9,"’","'"),SUBSTITUTE(F17,"’","'"))),'Référentiel films'!$B$9,""),IF(ISNUMBER(SEARCH(SUBSTITUTE('Référentiel films'!$A$10,"’","'"),SUBSTITUTE(F17,"’","'"))),'Référentiel films'!$B$10,""),IF(ISNUMBER(SEARCH(SUBSTITUTE('Référentiel films'!$A$11,"’","'"),SUBSTITUTE(F17,"’","'"))),'Référentiel films'!$B$11,""),IF(ISNUMBER(SEARCH(SUBSTITUTE('Référentiel films'!$A$12,"’","'"),SUBSTITUTE(F17,"’","'"))),'Référentiel films'!$B$12,""),IF(ISNUMBER(SEARCH(SUBSTITUTE('Référentiel films'!$A$13,"’","'"),SUBSTITUTE(F17,"’","'"))),'Référentiel films'!$B$13,""),IF(ISNUMBER(SEARCH(SUBSTITUTE('Référentiel films'!$A$14,"’","'"),SUBSTITUTE(F17,"’","'"))),'Référentiel films'!$B$14,""),IF(ISNUMBER(SEARCH(SUBSTITUTE('Référentiel films'!$A$15,"’","'"),SUBSTITUTE(F17,"’","'"))),'Référentiel films'!$B$15,""),IF(ISNUMBER(SEARCH(SUBSTITUTE('Référentiel films'!$A$16,"’","'"),SUBSTITUTE(F17,"’","'"))),'Référentiel films'!$B$16,""),IF(ISNUMBER(SEARCH(SUBSTITUTE('Référentiel films'!$A$17,"’","'"),SUBSTITUTE(F17,"’","'"))),'Référentiel films'!$B$17,""),IF(ISNUMBER(SEARCH(SUBSTITUTE('Référentiel films'!$A$18,"’","'"),SUBSTITUTE(F17,"’","'"))),'Référentiel films'!$B$18,""),IF(ISNUMBER(SEARCH(SUBSTITUTE('Référentiel films'!$A$19,"’","'"),SUBSTITUTE(F17,"’","'"))),'Référentiel films'!$B$19,""),IF(ISNUMBER(SEARCH(SUBSTITUTE('Référentiel films'!$A$20,"’","'"),SUBSTITUTE(F17,"’","'"))),'Référentiel films'!$B$20,""),IF(ISNUMBER(SEARCH(SUBSTITUTE('Référentiel films'!$A$21,"’","'"),SUBSTITUTE(F17,"’","'"))),'Référentiel films'!$B$21,""),IF(ISNUMBER(SEARCH(SUBSTITUTE('Référentiel films'!$A$22,"’","'"),SUBSTITUTE(F17,"’","'"))),'Référentiel films'!$B$22,""),IF(ISNUMBER(SEARCH(SUBSTITUTE('Référentiel films'!$A$23,"’","'"),SUBSTITUTE(F17,"’","'"))),'Référentiel films'!$B$23,""),IF(ISNUMBER(SEARCH(SUBSTITUTE('Référentiel films'!$A$24,"’","'"),SUBSTITUTE(F17,"’","'"))),'Référentiel films'!$B$24,""),IF(ISNUMBER(SEARCH(SUBSTITUTE('Référentiel films'!$A$25,"’","'"),SUBSTITUTE(F17,"’","'"))),'Référentiel films'!$B$25,""),IF(ISNUMBER(SEARCH(SUBSTITUTE('Référentiel films'!$A$26,"’","'"),SUBSTITUTE(F17,"’","'"))),'Référentiel films'!$B$26,""),IF(ISNUMBER(SEARCH(SUBSTITUTE('Référentiel films'!$A$27,"’","'"),SUBSTITUTE(F17,"’","'"))),'Référentiel films'!$B$27,""),IF(ISNUMBER(SEARCH(SUBSTITUTE('Référentiel films'!$A$28,"’","'"),SUBSTITUTE(F17,"’","'"))),'Référentiel films'!$B$28,""),IF(ISNUMBER(SEARCH(SUBSTITUTE('Référentiel films'!$A$29,"’","'"),SUBSTITUTE(F17,"’","'"))),'Référentiel films'!$B$29,""),IF(ISNUMBER(SEARCH(SUBSTITUTE('Référentiel films'!$A$30,"’","'"),SUBSTITUTE(F17,"’","'"))),'Référentiel films'!$B$30,""),IF(ISNUMBER(SEARCH(SUBSTITUTE('Référentiel films'!$A$31,"’","'"),SUBSTITUTE(F17,"’","'"))),'Référentiel films'!$B$31,""),IF(ISNUMBER(SEARCH(SUBSTITUTE('Référentiel films'!$A$32,"’","'"),SUBSTITUTE(F17,"’","'"))),'Référentiel films'!$B$32,""),IF(ISNUMBER(SEARCH(SUBSTITUTE('Référentiel films'!$A$33,"’","'"),SUBSTITUTE(F17,"’","'"))),'Référentiel films'!$B$33,""),IF(ISNUMBER(SEARCH(SUBSTITUTE('Référentiel films'!$A$34,"’","'"),SUBSTITUTE(F17,"’","'"))),'Référentiel films'!$B$34,""),IF(ISNUMBER(SEARCH(SUBSTITUTE('Référentiel films'!$A$35,"’","'"),SUBSTITUTE(F17,"’","'"))),'Référentiel films'!$B$35,""),IF(ISNUMBER(SEARCH(SUBSTITUTE('Référentiel films'!$A$36,"’","'"),SUBSTITUTE(F17,"’","'"))),'Référentiel films'!$B$36,""),IF(ISNUMBER(SEARCH(SUBSTITUTE('Référentiel films'!$A$37,"’","'"),SUBSTITUTE(F17,"’","'"))),'Référentiel films'!$B$37,""),IF(ISNUMBER(SEARCH(SUBSTITUTE('Référentiel films'!$A$38,"’","'"),SUBSTITUTE(F17,"’","'"))),'Référentiel films'!$B$38,""),IF(ISNUMBER(SEARCH(SUBSTITUTE('Référentiel films'!$A$39,"’","'"),SUBSTITUTE(F17,"’","'"))),'Référentiel films'!$B$39,""),IF(ISNUMBER(SEARCH(SUBSTITUTE('Référentiel films'!$A$40,"’","'"),SUBSTITUTE(F17,"’","'"))),'Référentiel films'!$B$40,""),IF(ISNUMBER(SEARCH(SUBSTITUTE('Référentiel films'!$A$41,"’","'"),SUBSTITUTE(F17,"’","'"))),'Référentiel films'!$B$41,"")))
A18: 1962 | B18: 1961-1966 | C18: Exécution d'Eichmann après sa condamnation à la peine de mort | D18: A l'occasion du festival du film documentaire d'Oberhausen, publication du Manifeste d'Oberhausen : naissance du Nouveau Cinéma Allemand ("Le vieux cinéma est mort"). Les Beatles entament eur carrière par un concert à Hambourg | L18: "Représenter l'Allemagne, ce n'est pas seulement adopter une position critique, c'est inventer une nouvelle manière". R. W. Fassbinder, cinéaste d’Allemagne, de Thomas Elsaesser, Centre Pompidou, 2005, p.26 | M18: Adenauer.jpeg | N18: Portrait d'Adenauer | U18: =IF(F18="","",_xlfn.TEXTJOIN("; ",TRUE(),IF(ISNUMBER(SEARCH(SUBSTITUTE('Référentiel films'!$A$2,"’","'"),SUBSTITUTE(F18,"’","'"))),'Référentiel films'!$B$2,""),IF(ISNUMBER(SEARCH(SUBSTITUTE('Référentiel films'!$A$3,"’","'"),SUBSTITUTE(F18,"’","'"))),'Référentiel films'!$B$3,""),IF(ISNUMBER(SEARCH(SUBSTITUTE('Référentiel films'!$A$4,"’","'"),SUBSTITUTE(F18,"’","'"))),'Référentiel films'!$B$4,""),IF(ISNUMBER(SEARCH(SUBSTITUTE('Référentiel films'!$A$5,"’","'"),SUBSTITUTE(F18,"’","'"))),'Référentiel films'!$B$5,""),IF(ISNUMBER(SEARCH(SUBSTITUTE('Référentiel films'!$A$6,"’","'"),SUBSTITUTE(F18,"’","'"))),'Référentiel films'!$B$6,""),IF(ISNUMBER(SEARCH(SUBSTITUTE('Référentiel films'!$A$7,"’","'"),SUBSTITUTE(F18,"’","'"))),'Référentiel films'!$B$7,""),IF(ISNUMBER(SEARCH(SUBSTITUTE('Référentiel films'!$A$8,"’","'"),SUBSTITUTE(F18,"’","'"))),'Référentiel films'!$B$8,""),IF(ISNUMBER(SEARCH(SUBSTITUTE('Référentiel films'!$A$9,"’","'"),SUBSTITUTE(F18,"’","'"))),'Référentiel films'!$B$9,""),IF(ISNUMBER(SEARCH(SUBSTITUTE('Référentiel films'!$A$10,"’","'"),SUBSTITUTE(F18,"’","'"))),'Référentiel films'!$B$10,""),IF(ISNUMBER(SEARCH(SUBSTITUTE('Référentiel films'!$A$11,"’","'"),SUBSTITUTE(F18,"’","'"))),'Référentiel films'!$B$11,""),IF(ISNUMBER(SEARCH(SUBSTITUTE('Référentiel films'!$A$12,"’","'"),SUBSTITUTE(F18,"’","'"))),'Référentiel films'!$B$12,""),IF(ISNUMBER(SEARCH(SUBSTITUTE('Référentiel films'!$A$13,"’","'"),SUBSTITUTE(F18,"’","'"))),'Référentiel films'!$B$13,""),IF(ISNUMBER(SEARCH(SUBSTITUTE('Référentiel films'!$A$14,"’","'"),SUBSTITUTE(F18,"’","'"))),'Référentiel films'!$B$14,""),IF(ISNUMBER(SEARCH(SUBSTITUTE('Référentiel films'!$A$15,"’","'"),SUBSTITUTE(F18,"’","'"))),'Référentiel films'!$B$15,""),IF(ISNUMBER(SEARCH(SUBSTITUTE('Référentiel films'!$A$16,"’","'"),SUBSTITUTE(F18,"’","'"))),'Référentiel films'!$B$16,""),IF(ISNUMBER(SEARCH(SUBSTITUTE('Référentiel films'!$A$17,"’","'"),SUBSTITUTE(F18,"’","'"))),'Référentiel films'!$B$17,""),IF(ISNUMBER(SEARCH(SUBSTITUTE('Référentiel films'!$A$18,"’","'"),SUBSTITUTE(F18,"’","'"))),'Référentiel films'!$B$18,""),IF(ISNUMBER(SEARCH(SUBSTITUTE('Référentiel films'!$A$19,"’","'"),SUBSTITUTE(F18,"’","'"))),'Référentiel films'!$B$19,""),IF(ISNUMBER(SEARCH(SUBSTITUTE('Référentiel films'!$A$20,"’","'"),SUBSTITUTE(F18,"’","'"))),'Référentiel films'!$B$20,""),IF(ISNUMBER(SEARCH(SUBSTITUTE('Référentiel films'!$A$21,"’","'"),SUBSTITUTE(F18,"’","'"))),'Référentiel films'!$B$21,""),IF(ISNUMBER(SEARCH(SUBSTITUTE('Référentiel films'!$A$22,"’","'"),SUBSTITUTE(F18,"’","'"))),'Référentiel films'!$B$22,""),IF(ISNUMBER(SEARCH(SUBSTITUTE('Référentiel films'!$A$23,"’","'"),SUBSTITUTE(F18,"’","'"))),'Référentiel films'!$B$23,""),IF(ISNUMBER(SEARCH(SUBSTITUTE('Référentiel films'!$A$24,"’","'"),SUBSTITUTE(F18,"’","'"))),'Référentiel films'!$B$24,""),IF(ISNUMBER(SEARCH(SUBSTITUTE('Référentiel films'!$A$25,"’","'"),SUBSTITUTE(F18,"’","'"))),'Référentiel films'!$B$25,""),IF(ISNUMBER(SEARCH(SUBSTITUTE('Référentiel films'!$A$26,"’","'"),SUBSTITUTE(F18,"’","'"))),'Référentiel films'!$B$26,""),IF(ISNUMBER(SEARCH(SUBSTITUTE('Référentiel films'!$A$27,"’","'"),SUBSTITUTE(F18,"’","'"))),'Référentiel films'!$B$27,""),IF(ISNUMBER(SEARCH(SUBSTITUTE('Référentiel films'!$A$28,"’","'"),SUBSTITUTE(F18,"’","'"))),'Référentiel films'!$B$28,""),IF(ISNUMBER(SEARCH(SUBSTITUTE('Référentiel films'!$A$29,"’","'"),SUBSTITUTE(F18,"’","'"))),'Référentiel films'!$B$29,""),IF(ISNUMBER(SEARCH(SUBSTITUTE('Référentiel films'!$A$30,"’","'"),SUBSTITUTE(F18,"’","'"))),'Référentiel films'!$B$30,""),IF(ISNUMBER(SEARCH(SUBSTITUTE('Référentiel films'!$A$31,"’","'"),SUBSTITUTE(F18,"’","'"))),'Référentiel films'!$B$31,""),IF(ISNUMBER(SEARCH(SUBSTITUTE('Référentiel films'!$A$32,"’","'"),SUBSTITUTE(F18,"’","'"))),'Référentiel films'!$B$32,""),IF(ISNUMBER(SEARCH(SUBSTITUTE('Référentiel films'!$A$33,"’","'"),SUBSTITUTE(F18,"’","'"))),'Référentiel films'!$B$33,""),IF(ISNUMBER(SEARCH(SUBSTITUTE('Référentiel films'!$A$34,"’","'"),SUBSTITUTE(F18,"’","'"))),'Référentiel films'!$B$34,""),IF(ISNUMBER(SEARCH(SUBSTITUTE('Référentiel films'!$A$35,"’","'"),SUBSTITUTE(F18,"’","'"))),'Référentiel films'!$B$35,""),IF(ISNUMBER(SEARCH(SUBSTITUTE('Référentiel films'!$A$36,"’","'"),SUBSTITUTE(F18,"’","'"))),'Référentiel films'!$B$36,""),IF(ISNUMBER(SEARCH(SUBSTITUTE('Référentiel films'!$A$37,"’","'"),SUBSTITUTE(F18,"’","'"))),'Référentiel films'!$B$37,""),IF(ISNUMBER(SEARCH(SUBSTITUTE('Référentiel films'!$A$38,"’","'"),SUBSTITUTE(F18,"’","'"))),'Référentiel films'!$B$38,""),IF(ISNUMBER(SEARCH(SUBSTITUTE('Référentiel films'!$A$39,"’","'"),SUBSTITUTE(F18,"’","'"))),'Référentiel films'!$B$39,""),IF(ISNUMBER(SEARCH(SUBSTITUTE('Référentiel films'!$A$40,"’","'"),SUBSTITUTE(F18,"’","'"))),'Référentiel films'!$B$40,""),IF(ISNUMBER(SEARCH(SUBSTITUTE('Référentiel films'!$A$41,"’","'"),SUBSTITUTE(F18,"’","'"))),'Référentiel films'!$B$41,"")))
A19: 1963 | C19: Visite de J.F Kennedy à Berlin-ouest : "ich bin ein Berliner". Procès d'Auschwitz à Francfort (1963-1965) Démission d'Adenauer à 87 ans. Ludwijg Ehrard, père du "miracle économique", devient Chancelier de la RFA. | D19: Jean-Marie Straub sort son premier court-métrage, Machorka Muff, d'après un roman d'Heinrich Böll. Création de la deuxième chaîne de télévision ouest-allemande, la ZDF. Hannah Arendt, qui a suivi le procès d'Eichmann pour la revue Le New-Yorker, publie Eichmann à Jérusalem : Rapport sur la banalité du mal Alexander Mitscherlich publie La société sans père qui décrit l'affaiblissement et la crise du système patriarcal dans les sociétés modernes d'après-guerre. La figure du père n'est plus un modèle absolu et le vide de son absence (d'abord concrète puisqu'il travaille mais aussi symbolique du fait du manque de figures crédibles ) entraine l'expression, plus ou moins anarchique et violente, des forces pulsionnelles négatives. celles-ci sont le fait d'une autorité sociale dont les contraintes paraissent de plus en plus absurdes et répressives puisqu'elles ne sont plus intégrées par l'identificaion à une figure individuelle affective. | E19: RWF retourne à Munich et contitnue d'écire, pièces, romans, scénarios. Il travaille quelques temps au département documentation au journal Südedeutsche Zeitung . RWF prend des cours privés de théâtre. | H19: Portrait de Straub et carrière | I19: Machorka Muff de Jean-Marie Straub | J19: Court-métrage de Jean-Marie Straub. Straub exercera une influence certaine sur le début de carrière de RWF. Le court-métrage s'inscrit dans une réflexion sur le passé nazi de l'Allemagne et dénonce la remilitarisation de l'Allemagne. | M19: Jean-Marie Straub.jpg | N19: Jean-Marie Straub | U19: =IF(F19="","",_xlfn.TEXTJOIN("; ",TRUE(),IF(ISNUMBER(SEARCH(SUBSTITUTE('Référentiel films'!$A$2,"’","'"),SUBSTITUTE(F19,"’","'"))),'Référentiel films'!$B$2,""),IF(ISNUMBER(SEARCH(SUBSTITUTE('Référentiel films'!$A$3,"’","'"),SUBSTITUTE(F19,"’","'"))),'Référentiel films'!$B$3,""),IF(ISNUMBER(SEARCH(SUBSTITUTE('Référentiel films'!$A$4,"’","'"),SUBSTITUTE(F19,"’","'"))),'Référentiel films'!$B$4,""),IF(ISNUMBER(SEARCH(SUBSTITUTE('Référentiel films'!$A$5,"’","'"),SUBSTITUTE(F19,"’","'"))),'Référentiel films'!$B$5,""),IF(ISNUMBER(SEARCH(SUBSTITUTE('Référentiel films'!$A$6,"’","'"),SUBSTITUTE(F19,"’","'"))),'Référentiel films'!$B$6,""),IF(ISNUMBER(SEARCH(SUBSTITUTE('Référentiel films'!$A$7,"’","'"),SUBSTITUTE(F19,"’","'"))),'Référentiel films'!$B$7,""),IF(ISNUMBER(SEARCH(SUBSTITUTE('Référentiel films'!$A$8,"’","'"),SUBSTITUTE(F19,"’","'"))),'Référentiel films'!$B$8,""),IF(ISNUMBER(SEARCH(SUBSTITUTE('Référentiel films'!$A$9,"’","'"),SUBSTITUTE(F19,"’","'"))),'Référentiel films'!$B$9,""),IF(ISNUMBER(SEARCH(SUBSTITUTE('Référentiel films'!$A$10,"’","'"),SUBSTITUTE(F19,"’","'"))),'Référentiel films'!$B$10,""),IF(ISNUMBER(SEARCH(SUBSTITUTE('Référentiel films'!$A$11,"’","'"),SUBSTITUTE(F19,"’","'"))),'Référentiel films'!$B$11,""),IF(ISNUMBER(SEARCH(SUBSTITUTE('Référentiel films'!$A$12,"’","'"),SUBSTITUTE(F19,"’","'"))),'Référentiel films'!$B$12,""),IF(ISNUMBER(SEARCH(SUBSTITUTE('Référentiel films'!$A$13,"’","'"),SUBSTITUTE(F19,"’","'"))),'Référentiel films'!$B$13,""),IF(ISNUMBER(SEARCH(SUBSTITUTE('Référentiel films'!$A$14,"’","'"),SUBSTITUTE(F19,"’","'"))),'Référentiel films'!$B$14,""),IF(ISNUMBER(SEARCH(SUBSTITUTE('Référentiel films'!$A$15,"’","'"),SUBSTITUTE(F19,"’","'"))),'Référentiel films'!$B$15,""),IF(ISNUMBER(SEARCH(SUBSTITUTE('Référentiel films'!$A$16,"’","'"),SUBSTITUTE(F19,"’","'"))),'Référentiel films'!$B$16,""),IF(ISNUMBER(SEARCH(SUBSTITUTE('Référentiel films'!$A$17,"’","'"),SUBSTITUTE(F19,"’","'"))),'Référentiel films'!$B$17,""),IF(ISNUMBER(SEARCH(SUBSTITUTE('Référentiel films'!$A$18,"’","'"),SUBSTITUTE(F19,"’","'"))),'Référentiel films'!$B$18,""),IF(ISNUMBER(SEARCH(SUBSTITUTE('Référentiel films'!$A$19,"’","'"),SUBSTITUTE(F19,"’","'"))),'Référentiel films'!$B$19,""),IF(ISNUMBER(SEARCH(SUBSTITUTE('Référentiel films'!$A$20,"’","'"),SUBSTITUTE(F19,"’","'"))),'Référentiel films'!$B$20,""),IF(ISNUMBER(SEARCH(SUBSTITUTE('Référentiel films'!$A$21,"’","'"),SUBSTITUTE(F19,"’","'"))),'Référentiel films'!$B$21,""),IF(ISNUMBER(SEARCH(SUBSTITUTE('Référentiel films'!$A$22,"’","'"),SUBSTITUTE(F19,"’","'"))),'Référentiel films'!$B$22,""),IF(ISNUMBER(SEARCH(SUBSTITUTE('Référentiel films'!$A$23,"’","'"),SUBSTITUTE(F19,"’","'"))),'Référentiel films'!$B$23,""),IF(ISNUMBER(SEARCH(SUBSTITUTE('Référentiel films'!$A$24,"’","'"),SUBSTITUTE(F19,"’","'"))),'Référentiel films'!$B$24,""),IF(ISNUMBER(SEARCH(SUBSTITUTE('Référentiel films'!$A$25,"’","'"),SUBSTITUTE(F19,"’","'"))),'Référentiel films'!$B$25,""),IF(ISNUMBER(SEARCH(SUBSTITUTE('Référentiel films'!$A$26,"’","'"),SUBSTITUTE(F19,"’","'"))),'Référentiel films'!$B$26,""),IF(ISNUMBER(SEARCH(SUBSTITUTE('Référentiel films'!$A$27,"’","'"),SUBSTITUTE(F19,"’","'"))),'Référentiel films'!$B$27,""),IF(ISNUMBER(SEARCH(SUBSTITUTE('Référentiel films'!$A$28,"’","'"),SUBSTITUTE(F19,"’","'"))),'Référentiel films'!$B$28,""),IF(ISNUMBER(SEARCH(SUBSTITUTE('Référentiel films'!$A$29,"’","'"),SUBSTITUTE(F19,"’","'"))),'Référentiel films'!$B$29,""),IF(ISNUMBER(SEARCH(SUBSTITUTE('Référentiel films'!$A$30,"’","'"),SUBSTITUTE(F19,"’","'"))),'Référentiel films'!$B$30,""),IF(ISNUMBER(SEARCH(SUBSTITUTE('Référentiel films'!$A$31,"’","'"),SUBSTITUTE(F19,"’","'"))),'Référentiel films'!$B$31,""),IF(ISNUMBER(SEARCH(SUBSTITUTE('Référentiel films'!$A$32,"’","'"),SUBSTITUTE(F19,"’","'"))),'Référentiel films'!$B$32,""),IF(ISNUMBER(SEARCH(SUBSTITUTE('Référentiel films'!$A$33,"’","'"),SUBSTITUTE(F19,"’","'"))),'Référentiel films'!$B$33,""),IF(ISNUMBER(SEARCH(SUBSTITUTE('Référentiel films'!$A$34,"’","'"),SUBSTITUTE(F19,"’","'"))),'Référentiel films'!$B$34,""),IF(ISNUMBER(SEARCH(SUBSTITUTE('Référentiel films'!$A$35,"’","'"),SUBSTITUTE(F19,"’","'"))),'Référentiel films'!$B$35,""),IF(ISNUMBER(SEARCH(SUBSTITUTE('Référentiel films'!$A$36,"’","'"),SUBSTITUTE(F19,"’","'"))),'Référentiel films'!$B$36,""),IF(ISNUMBER(SEARCH(SUBSTITUTE('Référentiel films'!$A$37,"’","'"),SUBSTITUTE(F19,"’","'"))),'Référentiel films'!$B$37,""),IF(ISNUMBER(SEARCH(SUBSTITUTE('Référentiel films'!$A$38,"’","'"),SUBSTITUTE(F19,"’","'"))),'Référentiel films'!$B$38,""),IF(ISNUMBER(SEARCH(SUBSTITUTE('Référentiel films'!$A$39,"’","'"),SUBSTITUTE(F19,"’","'"))),'Référentiel films'!$B$39,""),IF(ISNUMBER(SEARCH(SUBSTITUTE('Référentiel films'!$A$40,"’","'"),SUBSTITUTE(F19,"’","'"))),'Référentiel films'!$B$40,""),IF(ISNUMBER(SEARCH(SUBSTITUTE('Référentiel films'!$A$41,"’","'"),SUBSTITUTE(F19,"’","'"))),'Référentiel films'!$B$41,"")))
A20: 1964 | E20: RWF s'inscrit à l'école d'art dramatique Fridl Loeonhard | U20: =IF(F20="","",_xlfn.TEXTJOIN("; ",TRUE(),IF(ISNUMBER(SEARCH(SUBSTITUTE('Référentiel films'!$A$2,"’","'"),SUBSTITUTE(F20,"’","'"))),'Référentiel films'!$B$2,""),IF(ISNUMBER(SEARCH(SUBSTITUTE('Référentiel films'!$A$3,"’","'"),SUBSTITUTE(F20,"’","'"))),'Référentiel films'!$B$3,""),IF(ISNUMBER(SEARCH(SUBSTITUTE('Référentiel films'!$A$4,"’","'"),SUBSTITUTE(F20,"’","'"))),'Référentiel films'!$B$4,""),IF(ISNUMBER(SEARCH(SUBSTITUTE('Référentiel films'!$A$5,"’","'"),SUBSTITUTE(F20,"’","'"))),'Référentiel films'!$B$5,""),IF(ISNUMBER(SEARCH(SUBSTITUTE('Référentiel films'!$A$6,"’","'"),SUBSTITUTE(F20,"’","'"))),'Référentiel films'!$B$6,""),IF(ISNUMBER(SEARCH(SUBSTITUTE('Référentiel films'!$A$7,"’","'"),SUBSTITUTE(F20,"’","'"))),'Référentiel films'!$B$7,""),IF(ISNUMBER(SEARCH(SUBSTITUTE('Référentiel films'!$A$8,"’","'"),SUBSTITUTE(F20,"’","'"))),'Référentiel films'!$B$8,""),IF(ISNUMBER(SEARCH(SUBSTITUTE('Référentiel films'!$A$9,"’","'"),SUBSTITUTE(F20,"’","'"))),'Référentiel films'!$B$9,""),IF(ISNUMBER(SEARCH(SUBSTITUTE('Référentiel films'!$A$10,"’","'"),SUBSTITUTE(F20,"’","'"))),'Référentiel films'!$B$10,""),IF(ISNUMBER(SEARCH(SUBSTITUTE('Référentiel films'!$A$11,"’","'"),SUBSTITUTE(F20,"’","'"))),'Référentiel films'!$B$11,""),IF(ISNUMBER(SEARCH(SUBSTITUTE('Référentiel films'!$A$12,"’","'"),SUBSTITUTE(F20,"’","'"))),'Référentiel films'!$B$12,""),IF(ISNUMBER(SEARCH(SUBSTITUTE('Référentiel films'!$A$13,"’","'"),SUBSTITUTE(F20,"’","'"))),'Référentiel films'!$B$13,""),IF(ISNUMBER(SEARCH(SUBSTITUTE('Référentiel films'!$A$14,"’","'"),SUBSTITUTE(F20,"’","'"))),'Référentiel films'!$B$14,""),IF(ISNUMBER(SEARCH(SUBSTITUTE('Référentiel films'!$A$15,"’","'"),SUBSTITUTE(F20,"’","'"))),'Référentiel films'!$B$15,""),IF(ISNUMBER(SEARCH(SUBSTITUTE('Référentiel films'!$A$16,"’","'"),SUBSTITUTE(F20,"’","'"))),'Référentiel films'!$B$16,""),IF(ISNUMBER(SEARCH(SUBSTITUTE('Référentiel films'!$A$17,"’","'"),SUBSTITUTE(F20,"’","'"))),'Référentiel films'!$B$17,""),IF(ISNUMBER(SEARCH(SUBSTITUTE('Référentiel films'!$A$18,"’","'"),SUBSTITUTE(F20,"’","'"))),'Référentiel films'!$B$18,""),IF(ISNUMBER(SEARCH(SUBSTITUTE('Référentiel films'!$A$19,"’","'"),SUBSTITUTE(F20,"’","'"))),'Référentiel films'!$B$19,""),IF(ISNUMBER(SEARCH(SUBSTITUTE('Référentiel films'!$A$20,"’","'"),SUBSTITUTE(F20,"’","'"))),'Référentiel films'!$B$20,""),IF(ISNUMBER(SEARCH(SUBSTITUTE('Référentiel films'!$A$21,"’","'"),SUBSTITUTE(F20,"’","'"))),'Référentiel films'!$B$21,""),IF(ISNUMBER(SEARCH(SUBSTITUTE('Référentiel films'!$A$22,"’","'"),SUBSTITUTE(F20,"’","'"))),'Référentiel films'!$B$22,""),IF(ISNUMBER(SEARCH(SUBSTITUTE('Référentiel films'!$A$23,"’","'"),SUBSTITUTE(F20,"’","'"))),'Référentiel films'!$B$23,""),IF(ISNUMBER(SEARCH(SUBSTITUTE('Référentiel films'!$A$24,"’","'"),SUBSTITUTE(F20,"’","'"))),'Référentiel films'!$B$24,""),IF(ISNUMBER(SEARCH(SUBSTITUTE('Référentiel films'!$A$25,"’","'"),SUBSTITUTE(F20,"’","'"))),'Référentiel films'!$B$25,""),IF(ISNUMBER(SEARCH(SUBSTITUTE('Référentiel films'!$A$26,"’","'"),SUBSTITUTE(F20,"’","'"))),'Référentiel films'!$B$26,""),IF(ISNUMBER(SEARCH(SUBSTITUTE('Référentiel films'!$A$27,"’","'"),SUBSTITUTE(F20,"’","'"))),'Référentiel films'!$B$27,""),IF(ISNUMBER(SEARCH(SUBSTITUTE('Référentiel films'!$A$28,"’","'"),SUBSTITUTE(F20,"’","'"))),'Référentiel films'!$B$28,""),IF(ISNUMBER(SEARCH(SUBSTITUTE('Référentiel films'!$A$29,"’","'"),SUBSTITUTE(F20,"’","'"))),'Référentiel films'!$B$29,""),IF(ISNUMBER(SEARCH(SUBSTITUTE('Référentiel films'!$A$30,"’","'"),SUBSTITUTE(F20,"’","'"))),'Référentiel films'!$B$30,""),IF(ISNUMBER(SEARCH(SUBSTITUTE('Référentiel films'!$A$31,"’","'"),SUBSTITUTE(F20,"’","'"))),'Référentiel films'!$B$31,""),IF(ISNUMBER(SEARCH(SUBSTITUTE('Référentiel films'!$A$32,"’","'"),SUBSTITUTE(F20,"’","'"))),'Référentiel films'!$B$32,""),IF(ISNUMBER(SEARCH(SUBSTITUTE('Référentiel films'!$A$33,"’","'"),SUBSTITUTE(F20,"’","'"))),'Référentiel films'!$B$33,""),IF(ISNUMBER(SEARCH(SUBSTITUTE('Référentiel films'!$A$34,"’","'"),SUBSTITUTE(F20,"’","'"))),'Référentiel films'!$B$34,""),IF(ISNUMBER(SEARCH(SUBSTITUTE('Référentiel films'!$A$35,"’","'"),SUBSTITUTE(F20,"’","'"))),'Référentiel films'!$B$35,""),IF(ISNUMBER(SEARCH(SUBSTITUTE('Référentiel films'!$A$36,"’","'"),SUBSTITUTE(F20,"’","'"))),'Référentiel films'!$B$36,""),IF(ISNUMBER(SEARCH(SUBSTITUTE('Référentiel films'!$A$37,"’","'"),SUBSTITUTE(F20,"’","'"))),'Référentiel films'!$B$37,""),IF(ISNUMBER(SEARCH(SUBSTITUTE('Référentiel films'!$A$38,"’","'"),SUBSTITUTE(F20,"’","'"))),'Référentiel films'!$B$38,""),IF(ISNUMBER(SEARCH(SUBSTITUTE('Référentiel films'!$A$39,"’","'"),SUBSTITUTE(F20,"’","'"))),'Référentiel films'!$B$39,""),IF(ISNUMBER(SEARCH(SUBSTITUTE('Référentiel films'!$A$40,"’","'"),SUBSTITUTE(F20,"’","'"))),'Référentiel films'!$B$40,""),IF(ISNUMBER(SEARCH(SUBSTITUTE('Référentiel films'!$A$41,"’","'"),SUBSTITUTE(F20,"’","'"))),'Référentiel films'!$B$41,"")))
A21: 1966 | B21: 1961-1966 | C21: Une grande coaltion chrétienne-démocrate voit le jour sous l'autorité du nouveau chancelier Kurt Georg Kiesinger. Willy Brandt est ministre des affaires étrangères et vice-chancelier. | D21: La pièce outrage au public du dramaturge allemand Peter Handke témoigne du goût de l'avant-garde artistique subentionnée pour une forme de provocation à l'égard du public, manière paradoxale de s'affranchir de la tutelle culturelle dont ils bénéficient. | F21: Réalise ses premiers courts métrages : This Night (1966) et Le Clochard (1966). Confrontation de la mémoire de la Shoah. | U21: =IF(F21="","",_xlfn.TEXTJOIN("; ",TRUE(),IF(ISNUMBER(SEARCH(SUBSTITUTE('Référentiel films'!$A$2,"’","'"),SUBSTITUTE(F21,"’","'"))),'Référentiel films'!$B$2,""),IF(ISNUMBER(SEARCH(SUBSTITUTE('Référentiel films'!$A$3,"’","'"),SUBSTITUTE(F21,"’","'"))),'Référentiel films'!$B$3,""),IF(ISNUMBER(SEARCH(SUBSTITUTE('Référentiel films'!$A$4,"’","'"),SUBSTITUTE(F21,"’","'"))),'Référentiel films'!$B$4,""),IF(ISNUMBER(SEARCH(SUBSTITUTE('Référentiel films'!$A$5,"’","'"),SUBSTITUTE(F21,"’","'"))),'Référentiel films'!$B$5,""),IF(ISNUMBER(SEARCH(SUBSTITUTE('Référentiel films'!$A$6,"’","'"),SUBSTITUTE(F21,"’","'"))),'Référentiel films'!$B$6,""),IF(ISNUMBER(SEARCH(SUBSTITUTE('Référentiel films'!$A$7,"’","'"),SUBSTITUTE(F21,"’","'"))),'Référentiel films'!$B$7,""),IF(ISNUMBER(SEARCH(SUBSTITUTE('Référentiel films'!$A$8,"’","'"),SUBSTITUTE(F21,"’","'"))),'Référentiel films'!$B$8,""),IF(ISNUMBER(SEARCH(SUBSTITUTE('Référentiel films'!$A$9,"’","'"),SUBSTITUTE(F21,"’","'"))),'Référentiel films'!$B$9,""),IF(ISNUMBER(SEARCH(SUBSTITUTE('Référentiel films'!$A$10,"’","'"),SUBSTITUTE(F21,"’","'"))),'Référentiel films'!$B$10,""),IF(ISNUMBER(SEARCH(SUBSTITUTE('Référentiel films'!$A$11,"’","'"),SUBSTITUTE(F21,"’","'"))),'Référentiel films'!$B$11,""),IF(ISNUMBER(SEARCH(SUBSTITUTE('Référentiel films'!$A$12,"’","'"),SUBSTITUTE(F21,"’","'"))),'Référentiel films'!$B$12,""),IF(ISNUMBER(SEARCH(SUBSTITUTE('Référentiel films'!$A$13,"’","'"),SUBSTITUTE(F21,"’","'"))),'Référentiel films'!$B$13,""),IF(ISNUMBER(SEARCH(SUBSTITUTE('Référentiel films'!$A$14,"’","'"),SUBSTITUTE(F21,"’","'"))),'Référentiel films'!$B$14,""),IF(ISNUMBER(SEARCH(SUBSTITUTE('Référentiel films'!$A$15,"’","'"),SUBSTITUTE(F21,"’","'"))),'Référentiel films'!$B$15,""),IF(ISNUMBER(SEARCH(SUBSTITUTE('Référentiel films'!$A$16,"’","'"),SUBSTITUTE(F21,"’","'"))),'Référentiel films'!$B$16,""),IF(ISNUMBER(SEARCH(SUBSTITUTE('Référentiel films'!$A$17,"’","'"),SUBSTITUTE(F21,"’","'"))),'Référentiel films'!$B$17,""),IF(ISNUMBER(SEARCH(SUBSTITUTE('Référentiel films'!$A$18,"’","'"),SUBSTITUTE(F21,"’","'"))),'Référentiel films'!$B$18,""),IF(ISNUMBER(SEARCH(SUBSTITUTE('Référentiel films'!$A$19,"’","'"),SUBSTITUTE(F21,"’","'"))),'Référentiel films'!$B$19,""),IF(ISNUMBER(SEARCH(SUBSTITUTE('Référentiel films'!$A$20,"’","'"),SUBSTITUTE(F21,"’","'"))),'Référentiel films'!$B$20,""),IF(ISNUMBER(SEARCH(SUBSTITUTE('Référentiel films'!$A$21,"’","'"),SUBSTITUTE(F21,"’","'"))),'Référentiel films'!$B$21,""),IF(ISNUMBER(SEARCH(SUBSTITUTE('Référentiel films'!$A$22,"’","'"),SUBSTITUTE(F21,"’","'"))),'Référentiel films'!$B$22,""),IF(ISNUMBER(SEARCH(SUBSTITUTE('Référentiel films'!$A$23,"’","'"),SUBSTITUTE(F21,"’","'"))),'Référentiel films'!$B$23,""),IF(ISNUMBER(SEARCH(SUBSTITUTE('Référentiel films'!$A$24,"’","'"),SUBSTITUTE(F21,"’","'"))),'Référentiel films'!$B$24,""),IF(ISNUMBER(SEARCH(SUBSTITUTE('Référentiel films'!$A$25,"’","'"),SUBSTITUTE(F21,"’","'"))),'Référentiel films'!$B$25,""),IF(ISNUMBER(SEARCH(SUBSTITUTE('Référentiel films'!$A$26,"’","'"),SUBSTITUTE(F21,"’","'"))),'Référentiel films'!$B$26,""),IF(ISNUMBER(SEARCH(SUBSTITUTE('Référentiel films'!$A$27,"’","'"),SUBSTITUTE(F21,"’","'"))),'Référentiel films'!$B$27,""),IF(ISNUMBER(SEARCH(SUBSTITUTE('Référentiel films'!$A$28,"’","'"),SUBSTITUTE(F21,"’","'"))),'Référentiel films'!$B$28,""),IF(ISNUMBER(SEARCH(SUBSTITUTE('Référentiel films'!$A$29,"’","'"),SUBSTITUTE(F21,"’","'"))),'Référentiel films'!$B$29,""),IF(ISNUMBER(SEARCH(SUBSTITUTE('Référentiel films'!$A$30,"’","'"),SUBSTITUTE(F21,"’","'"))),'Référentiel films'!$B$30,""),IF(ISNUMBER(SEARCH(SUBSTITUTE('Référentiel films'!$A$31,"’","'"),SUBSTITUTE(F21,"’","'"))),'Référentiel films'!$B$31,""),IF(ISNUMBER(SEARCH(SUBSTITUTE('Référentiel films'!$A$32,"’","'"),SUBSTITUTE(F21,"’","'"))),'Référentiel films'!$B$32,""),IF(ISNUMBER(SEARCH(SUBSTITUTE('Référentiel films'!$A$33,"’","'"),SUBSTITUTE(F21,"’","'"))),'Référentiel films'!$B$33,""),IF(ISNUMBER(SEARCH(SUBSTITUTE('Référentiel films'!$A$34,"’","'"),SUBSTITUTE(F21,"’","'"))),'Référentiel films'!$B$34,""),IF(ISNUMBER(SEARCH(SUBSTITUTE('Référentiel films'!$A$35,"’","'"),SUBSTITUTE(F21,"’","'"))),'Référentiel films'!$B$35,""),IF(ISNUMBER(SEARCH(SUBSTITUTE('Référentiel films'!$A$36,"’","'"),SUBSTITUTE(F21,"’","'"))),'Référentiel films'!$B$36,""),IF(ISNUMBER(SEARCH(SUBSTITUTE('Référentiel films'!$A$37,"’","'"),SUBSTITUTE(F21,"’","'"))),'Référentiel films'!$B$37,""),IF(ISNUMBER(SEARCH(SUBSTITUTE('Référentiel films'!$A$38,"’","'"),SUBSTITUTE(F21,"’","'"))),'Référentiel films'!$B$38,""),IF(ISNUMBER(SEARCH(SUBSTITUTE('Référentiel films'!$A$39,"’","'"),SUBSTITUTE(F21,"’","'"))),'Référentiel films'!$B$39,""),IF(ISNUMBER(SEARCH(SUBSTITUTE('Référentiel films'!$A$40,"’","'"),SUBSTITUTE(F21,"’","'"))),'Référentiel films'!$B$40,""),IF(ISNUMBER(SEARCH(SUBSTITUTE('Référentiel films'!$A$41,"’","'"),SUBSTITUTE(F21,"’","'"))),'Référentiel films'!$B$41,"")))
A22: 1967 | B22: 1967-1970 | D22: La parution du Deuil impossible de Alexander et Margarete Mitscherlich fait scandale. A travers l'exposé des troubles psychosomatiques de certains patients, les psychanalystes Alexander et Margarete Mitscherlich y analysent le refoulement collectif des souvenirs du IIIe Reich en Allemagne. Il doit exister, selon les auteurs, un lien de cause à effet entre une forme de conservatisme teinté et de provincialisme, qui règnent RFA, le refoulement dedu passé. L'ouvrage exercce une influence sur les artistes allemands de l'époque. Une réflexion sur la mémoire et l'oubli qui n'a rien perdu de son actualité | E22: Rejoint l'Action-Theater (1967). | U22: =IF(F22="","",_xlfn.TEXTJOIN("; ",TRUE(),IF(ISNUMBER(SEARCH(SUBSTITUTE('Référentiel films'!$A$2,"’","'"),SUBSTITUTE(F22,"’","'"))),'Référentiel films'!$B$2,""),IF(ISNUMBER(SEARCH(SUBSTITUTE('Référentiel films'!$A$3,"’","'"),SUBSTITUTE(F22,"’","'"))),'Référentiel films'!$B$3,""),IF(ISNUMBER(SEARCH(SUBSTITUTE('Référentiel films'!$A$4,"’","'"),SUBSTITUTE(F22,"’","'"))),'Référentiel films'!$B$4,""),IF(ISNUMBER(SEARCH(SUBSTITUTE('Référentiel films'!$A$5,"’","'"),SUBSTITUTE(F22,"’","'"))),'Référentiel films'!$B$5,""),IF(ISNUMBER(SEARCH(SUBSTITUTE('Référentiel films'!$A$6,"’","'"),SUBSTITUTE(F22,"’","'"))),'Référentiel films'!$B$6,""),IF(ISNUMBER(SEARCH(SUBSTITUTE('Référentiel films'!$A$7,"’","'"),SUBSTITUTE(F22,"’","'"))),'Référentiel films'!$B$7,""),IF(ISNUMBER(SEARCH(SUBSTITUTE('Référentiel films'!$A$8,"’","'"),SUBSTITUTE(F22,"’","'"))),'Référentiel films'!$B$8,""),IF(ISNUMBER(SEARCH(SUBSTITUTE('Référentiel films'!$A$9,"’","'"),SUBSTITUTE(F22,"’","'"))),'Référentiel films'!$B$9,""),IF(ISNUMBER(SEARCH(SUBSTITUTE('Référentiel films'!$A$10,"’","'"),SUBSTITUTE(F22,"’","'"))),'Référentiel films'!$B$10,""),IF(ISNUMBER(SEARCH(SUBSTITUTE('Référentiel films'!$A$11,"’","'"),SUBSTITUTE(F22,"’","'"))),'Référentiel films'!$B$11,""),IF(ISNUMBER(SEARCH(SUBSTITUTE('Référentiel films'!$A$12,"’","'"),SUBSTITUTE(F22,"’","'"))),'Référentiel films'!$B$12,""),IF(ISNUMBER(SEARCH(SUBSTITUTE('Référentiel films'!$A$13,"’","'"),SUBSTITUTE(F22,"’","'"))),'Référentiel films'!$B$13,""),IF(ISNUMBER(SEARCH(SUBSTITUTE('Référentiel films'!$A$14,"’","'"),SUBSTITUTE(F22,"’","'"))),'Référentiel films'!$B$14,""),IF(ISNUMBER(SEARCH(SUBSTITUTE('Référentiel films'!$A$15,"’","'"),SUBSTITUTE(F22,"’","'"))),'Référentiel films'!$B$15,""),IF(ISNUMBER(SEARCH(SUBSTITUTE('Référentiel films'!$A$16,"’","'"),SUBSTITUTE(F22,"’","'"))),'Référentiel films'!$B$16,""),IF(ISNUMBER(SEARCH(SUBSTITUTE('Référentiel films'!$A$17,"’","'"),SUBSTITUTE(F22,"’","'"))),'Référentiel films'!$B$17,""),IF(ISNUMBER(SEARCH(SUBSTITUTE('Référentiel films'!$A$18,"’","'"),SUBSTITUTE(F22,"’","'"))),'Référentiel films'!$B$18,""),IF(ISNUMBER(SEARCH(SUBSTITUTE('Référentiel films'!$A$19,"’","'"),SUBSTITUTE(F22,"’","'"))),'Référentiel films'!$B$19,""),IF(ISNUMBER(SEARCH(SUBSTITUTE('Référentiel films'!$A$20,"’","'"),SUBSTITUTE(F22,"’","'"))),'Référentiel films'!$B$20,""),IF(ISNUMBER(SEARCH(SUBSTITUTE('Référentiel films'!$A$21,"’","'"),SUBSTITUTE(F22,"’","'"))),'Référentiel films'!$B$21,""),IF(ISNUMBER(SEARCH(SUBSTITUTE('Référentiel films'!$A$22,"’","'"),SUBSTITUTE(F22,"’","'"))),'Référentiel films'!$B$22,""),IF(ISNUMBER(SEARCH(SUBSTITUTE('Référentiel films'!$A$23,"’","'"),SUBSTITUTE(F22,"’","'"))),'Référentiel films'!$B$23,""),IF(ISNUMBER(SEARCH(SUBSTITUTE('Référentiel films'!$A$24,"’","'"),SUBSTITUTE(F22,"’","'"))),'Référentiel films'!$B$24,""),IF(ISNUMBER(SEARCH(SUBSTITUTE('Référentiel films'!$A$25,"’","'"),SUBSTITUTE(F22,"’","'"))),'Référentiel films'!$B$25,""),IF(ISNUMBER(SEARCH(SUBSTITUTE('Référentiel films'!$A$26,"’","'"),SUBSTITUTE(F22,"’","'"))),'Référentiel films'!$B$26,""),IF(ISNUMBER(SEARCH(SUBSTITUTE('Référentiel films'!$A$27,"’","'"),SUBSTITUTE(F22,"’","'"))),'Référentiel films'!$B$27,""),IF(ISNUMBER(SEARCH(SUBSTITUTE('Référentiel films'!$A$28,"’","'"),SUBSTITUTE(F22,"’","'"))),'Référentiel films'!$B$28,""),IF(ISNUMBER(SEARCH(SUBSTITUTE('Référentiel films'!$A$29,"’","'"),SUBSTITUTE(F22,"’","'"))),'Référentiel films'!$B$29,""),IF(ISNUMBER(SEARCH(SUBSTITUTE('Référentiel films'!$A$30,"’","'"),SUBSTITUTE(F22,"’","'"))),'Référentiel films'!$B$30,""),IF(ISNUMBER(SEARCH(SUBSTITUTE('Référentiel films'!$A$31,"’","'"),SUBSTITUTE(F22,"’","'"))),'Référentiel films'!$B$31,""),IF(ISNUMBER(SEARCH(SUBSTITUTE('Référentiel films'!$A$32,"’","'"),SUBSTITUTE(F22,"’","'"))),'Référentiel films'!$B$32,""),IF(ISNUMBER(SEARCH(SUBSTITUTE('Référentiel films'!$A$33,"’","'"),SUBSTITUTE(F22,"’","'"))),'Référentiel films'!$B$33,""),IF(ISNUMBER(SEARCH(SUBSTITUTE('Référentiel films'!$A$34,"’","'"),SUBSTITUTE(F22,"’","'"))),'Référentiel films'!$B$34,""),IF(ISNUMBER(SEARCH(SUBSTITUTE('Référentiel films'!$A$35,"’","'"),SUBSTITUTE(F22,"’","'"))),'Référentiel films'!$B$35,""),IF(ISNUMBER(SEARCH(SUBSTITUTE('Référentiel films'!$A$36,"’","'"),SUBSTITUTE(F22,"’","'"))),'Référentiel films'!$B$36,""),IF(ISNUMBER(SEARCH(SUBSTITUTE('Référentiel films'!$A$37,"’","'"),SUBSTITUTE(F22,"’","'"))),'Référentiel films'!$B$37,""),IF(ISNUMBER(SEARCH(SUBSTITUTE('Référentiel films'!$A$38,"’","'"),SUBSTITUTE(F22,"’","'"))),'Référentiel films'!$B$38,""),IF(ISNUMBER(SEARCH(SUBSTITUTE('Référentiel films'!$A$39,"’","'"),SUBSTITUTE(F22,"’","'"))),'Référentiel films'!$B$39,""),IF(ISNUMBER(SEARCH(SUBSTITUTE('Référentiel films'!$A$40,"’","'"),SUBSTITUTE(F22,"’","'"))),'Référentiel films'!$B$40,""),IF(ISNUMBER(SEARCH(SUBSTITUTE('Référentiel films'!$A$41,"’","'"),SUBSTITUTE(F22,"’","'"))),'Référentiel films'!$B$41,"")))
A23: 1968 | B23: 1967-1970 | C23: Mouvements étudiants de 1968. Tentative d'assassinat contre Rudi Dutschke. Victoire de Willy Brandt (SPD, 1969). Abrogation partielle de l'article 175 (homosexualité). | D23: Émergence de l'Anti-teater à Munich. Influence de la Nouvelle Vague française. Le cinéma devient politique et théorique. | E23: Fonde l' antiteater (1968). Collaboration intense avec sa "troupe" (Schygulla, Hermann, Raab, Baer, Lommel). Mariage avec Ingrid Caven (1970). | F23: L'amour est plus froid que la mort (1969), Le Bouc (1969, succès à Mannheim) : critique de la xénophobie et de l'apathie bourgeoise. | G23: Premier film accueili froidement à Berlin. Le second,une critique de la xénophobie et de l'apathie bourgeoise, remporte 5 distinctions cinématographiques en Allemagne. Le coût de production de 80000 marks est largement couvert : avec 650000 malrs de prix et 200000 marks de subventions a posteri, le film assure à RWF de quoi poursuivre son travail pour quelques années. | U23: =IF(F23="","",_xlfn.TEXTJOIN("; ",TRUE(),IF(ISNUMBER(SEARCH(SUBSTITUTE('Référentiel films'!$A$2,"’","'"),SUBSTITUTE(F23,"’","'"))),'Référentiel films'!$B$2,""),IF(ISNUMBER(SEARCH(SUBSTITUTE('Référentiel films'!$A$3,"’","'"),SUBSTITUTE(F23,"’","'"))),'Référentiel films'!$B$3,""),IF(ISNUMBER(SEARCH(SUBSTITUTE('Référentiel films'!$A$4,"’","'"),SUBSTITUTE(F23,"’","'"))),'Référentiel films'!$B$4,""),IF(ISNUMBER(SEARCH(SUBSTITUTE('Référentiel films'!$A$5,"’","'"),SUBSTITUTE(F23,"’","'"))),'Référentiel films'!$B$5,""),IF(ISNUMBER(SEARCH(SUBSTITUTE('Référentiel films'!$A$6,"’","'"),SUBSTITUTE(F23,"’","'"))),'Référentiel films'!$B$6,""),IF(ISNUMBER(SEARCH(SUBSTITUTE('Référentiel films'!$A$7,"’","'"),SUBSTITUTE(F23,"’","'"))),'Référentiel films'!$B$7,""),IF(ISNUMBER(SEARCH(SUBSTITUTE('Référentiel films'!$A$8,"’","'"),SUBSTITUTE(F23,"’","'"))),'Référentiel films'!$B$8,""),IF(ISNUMBER(SEARCH(SUBSTITUTE('Référentiel films'!$A$9,"’","'"),SUBSTITUTE(F23,"’","'"))),'Référentiel films'!$B$9,""),IF(ISNUMBER(SEARCH(SUBSTITUTE('Référentiel films'!$A$10,"’","'"),SUBSTITUTE(F23,"’","'"))),'Référentiel films'!$B$10,""),IF(ISNUMBER(SEARCH(SUBSTITUTE('Référentiel films'!$A$11,"’","'"),SUBSTITUTE(F23,"’","'"))),'Référentiel films'!$B$11,""),IF(ISNUMBER(SEARCH(SUBSTITUTE('Référentiel films'!$A$12,"’","'"),SUBSTITUTE(F23,"’","'"))),'Référentiel films'!$B$12,""),IF(ISNUMBER(SEARCH(SUBSTITUTE('Référentiel films'!$A$13,"’","'"),SUBSTITUTE(F23,"’","'"))),'Référentiel films'!$B$13,""),IF(ISNUMBER(SEARCH(SUBSTITUTE('Référentiel films'!$A$14,"’","'"),SUBSTITUTE(F23,"’","'"))),'Référentiel films'!$B$14,""),IF(ISNUMBER(SEARCH(SUBSTITUTE('Référentiel films'!$A$15,"’","'"),SUBSTITUTE(F23,"’","'"))),'Référentiel films'!$B$15,""),IF(ISNUMBER(SEARCH(SUBSTITUTE('Référentiel films'!$A$16,"’","'"),SUBSTITUTE(F23,"’","'"))),'Référentiel films'!$B$16,""),IF(ISNUMBER(SEARCH(SUBSTITUTE('Référentiel films'!$A$17,"’","'"),SUBSTITUTE(F23,"’","'"))),'Référentiel films'!$B$17,""),IF(ISNUMBER(SEARCH(SUBSTITUTE('Référentiel films'!$A$18,"’","'"),SUBSTITUTE(F23,"’","'"))),'Référentiel films'!$B$18,""),IF(ISNUMBER(SEARCH(SUBSTITUTE('Référentiel films'!$A$19,"’","'"),SUBSTITUTE(F23,"’","'"))),'Référentiel films'!$B$19,""),IF(ISNUMBER(SEARCH(SUBSTITUTE('Référentiel films'!$A$20,"’","'"),SUBSTITUTE(F23,"’","'"))),'Référentiel films'!$B$20,""),IF(ISNUMBER(SEARCH(SUBSTITUTE('Référentiel films'!$A$21,"’","'"),SUBSTITUTE(F23,"’","'"))),'Référentiel films'!$B$21,""),IF(ISNUMBER(SEARCH(SUBSTITUTE('Référentiel films'!$A$22,"’","'"),SUBSTITUTE(F23,"’","'"))),'Référentiel films'!$B$22,""),IF(ISNUMBER(SEARCH(SUBSTITUTE('Référentiel films'!$A$23,"’","'"),SUBSTITUTE(F23,"’","'"))),'Référentiel films'!$B$23,""),IF(ISNUMBER(SEARCH(SUBSTITUTE('Référentiel films'!$A$24,"’","'"),SUBSTITUTE(F23,"’","'"))),'Référentiel films'!$B$24,""),IF(ISNUMBER(SEARCH(SUBSTITUTE('Référentiel films'!$A$25,"’","'"),SUBSTITUTE(F23,"’","'"))),'Référentiel films'!$B$25,""),IF(ISNUMBER(SEARCH(SUBSTITUTE('Référentiel films'!$A$26,"’","'"),SUBSTITUTE(F23,"’","'"))),'Référentiel films'!$B$26,""),IF(ISNUMBER(SEARCH(SUBSTITUTE('Référentiel films'!$A$27,"’","'"),SUBSTITUTE(F23,"’","'"))),'Référentiel films'!$B$27,""),IF(ISNUMBER(SEARCH(SUBSTITUTE('Référentiel films'!$A$28,"’","'"),SUBSTITUTE(F23,"’","'"))),'Référentiel films'!$B$28,""),IF(ISNUMBER(SEARCH(SUBSTITUTE('Référentiel films'!$A$29,"’","'"),SUBSTITUTE(F23,"’","'"))),'Référentiel films'!$B$29,""),IF(ISNUMBER(SEARCH(SUBSTITUTE('Référentiel films'!$A$30,"’","'"),SUBSTITUTE(F23,"’","'"))),'Référentiel films'!$B$30,""),IF(ISNUMBER(SEARCH(SUBSTITUTE('Référentiel films'!$A$31,"’","'"),SUBSTITUTE(F23,"’","'"))),'Référentiel films'!$B$31,""),IF(ISNUMBER(SEARCH(SUBSTITUTE('Référentiel films'!$A$32,"’","'"),SUBSTITUTE(F23,"’","'"))),'Référentiel films'!$B$32,""),IF(ISNUMBER(SEARCH(SUBSTITUTE('Référentiel films'!$A$33,"’","'"),SUBSTITUTE(F23,"’","'"))),'Référentiel films'!$B$33,""),IF(ISNUMBER(SEARCH(SUBSTITUTE('Référentiel films'!$A$34,"’","'"),SUBSTITUTE(F23,"’","'"))),'Référentiel films'!$B$34,""),IF(ISNUMBER(SEARCH(SUBSTITUTE('Référentiel films'!$A$35,"’","'"),SUBSTITUTE(F23,"’","'"))),'Référentiel films'!$B$35,""),IF(ISNUMBER(SEARCH(SUBSTITUTE('Référentiel films'!$A$36,"’","'"),SUBSTITUTE(F23,"’","'"))),'Référentiel films'!$B$36,""),IF(ISNUMBER(SEARCH(SUBSTITUTE('Référentiel films'!$A$37,"’","'"),SUBSTITUTE(F23,"’","'"))),'Référentiel films'!$B$37,""),IF(ISNUMBER(SEARCH(SUBSTITUTE('Référentiel films'!$A$38,"’","'"),SUBSTITUTE(F23,"’","'"))),'Référentiel films'!$B$38,""),IF(ISNUMBER(SEARCH(SUBSTITUTE('Référentiel films'!$A$39,"’","'"),SUBSTITUTE(F23,"’","'"))),'Référentiel films'!$B$39,""),IF(ISNUMBER(SEARCH(SUBSTITUTE('Référentiel films'!$A$40,"’","'"),SUBSTITUTE(F23,"’","'"))),'Référentiel films'!$B$40,""),IF(ISNUMBER(SEARCH(SUBSTITUTE('Référentiel films'!$A$41,"’","'"),SUBSTITUTE(F23,"’","'"))),'Référentiel films'!$B$41,""))) -> film-1969-l-amour-est-plus-froid-que-la-mort; film-1969-le-bouc
A24: 1969 | B24: 1967-1970 | C24: Une majorité sociale-libérale place Willy Brandt au pouvoir. | D24: Les damnés, mélodrame de Visconti, travaille à interroger le régime nazi et sla manière dont l'imagerie nazie, qui érotise de manière spectaculaire le pouvoir, contamine moralement les esprits. L'éloignement du néoréalisme est maximal. | U24: =IF(F24="","",_xlfn.TEXTJOIN("; ",TRUE(),IF(ISNUMBER(SEARCH(SUBSTITUTE('Référentiel films'!$A$2,"’","'"),SUBSTITUTE(F24,"’","'"))),'Référentiel films'!$B$2,""),IF(ISNUMBER(SEARCH(SUBSTITUTE('Référentiel films'!$A$3,"’","'"),SUBSTITUTE(F24,"’","'"))),'Référentiel films'!$B$3,""),IF(ISNUMBER(SEARCH(SUBSTITUTE('Référentiel films'!$A$4,"’","'"),SUBSTITUTE(F24,"’","'"))),'Référentiel films'!$B$4,""),IF(ISNUMBER(SEARCH(SUBSTITUTE('Référentiel films'!$A$5,"’","'"),SUBSTITUTE(F24,"’","'"))),'Référentiel films'!$B$5,""),IF(ISNUMBER(SEARCH(SUBSTITUTE('Référentiel films'!$A$6,"’","'"),SUBSTITUTE(F24,"’","'"))),'Référentiel films'!$B$6,""),IF(ISNUMBER(SEARCH(SUBSTITUTE('Référentiel films'!$A$7,"’","'"),SUBSTITUTE(F24,"’","'"))),'Référentiel films'!$B$7,""),IF(ISNUMBER(SEARCH(SUBSTITUTE('Référentiel films'!$A$8,"’","'"),SUBSTITUTE(F24,"’","'"))),'Référentiel films'!$B$8,""),IF(ISNUMBER(SEARCH(SUBSTITUTE('Référentiel films'!$A$9,"’","'"),SUBSTITUTE(F24,"’","'"))),'Référentiel films'!$B$9,""),IF(ISNUMBER(SEARCH(SUBSTITUTE('Référentiel films'!$A$10,"’","'"),SUBSTITUTE(F24,"’","'"))),'Référentiel films'!$B$10,""),IF(ISNUMBER(SEARCH(SUBSTITUTE('Référentiel films'!$A$11,"’","'"),SUBSTITUTE(F24,"’","'"))),'Référentiel films'!$B$11,""),IF(ISNUMBER(SEARCH(SUBSTITUTE('Référentiel films'!$A$12,"’","'"),SUBSTITUTE(F24,"’","'"))),'Référentiel films'!$B$12,""),IF(ISNUMBER(SEARCH(SUBSTITUTE('Référentiel films'!$A$13,"’","'"),SUBSTITUTE(F24,"’","'"))),'Référentiel films'!$B$13,""),IF(ISNUMBER(SEARCH(SUBSTITUTE('Référentiel films'!$A$14,"’","'"),SUBSTITUTE(F24,"’","'"))),'Référentiel films'!$B$14,""),IF(ISNUMBER(SEARCH(SUBSTITUTE('Référentiel films'!$A$15,"’","'"),SUBSTITUTE(F24,"’","'"))),'Référentiel films'!$B$15,""),IF(ISNUMBER(SEARCH(SUBSTITUTE('Référentiel films'!$A$16,"’","'"),SUBSTITUTE(F24,"’","'"))),'Référentiel films'!$B$16,""),IF(ISNUMBER(SEARCH(SUBSTITUTE('Référentiel films'!$A$17,"’","'"),SUBSTITUTE(F24,"’","'"))),'Référentiel films'!$B$17,""),IF(ISNUMBER(SEARCH(SUBSTITUTE('Référentiel films'!$A$18,"’","'"),SUBSTITUTE(F24,"’","'"))),'Référentiel films'!$B$18,""),IF(ISNUMBER(SEARCH(SUBSTITUTE('Référentiel films'!$A$19,"’","'"),SUBSTITUTE(F24,"’","'"))),'Référentiel films'!$B$19,""),IF(ISNUMBER(SEARCH(SUBSTITUTE('Référentiel films'!$A$20,"’","'"),SUBSTITUTE(F24,"’","'"))),'Référentiel films'!$B$20,""),IF(ISNUMBER(SEARCH(SUBSTITUTE('Référentiel films'!$A$21,"’","'"),SUBSTITUTE(F24,"’","'"))),'Référentiel films'!$B$21,""),IF(ISNUMBER(SEARCH(SUBSTITUTE('Référentiel films'!$A$22,"’","'"),SUBSTITUTE(F24,"’","'"))),'Référentiel films'!$B$22,""),IF(ISNUMBER(SEARCH(SUBSTITUTE('Référentiel films'!$A$23,"’","'"),SUBSTITUTE(F24,"’","'"))),'Référentiel films'!$B$23,""),IF(ISNUMBER(SEARCH(SUBSTITUTE('Référentiel films'!$A$24,"’","'"),SUBSTITUTE(F24,"’","'"))),'Référentiel films'!$B$24,""),IF(ISNUMBER(SEARCH(SUBSTITUTE('Référentiel films'!$A$25,"’","'"),SUBSTITUTE(F24,"’","'"))),'Référentiel films'!$B$25,""),IF(ISNUMBER(SEARCH(SUBSTITUTE('Référentiel films'!$A$26,"’","'"),SUBSTITUTE(F24,"’","'"))),'Référentiel films'!$B$26,""),IF(ISNUMBER(SEARCH(SUBSTITUTE('Référentiel films'!$A$27,"’","'"),SUBSTITUTE(F24,"’","'"))),'Référentiel films'!$B$27,""),IF(ISNUMBER(SEARCH(SUBSTITUTE('Référentiel films'!$A$28,"’","'"),SUBSTITUTE(F24,"’","'"))),'Référentiel films'!$B$28,""),IF(ISNUMBER(SEARCH(SUBSTITUTE('Référentiel films'!$A$29,"’","'"),SUBSTITUTE(F24,"’","'"))),'Référentiel films'!$B$29,""),IF(ISNUMBER(SEARCH(SUBSTITUTE('Référentiel films'!$A$30,"’","'"),SUBSTITUTE(F24,"’","'"))),'Référentiel films'!$B$30,""),IF(ISNUMBER(SEARCH(SUBSTITUTE('Référentiel films'!$A$31,"’","'"),SUBSTITUTE(F24,"’","'"))),'Référentiel films'!$B$31,""),IF(ISNUMBER(SEARCH(SUBSTITUTE('Référentiel films'!$A$32,"’","'"),SUBSTITUTE(F24,"’","'"))),'Référentiel films'!$B$32,""),IF(ISNUMBER(SEARCH(SUBSTITUTE('Référentiel films'!$A$33,"’","'"),SUBSTITUTE(F24,"’","'"))),'Référentiel films'!$B$33,""),IF(ISNUMBER(SEARCH(SUBSTITUTE('Référentiel films'!$A$34,"’","'"),SUBSTITUTE(F24,"’","'"))),'Référentiel films'!$B$34,""),IF(ISNUMBER(SEARCH(SUBSTITUTE('Référentiel films'!$A$35,"’","'"),SUBSTITUTE(F24,"’","'"))),'Référentiel films'!$B$35,""),IF(ISNUMBER(SEARCH(SUBSTITUTE('Référentiel films'!$A$36,"’","'"),SUBSTITUTE(F24,"’","'"))),'Référentiel films'!$B$36,""),IF(ISNUMBER(SEARCH(SUBSTITUTE('Référentiel films'!$A$37,"’","'"),SUBSTITUTE(F24,"’","'"))),'Référentiel films'!$B$37,""),IF(ISNUMBER(SEARCH(SUBSTITUTE('Référentiel films'!$A$38,"’","'"),SUBSTITUTE(F24,"’","'"))),'Référentiel films'!$B$38,""),IF(ISNUMBER(SEARCH(SUBSTITUTE('Référentiel films'!$A$39,"’","'"),SUBSTITUTE(F24,"’","'"))),'Référentiel films'!$B$39,""),IF(ISNUMBER(SEARCH(SUBSTITUTE('Référentiel films'!$A$40,"’","'"),SUBSTITUTE(F24,"’","'"))),'Référentiel films'!$B$40,""),IF(ISNUMBER(SEARCH(SUBSTITUTE('Référentiel films'!$A$41,"’","'"),SUBSTITUTE(F24,"’","'"))),'Référentiel films'!$B$41,"")))
A25: 1970 | C25: Le chancelier Willy Brandt se rend en Pologne et s'agenouille devant le mémorial du ghetto de Varsovie. | F25: Whity, Prenez garde à la sainte putain | U25: =IF(F25="","",_xlfn.TEXTJOIN("; ",TRUE(),IF(ISNUMBER(SEARCH(SUBSTITUTE('Référentiel films'!$A$2,"’","'"),SUBSTITUTE(F25,"’","'"))),'Référentiel films'!$B$2,""),IF(ISNUMBER(SEARCH(SUBSTITUTE('Référentiel films'!$A$3,"’","'"),SUBSTITUTE(F25,"’","'"))),'Référentiel films'!$B$3,""),IF(ISNUMBER(SEARCH(SUBSTITUTE('Référentiel films'!$A$4,"’","'"),SUBSTITUTE(F25,"’","'"))),'Référentiel films'!$B$4,""),IF(ISNUMBER(SEARCH(SUBSTITUTE('Référentiel films'!$A$5,"’","'"),SUBSTITUTE(F25,"’","'"))),'Référentiel films'!$B$5,""),IF(ISNUMBER(SEARCH(SUBSTITUTE('Référentiel films'!$A$6,"’","'"),SUBSTITUTE(F25,"’","'"))),'Référentiel films'!$B$6,""),IF(ISNUMBER(SEARCH(SUBSTITUTE('Référentiel films'!$A$7,"’","'"),SUBSTITUTE(F25,"’","'"))),'Référentiel films'!$B$7,""),IF(ISNUMBER(SEARCH(SUBSTITUTE('Référentiel films'!$A$8,"’","'"),SUBSTITUTE(F25,"’","'"))),'Référentiel films'!$B$8,""),IF(ISNUMBER(SEARCH(SUBSTITUTE('Référentiel films'!$A$9,"’","'"),SUBSTITUTE(F25,"’","'"))),'Référentiel films'!$B$9,""),IF(ISNUMBER(SEARCH(SUBSTITUTE('Référentiel films'!$A$10,"’","'"),SUBSTITUTE(F25,"’","'"))),'Référentiel films'!$B$10,""),IF(ISNUMBER(SEARCH(SUBSTITUTE('Référentiel films'!$A$11,"’","'"),SUBSTITUTE(F25,"’","'"))),'Référentiel films'!$B$11,""),IF(ISNUMBER(SEARCH(SUBSTITUTE('Référentiel films'!$A$12,"’","'"),SUBSTITUTE(F25,"’","'"))),'Référentiel films'!$B$12,""),IF(ISNUMBER(SEARCH(SUBSTITUTE('Référentiel films'!$A$13,"’","'"),SUBSTITUTE(F25,"’","'"))),'Référentiel films'!$B$13,""),IF(ISNUMBER(SEARCH(SUBSTITUTE('Référentiel films'!$A$14,"’","'"),SUBSTITUTE(F25,"’","'"))),'Référentiel films'!$B$14,""),IF(ISNUMBER(SEARCH(SUBSTITUTE('Référentiel films'!$A$15,"’","'"),SUBSTITUTE(F25,"’","'"))),'Référentiel films'!$B$15,""),IF(ISNUMBER(SEARCH(SUBSTITUTE('Référentiel films'!$A$16,"’","'"),SUBSTITUTE(F25,"’","'"))),'Référentiel films'!$B$16,""),IF(ISNUMBER(SEARCH(SUBSTITUTE('Référentiel films'!$A$17,"’","'"),SUBSTITUTE(F25,"’","'"))),'Référentiel films'!$B$17,""),IF(ISNUMBER(SEARCH(SUBSTITUTE('Référentiel films'!$A$18,"’","'"),SUBSTITUTE(F25,"’","'"))),'Référentiel films'!$B$18,""),IF(ISNUMBER(SEARCH(SUBSTITUTE('Référentiel films'!$A$19,"’","'"),SUBSTITUTE(F25,"’","'"))),'Référentiel films'!$B$19,""),IF(ISNUMBER(SEARCH(SUBSTITUTE('Référentiel films'!$A$20,"’","'"),SUBSTITUTE(F25,"’","'"))),'Référentiel films'!$B$20,""),IF(ISNUMBER(SEARCH(SUBSTITUTE('Référentiel films'!$A$21,"’","'"),SUBSTITUTE(F25,"’","'"))),'Référentiel films'!$B$21,""),IF(ISNUMBER(SEARCH(SUBSTITUTE('Référentiel films'!$A$22,"’","'"),SUBSTITUTE(F25,"’","'"))),'Référentiel films'!$B$22,""),IF(ISNUMBER(SEARCH(SUBSTITUTE('Référentiel films'!$A$23,"’","'"),SUBSTITUTE(F25,"’","'"))),'Référentiel films'!$B$23,""),IF(ISNUMBER(SEARCH(SUBSTITUTE('Référentiel films'!$A$24,"’","'"),SUBSTITUTE(F25,"’","'"))),'Référentiel films'!$B$24,""),IF(ISNUMBER(SEARCH(SUBSTITUTE('Référentiel films'!$A$25,"’","'"),SUBSTITUTE(F25,"’","'"))),'Référentiel films'!$B$25,""),IF(ISNUMBER(SEARCH(SUBSTITUTE('Référentiel films'!$A$26,"’","'"),SUBSTITUTE(F25,"’","'"))),'Référentiel films'!$B$26,""),IF(ISNUMBER(SEARCH(SUBSTITUTE('Référentiel films'!$A$27,"’","'"),SUBSTITUTE(F25,"’","'"))),'Référentiel films'!$B$27,""),IF(ISNUMBER(SEARCH(SUBSTITUTE('Référentiel films'!$A$28,"’","'"),SUBSTITUTE(F25,"’","'"))),'Référentiel films'!$B$28,""),IF(ISNUMBER(SEARCH(SUBSTITUTE('Référentiel films'!$A$29,"’","'"),SUBSTITUTE(F25,"’","'"))),'Référentiel films'!$B$29,""),IF(ISNUMBER(SEARCH(SUBSTITUTE('Référentiel films'!$A$30,"’","'"),SUBSTITUTE(F25,"’","'"))),'Référentiel films'!$B$30,""),IF(ISNUMBER(SEARCH(SUBSTITUTE('Référentiel films'!$A$31,"’","'"),SUBSTITUTE(F25,"’","'"))),'Référentiel films'!$B$31,""),IF(ISNUMBER(SEARCH(SUBSTITUTE('Référentiel films'!$A$32,"’","'"),SUBSTITUTE(F25,"’","'"))),'Référentiel films'!$B$32,""),IF(ISNUMBER(SEARCH(SUBSTITUTE('Référentiel films'!$A$33,"’","'"),SUBSTITUTE(F25,"’","'"))),'Référentiel films'!$B$33,""),IF(ISNUMBER(SEARCH(SUBSTITUTE('Référentiel films'!$A$34,"’","'"),SUBSTITUTE(F25,"’","'"))),'Référentiel films'!$B$34,""),IF(ISNUMBER(SEARCH(SUBSTITUTE('Référentiel films'!$A$35,"’","'"),SUBSTITUTE(F25,"’","'"))),'Référentiel films'!$B$35,""),IF(ISNUMBER(SEARCH(SUBSTITUTE('Référentiel films'!$A$36,"’","'"),SUBSTITUTE(F25,"’","'"))),'Référentiel films'!$B$36,""),IF(ISNUMBER(SEARCH(SUBSTITUTE('Référentiel films'!$A$37,"’","'"),SUBSTITUTE(F25,"’","'"))),'Référentiel films'!$B$37,""),IF(ISNUMBER(SEARCH(SUBSTITUTE('Référentiel films'!$A$38,"’","'"),SUBSTITUTE(F25,"’","'"))),'Référentiel films'!$B$38,""),IF(ISNUMBER(SEARCH(SUBSTITUTE('Référentiel films'!$A$39,"’","'"),SUBSTITUTE(F25,"’","'"))),'Référentiel films'!$B$39,""),IF(ISNUMBER(SEARCH(SUBSTITUTE('Référentiel films'!$A$40,"’","'"),SUBSTITUTE(F25,"’","'"))),'Référentiel films'!$B$40,""),IF(ISNUMBER(SEARCH(SUBSTITUTE('Référentiel films'!$A$41,"’","'"),SUBSTITUTE(F25,"’","'"))),'Référentiel films'!$B$41,""))) -> film-1971-whity; film-1971-prenez-garde-a-la-sainte-putain
A26: 1971 | B26: 1971-1974 | C26: Terrorisme de la RAF (arrestations en 1972). Attentat des JO de Munich (1972). Démission de Willy Brandt (1974) suite à l'affaire Guillaume. Un virage conservateur s'opère. | D26: Fondation du Filmverlag der Autoren (1971), une société indépendante, par quelques cinéastes dont RWF. La société est d'abord autogérée. Accords Film-Télévision (1974) favorisant les coproductions (WDR). | E26: Liaison avec El Hedi ben Salem. Direction du TAT à Francfort. Collaboration avec le caméraman Michael Ballhaus. Succès international. | F26: Découverte des mélodrames de Douglas Sirk . Période Sirkienne : Le Marchand des quatre saisons (1971). | G26: Si RWF ne renonce pas à l'expérimentation l'attention qu'il porte à la réception de ses films et donc au public est de plus en plus grande. L'intérêt pour le mélodrame, genre populaire américain, son travail pour la télévision et notamment la création de séries, plus tard le développement de productions internationales, traduisent sa volonté de toucher un public large et populaire. RWF intègre dans oeuvre sentiment et distanciation réflexive, échappant à la seule création de cas sociaux. | L26: "Il m'est impossible de comprende qu'on puisse travailler avec un outil comme la caméra en ne se souciant pas du spectateur", interview avec Norbert Sparrow, in Cinéste, WIII/2 automne 1977 | M26: Maria_braun.jpeg | N26: Affiche du Mariage de Maria Braun | S26: mélodrame | U26: =IF(F26="","",_xlfn.TEXTJOIN("; ",TRUE(),IF(ISNUMBER(SEARCH(SUBSTITUTE('Référentiel films'!$A$2,"’","'"),SUBSTITUTE(F26,"’","'"))),'Référentiel films'!$B$2,""),IF(ISNUMBER(SEARCH(SUBSTITUTE('Référentiel films'!$A$3,"’","'"),SUBSTITUTE(F26,"’","'"))),'Référentiel films'!$B$3,""),IF(ISNUMBER(SEARCH(SUBSTITUTE('Référentiel films'!$A$4,"’","'"),SUBSTITUTE(F26,"’","'"))),'Référentiel films'!$B$4,""),IF(ISNUMBER(SEARCH(SUBSTITUTE('Référentiel films'!$A$5,"’","'"),SUBSTITUTE(F26,"’","'"))),'Référentiel films'!$B$5,""),IF(ISNUMBER(SEARCH(SUBSTITUTE('Référentiel films'!$A$6,"’","'"),SUBSTITUTE(F26,"’","'"))),'Référentiel films'!$B$6,""),IF(ISNUMBER(SEARCH(SUBSTITUTE('Référentiel films'!$A$7,"’","'"),SUBSTITUTE(F26,"’","'"))),'Référentiel films'!$B$7,""),IF(ISNUMBER(SEARCH(SUBSTITUTE('Référentiel films'!$A$8,"’","'"),SUBSTITUTE(F26,"’","'"))),'Référentiel films'!$B$8,""),IF(ISNUMBER(SEARCH(SUBSTITUTE('Référentiel films'!$A$9,"’","'"),SUBSTITUTE(F26,"’","'"))),'Référentiel films'!$B$9,""),IF(ISNUMBER(SEARCH(SUBSTITUTE('Référentiel films'!$A$10,"’","'"),SUBSTITUTE(F26,"’","'"))),'Référentiel films'!$B$10,""),IF(ISNUMBER(SEARCH(SUBSTITUTE('Référentiel films'!$A$11,"’","'"),SUBSTITUTE(F26,"’","'"))),'Référentiel films'!$B$11,""),IF(ISNUMBER(SEARCH(SUBSTITUTE('Référentiel films'!$A$12,"’","'"),SUBSTITUTE(F26,"’","'"))),'Référentiel films'!$B$12,""),IF(ISNUMBER(SEARCH(SUBSTITUTE('Référentiel films'!$A$13,"’","'"),SUBSTITUTE(F26,"’","'"))),'Référentiel films'!$B$13,""),IF(ISNUMBER(SEARCH(SUBSTITUTE('Référentiel films'!$A$14,"’","'"),SUBSTITUTE(F26,"’","'"))),'Référentiel films'!$B$14,""),IF(ISNUMBER(SEARCH(SUBSTITUTE('Référentiel films'!$A$15,"’","'"),SUBSTITUTE(F26,"’","'"))),'Référentiel films'!$B$15,""),IF(ISNUMBER(SEARCH(SUBSTITUTE('Référentiel films'!$A$16,"’","'"),SUBSTITUTE(F26,"’","'"))),'Référentiel films'!$B$16,""),IF(ISNUMBER(SEARCH(SUBSTITUTE('Référentiel films'!$A$17,"’","'"),SUBSTITUTE(F26,"’","'"))),'Référentiel films'!$B$17,""),IF(ISNUMBER(SEARCH(SUBSTITUTE('Référentiel films'!$A$18,"’","'"),SUBSTITUTE(F26,"’","'"))),'Référentiel films'!$B$18,""),IF(ISNUMBER(SEARCH(SUBSTITUTE('Référentiel films'!$A$19,"’","'"),SUBSTITUTE(F26,"’","'"))),'Référentiel films'!$B$19,""),IF(ISNUMBER(SEARCH(SUBSTITUTE('Référentiel films'!$A$20,"’","'"),SUBSTITUTE(F26,"’","'"))),'Référentiel films'!$B$20,""),IF(ISNUMBER(SEARCH(SUBSTITUTE('Référentiel films'!$A$21,"’","'"),SUBSTITUTE(F26,"’","'"))),'Référentiel films'!$B$21,""),IF(ISNUMBER(SEARCH(SUBSTITUTE('Référentiel films'!$A$22,"’","'"),SUBSTITUTE(F26,"’","'"))),'Référentiel films'!$B$22,""),IF(ISNUMBER(SEARCH(SUBSTITUTE('Référentiel films'!$A$23,"’","'"),SUBSTITUTE(F26,"’","'"))),'Référentiel films'!$B$23,""),IF(ISNUMBER(SEARCH(SUBSTITUTE('Référentiel films'!$A$24,"’","'"),SUBSTITUTE(F26,"’","'"))),'Référentiel films'!$B$24,""),IF(ISNUMBER(SEARCH(SUBSTITUTE('Référentiel films'!$A$25,"’","'"),SUBSTITUTE(F26,"’","'"))),'Référentiel films'!$B$25,""),IF(ISNUMBER(SEARCH(SUBSTITUTE('Référentiel films'!$A$26,"’","'"),SUBSTITUTE(F26,"’","'"))),'Référentiel films'!$B$26,""),IF(ISNUMBER(SEARCH(SUBSTITUTE('Référentiel films'!$A$27,"’","'"),SUBSTITUTE(F26,"’","'"))),'Référentiel films'!$B$27,""),IF(ISNUMBER(SEARCH(SUBSTITUTE('Référentiel films'!$A$28,"’","'"),SUBSTITUTE(F26,"’","'"))),'Référentiel films'!$B$28,""),IF(ISNUMBER(SEARCH(SUBSTITUTE('Référentiel films'!$A$29,"’","'"),SUBSTITUTE(F26,"’","'"))),'Référentiel films'!$B$29,""),IF(ISNUMBER(SEARCH(SUBSTITUTE('Référentiel films'!$A$30,"’","'"),SUBSTITUTE(F26,"’","'"))),'Référentiel films'!$B$30,""),IF(ISNUMBER(SEARCH(SUBSTITUTE('Référentiel films'!$A$31,"’","'"),SUBSTITUTE(F26,"’","'"))),'Référentiel films'!$B$31,""),IF(ISNUMBER(SEARCH(SUBSTITUTE('Référentiel films'!$A$32,"’","'"),SUBSTITUTE(F26,"’","'"))),'Référentiel films'!$B$32,""),IF(ISNUMBER(SEARCH(SUBSTITUTE('Référentiel films'!$A$33,"’","'"),SUBSTITUTE(F26,"’","'"))),'Référentiel films'!$B$33,""),IF(ISNUMBER(SEARCH(SUBSTITUTE('Référentiel films'!$A$34,"’","'"),SUBSTITUTE(F26,"’","'"))),'Référentiel films'!$B$34,""),IF(ISNUMBER(SEARCH(SUBSTITUTE('Référentiel films'!$A$35,"’","'"),SUBSTITUTE(F26,"’","'"))),'Référentiel films'!$B$35,""),IF(ISNUMBER(SEARCH(SUBSTITUTE('Référentiel films'!$A$36,"’","'"),SUBSTITUTE(F26,"’","'"))),'Référentiel films'!$B$36,""),IF(ISNUMBER(SEARCH(SUBSTITUTE('Référentiel films'!$A$37,"’","'"),SUBSTITUTE(F26,"’","'"))),'Référentiel films'!$B$37,""),IF(ISNUMBER(SEARCH(SUBSTITUTE('Référentiel films'!$A$38,"’","'"),SUBSTITUTE(F26,"’","'"))),'Référentiel films'!$B$38,""),IF(ISNUMBER(SEARCH(SUBSTITUTE('Référentiel films'!$A$39,"’","'"),SUBSTITUTE(F26,"’","'"))),'Référentiel films'!$B$39,""),IF(ISNUMBER(SEARCH(SUBSTITUTE('Référentiel films'!$A$40,"’","'"),SUBSTITUTE(F26,"’","'"))),'Référentiel films'!$B$40,""),IF(ISNUMBER(SEARCH(SUBSTITUTE('Référentiel films'!$A$41,"’","'"),SUBSTITUTE(F26,"’","'"))),'Référentiel films'!$B$41,""))) -> film-1972-le-marchand-des-quatre-saisons
A27: 1972 | D27: Aguirre, la colère de Dieu de Werner Herzog (1972) Cabaret de Bob Fosse met en scène la période de Weimar et l'ascension d'Htiler sous forme de comédie musicale. Sa mise en scène de l'homosexualité comme espace de réistance à l'oppression nazi fait advenir une représentation des persécutions dont la communauté LGBT a fait l'objet sous le nazisme, elle déconstruit aussi le cliché homophobe de l'officier nazi associé à une forme de perversion sexuelle souvent assimilée à une homosexualité refoulée. La mise en scène de la culture populaire (la chanson) et l'inscription dans un genre hollywoodien majeur constituent elles aussi des transfressions culturelles qui bouleversent l'histoire des représentations. | U27: =IF(F27="","",_xlfn.TEXTJOIN("; ",TRUE(),IF(ISNUMBER(SEARCH(SUBSTITUTE('Référentiel films'!$A$2,"’","'"),SUBSTITUTE(F27,"’","'"))),'Référentiel films'!$B$2,""),IF(ISNUMBER(SEARCH(SUBSTITUTE('Référentiel films'!$A$3,"’","'"),SUBSTITUTE(F27,"’","'"))),'Référentiel films'!$B$3,""),IF(ISNUMBER(SEARCH(SUBSTITUTE('Référentiel films'!$A$4,"’","'"),SUBSTITUTE(F27,"’","'"))),'Référentiel films'!$B$4,""),IF(ISNUMBER(SEARCH(SUBSTITUTE('Référentiel films'!$A$5,"’","'"),SUBSTITUTE(F27,"’","'"))),'Référentiel films'!$B$5,""),IF(ISNUMBER(SEARCH(SUBSTITUTE('Référentiel films'!$A$6,"’","'"),SUBSTITUTE(F27,"’","'"))),'Référentiel films'!$B$6,""),IF(ISNUMBER(SEARCH(SUBSTITUTE('Référentiel films'!$A$7,"’","'"),SUBSTITUTE(F27,"’","'"))),'Référentiel films'!$B$7,""),IF(ISNUMBER(SEARCH(SUBSTITUTE('Référentiel films'!$A$8,"’","'"),SUBSTITUTE(F27,"’","'"))),'Référentiel films'!$B$8,""),IF(ISNUMBER(SEARCH(SUBSTITUTE('Référentiel films'!$A$9,"’","'"),SUBSTITUTE(F27,"’","'"))),'Référentiel films'!$B$9,""),IF(ISNUMBER(SEARCH(SUBSTITUTE('Référentiel films'!$A$10,"’","'"),SUBSTITUTE(F27,"’","'"))),'Référentiel films'!$B$10,""),IF(ISNUMBER(SEARCH(SUBSTITUTE('Référentiel films'!$A$11,"’","'"),SUBSTITUTE(F27,"’","'"))),'Référentiel films'!$B$11,""),IF(ISNUMBER(SEARCH(SUBSTITUTE('Référentiel films'!$A$12,"’","'"),SUBSTITUTE(F27,"’","'"))),'Référentiel films'!$B$12,""),IF(ISNUMBER(SEARCH(SUBSTITUTE('Référentiel films'!$A$13,"’","'"),SUBSTITUTE(F27,"’","'"))),'Référentiel films'!$B$13,""),IF(ISNUMBER(SEARCH(SUBSTITUTE('Référentiel films'!$A$14,"’","'"),SUBSTITUTE(F27,"’","'"))),'Référentiel films'!$B$14,""),IF(ISNUMBER(SEARCH(SUBSTITUTE('Référentiel films'!$A$15,"’","'"),SUBSTITUTE(F27,"’","'"))),'Référentiel films'!$B$15,""),IF(ISNUMBER(SEARCH(SUBSTITUTE('Référentiel films'!$A$16,"’","'"),SUBSTITUTE(F27,"’","'"))),'Référentiel films'!$B$16,""),IF(ISNUMBER(SEARCH(SUBSTITUTE('Référentiel films'!$A$17,"’","'"),SUBSTITUTE(F27,"’","'"))),'Référentiel films'!$B$17,""),IF(ISNUMBER(SEARCH(SUBSTITUTE('Référentiel films'!$A$18,"’","'"),SUBSTITUTE(F27,"’","'"))),'Référentiel films'!$B$18,""),IF(ISNUMBER(SEARCH(SUBSTITUTE('Référentiel films'!$A$19,"’","'"),SUBSTITUTE(F27,"’","'"))),'Référentiel films'!$B$19,""),IF(ISNUMBER(SEARCH(SUBSTITUTE('Référentiel films'!$A$20,"’","'"),SUBSTITUTE(F27,"’","'"))),'Référentiel films'!$B$20,""),IF(ISNUMBER(SEARCH(SUBSTITUTE('Référentiel films'!$A$21,"’","'"),SUBSTITUTE(F27,"’","'"))),'Référentiel films'!$B$21,""),IF(ISNUMBER(SEARCH(SUBSTITUTE('Référentiel films'!$A$22,"’","'"),SUBSTITUTE(F27,"’","'"))),'Référentiel films'!$B$22,""),IF(ISNUMBER(SEARCH(SUBSTITUTE('Référentiel films'!$A$23,"’","'"),SUBSTITUTE(F27,"’","'"))),'Référentiel films'!$B$23,""),IF(ISNUMBER(SEARCH(SUBSTITUTE('Référentiel films'!$A$24,"’","'"),SUBSTITUTE(F27,"’","'"))),'Référentiel films'!$B$24,""),IF(ISNUMBER(SEARCH(SUBSTITUTE('Référentiel films'!$A$25,"’","'"),SUBSTITUTE(F27,"’","'"))),'Référentiel films'!$B$25,""),IF(ISNUMBER(SEARCH(SUBSTITUTE('Référentiel films'!$A$26,"’","'"),SUBSTITUTE(F27,"’","'"))),'Référentiel films'!$B$26,""),IF(ISNUMBER(SEARCH(SUBSTITUTE('Référentiel films'!$A$27,"’","'"),SUBSTITUTE(F27,"’","'"))),'Référentiel films'!$B$27,""),IF(ISNUMBER(SEARCH(SUBSTITUTE('Référentiel films'!$A$28,"’","'"),SUBSTITUTE(F27,"’","'"))),'Référentiel films'!$B$28,""),IF(ISNUMBER(SEARCH(SUBSTITUTE('Référentiel films'!$A$29,"’","'"),SUBSTITUTE(F27,"’","'"))),'Référentiel films'!$B$29,""),IF(ISNUMBER(SEARCH(SUBSTITUTE('Référentiel films'!$A$30,"’","'"),SUBSTITUTE(F27,"’","'"))),'Référentiel films'!$B$30,""),IF(ISNUMBER(SEARCH(SUBSTITUTE('Référentiel films'!$A$31,"’","'"),SUBSTITUTE(F27,"’","'"))),'Référentiel films'!$B$31,""),IF(ISNUMBER(SEARCH(SUBSTITUTE('Référentiel films'!$A$32,"’","'"),SUBSTITUTE(F27,"’","'"))),'Référentiel films'!$B$32,""),IF(ISNUMBER(SEARCH(SUBSTITUTE('Référentiel films'!$A$33,"’","'"),SUBSTITUTE(F27,"’","'"))),'Référentiel films'!$B$33,""),IF(ISNUMBER(SEARCH(SUBSTITUTE('Référentiel films'!$A$34,"’","'"),SUBSTITUTE(F27,"’","'"))),'Référentiel films'!$B$34,""),IF(ISNUMBER(SEARCH(SUBSTITUTE('Référentiel films'!$A$35,"’","'"),SUBSTITUTE(F27,"’","'"))),'Référentiel films'!$B$35,""),IF(ISNUMBER(SEARCH(SUBSTITUTE('Référentiel films'!$A$36,"’","'"),SUBSTITUTE(F27,"’","'"))),'Référentiel films'!$B$36,""),IF(ISNUMBER(SEARCH(SUBSTITUTE('Référentiel films'!$A$37,"’","'"),SUBSTITUTE(F27,"’","'"))),'Référentiel films'!$B$37,""),IF(ISNUMBER(SEARCH(SUBSTITUTE('Référentiel films'!$A$38,"’","'"),SUBSTITUTE(F27,"’","'"))),'Référentiel films'!$B$38,""),IF(ISNUMBER(SEARCH(SUBSTITUTE('Référentiel films'!$A$39,"’","'"),SUBSTITUTE(F27,"’","'"))),'Référentiel films'!$B$39,""),IF(ISNUMBER(SEARCH(SUBSTITUTE('Référentiel films'!$A$40,"’","'"),SUBSTITUTE(F27,"’","'"))),'Référentiel films'!$B$40,""),IF(ISNUMBER(SEARCH(SUBSTITUTE('Référentiel films'!$A$41,"’","'"),SUBSTITUTE(F27,"’","'"))),'Référentiel films'!$B$41,"")))
